Workbook
Name Austria: 'Customer List'!$F$4:$F$31
Name Belgium: 'Customer List'!$B$4:$B$50
Name Country_List: 'Product List'!$A$5:$A$17
Name Emerging_Markets: 'Customer List'!$G$4:$G$60
Name ESS_SPR_Gen2: 'Product List'!$E$5:$E$20
Name ESS_TCL_CI: 'Product List'!$F$5:$F$20
Name ESS_TCL_Res: 'Product List'!$G$5:$G$20
Name France: 'Customer List'!$H$4:$H$80
Name Germany: 'Customer List'!$D$4:$D$120
Name Heat_Pump: 'Product List'!$Q$5:$Q$18
Name Incoterm_List: Incoterm[Incoterm]
Name Incoterm_List: Incoterm[Incoterm]
Name Incoterm_List: Incoterm[Incoterm]
Name Incoterm_List: Incoterm[Incoterm]
Name Incoterm_List: Incoterm[Incoterm]
Name Incoterm_List: Incoterm[Incoterm]
Name Incoterm_List: Incoterm[Incoterm]
Name Incoterm_List: Incoterm[Incoterm]
Name Italy: 'Customer List'!$I$4:$I$300
Name Netherlands: 'Customer List'!$C$4:$C$70
Name Nordic: 'Customer List'!$J$4:$J$20
Name Product_List: 'Product List'!$C$5:$C$19
Name Spain: 'Customer List'!$K$4:$K$120
Name SPR_BC: 'Product List'!$P$5:$P$20
Name SPR_M_Class: 'Product List'!$O$5:$O$20
Name SPR_MAX_P6: 'Product List'!$R$4:$R$20
Name SPR_P_Class: 'Product List'!$I$5:$I$20
Name SPR_P7: 'Product List'!$H$5:$H$20
Name Stage_List: Stage[Stage]
Name Stage_List: Stage[Stage]
Name Stage_List: Stage[Stage]
Name Stage_List: Stage[Stage]
Name Stage_List: Stage[Stage]
Name Stage_List: Stage[Stage]
Name Stage_List: Stage[Stage]
Name Stage_List: Stage[Stage]
Name Switzerland: 'Customer List'!$E$4:$E$15
Name TCL_C2_Series: 'Product List'!$N$5:$N$22
Name TCL_E_Class: 'Product List'!$M$5:$M$20
Name TCL_S_Class: 'Product List'!$J$5:$J$20
Name TCL_T_Class: 'Product List'!$L$5:$L$21
Name TCL_T5_Pro: 'Product List'!$K$5:$K$20
Name UK: 'Customer List'!$L$4:$L$120

Sheet Pivot Weekly report
A1: below Pivot keep for Arleen
A3: Customer name | B3: (全部)
A4: Product Line | B4: (多项)
A5: Stage | B5: (多项)
A7: 行标签 | B7: Sum of 26M04 | C7: Sum of 26M05 | D7: Sum of 26M06 | E7: 求和项:26M07 | F7: 求和项:26M08 | G7: 求和项:26M09 | H7: 求和项:26M10 | I7: 求和项:26M11 | J7: 求和项:26M12
A8: Benelux Region | B8: 1.27 | C8: 4.11 | D8: 8.14 | E8: 4.46 | F8: 2.84 | G8: 11 | H8: 9.2 | I8: 7.2 | J8: 7.2
A9: Central and Eastern Europe Region | B9: 14 | C9: 17.5 | D9: 15 | E9: 8.8 | F9: 8 | G9: 9 | H9: 17 | I9: 9
A10: France and Switzerland Region | B10: 18.429 | C10: 14 | D10: 14.8 | E10: 16.3 | F10: 13.522 | G10: 11.416 | H10: 10.67 | I10: 10.67 | J10: 10.67
A11: DACH Region | B11: 39 | C11: 21.4 | D11: 21 | E11: 19.2 | F11: 1.35 | G11: 44.6 | H11: 49.9 | I11: 61.75 | J11: 21.35
A12: Italy Region | B12: 19 | C12: 49 | D12: 36 | E12: 47 | F12: 11.6 | G12: 71 | H12: 34 | I12: 54 | J12: 17
A13: Southern Europe Region | B13: 8 | C13: 9 | D13: 9 | E13: 5.3 | F13: 8.4 | G13: 8.6 | H13: 7 | I13: 26.2 | J13: 4.4
A14: Nordics Region | B14: 6.4 | C14: 2.8 | D14: 2.4 | E14: 0.8 | F14: 2 | G14: 16.8 | H14: 12.6 | I14: 10
A15: UK Region | B15: 8.318 | C15: 11.091 | D15: 10.113 | E15: 21.081 | F15: 8.861 | G15: 11.811 | H15: 11.741 | I15: 15.102 | J15: 3.874
A16: #N/A | E16: 2.6 | F16: 2.6 | G16: 2.6 | H16: 0.5 | I16: 0.5 | J16: 0.5
A17: 总计 | B17: 114.417 | C17: 128.901 | D17: 116.453 | E17: 125.541 | F17: 59.173 | G17: 186.827 | H17: 152.611 | I17: 194.422 | J17: 64.994
A20: below Pivot keep for Arleen
A24: Customer name | B24: (全部)
A25: Product Line | B25: (多项)
A26: Stage | B26: (多项)
A28: 行标签 | B28: Sum of 26M04 | C28: Sum of 26M05 | D28: Sum of 26M06 | E28: 求和项:26M07 | F28: 求和项:26M08 | G28: 求和项:26M09 | H28: 求和项:26M10 | I28: 求和项:26M11 | J28: 求和项:26M12
A29: Benelux Region | B29: 0.42 | C29: 1.32 | D29: 0.42 | E29: 0.92 | F29: 0.1 | G29: 1.92 | H29: 2.5 | I29: 3.9 | J29: 3.8
A30: Central and Eastern Europe Region | C30: 3.5
A31: France and Switzerland Region | B31: 3.2 | C31: 1.9 | D31: 4.15 | E31: 3.057 | F31: 3.2 | G31: 3.479 | H31: 2.197 | I31: 1.7 | J31: 2.55
A32: DACH Region | B32: 6.490848 | C32: 4.7761 | D32: 5.53603 | E32: 2.6311 | F32: 3.629538 | G32: 5.56265 | H32: 5.73455 | I32: 7.736228 | J32: 2.89428
A33: Italy Region | B33: 17 | C33: 17 | D33: 19 | E33: 16 | F33: 11 | G33: 22 | H33: 22 | I33: 22 | J33: 18
A34: Southern Europe Region | B34: 1.05 | C34: 2.2 | D34: 2.6 | E34: 2.5 | F34: 0.9 | G34: 3.2 | H34: 2.8 | I34: 3.6 | J34: 2.2
A35: Nordics Region | C35: 0.2 | E35: 1 | H35: 1.2
A36: UK Region | B36: 6.5184 | C36: 7.548 | D36: 3.461 | E36: 3.692 | F36: 2.313 | G36: 4.303 | H36: 2.091 | I36: 2.679 | J36: 1.561
A37: #N/A | B37: 0.4 | C37: 0 | D37: 0.4 | E37: 0.8 | F37: 0.8 | G37: 0.8 | H37: 0.5 | I37: 0.5 | J37: 0.5
A38: 总计 | B38: 35.079248 | C38: 38.4441 | D38: 35.56703 | E38: 30.6001 | F38: 21.942538 | G38: 41.26465 | H38: 39.02255 | I38: 42.115228 | J38: 31.50528
A44: below Pivot keep for Arleen
A46: Customer name | B46: (全部)
A47: Product Line | B47: (多项)
A48: Stage | B48: (多项)
A49: Product Category | B49: ESS
A50: Model name | B50: (多项)
A52: 行标签 | B52: 求和项:26M07 | C52: 求和项:26M08 | D52: 求和项:26M09 | E52: 求和项:26M10 | F52: 求和项:26M11 | G52: 求和项:26M12
A53: Spain | B53: 70 | C53: 35 | D53: 70 | E53: 75 | F53: 75 | G53: 30
A54: France | B54: 128 | C54: 61 | D54: 91 | E54: 93 | F54: 103 | G54: 87
A55: Italy | B55: 650 | C55: 320 | D55: 630 | E55: 540 | F55: 650 | G55: 740
A56: Germany | B56: 8 | C56: 14 | D56: 18 | E56: 13 | F56: 21 | G56: 11
A57: 总计 | B57: 856 | C57: 430 | D57: 809 | E57: 721 | F57: 849 | G57: 868 | H57: 498 | I57: 586 | J57: 378 | K57: 280 | L57: 527
A63: Energy+ | B63: 26M10 | C63: 26 M11 | D63: 26M12
A64: Spain | B64: 75 | C64: 75 | D64: 30
A65: France | B65: 101 | C65: 103 | D65: 95
A66: Italy | B66: 540 | C66: 650 | D66: 740
A67: Germany | B67: 13 | C67: 21 | D67: 11
A68: Grand Total | B68: 721 | C68: 849 | D68: 868
A75: Customer name | B75: (全部)
A76: Product Line | B76: Heat_Pump
A77: Stage | B77: (多项)
A79: 行标签 | B79: Sum of 26M04 | C79: Sum of 26M05 | D79: Sum of 26M06 | E79: 求和项:26M07 | F79: 求和项:26M08 | G79: 求和项:26M09 | H79: 求和项:26M10 | I79: 求和项:26M11 | J79: 求和项:26M12
A80: Nordics | E80: 2
A81: 总计 | E81: 2
A88: Heat Pump | B88: 26M07 | C88: 26 M08 | D88: 26M09 | E88: 26M10 | F88: 26 M11 | G88: 26M12
A89: Nordics | B89: 2
A90: Grand Total | B90: 2
A98: below Pivot keep for Julia
A100: Product Line | B100: (多项)
A101: Stage | B101: (多项)
A103: Country | B103: Model name | C103: 求和项:26M07 | D103: 求和项:26M08 | E103: 求和项:26M09 | F103: 求和项:26M10 | G103: 求和项:26M11 | H103: 求和项:26M12
A104: France | B104: BlueArk X5-50K-100 | D104: 1 | E104: 1
A105: France 汇总 | D105: 1 | E105: 1
A106: Italy | B106: BlueArk X5-50K-100 | C106: 2 | D106: 2 | E106: 2 | F106: 4 | G106: 4 | H106: 6
A107: Italy 汇总 | C107: 2 | D107: 2 | E107: 2 | F107: 4 | G107: 4 | H107: 6
A108: Nordic | B108: BlueArk W10-125K-261
B109: BlueArk X5-50K-100
A110: Nordic 汇总
A111: Spain | B111: BlueArk W10-125K-261 | F111: 2 | G111: 4 | H111: 4
B112: BlueArk X5-50K-100 | E112: 4 | F112: 12 | G112: 12 | H112: 4
A113: Spain 汇总 | E113: 4 | F113: 14 | G113: 16 | H113: 8
A114: 总计 | C114: 2 | D114: 3 | E114: 7 | F114: 18 | G114: 20 | H114: 14
A134: below Pivot keep for Nan
A140: Customer name | B140: (全部)
A141: Product Line | B141: TCL_T_Class
A142: Stage | B142: (多项)
A144: 行标签 | B144: 求和项:26M07 | C144: 求和项:26M08 | D144: 求和项:26M09 | E144: 求和项:26M10 | F144: 求和项:26M11 | G144: 求和项:26M12
A145: BeNeLux | B145: 3.14 | C145: 0.84 | D145: 5.7
A146: France | B146: 16.3 | C146: 13.522 | D146: 9.346 | E146: 4.6 | F146: 4.6 | G146: 4.6
A147: Germany | B147: 19.2 | C147: 0 | D147: 14.7 | E147: 14 | F147: 14.3 | G147: 0
A148: Italy | B148: 34.4 | C148: 4.8 | D148: 44.6 | E148: 8 | F148: 28 | G148: 6
A149: Spain | C149: 0.4 | D149: 1.2 | E149: 4.2 | F149: 5.8 | G149: 1.6
A150: Nordics | B150: 0.8 | C150: 2 | D150: 16 | E150: 7 | F150: 6
A151: UK | B151: 3.292 | C151: 5.292 | D151: 8.242 | E151: 4.284 | F151: 3.021 | G151: 2.6
A152: #N/A | B152: 2.6 | C152: 2.6 | D152: 2.6 | E152: 0.5 | F152: 0.5 | G152: 0.5
A153: C&E EU | B153: 8.8 | C153: 8 | D153: 9 | E153: 17 | F153: 9
A154: Southern Europe Region | C154: 8 | D154: 1 | F154: 16
A155: 总计 | B155: 88.532 | C155: 45.454 | D155: 112.388 | E155: 59.584 | F155: 87.221 | G155: 15.3
A159: Country | B159: Model name | C159: 求和项:26M07 | D159: 求和项:26M08 | E159: 求和项:26M09 | F159: 求和项:26M10 | G159: 求和项:26M11 | H159: 求和项:26M12
A160: France | B160: 1P 10KW 1*5KWH | C160: 24 | D160: 16 | E160: 21 | F160: 21 | G160: 21 | H160: 21
B161: 1P 6KW 1*5KWH | C161: 80 | D161: 35 | E161: 61 | F161: 61 | G161: 49 | H161: 61
B162: 1P 8KW 1*5KWH | D162: 4 | F162: 4 | G162: 4
B163: 3P 10KW 2*5KWH | C163: 24 | D163: 0 | E163: 15 | F163: 5 | G163: 19 | H163: 13
B164: 3P 13KW 2*5KWH | C164: 0 | D164: 6 | E164: 6 | F164: 18 | G164: 14 | H164: 8
B165: addtl 5KWH BAT | C165: 80 | D165: 60 | E165: 120 | F165: 120 | G165: 80 | H165: 120
B166: BlueArk X5-50K-100 | D166: 1 | E166: 2
A167: Germany | B167: 3P 10KW 2*5KWH | D167: 1 | E167: 1 | G167: 2
B168: 3P 13KW 2*5KWH | C168: 8 | D168: 13 | E168: 17 | F168: 13 | G168: 19 | H168: 11
B169: addtl 5KWH BAT | C169: 2 | D169: 2 | E169: 1 | F169: 2 | G169: 2 | H169: 1
A170: Italy | B170: 1P 6kW 2*5kWh | C170: 600 | D170: 300 | E170: 600 | F170: 500 | G170: 600 | H170: 700
...

Sheet Fcst Accuracy data
A1: Country | B1: Sales Team.Region | C1: Product Category | D1: Attribute | E1: Fcst unweighted | F1: Fcst weighted
C2: PV | D2: 2026-04 | E2: 0.4 | F2: 0.28
C3: PV | D3: 2026-05 | E3: 0 | F3: 0
C4: PV | D4: 2026-06 | E4: 0.4 | F4: 0.28
C5: PV | D5: 2026-07 | E5: 3.4 | F5: 2.38
C6: PV | D6: 2026-08 | E6: 3.4 | F6: 2.38
C7: PV | D7: 2026-09 | E7: 3.4 | F7: 2.38
C8: PV | D8: 2026-10 | E8: 1 | F8: 0.7
C9: PV | D9: 2026-11 | E9: 1 | F9: 0.7
C10: PV | D10: 2026-12 | E10: 1 | F10: 0.7
A11: Belgium | B11: Benelux Region | C11: PV | D11: 2026-05 | E11: 3.38 | F11: 3.38
A12: Belgium | B12: Benelux Region | C12: PV | D12: 2026-06 | E12: 6.46 | F12: 6.46
A13: Belgium | B13: Benelux Region | C13: PV | D13: 2026-07 | E13: 4.06 | F13: 4.06
A14: Belgium | B14: Benelux Region | C14: PV | D14: 2026-08 | E14: 2.94 | F14: 2.94
A15: Belgium | B15: Benelux Region | C15: PV | D15: 2026-09 | E15: 11.72 | F15: 8.98
A16: Belgium | B16: Benelux Region | C16: PV | D16: 2026-10 | E16: 6.1 | F16: 3.45
A17: Belgium | B17: Benelux Region | C17: PV | D17: 2026-11 | E17: 5.5 | F17: 2.02
A18: Belgium | B18: Benelux Region | C18: PV | D18: 2026-12 | E18: 5.4 | F18: 1.92
A19: Belgium | B19: Benelux Region | C19: PV | D19: 2026-04 | E19: 0.84 | F19: 0.84
A20: Croatia | B20: Central and Eastern Europe Region | C20: PV | D20: 2026-05 | E20: 1.2 | F20: 1.2
A21: Cyprus | B21: Southern Europe Region | C21: PV | D21: 2026-09 | E21: 1 | F21: 0.3
A22: France | B22: France and Switzerland Region | C22: PV | D22: 2026-04 | E22: 21.629 | F22: 15.9461
... A146: italy | B146: Italy Region | C146: PV | D146: 2026-12 | E146: 5 | F146: 1.5

Sheet Conso
A1: Country | B1: Customer name | C1: RSM | D1: Product Line | E1: Model name | F1: Stage | G1: Comments (Deal Breaker, spec/requirements, etc) | H1: Supply Chain | I1: 26M04 | J1: 26M05 | K1: 26M06 | L1: 26M07 | M1: 26M08 | N1: 26M09 | O1: 26M10 | P1: 26M11 | Q1: 26M12 | R1: 27M01 | S1: 27M02 | T1: 27M03 | U1: 27M04 | V1: 27M05 | W1: 27M06 | X1: Product Category | Y1: Region | Z1: Sales Team | AA1: Product Conso
B2: Solarmarkt | C2: Manu | D2: TCL_C2_Series | E2: HSM-BE54-JD485/490 | F2: 2 - Initial offer | G2: Amarenco // CFP, 470W, CFP PPE2 V1<550 // | H2: EU | Q2: 0.4 | X2: PV | Y2: =VLOOKUP(Conso_FCST[[#This Row],[Country]],'Country-Region'!A:D,4,0) -> #N/A | Z2: =VLOOKUP(Conso_FCST[[#This Row],[Country]],'Country-Region'!A:D,3,0) -> #N/A | AA2: =IFERROR(VLOOKUP(Conso_FCST[[#This Row],[Model name]],Prod_T6[[#All],[Model name]:[Product Conso]],2,0),"exclude") -> HSM-BE54-JD
B3: Solarmarkt | C3: Manu | D3: SPR_P7 | E3: P7-BLK-2mm-460 | F3: 5 - Finalize contract | H3: EU | I3: 0.2 | J3: 0 | K3: 0.2 | L3: 0.4 | M3: 0.4 | N3: 0.4 | O3: 0.1 | P3: 0.1 | Q3: 0.1 | X3: PV | Y3: =VLOOKUP(Conso_FCST[[#This Row],[Country]],'Country-Region'!A:D,4,0) -> #N/A | Z3: =VLOOKUP(Conso_FCST[[#This Row],[Country]],'Country-Region'!A:D,3,0) -> #N/A | AA3: =IFERROR(VLOOKUP(Conso_FCST[[#This Row],[Model name]],Prod_T6[[#All],[Model name]:[Product Conso]],2,0),"exclude") -> P7 RES BLK 2.0
B4: Solarmarkt | C4: Manu | D4: TCL_T_Class | E4: HSM-ND54-DR500 | F4: 5 - Finalize contract | H4: EU | L4: 1.3 | M4: 1.3 | N4: 1.3 | O4: 0.1 | P4: 0.1 | Q4: 0.1 | X4: PV | Y4: =VLOOKUP(Conso_FCST[[#This Row],[Country]],'Country-Region'!A:D,4,0) -> #N/A | Z4: =VLOOKUP(Conso_FCST[[#This Row],[Country]],'Country-Region'!A:D,3,0) -> #N/A | AA4: =IFERROR(VLOOKUP(Conso_FCST[[#This Row],[Model name]],Prod_T6[[#All],[Model name]:[Product Conso]],2,0),"exclude") -> HSM-ND54-DR
B5: Solexis | C5: Manu | D5: SPR_P7 | E5: P7-BLK-P-510 | F5: 5 - Finalize contract | H5: EU | I5: 0.2 | J5: 0 | K5: 0.2 | L5: 0.4 | M5: 0.4 | N5: 0.4 | O5: 0.4 | P5: 0.4 | Q5: 0.4 | X5: PV | Y5: =VLOOKUP(Conso_FCST[[#This Row],[Country]],'Country-Region'!A:D,4,0) -> #N/A | Z5: =VLOOKUP(Conso_FCST[[#This Row],[Country]],'Country-Region'!A:D,3,0) -> #N/A | AA5: =IFERROR(VLOOKUP(Conso_FCST[[#This Row],[Model name]],Prod_T6[[#All],[Model name]:[Product Conso]],2,0),"exclude") -> P7 RES BLK-P
B6: Solexis | C6: Manu | D6: TCL_T_Class | E6: HSM-ND54-DR500 | F6: 5 - Finalize contract | H6: EU | L6: 1.3 | M6: 1.3 | N6: 1.3 | O6: 0.4 | P6: 0.4 | Q6: 0.4 | X6: PV | Y6: =VLOOKUP(Conso_FCST[[#This Row],[Country]],'Country-Region'!A:D,4,0) -> #N/A | Z6: =VLOOKUP(Conso_FCST[[#This Row],[Country]],'Country-Region'!A:D,3,0) -> #N/A | AA6: =IFERROR(VLOOKUP(Conso_FCST[[#This Row],[Model name]],Prod_T6[[#All],[Model name]:[Product Conso]],2,0),"exclude") -> HSM-ND54-DR
A7: 0.1 | B7: Solexis | C7: Manu | D7: TCL_C2_Series | E7: HSM-BE54-JD485/490 | F7: 2 - Initial offer | G7: Amarenco // CFP, 470W, CFP PPE2 V1<550 // | H7: EU | Q7: 0.4 | X7: PV | Y7: =VLOOKUP(Conso_FCST[[#This Row],[Country]],'Country-Region'!A:D,4,0) -> #N/A | Z7: =VLOOKUP(Conso_FCST[[#This Row],[Country]],'Country-Region'!A:D,3,0) -> #N/A | AA7: =IFERROR(VLOOKUP(Conso_FCST[[#This Row],[Model name]],Prod_T6[[#All],[Model name]:[Product Conso]],2,0),"exclude") -> HSM-BE54-JD
A8: Austria | B8: Wien Energie | D8: TCL_T_Class | E8: HSM-ND66-GK725 | F8: 2 - Initial offer | H8: EU | X8: PV | Y8: =VLOOKUP(Conso_FCST[[#This Row],[Country]],'Country-Region'!A:D,4,0) -> DACH Region | Z8: =VLOOKUP(Conso_FCST[[#This Row],[Country]],'Country-Region'!A:D,3,0) -> Germany | AA8: =IFERROR(VLOOKUP(Conso_FCST[[#This Row],[Model name]],Prod_T6[[#All],[Model name]:[Product Conso]],2,0),"exclude") -> HSM-ND66-GK
A9: Belgium | B9: ECOSTAL SPRL | C9: Romain | D9: TCL_T_Class | E9: HSM-ND48-DR450 | F9: 7 - Booked | G9: BOOKED | H9: Offshore | J9: 0.84 | K9: 0.84 | L9: 0.84 | M9: 0.84 | X9: PV | Y9: =VLOOKUP(Conso_FCST[[#This Row],[Country]],'Country-Region'!A:D,4,0) -> Benelux Region | Z9: =VLOOKUP(Conso_FCST[[#This Row],[Country]],'Country-Region'!A:D,3,0) -> BeNeLux | AA9: =IFERROR(VLOOKUP(Conso_FCST[[#This Row],[Model name]],Prod_T6[[#All],[Model name]:[Product Conso]],2,0),"exclude") -> HSM-ND48-DR
A10: Belgium | B10: bvba BeliVert | D10: SPR_BC | E10: SPR-BE54-HD490/495 | F10: 3 - Negotiation | H10: EU | P10: 0.9 | Q10: 0.9 | X10: PV | Y10: =VLOOKUP(Conso_FCST[[#This Row],[Country]],'Country-Region'!A:D,4,0) -> Benelux Region | Z10: =VLOOKUP(Conso_FCST[[#This Row],[Country]],'Country-Region'!A:D,3,0) -> BeNeLux | AA10: =IFERROR(VLOOKUP(Conso_FCST[[#This Row],[Model name]],Prod_T6[[#All],[Model name]:[Product Conso]],2,0),"exclude") -> SPR-BE54-HD
A11: Belgium | B11: SOLARPRO BVBA | C11: Regis | D11: SPR_P7 | E11: P7-BLK-2mm-460 | F11: 7 - Booked | H11: EU | J11: 0.1 | L11: 0.1 | M11: 0.1 | N11: 0.1 | X11: PV | Y11: =VLOOKUP(Conso_FCST[[#This Row],[Country]],'Country-Region'!A:D,4,0) -> Benelux Region | Z11: =VLOOKUP(Conso_FCST[[#This Row],[Country]],'Country-Region'!A:D,3,0) -> BeNeLux | AA11: =IFERROR(VLOOKUP(Conso_FCST[[#This Row],[Model name]],Prod_T6[[#All],[Model name]:[Product Conso]],2,0),"exclude") -> P7 RES BLK 2.0
A12: Belgium | B12: SOLARPRO | D12: SPR_BC | E12: SPR-BE54-HD490/495 | F12: 3 - Negotiation | H12: EU | O12: 0.2 | P12: 0.2 | Q12: 0.2 | X12: PV | Y12: =VLOOKUP(Conso_FCST[[#This Row],[Country]],'Country-Region'!A:D,4,0) -> Benelux Region | Z12: =VLOOKUP(Conso_FCST[[#This Row],[Country]],'Country-Region'!A:D,3,0) -> BeNeLux | AA12: =IFERROR(VLOOKUP(Conso_FCST[[#This Row],[Model name]],Prod_T6[[#All],[Model name]:[Product Conso]],2,0),"exclude") -> SPR-BE54-HD
A13: Belgium | B13: Reno.Energy SA | D13: ESS_TCL_CI | E13: BlueArk W10-125K-261 | F13: 2 - Initial offer | G13: AWAITING FEEDBACK NEW ASP | H13: EU | O13: 1 | P13: 1 | Q13: 1 | X13: ESS | Y13: =VLOOKUP(Conso_FCST[[#This Row],[Country]],'Country-Region'!A:D,4,0) -> Benelux Region | Z13: =VLOOKUP(Conso_FCST[[#This Row],[Country]],'Country-Region'!A:D,3,0) -> BeNeLux | AA13: =IFERROR(VLOOKUP(Conso_FCST[[#This Row],[Model name]],Prod_T6[[#All],[Model name]:[Product Conso]],2,0),"exclude") -> BlueArk W10-125K-261
A14: Belgium | B14: RENA SOLAR & CHARGE | D14: TCL_C2_Series | E14: SPR-BE54-HD490/495 | F14: 3 - Negotiation | H14: EU | O14: 0.1 | P14: 0.1 | Q14: 0.1 | X14: PV | Y14: =VLOOKUP(Conso_FCST[[#This Row],[Country]],'Country-Region'!A:D,4,0) -> Benelux Region | Z14: =VLOOKUP(Conso_FCST[[#This Row],[Country]],'Country-Region'!A:D,3,0) -> BeNeLux | AA14: =IFERROR(VLOOKUP(Conso_FCST[[#This Row],[Model name]],Prod_T6[[#All],[Model name]:[Product Conso]],2,0),"exclude") -> SPR-BE54-HD
A15: Belgium | B15: Neopower | C15: Romain | D15: SPR_P7 | E15: P7-BLK-2mm-460 | F15: 7 - Booked | H15: EU | J15: 0.1 | L15: 0.1 | N15: 0.1 | X15: PV | Y15: =VLOOKUP(Conso_FCST[[#This Row],[Country]],'Country-Region'!A:D,4,0) -> Benelux Region | Z15: =VLOOKUP(Conso_FCST[[#This Row],[Country]],'Country-Region'!A:D,3,0) -> BeNeLux | AA15: =IFERROR(VLOOKUP(Conso_FCST[[#This Row],[Model name]],Prod_T6[[#All],[Model name]:[Product Conso]],2,0),"exclude") -> P7 RES BLK 2.0
A16: Belgium | B16: bvba BeliVert | C16: Regis | D16: SPR_P7 | E16: P7-BLK-2mm-455 | F16: 7 - Booked | G16: AWAITING ORDER | H16: EU | I16: 0.42 | J16: 0.42 | K16: 0.42 | L16: 0.42 | N16: 0.42 | X16: PV | Y16: =VLOOKUP(Conso_FCST[[#This Row],[Country]],'Country-Region'!A:D,4,0) -> Benelux Region | Z16: =VLOOKUP(Conso_FCST[[#This Row],[Country]],'Country-Region'!A:D,3,0) -> BeNeLux | AA16: =IFERROR(VLOOKUP(Conso_FCST[[#This Row],[Model name]],Prod_T6[[#All],[Model name]:[Product Conso]],2,0),"exclude") -> P7 RES BLK 2.0
A17: Belgium | B17: Neopower | D17: SPR_BC | E17: SPR-BE54-HD490/495 | F17: 3 - Negotiation | H17: EU | O17: 0.1 | P17: 0.1 | Q17: 0.1 | X17: PV | Y17: =VLOOKUP(Conso_FCST[[#This Row],[Country]],'Country-Region'!A:D,4,0) -> Benelux Region | Z17: =VLOOKUP(Conso_FCST[[#This Row],[Country]],'Country-Region'!A:D,3,0) -> BeNeLux | AA17: =IFERROR(VLOOKUP(Conso_FCST[[#This Row],[Model name]],Prod_T6[[#All],[Model name]:[Product Conso]],2,0),"exclude") -> SPR-BE54-HD
A18: Belgium | B18: ENR Lux | D18: SPR_BC | E18: SPR-BE54-HD490/495 | F18: 7 - Booked | H18: EU | O18: 0.2 | P18: 0.2 | Q18: 0.2 | X18: PV | Y18: =VLOOKUP(Conso_FCST[[#This Row],[Country]],'Country-Region'!A:D,4,0) -> Benelux Region | Z18: =VLOOKUP(Conso_FCST[[#This Row],[Country]],'Country-Region'!A:D,3,0) -> BeNeLux | AA18: =IFERROR(VLOOKUP(Conso_FCST[[#This Row],[Model name]],Prod_T6[[#All],[Model name]:[Product Conso]],2,0),"exclude") -> SPR-BE54-HD
A19: Belgium | B19: MR group | D19: TCL_T5_Pro | E19: HSM-NT60-GH 580/585 | F19: 2 - Initial offer | H19: EU | O19: 0.9 | P19: 0.9 | Q19: 0.9 | X19: PV | Y19: =VLOOKUP(Conso_FCST[[#This Row],[Country]],'Country-Region'!A:D,4,0) -> Benelux Region | Z19: =VLOOKUP(Conso_FCST[[#This Row],[Country]],'Country-Region'!A:D,3,0) -> BeNeLux | AA19: =IFERROR(VLOOKUP(Conso_FCST[[#This Row],[Model name]],Prod_T6[[#All],[Model name]:[Product Conso]],2,0),"exclude") -> HSM-NT60-GH
A20: Belgium | B20: MR group | D20: TCL_C2_Series | E20: SPR-BE54-HD490/495 | F20: 3 - Negotiation | H20: EU | N20: 0.9 | O20: 0.9 | P20: 0.9 | Q20: 0.9 | X20: PV | Y20: =VLOOKUP(Conso_FCST[[#This Row],[Country]],'Country-Region'!A:D,4,0) -> Benelux Region | Z20: =VLOOKUP(Conso_FCST[[#This Row],[Country]],'Country-Region'!A:D,3,0) -> BeNeLux | AA20: =IFERROR(VLOOKUP(Conso_FCST[[#This Row],[Model name]],Prod_T6[[#All],[Model name]:[Product Conso]],2,0),"exclude") -> SPR-BE54-HD
A21: Belgium | B21: ECOSTAL SPRL | D21: ESS_TCL_CI | E21: BlueArk X5-50K-100 | F21: 2 - Initial offer | G21: AWAITING FEEDBACK NEW ASP | H21: Offshore | O21: 2 | P21: 2 | Q21: 2 | X21: ESS | Y21: =VLOOKUP(Conso_FCST[[#This Row],[Country]],'Country-Region'!A:D,4,0) -> Benelux Region | Z21: =VLOOKUP(Conso_FCST[[#This Row],[Country]],'Country-Region'!A:D,3,0) -> BeNeLux | AA21: =IFERROR(VLOOKUP(Conso_FCST[[#This Row],[Model name]],Prod_T6[[#All],[Model name]:[Product Conso]],2,0),"exclude") -> BlueArk X5-50K-100
A22: Belgium | B22: ECOSTAL SPRL | D22: ESS_TCL_CI | E22: BlueArk W10-125K-261 | F22: 2 - Initial offer | G22: AWAITING FEEDBACK NEW ASP | H22: Offshore | O22: 2 | P22: 3 | Q22: 3 | X22: ESS | Y22: =VLOOKUP(Conso_FCST[[#This Row],[Country]],'Country-Region'!A:D,4,0) -> Benelux Region | Z22: =VLOOKUP(Conso_FCST[[#This Row],[Country]],'Country-Region'!A:D,3,0) -> BeNeLux | AA22: =IFERROR(VLOOKUP(Conso_FCST[[#This Row],[Model name]],Prod_T6[[#All],[Model name]:[Product Conso]],2,0),"exclude") -> BlueArk W10-125K-261
A23: Belgium | B23: Reno.Energy SA | D23: ESS_TCL_CI | E23: BlueArk X5-50K-100 | F23: 2 - Initial offer | G23: AWAITING FEEDBACK NEW ASP | H23: EU | O23: 1 | P23: 1 | Q23: 1 | X23: ESS | Y23: =VLOOKUP(Conso_FCST[[#This Row],[Country]],'Country-Region'!A:D,4,0) -> Benelux Region | Z23: =VLOOKUP(Conso_FCST[[#This Row],[Country]],'Country-Region'!A:D,3,0) -> BeNeLux | AA23: =IFERROR(VLOOKUP(Conso_FCST[[#This Row],[Model name]],Prod_T6[[#All],[Model name]:[Product Conso]],2,0),"exclude") -> BlueArk X5-50K-100
A24: Belgium | B24: ENR Lux | D24: SPR_P7 | E24: P7-BLK-2mm-460 | F24: 7 - Booked | H24: EU | J24: 0.2 | L24: 0.2 | N24: 0.2 | X24: PV | Y24: =VLOOKUP(Conso_FCST[[#This Row],[Country]],'Country-Region'!A:D,4,0) -> Benelux Region | Z24: =VLOOKUP(Conso_FCST[[#This Row],[Country]],'Country-Region'!A:D,3,0) -> BeNeLux | AA24: =IFERROR(VLOOKUP(Conso_FCST[[#This Row],[Model name]],Prod_T6[[#All],[Model name]:[Product Conso]],2,0),"exclude") -> P7 RES BLK 2.0
A25: Belgium | B25: Reno.Energy SA | D25: SPR_BC | E25: SPR-BE54-HD490/495 | F25: 3 - Negotiation | G25: AWAITING FORECAST | H25: EU | N25: 1 | X25: PV | Y25: =VLOOKUP(Conso_FCST[[#This Row],[Country]],'Country-Region'!A:D,4,0) -> Benelux Region | Z25: =VLOOKUP(Conso_FCST[[#This Row],[Country]],'Country-Region'!A:D,3,0) -> BeNeLux | AA25: =IFERROR(VLOOKUP(Conso_FCST[[#This Row],[Model name]],Prod_T6[[#All],[Model name]:[Product Conso]],2,0),"exclude") -> SPR-BE54-HD
A26: Belgium | B26: RENA SOLAR & CHARGE | C26: Regis | D26: SPR_P7 | E26: P7-BLK-2mm-460 | F26: 7 - Booked | H26: EU | J26: 0.1 | L26: 0.1 | N26: 0.1 | P26: 0.1 | X26: PV | Y26: =VLOOKUP(Conso_FCST[[#This Row],[Country]],'Country-Region'!A:D,4,0) -> Benelux Region | Z26: =VLOOKUP(Conso_FCST[[#This Row],[Country]],'Country-Region'!A:D,3,0) -> BeNeLux | AA26: =IFERROR(VLOOKUP(Conso_FCST[[#This Row],[Model name]],Prod_T6[[#All],[Model name]:[Product Conso]],2,0),"exclude") -> P7 RES BLK 2.0
A27: Belgium | B27: Reno.Energy SA | D27: TCL_T5_Pro | E27: HSM-NT48-HH 465/470-Black | F27: 3 - Negotiation | G27: AWAITING FORECAST | H27: EU | N27: 0.8 | O27: 0.8 | P27: 0.8 | Q27: 0.8 | X27: PV | Y27: =VLOOKUP(Conso_FCST[[#This Row],[Country]],'Country-Region'!A:D,4,0) -> Benelux Region | Z27: =VLOOKUP(Conso_FCST[[#This Row],[Country]],'Country-Region'!A:D,3,0) -> BeNeLux | AA27: =IFERROR(VLOOKUP(Conso_FCST[[#This Row],[Model name]],Prod_T6[[#All],[Model name]:[Product Conso]],2,0),"exclude") -> HSM-NT48-HH
A28: Belgium | B28: Reno.Energy SA | D28: TCL_C2_Series | E28: HSM-BE54-HD485/490 | F28: 3 - Negotiation | G28: AWAITING FORECAST | H28: EU | N28: 0.4 | O28: 0.4 | P28: 0.4 | Q28: 0.4 | X28: PV | Y28: =VLOOKUP(Conso_FCST[[#This Row],[Country]],'Country-Region'!A:D,4,0) -> Benelux Region | Z28: =VLOOKUP(Conso_FCST[[#This Row],[Country]],'Country-Region'!A:D,3,0) -> BeNeLux | AA28: =IFERROR(VLOOKUP(Conso_FCST[[#This Row],[Model name]],Prod_T6[[#All],[Model name]:[Product Conso]],2,0),"exclude") -> HSM-BE54-HD
A29: Belgium | B29: ECOSTAL SPRL | D29: SPR_BC | E29: SPR-BE54-HD490/495 | F29: 4 - BAFO | G29: AWAITING FORECAST | H29: Offshore | P29: 0.4 | Q29: 0.4 | X29: PV | Y29: =VLOOKUP(Conso_FCST[[#This Row],[Country]],'Country-Region'!A:D,4,0) -> Benelux Region | Z29: =VLOOKUP(Conso_FCST[[#This Row],[Country]],'Country-Region'!A:D,3,0) -> BeNeLux | AA29: =IFERROR(VLOOKUP(Conso_FCST[[#This Row],[Model name]],Prod_T6[[#All],[Model name]:[Product Conso]],2,0),"exclude") -> SPR-BE54-HD
A30: Belgium | B30: ECOSTAL SPRL | D30: TCL_T5_Pro | E30: HSM-NT66-GH 640/645 | F30: 4 - BAFO | G30: AWAITING FORECAST | H30: Offshore | O30: 0.4 | P30: 0.4 | Q30: 0.4 | X30: PV | Y30: =VLOOKUP(Conso_FCST[[#This Row],[Country]],'Country-Region'!A:D,4,0) -> Benelux Region | Z30: =VLOOKUP(Conso_FCST[[#This Row],[Country]],'Country-Region'!A:D,3,0) -> BeNeLux | AA30: =IFERROR(VLOOKUP(Conso_FCST[[#This Row],[Model name]],Prod_T6[[#All],[Model name]:[Product Conso]],2,0),"exclude") -> HSM-NT66-GH
A31: Belgium | B31: ECOSTAL SPRL | C31: Romain | D31: TCL_T_Class | E31: HSM-ND66-GK725 | F31: 6 - Won | G31: WON | H31: Offshore | N31: 5.7 | X31: PV | Y31: =VLOOKUP(Conso_FCST[[#This Row],[Country]],'Country-Region'!A:D,4,0) -> Benelux Region | Z31: =VLOOKUP(Conso_FCST[[#This Row],[Country]],'Country-Region'!A:D,3,0) -> BeNeLux | AA31: =IFERROR(VLOOKUP(Conso_FCST[[#This Row],[Model name]],Prod_T6[[#All],[Model name]:[Product Conso]],2,0),"exclude") -> HSM-ND66-GK
A32: Belgium | B32: SOLAR DEPOT SARL. | C32: Romain | D32: TCL_T_Class | E32: HSM-ND48-DR455 | F32: 7 - Booked | G32: AWAITING ORDER | H32: EU | I32: 0.42 | X32: PV | Y32: =VLOOKUP(Conso_FCST[[#This Row],[Country]],'Country-Region'!A:D,4,0) -> Benelux Region | Z32: =VLOOKUP(Conso_FCST[[#This Row],[Country]],'Country-Region'!A:D,3,0) -> BeNeLux | AA32: =IFERROR(VLOOKUP(Conso_FCST[[#This Row],[Model name]],Prod_T6[[#All],[Model name]:[Product Conso]],2,0),"exclude") -> HSM-ND48-DR
A33: Belgium | B33: ECOSTAL SPRL | D33: TCL_T_Class | E33: HSM-ND54-DR505 | F33: 7 - Booked | G33: Q1 PROJECT | H33: Offshore | J33: 1.2 | K33: 1.2 | X33: PV | Y33: =VLOOKUP(Conso_FCST[[#This Row],[Country]],'Country-Region'!A:D,4,0) -> Benelux Region | Z33: =VLOOKUP(Conso_FCST[[#This Row],[Country]],'Country-Region'!A:D,3,0) -> BeNeLux | AA33: =IFERROR(VLOOKUP(Conso_FCST[[#This Row],[Model name]],Prod_T6[[#All],[Model name]:[Product Conso]],2,0),"exclude") -> HSM-ND54-DR
A34: Belgium | B34: ECOSTAL SPRL | D34: TCL_C2_Series | E34: HSM-BE54-HD485/490 | F34: 3 - Negotiation | G34: AWAITING FORECAST | H34: offshore | O34: 1 | P34: 1 | Q34: 1 | X34: PV | Y34: =VLOOKUP(Conso_FCST[[#This Row],[Country]],'Country-Region'!A:D,4,0) -> Benelux Region | Z34: =VLOOKUP(Conso_FCST[[#This Row],[Country]],'Country-Region'!A:D,3,0) -> BeNeLux | AA34: =IFERROR(VLOOKUP(Conso_FCST[[#This Row],[Model name]],Prod_T6[[#All],[Model name]:[Product Conso]],2,0),"exclude") -> HSM-BE54-HD
A35: Belgium | B35: ECOSTAL SPRL | D35: TCL_T5_Pro | E35: HSM-NT48-HH 465/470-Black | F35: 7 - Booked | G35: BOOKED | H35: Offshore | M35: 2 | N35: 2 | O35: 2 | X35: PV | Y35: =VLOOKUP(Conso_FCST[[#This Row],[Country]],'Country-Region'!A:D,4,0) -> Benelux Region | Z35: =VLOOKUP(Conso_FCST[[#This Row],[Country]],'Country-Region'!A:D,3,0) -> BeNeLux | AA35: =IFERROR(VLOOKUP(Conso_FCST[[#This Row],[Model name]],Prod_T6[[#All],[Model name]:[Product Conso]],2,0),"exclude") -> HSM-NT48-HH
A36: Belgium | B36: ECOSTAL SPRL | D36: TCL_T_Class | E36: HSM-ND48-DR450 | F36: 7 - Booked | G36: H1-2026 | H36: Offshore | J36: 0.42 | K36: 4 | L36: 2.3 | X36: PV | Y36: =VLOOKUP(Conso_FCST[[#This Row],[Country]],'Country-Region'!A:D,4,0) -> Benelux Region | Z36: =VLOOKUP(Conso_FCST[[#This Row],[Country]],'Country-Region'!A:D,3,0) -> BeNeLux | AA36: =IFERROR(VLOOKUP(Conso_FCST[[#This Row],[Model name]],Prod_T6[[#All],[Model name]:[Product Conso]],2,0),"exclude") -> HSM-ND48-DR
A37: Belgium | B37: SOLAR DEPOT SARL. | D37: TCL_T5_Pro | E37: HSM-NT48-HH 465/470-Black | F37: 7 - Booked | H37: EU | X37: PV | Y37: =VLOOKUP(Conso_FCST[[#This Row],[Country]],'Country-Region'!A:D,4,0) -> Benelux Region | Z37: =VLOOKUP(Conso_FCST[[#This Row],[Country]],'Country-Region'!A:D,3,0) -> BeNeLux | AA37: =IFERROR(VLOOKUP(Conso_FCST[[#This Row],[Model name]],Prod_T6[[#All],[Model name]:[Product Conso]],2,0),"exclude") -> HSM-NT48-HH
A38: Bulgaria | B38: New customer | D38: TCL_T_Class | E38: HSM-ND66-GR625 | F38: 2 - Initial offer | G38: 2 containers CIF Thessaloniki | H38: Offshore | L38: 0.8 | X38: PV | Y38: =VLOOKUP(Conso_FCST[[#This Row],[Country]],'Country-Region'!A:D,4,0) -> Southern Europe Region | Z38: =VLOOKUP(Conso_FCST[[#This Row],[Country]],'Country-Region'!A:D,3,0) -> Southern Europe Region | AA38: =IFERROR(VLOOKUP(Conso_FCST[[#This Row],[Model name]],Prod_T6[[#All],[Model name]:[Product Conso]],2,0),"exclude") -> HSM-ND66-GR
A39: Bulgaria | B39: New customer | D39: TCL_T_Class | E39: HSM-ND48-DR450 | F39: 2 - Initial offer | G39: 2 containers CIF Thessaloniki | H39: Offshore | L39: 0.8 | X39: PV | Y39: =VLOOKUP(Conso_FCST[[#This Row],[Country]],'Country-Region'!A:D,4,0) -> Southern Europe Region | Z39: =VLOOKUP(Conso_FCST[[#This Row],[Country]],'Country-Region'!A:D,3,0) -> Southern Europe Region | AA39: =IFERROR(VLOOKUP(Conso_FCST[[#This Row],[Model name]],Prod_T6[[#All],[Model name]:[Product Conso]],2,0),"exclude") -> HSM-ND48-DR
A40: Croatia | B40: Mobis | D40: TCL_T_Class | E40: HSM-ND66-GK725 | F40: 7 - Booked | G40: FCA RTD, 3 containers | H40: Offshore | J40: 1.2 | X40: PV | Y40: =VLOOKUP(Conso_FCST[[#This Row],[Country]],'Country-Region'!A:D,4,0) -> Central and Eastern Europe Region | Z40: =VLOOKUP(Conso_FCST[[#This Row],[Country]],'Country-Region'!A:D,3,0) -> C&E EU | AA40: =IFERROR(VLOOKUP(Conso_FCST[[#This Row],[Model name]],Prod_T6[[#All],[Model name]:[Product Conso]],2,0),"exclude") -> HSM-ND66-GK
A41: Croatia | B41: Mobis | D41: TCL_T_Class | E41: HSM-ND66-GR620 | F41: 2 - Initial offer | G41: 4,9MW (11 containers) CIF Rijeka | H41: Offshore | N41: 4.9 | X41: PV | Y41: =VLOOKUP(Conso_FCST[[#This Row],[Country]],'Country-Region'!A:D,4,0) -> Central and Eastern Europe Region | Z41: =VLOOKUP(Conso_FCST[[#This Row],[Country]],'Country-Region'!A:D,3,0) -> C&E EU | AA41: =IFERROR(VLOOKUP(Conso_FCST[[#This Row],[Model name]],Prod_T6[[#All],[Model name]:[Product Conso]],2,0),"exclude") -> HSM-ND66-GR
A42: Cyprus | B42: Dracoudis | D42: TCL_T_Class | E42: HSM-ND48-DR455 | F42: 3 - Negotiation | G42: 3 containers CIF Limassol | H42: Offshore | N42: 1 | X42: PV | Y42: =VLOOKUP(Conso_FCST[[#This Row],[Country]],'Country-Region'!A:D,4,0) -> Southern Europe Region | Z42: =VLOOKUP(Conso_FCST[[#This Row],[Country]],'Country-Region'!A:D,3,0) -> Southern Europe Region | AA42: =IFERROR(VLOOKUP(Conso_FCST[[#This Row],[Model name]],Prod_T6[[#All],[Model name]:[Product Conso]],2,0),"exclude") -> HSM-ND48-DR
A43: Czech Republic | B43: Spark Invest | D43: TCL_T_Class | E43: HSM-ND66-GR620 | F43: 2 - Initial offer | G43: 5MW / delivered to Europe Q3 | H43: Offshore | M43: 5 | X43: PV | Y43: =VLOOKUP(Conso_FCST[[#This Row],[Country]],'Country-Region'!A:D,4,0) -> Central and Eastern Europe Region | Z43: =VLOOKUP(Conso_FCST[[#This Row],[Country]],'Country-Region'!A:D,3,0) -> C&E EU | AA43: =IFERROR(VLOOKUP(Conso_FCST[[#This Row],[Model name]],Prod_T6[[#All],[Model name]:[Product Conso]],2,0),"exclude") -> HSM-ND66-GR
A44: Czech Republic | B44: Solsol | D44: TCL_T_Class | E44: HSM-ND66-GK725 | F44: 2 - Initial offer | G44: 130MW of 720W - delivery Q3-Q4 price sensitive tender-low probablity | H44: Offshore | N44: 43.3 | O44: 43.3 | P44: 43.3 | X44: PV | Y44: =VLOOKUP(Conso_FCST[[#This Row],[Country]],'Country-Region'!A:D,4,0) -> Central and Eastern Europe Region | Z44: =VLOOKUP(Conso_FCST[[#This Row],[Country]],'Country-Region'!A:D,3,0) -> C&E EU | AA44: =IFERROR(VLOOKUP(Conso_FCST[[#This Row],[Model name]],Prod_T6[[#All],[Model name]:[Product Conso]],2,0),"exclude") -> HSM-ND66-GK
A45: Czech Republic | B45: Krannich | D45: SPR_P7 | E45: P7-BLK-P-515 | F45: 2 - Initial offer | G45: 1,8MW CIP Czech Rep. - lower probablity as requested TCL, not Sunpower | H45: EU | K45: 1.8 | X45: PV | Y45: =VLOOKUP(Conso_FCST[[#This Row],[Country]],'Country-Region'!A:D,4,0) -> Central and Eastern Europe Region | Z45: =VLOOKUP(Conso_FCST[[#This Row],[Country]],'Country-Region'!A:D,3,0) -> C&E EU | AA45: =IFERROR(VLOOKUP(Conso_FCST[[#This Row],[Model name]],Prod_T6[[#All],[Model name]:[Product Conso]],2,0),"exclude") -> P7 RES BLK-P
A46: Czech Republic | B46: Solsol | D46: TCL_C2_Series | E46: HSM-BD66-GR650/655 | F46: 2 - Initial offer | G46: 128MW of 650/655 | H46: Offshore | O46: 64 | P46: 64 | X46: PV | Y46: =VLOOKUP(Conso_FCST[[#This Row],[Country]],'Country-Region'!A:D,4,0) -> Central and Eastern Europe Region | Z46: =VLOOKUP(Conso_FCST[[#This Row],[Country]],'Country-Region'!A:D,3,0) -> C&E EU | AA46: =IFERROR(VLOOKUP(Conso_FCST[[#This Row],[Model name]],Prod_T6[[#All],[Model name]:[Product Conso]],2,0),"exclude") -> HSM-BE66-GD
A47: Czech Republic | B47: Solsol | D47: TCL_T_Class | E47: HSM-ND66-GK725 | F47: 2 - Initial offer | G47: 44MW of 720W ? one power bin only allowed | H47: Offshore | O47: 22 | P47: 22 | X47: PV | Y47: =VLOOKUP(Conso_FCST[[#This Row],[Country]],'Country-Region'!A:D,4,0) -> Central and Eastern Europe Region | Z47: =VLOOKUP(Conso_FCST[[#This Row],[Country]],'Country-Region'!A:D,3,0) -> C&E EU | AA47: =IFERROR(VLOOKUP(Conso_FCST[[#This Row],[Model name]],Prod_T6[[#All],[Model name]:[Product Conso]],2,0),"exclude") -> HSM-ND66-GK
A48: France | B48: Richardson | C48: Antoine | D48: TCL_T5_Pro | E48: HSM-NT48-JH 470/475 CFP-White | F48: 5 - Finalize contract | H48: EU | N48: 0.4 | O48: 0.8 | P48: 0.8 | Q48: 0.8 | X48: PV | Y48: =VLOOKUP(Conso_FCST[[#This Row],[Country]],'Country-Region'!A:D,4,0) -> France and Switzerland Region | Z48: =VLOOKUP(Conso_FCST[[#This Row],[Country]],'Country-Region'!A:D,3,0) -> France | AA48: =IFERROR(VLOOKUP(Conso_FCST[[#This Row],[Model name]],Prod_T6[[#All],[Model name]:[Product Conso]],2,0),"exclude") -> HSM-NT48-JH CFP
A49: France | B49: Voltaneo | C49: Antoine | D49: TCL_T5_Pro | E49: HSM-NT48-JH 470/475 CFP-White | F49: 5 - Finalize contract | H49: EU | N49: 0.8 | O49: 0.8 | P49: 0.8 | Q49: 0.8 | X49: PV | Y49: =VLOOKUP(Conso_FCST[[#This Row],[Country]],'Country-Region'!A:D,4,0) -> France and Switzerland Region | Z49: =VLOOKUP(Conso_FCST[[#This Row],[Country]],'Country-Region'!A:D,3,0) -> France | AA49: =IFERROR(VLOOKUP(Conso_FCST[[#This Row],[Model name]],Prod_T6[[#All],[Model name]:[Product Conso]],2,0),"exclude") -> HSM-NT48-JH CFP
A50: France | B50: NED | C50: Antoine | D50: TCL_T5_Pro | E50: HSM-NT48-JH 470/475 CFP-White | F50: 5 - Finalize contract | H50: EU | O50: 1.2 | P50: 1.2 | Q50: 1.2 | X50: PV | Y50: =VLOOKUP(Conso_FCST[[#This Row],[Country]],'Country-Region'!A:D,4,0) -> France and Switzerland Region | Z50: =VLOOKUP(Conso_FCST[[#This Row],[Country]],'Country-Region'!A:D,3,0) -> France | AA50: =IFERROR(VLOOKUP(Conso_FCST[[#This Row],[Model name]],Prod_T6[[#All],[Model name]:[Product Conso]],2,0),"exclude") -> HSM-NT48-JH CFP
A51: France | B51: ISOSSUN | C51: Antoine | D51: TCL_T5_Pro | E51: HSM-NT48-JH 470/475 CFP-White | F51: 5 - Finalize contract | H51: EU | X51: PV | Y51: =VLOOKUP(Conso_FCST[[#This Row],[Country]],'Country-Region'!A:D,4,0) -> France and Switzerland Region | Z51: =VLOOKUP(Conso_FCST[[#This Row],[Country]],'Country-Region'!A:D,3,0) -> France | AA51: =IFERROR(VLOOKUP(Conso_FCST[[#This Row],[Model name]],Prod_T6[[#All],[Model name]:[Product Conso]],2,0),"exclude") -> HSM-NT48-JH CFP
A52: France | B52: Courant Naturel | C52: Cedric | D52: TCL_T_Class | E52: HSM-ND48-DR455-CFP | F52: 2 - Initial offer | H52: EU | O52: 2 | X52: PV | Y52: =VLOOKUP(Conso_FCST[[#This Row],[Country]],'Country-Region'!A:D,4,0) -> France and Switzerland Region | Z52: =VLOOKUP(Conso_FCST[[#This Row],[Country]],'Country-Region'!A:D,3,0) -> France | AA52: =IFERROR(VLOOKUP(Conso_FCST[[#This Row],[Model name]],Prod_T6[[#All],[Model name]:[Product Conso]],2,0),"exclude") -> HSM-ND48-DR CFP
A53: France | B53: Lamazouade | C53: Cedric | D53: TCL_T5_Pro | E53: HSM-NT48-GH 470/475 CFP-White | F53: 2 - Initial offer | G53: LAMAZOUADE // CFP // 465Wp/470Wp // Need BIF for 1.5MW | H53: EU | N53: 3 | X53: PV | Y53: =VLOOKUP(Conso_FCST[[#This Row],[Country]],'Country-Region'!A:D,4,0) -> France and Switzerland Region | Z53: =VLOOKUP(Conso_FCST[[#This Row],[Country]],'Country-Region'!A:D,3,0) -> France | AA53: =IFERROR(VLOOKUP(Conso_FCST[[#This Row],[Model name]],Prod_T6[[#All],[Model name]:[Product Conso]],2,0),"exclude") -> HSM-NT48-GH CFP
A54: France | B54: Richardson | C54: Antoine | D54: ESS_SPR_Gen2 | E54: 1P 6KW 1*5KWH | F54: 5 - Finalize contract | H54: EU | X54: ESS | Y54: =VLOOKUP(Conso_FCST[[#This Row],[Country]],'Country-Region'!A:D,4,0) -> France and Switzerland Region | Z54: =VLOOKUP(Conso_FCST[[#This Row],[Country]],'Country-Region'!A:D,3,0) -> France | AA54: =IFERROR(VLOOKUP(Conso_FCST[[#This Row],[Model name]],Prod_T6[[#All],[Model name]:[Product Conso]],2,0),"exclude") -> Gen2 1P 6kw
A55: France | B55: Ecostal | C55: Antoine | D55: TCL_T5_Pro | E55: HSM-NT48-JH 470/475 CFP-White | F55: 5 - Finalize contract | H55: Offshore | O55: 0.8 | P55: 1.2 | Q55: 1.2 | X55: PV | Y55: =VLOOKUP(Conso_FCST[[#This Row],[Country]],'Country-Region'!A:D,4,0) -> France and Switzerland Region | Z55: =VLOOKUP(Conso_FCST[[#This Row],[Country]],'Country-Region'!A:D,3,0) -> France | AA55: =IFERROR(VLOOKUP(Conso_FCST[[#This Row],[Model name]],Prod_T6[[#All],[Model name]:[Product Conso]],2,0),"exclude") -> HSM-NT48-JH CFP
A56: France | B56: APPROSUD ENVIRONNEMENT | C56: Antoine | D56: TCL_T5_Pro | E56: HSM-NT48-JH 470/475 CFP-White | F56: 5 - Finalize contract | H56: EU | O56: 0.8 | P56: 1.2 | Q56: 1.2 | X56: PV | Y56: =VLOOKUP(Conso_FCST[[#This Row],[Country]],'Country-Region'!A:D,4,0) -> France and Switzerland Region | Z56: =VLOOKUP(Conso_FCST[[#This Row],[Country]],'Country-Region'!A:D,3,0) -> France | AA56: =IFERROR(VLOOKUP(Conso_FCST[[#This Row],[Model name]],Prod_T6[[#All],[Model name]:[Product Conso]],2,0),"exclude") -> HSM-NT48-JH CFP
A57: France | B57: Richardson | C57: Antoine | D57: TCL_T_Class | E57: HSM-ND54-DR500 | F57: 5 - Finalize contract | H57: EU | I57: 0.4 | J57: 0.8 | K57: 0.8 | L57: 0.8 | M57: 0.4 | N57: 0.4 | O57: 0.4 | P57: 0.4 | Q57: 0.4 | X57: PV | Y57: =VLOOKUP(Conso_FCST[[#This Row],[Country]],'Country-Region'!A:D,4,0) -> France and Switzerland Region | Z57: =VLOOKUP(Conso_FCST[[#This Row],[Country]],'Country-Region'!A:D,3,0) -> France | AA57: =IFERROR(VLOOKUP(Conso_FCST[[#This Row],[Model name]],Prod_T6[[#All],[Model name]:[Product Conso]],2,0),"exclude") -> HSM-ND54-DR
A58: France | B58: LARIVIERE | C58: Antoine | D58: TCL_T_Class | E58: HSM-ND48-DR450-CFP | F58: 5 - Finalize contract | H58: Offshore | I58: 0.8 | J58: 0.8 | K58: 0.8 | L58: 0.8 | M58: 0.8 | N58: 0 | O58: 0 | P58: 0 | Q58: 0 | X58: PV | Y58: =VLOOKUP(Conso_FCST[[#This Row],[Country]],'Country-Region'!A:D,4,0) -> France and Switzerland Region | Z58: =VLOOKUP(Conso_FCST[[#This Row],[Country]],'Country-Region'!A:D,3,0) -> France | AA58: =IFERROR(VLOOKUP(Conso_FCST[[#This Row],[Model name]],Prod_T6[[#All],[Model name]:[Product Conso]],2,0),"exclude") -> HSM-ND48-DR CFP
A59: France | B59: LARIVIERE | C59: Antoine | D59: ESS_SPR_Gen2 | E59: 1P 6KW 1*5KWH | F59: 5 - Finalize contract | H59: EU | X59: ESS | Y59: =VLOOKUP(Conso_FCST[[#This Row],[Country]],'Country-Region'!A:D,4,0) -> France and Switzerland Region | Z59: =VLOOKUP(Conso_FCST[[#This Row],[Country]],'Country-Region'!A:D,3,0) -> France | AA59: =IFERROR(VLOOKUP(Conso_FCST[[#This Row],[Model name]],Prod_T6[[#All],[Model name]:[Product Conso]],2,0),"exclude") -> Gen2 1P 6kw
A60: France | B60: Richardson | C60: Antoine | D60: TCL_T_Class | E60: HSM-ND48-DR450-CFP | F60: 5 - Finalize contract | H60: EU | I60: 0.4 | J60: 0.4 | K60: 0.4 | L60: 0.4 | M60: 0.4 | N60: 0 | O60: 0 | P60: 0 | Q60: 0 | X60: PV | Y60: =VLOOKUP(Conso_FCST[[#This Row],[Country]],'Country-Region'!A:D,4,0) -> France and Switzerland Region | Z60: =VLOOKUP(Conso_FCST[[#This Row],[Country]],'Country-Region'!A:D,3,0) -> France | AA60: =IFERROR(VLOOKUP(Conso_FCST[[#This Row],[Model name]],Prod_T6[[#All],[Model name]:[Product Conso]],2,0),"exclude") -> HSM-ND48-DR CFP
A61: France | B61: Voltaneo | C61: Antoine | D61: TCL_T_Class | E61: HSM-ND54-DR500 | F61: 5 - Finalize contract | H61: EU | I61: 1.2 | J61: 1.2 | K61: 2 | L61: 2 | M61: 0.2 | N61: 0.2 | O61: 0.4 | P61: 0.4 | Q61: 0.4 | X61: PV | Y61: =VLOOKUP(Conso_FCST[[#This Row],[Country]],'Country-Region'!A:D,4,0) -> France and Switzerland Region | Z61: =VLOOKUP(Conso_FCST[[#This Row],[Country]],'Country-Region'!A:D,3,0) -> France | AA61: =IFERROR(VLOOKUP(Conso_FCST[[#This Row],[Model name]],Prod_T6[[#All],[Model name]:[Product Conso]],2,0),"exclude") -> HSM-ND54-DR
A62: France | B62: Voltaneo | C62: Antoine | D62: TCL_T_Class | E62: HSM-ND54-DR500-CFP | F62: 5 - Finalize contract | H62: EU | I62: 0.8 | J62: 0.8 | K62: 0.8 | L62: 0.8 | O62: 0.4 | P62: 0.4 | Q62: 0.4 | X62: PV | Y62: =VLOOKUP(Conso_FCST[[#This Row],[Country]],'Country-Region'!A:D,4,0) -> France and Switzerland Region | Z62: =VLOOKUP(Conso_FCST[[#This Row],[Country]],'Country-Region'!A:D,3,0) -> France | AA62: =IFERROR(VLOOKUP(Conso_FCST[[#This Row],[Model name]],Prod_T6[[#All],[Model name]:[Product Conso]],2,0),"exclude") -> HSM-ND54-DR CFP
A63: France | B63: Voltaneo | C63: Antoine | D63: TCL_T_Class | E63: HSM-ND48-DR450-CFP | F63: 5 - Finalize contract | H63: EU | I63: 1.2 | J63: 1 | K63: 1 | L63: 1.2 | M63: 0.4 | N63: 0 | O63: 0 | P63: 0 | Q63: 0 | X63: PV | Y63: =VLOOKUP(Conso_FCST[[#This Row],[Country]],'Country-Region'!A:D,4,0) -> France and Switzerland Region | Z63: =VLOOKUP(Conso_FCST[[#This Row],[Country]],'Country-Region'!A:D,3,0) -> France | AA63: =IFERROR(VLOOKUP(Conso_FCST[[#This Row],[Model name]],Prod_T6[[#All],[Model name]:[Product Conso]],2,0),"exclude") -> HSM-ND48-DR CFP
A64: France | B64: NED | C64: Antoine | D64: TCL_T_Class | E64: HSM-ND54-DR500 | F64: 5 - Finalize contract | H64: EU | I64: 1.2 | J64: 0.8 | K64: 0.8 | L64: 0.8 | M64: 0.4 | N64: 0.4 | O64: 0.4 | P64: 0.4 | Q64: 0.4 | X64: PV | Y64: =VLOOKUP(Conso_FCST[[#This Row],[Country]],'Country-Region'!A:D,4,0) -> France and Switzerland Region | Z64: =VLOOKUP(Conso_FCST[[#This Row],[Country]],'Country-Region'!A:D,3,0) -> France | AA64: =IFERROR(VLOOKUP(Conso_FCST[[#This Row],[Model name]],Prod_T6[[#All],[Model name]:[Product Conso]],2,0),"exclude") -> HSM-ND54-DR
A65: France | B65: Voltaneo | D65: ESS_SPR_Gen2 | E65: 3P 13KW 2*5KWH | F65: 5 - Finalize contract | H65: EU | I65: 4 | J65: 0 | K65: 0 | L65: 0 | M65: 2 | N65: 2 | O65: 2 | P65: 2 | Q65: 2 | X65: ESS | Y65: =VLOOKUP(Conso_FCST[[#This Row],[Country]],'Country-Region'!A:D,4,0) -> France and Switzerland Region | Z65: =VLOOKUP(Conso_FCST[[#This Row],[Country]],'Country-Region'!A:D,3,0) -> France | AA65: =IFERROR(VLOOKUP(Conso_FCST[[#This Row],[Model name]],Prod_T6[[#All],[Model name]:[Product Conso]],2,0),"exclude") -> Gen2 3P 13kw
A66: France | B66: Voltaneo | C66: Antoine | D66: ESS_SPR_Gen2 | E66: 3P 10KW 2*5KWH | F66: 5 - Finalize contract | H66: EU | I66: 4 | J66: 0 | K66: 0 | L66: 8 | M66: 0 | N66: 3 | O66: 3 | P66: 3 | Q66: 3 | X66: ESS | Y66: =VLOOKUP(Conso_FCST[[#This Row],[Country]],'Country-Region'!A:D,4,0) -> France and Switzerland Region | Z66: =VLOOKUP(Conso_FCST[[#This Row],[Country]],'Country-Region'!A:D,3,0) -> France | AA66: =IFERROR(VLOOKUP(Conso_FCST[[#This Row],[Model name]],Prod_T6[[#All],[Model name]:[Product Conso]],2,0),"exclude") -> Gen2 3P 10kw
A67: France | B67: LARIVIERE | C67: Antoine | D67: TCL_T_Class | E67: HSM-ND54-DR500 | F67: 5 - Finalize contract | H67: EU | I67: 0.8 | J67: 0.8 | K67: 0.8 | L67: 0.8 | M67: 0.4 | N67: 0.4 | O67: 0.4 | P67: 0.4 | Q67: 0.4 | X67: PV | Y67: =VLOOKUP(Conso_FCST[[#This Row],[Country]],'Country-Region'!A:D,4,0) -> France and Switzerland Region | Z67: =VLOOKUP(Conso_FCST[[#This Row],[Country]],'Country-Region'!A:D,3,0) -> France | AA67: =IFERROR(VLOOKUP(Conso_FCST[[#This Row],[Model name]],Prod_T6[[#All],[Model name]:[Product Conso]],2,0),"exclude") -> HSM-ND54-DR
A68: France | B68: New Customer / Balance of others customers FR | C68: Cedric / Systeko | D68: TCL_T5_Pro | E68: HSM-NT66-GH 645/650 CFP | F68: 2 - Initial offer | G68: SUNZIL // CFP // Price point 0,115€/Wc | H68: EU | N68: 3 | X68: PV | Y68: =VLOOKUP(Conso_FCST[[#This Row],[Country]],'Country-Region'!A:D,4,0) -> France and Switzerland Region | Z68: =VLOOKUP(Conso_FCST[[#This Row],[Country]],'Country-Region'!A:D,3,0) -> France | AA68: =IFERROR(VLOOKUP(Conso_FCST[[#This Row],[Model name]],Prod_T6[[#All],[Model name]:[Product Conso]],2,0),"exclude") -> HSM-NT66-GH CFP
A69: France | B69: New Customer / Balance of others customers FR | C69: Seb / GreenPower | D69: TCL_C2_Series | E69: HSM-BE54-JD485/490-CFP | F69: 2 - Initial offer | G69: WeWise // CFP // 470Wp/475Wp, CFP | H69: EU | R69: 5 | S69: 5 | T69: 5 | U69: 5 | V69: 5 | W69: 5 | X69: PV | Y69: =VLOOKUP(Conso_FCST[[#This Row],[Country]],'Country-Region'!A:D,4,0) -> France and Switzerland Region | Z69: =VLOOKUP(Conso_FCST[[#This Row],[Country]],'Country-Region'!A:D,3,0) -> France | AA69: =IFERROR(VLOOKUP(Conso_FCST[[#This Row],[Model name]],Prod_T6[[#All],[Model name]:[Product Conso]],2,0),"exclude") -> HSM-BE54-JD CFP
A70: France | B70: New Customer / Balance of others customers FR | C70: Seb / Synapsun | D70: TCL_C2_Series | E70: HSM-BE54-JD485/490-CFP | F70: 2 - Initial offer | G70: WeWise // CFP // 470Wp/475Wp, CFP | H70: EU | R70: 4 | S70: 4 | T70: 4 | U70: 4 | V70: 4 | W70: 4 | X70: PV | Y70: =VLOOKUP(Conso_FCST[[#This Row],[Country]],'Country-Region'!A:D,4,0) -> France and Switzerland Region | Z70: =VLOOKUP(Conso_FCST[[#This Row],[Country]],'Country-Region'!A:D,3,0) -> France | AA70: =IFERROR(VLOOKUP(Conso_FCST[[#This Row],[Model name]],Prod_T6[[#All],[Model name]:[Product Conso]],2,0),"exclude") -> HSM-BE54-JD CFP
A71: France | B71: LARIVIERE | C71: Antoine | D71: TCL_T5_Pro | E71: HSM-NT48-JH 470/475 CFP-White | F71: 5 - Finalize contract | H71: EU | O71: 0.8 | X71: PV | Y71: =VLOOKUP(Conso_FCST[[#This Row],[Country]],'Country-Region'!A:D,4,0) -> France and Switzerland Region | Z71: =VLOOKUP(Conso_FCST[[#This Row],[Country]],'Country-Region'!A:D,3,0) -> France | AA71: =IFERROR(VLOOKUP(Conso_FCST[[#This Row],[Model name]],Prod_T6[[#All],[Model name]:[Product Conso]],2,0),"exclude") -> HSM-NT48-JH CFP
A72: France | B72: divers | C72: Antoine | D72: ESS_SPR_Gen2 | E72: addtl 5KWH BAT | F72: 5 - Finalize contract | H72: EU | L72: 80 | M72: 60 | N72: 120 | O72: 30 | P72: 30 | Q72: 30 | X72: ESS | Y72: =VLOOKUP(Conso_FCST[[#This Row],[Country]],'Country-Region'!A:D,4,0) -> France and Switzerland Region | Z72: =VLOOKUP(Conso_FCST[[#This Row],[Country]],'Country-Region'!A:D,3,0) -> France | AA72: =IFERROR(VLOOKUP(Conso_FCST[[#This Row],[Model name]],Prod_T6[[#All],[Model name]:[Product Conso]],2,0),"exclude") -> Gen2 BAT 5kWh
A73: France | B73: Voltaneo | C73: Romain / Solstice HD | D73: ESS_TCL_CI | E73: BlueArk X5-50K-100 | F73: 1 - Lead qualification | H73: EU | Q73: 8 | X73: ESS | Y73: =VLOOKUP(Conso_FCST[[#This Row],[Country]],'Country-Region'!A:D,4,0) -> France and Switzerland Region | Z73: =VLOOKUP(Conso_FCST[[#This Row],[Country]],'Country-Region'!A:D,3,0) -> France | AA73: =IFERROR(VLOOKUP(Conso_FCST[[#This Row],[Model name]],Prod_T6[[#All],[Model name]:[Product Conso]],2,0),"exclude") -> BlueArk X5-50K-100
A74: France | B74: NED | C74: Patrice / LTE | D74: ESS_TCL_CI | E74: BlueArk X5-50K-100 | F74: 1 - Lead qualification | H74: EU | Q74: 1 | X74: ESS | Y74: =VLOOKUP(Conso_FCST[[#This Row],[Country]],'Country-Region'!A:D,4,0) -> France and Switzerland Region | Z74: =VLOOKUP(Conso_FCST[[#This Row],[Country]],'Country-Region'!A:D,3,0) -> France | AA74: =IFERROR(VLOOKUP(Conso_FCST[[#This Row],[Model name]],Prod_T6[[#All],[Model name]:[Product Conso]],2,0),"exclude") -> BlueArk X5-50K-100
A75: France | B75: Voltaneo | C75: Julien / Rolhion | D75: ESS_TCL_CI | E75: BlueArk X5-50K-100 | F75: 1 - Lead qualification | H75: EU | Q75: 1 | X75: ESS | Y75: =VLOOKUP(Conso_FCST[[#This Row],[Country]],'Country-Region'!A:D,4,0) -> France and Switzerland Region | Z75: =VLOOKUP(Conso_FCST[[#This Row],[Country]],'Country-Region'!A:D,3,0) -> France | AA75: =IFERROR(VLOOKUP(Conso_FCST[[#This Row],[Model name]],Prod_T6[[#All],[Model name]:[Product Conso]],2,0),"exclude") -> BlueArk X5-50K-100
A76: France | B76: Ecostal | C76: Cedric / Gallium | D76: ESS_TCL_CI | E76: BlueArk X5-50K-100 | F76: 1 - Lead qualification | H76: EU | Q76: 1 | X76: ESS | Y76: =VLOOKUP(Conso_FCST[[#This Row],[Country]],'Country-Region'!A:D,4,0) -> France and Switzerland Region | Z76: =VLOOKUP(Conso_FCST[[#This Row],[Country]],'Country-Region'!A:D,3,0) -> France | AA76: =IFERROR(VLOOKUP(Conso_FCST[[#This Row],[Model name]],Prod_T6[[#All],[Model name]:[Product Conso]],2,0),"exclude") -> BlueArk X5-50K-100
A77: France | B77: Dubecq et Fils Sarl | C77: Cedric | D77: ESS_TCL_CI | E77: BlueArk X5-50K-100 | F77: 2 - Initial offer | H77: EU | Q77: 2 | X77: ESS | Y77: =VLOOKUP(Conso_FCST[[#This Row],[Country]],'Country-Region'!A:D,4,0) -> France and Switzerland Region | Z77: =VLOOKUP(Conso_FCST[[#This Row],[Country]],'Country-Region'!A:D,3,0) -> France | AA77: =IFERROR(VLOOKUP(Conso_FCST[[#This Row],[Model name]],Prod_T6[[#All],[Model name]:[Product Conso]],2,0),"exclude") -> BlueArk X5-50K-100
A78: France | B78: New Customer / Balance of others customers FR | C78: Sebastien/ Mexens Q2 27 | D78: ESS_TCL_CI | E78: BlueArk W10-125K-261 | F78: 1 - Lead qualification | H78: EU | R78: 3 | S78: 3 | X78: ESS | Y78: =VLOOKUP(Conso_FCST[[#This Row],[Country]],'Country-Region'!A:D,4,0) -> France and Switzerland Region | Z78: =VLOOKUP(Conso_FCST[[#This Row],[Country]],'Country-Region'!A:D,3,0) -> France | AA78: =IFERROR(VLOOKUP(Conso_FCST[[#This Row],[Model name]],Prod_T6[[#All],[Model name]:[Product Conso]],2,0),"exclude") -> BlueArk W10-125K-261
A79: France | B79: New Customer / Balance of others customers FR | C79: Sebastien/ GreenYellow | D79: ESS_TCL_CI | E79: BlueArk W10-125K-261 | F79: 1 - Lead qualification | H79: EU | S79: 10 | T79: 10 | U79: 10 | V79: 10 | W79: 10 | X79: ESS | Y79: =VLOOKUP(Conso_FCST[[#This Row],[Country]],'Country-Region'!A:D,4,0) -> France and Switzerland Region | Z79: =VLOOKUP(Conso_FCST[[#This Row],[Country]],'Country-Region'!A:D,3,0) -> France | AA79: =IFERROR(VLOOKUP(Conso_FCST[[#This Row],[Model name]],Prod_T6[[#All],[Model name]:[Product Conso]],2,0),"exclude") -> BlueArk W10-125K-261
A80: France | B80: Ecostal | C80: Patrice / Tokeim | D80: ESS_TCL_CI | E80: BlueArk X5-50K-100 | F80: 2 - Initial offer | H80: EU | N80: 1 | X80: ESS | Y80: =VLOOKUP(Conso_FCST[[#This Row],[Country]],'Country-Region'!A:D,4,0) -> France and Switzerland Region | Z80: =VLOOKUP(Conso_FCST[[#This Row],[Country]],'Country-Region'!A:D,3,0) -> France | AA80: =IFERROR(VLOOKUP(Conso_FCST[[#This Row],[Model name]],Prod_T6[[#All],[Model name]:[Product Conso]],2,0),"exclude") -> BlueArk X5-50K-100
A81: France | B81: NED | C81: Patrice / Solair3tech | D81: ESS_TCL_CI | E81: BlueArk X5-50K-100 | F81: 3 - Negotiation | H81: EU | N81: 1 | X81: ESS | Y81: =VLOOKUP(Conso_FCST[[#This Row],[Country]],'Country-Region'!A:D,4,0) -> France and Switzerland Region | Z81: =VLOOKUP(Conso_FCST[[#This Row],[Country]],'Country-Region'!A:D,3,0) -> France | AA81: =IFERROR(VLOOKUP(Conso_FCST[[#This Row],[Model name]],Prod_T6[[#All],[Model name]:[Product Conso]],2,0),"exclude") -> BlueArk X5-50K-100
A82: France | B82: Voltaneo | C82: Romain / Solstice HD | D82: ESS_TCL_CI | E82: BlueArk X5-50K-100 | F82: 5 - Finalize contract | H82: EU | M82: 1 | X82: ESS | Y82: =VLOOKUP(Conso_FCST[[#This Row],[Country]],'Country-Region'!A:D,4,0) -> France and Switzerland Region | Z82: =VLOOKUP(Conso_FCST[[#This Row],[Country]],'Country-Region'!A:D,3,0) -> France | AA82: =IFERROR(VLOOKUP(Conso_FCST[[#This Row],[Model name]],Prod_T6[[#All],[Model name]:[Product Conso]],2,0),"exclude") -> BlueArk X5-50K-100
A83: France | B83: New Customer / Balance of others customers FR | C83: Patrice / LTDS unit | D83: ESS_TCL_CI | E83: BlueArk X5-50K-100 | F83: 6 - Won | H83: EU | N83: 1 | X83: ESS | Y83: =VLOOKUP(Conso_FCST[[#This Row],[Country]],'Country-Region'!A:D,4,0) -> France and Switzerland Region | Z83: =VLOOKUP(Conso_FCST[[#This Row],[Country]],'Country-Region'!A:D,3,0) -> France | AA83: =IFERROR(VLOOKUP(Conso_FCST[[#This Row],[Model name]],Prod_T6[[#All],[Model name]:[Product Conso]],2,0),"exclude") -> BlueArk X5-50K-100
A84: France | B84: New Customer / Balance of others customers FR | C84: Cedric / AgriSolarPv | D84: TCL_T5_Pro | E84: HSM-NT48-JH 470/475 CFP-White | F84: 2 - Initial offer | H84: EU | O84: 5 | X84: PV | Y84: =VLOOKUP(Conso_FCST[[#This Row],[Country]],'Country-Region'!A:D,4,0) -> France and Switzerland Region | Z84: =VLOOKUP(Conso_FCST[[#This Row],[Country]],'Country-Region'!A:D,3,0) -> France | AA84: =IFERROR(VLOOKUP(Conso_FCST[[#This Row],[Model name]],Prod_T6[[#All],[Model name]:[Product Conso]],2,0),"exclude") -> HSM-NT48-JH CFP
A85: France | B85: Maisolia | C85: Cedric | D85: ESS_SPR_Gen2 | E85: 3P 13KW 2*5KWH | F85: 5 - Finalize contract | H85: EU | K85: 3 | O85: 4 | X85: ESS | Y85: =VLOOKUP(Conso_FCST[[#This Row],[Country]],'Country-Region'!A:D,4,0) -> France and Switzerland Region | Z85: =VLOOKUP(Conso_FCST[[#This Row],[Country]],'Country-Region'!A:D,3,0) -> France | AA85: =IFERROR(VLOOKUP(Conso_FCST[[#This Row],[Model name]],Prod_T6[[#All],[Model name]:[Product Conso]],2,0),"exclude") -> Gen2 3P 13kw
A86: France | B86: Maisolia | C86: Cedric | D86: ESS_SPR_Gen2 | E86: 1P 8KW 1*5KWH | F86: 5 - Finalize contract | H86: EU | J86: 4 | M86: 4 | O86: 4 | P86: 4 | X86: ESS | Y86: =VLOOKUP(Conso_FCST[[#This Row],[Country]],'Country-Region'!A:D,4,0) -> France and Switzerland Region | Z86: =VLOOKUP(Conso_FCST[[#This Row],[Country]],'Country-Region'!A:D,3,0) -> France | AA86: =IFERROR(VLOOKUP(Conso_FCST[[#This Row],[Model name]],Prod_T6[[#All],[Model name]:[Product Conso]],2,0),"exclude") -> Gen2 1P 8kw
A87: France | B87: New Customer / Balance of others customers FR | C87: Seb / Reden | D87: TCL_T5_Pro | E87: HSM-NT48-GH 470/475 CFP-White | F87: 2 - Initial offer | G87: GreenYellow // CFP // 470Wp BIF, CFP | H87: EU | S87: 4 | X87: PV | Y87: =VLOOKUP(Conso_FCST[[#This Row],[Country]],'Country-Region'!A:D,4,0) -> France and Switzerland Region | Z87: =VLOOKUP(Conso_FCST[[#This Row],[Country]],'Country-Region'!A:D,3,0) -> France | AA87: =IFERROR(VLOOKUP(Conso_FCST[[#This Row],[Model name]],Prod_T6[[#All],[Model name]:[Product Conso]],2,0),"exclude") -> HSM-NT48-GH CFP
A88: France | B88: New Customer / Balance of others customers FR | C88: Seb / Ineo Equans | D88: TCL_T5_Pro | E88: HSM-NT48-GH 470/475 CFP-White | F88: 2 - Initial offer | G88: GreenYellow // CFP // 470Wp BIF, CFP | H88: EU | R88: 4 | X88: PV | Y88: =VLOOKUP(Conso_FCST[[#This Row],[Country]],'Country-Region'!A:D,4,0) -> France and Switzerland Region | Z88: =VLOOKUP(Conso_FCST[[#This Row],[Country]],'Country-Region'!A:D,3,0) -> France | AA88: =IFERROR(VLOOKUP(Conso_FCST[[#This Row],[Model name]],Prod_T6[[#All],[Model name]:[Product Conso]],2,0),"exclude") -> HSM-NT48-GH CFP
A89: France | B89: Voltaneo | C89: Antoine | D89: ESS_SPR_Gen2 | E89: 1P 10KW 1*5KWH | F89: 5 - Finalize contract | H89: EU | I89: 8 | J89: 0 | K89: 0 | L89: 8 | N89: 5 | O89: 5 | P89: 5 | Q89: 5 | X89: ESS | Y89: =VLOOKUP(Conso_FCST[[#This Row],[Country]],'Country-Region'!A:D,4,0) -> France and Switzerland Region | Z89: =VLOOKUP(Conso_FCST[[#This Row],[Country]],'Country-Region'!A:D,3,0) -> France | AA89: =IFERROR(VLOOKUP(Conso_FCST[[#This Row],[Model name]],Prod_T6[[#All],[Model name]:[Product Conso]],2,0),"exclude") -> Gen2 1P 10kw
A90: France | B90: New Customer / Balance of others customers FR | C90: Cedric | D90: TCL_T5_Pro | E90: HSM-NT48-JH 470/475 CFP-White | F90: 2 - Initial offer | G90: WEGREEN // CFP // 465Wp/470Wp | H90: EU | Q90: 5 | X90: PV | Y90: =VLOOKUP(Conso_FCST[[#This Row],[Country]],'Country-Region'!A:D,4,0) -> France and Switzerland Region | Z90: =VLOOKUP(Conso_FCST[[#This Row],[Country]],'Country-Region'!A:D,3,0) -> France | AA90: =IFERROR(VLOOKUP(Conso_FCST[[#This Row],[Model name]],Prod_T6[[#All],[Model name]:[Product Conso]],2,0),"exclude") -> HSM-NT48-JH CFP
A91: France | B91: APPROSUD ENVIRONNEMENT | C91: Antoine | D91: ESS_SPR_Gen2 | E91: 1P 6kW 1*5kWh | F91: 5 - Finalize contract | H91: EU | I91: 8 | J91: 0 | K91: 0 | L91: 16 | M91: 12 | N91: 8 | O91: 8 | P91: 8 | Q91: 8 | X91: ESS | Y91: =VLOOKUP(Conso_FCST[[#This Row],[Country]],'Country-Region'!A:D,4,0) -> France and Switzerland Region | Z91: =VLOOKUP(Conso_FCST[[#This Row],[Country]],'Country-Region'!A:D,3,0) -> France | AA91: =IFERROR(VLOOKUP(Conso_FCST[[#This Row],[Model name]],Prod_T6[[#All],[Model name]:[Product Conso]],2,0),"exclude") -> Gen2 1P 6kw
A92: France | B92: Voltaneo | C92: Antoine | D92: ESS_SPR_Gen2 | E92: 1P 6KW 1*5KWH | F92: 5 - Finalize contract | H92: EU | I92: 12 | J92: 0 | K92: 0 | L92: 40 | M92: 8 | N92: 25 | O92: 25 | P92: 25 | Q92: 25 | X92: ESS | Y92: =VLOOKUP(Conso_FCST[[#This Row],[Country]],'Country-Region'!A:D,4,0) -> France and Switzerland Region | Z92: =VLOOKUP(Conso_FCST[[#This Row],[Country]],'Country-Region'!A:D,3,0) -> France | AA92: =IFERROR(VLOOKUP(Conso_FCST[[#This Row],[Model name]],Prod_T6[[#All],[Model name]:[Product Conso]],2,0),"exclude") -> Gen2 1P 6kw
A93: France | B93: NED | C93: Antoine | D93: TCL_T_Class | E93: HSM-ND48-DR450-CFP | F93: 5 - Finalize contract | H93: EU | I93: 0.8 | J93: 0.4 | K93: 0.4 | L93: 0.8 | M93: 0.4 | N93: 0 | O93: 0 | P93: 0 | Q93: 0 | X93: PV | Y93: =VLOOKUP(Conso_FCST[[#This Row],[Country]],'Country-Region'!A:D,4,0) -> France and Switzerland Region | Z93: =VLOOKUP(Conso_FCST[[#This Row],[Country]],'Country-Region'!A:D,3,0) -> France | AA93: =IFERROR(VLOOKUP(Conso_FCST[[#This Row],[Model name]],Prod_T6[[#All],[Model name]:[Product Conso]],2,0),"exclude") -> HSM-ND48-DR CFP
A94: France | B94: LARIVIERE | C94: Antoine | D94: SPR_P7 | E94: P7-BLK-P-510 | F94: 5 - Finalize contract | H94: EU | N94: 0.2 | O94: 0.1 | P94: 0.1 | Q94: 0.1 | X94: PV | Y94: =VLOOKUP(Conso_FCST[[#This Row],[Country]],'Country-Region'!A:D,4,0) -> France and Switzerland Region | Z94: =VLOOKUP(Conso_FCST[[#This Row],[Country]],'Country-Region'!A:D,3,0) -> France | AA94: =IFERROR(VLOOKUP(Conso_FCST[[#This Row],[Model name]],Prod_T6[[#All],[Model name]:[Product Conso]],2,0),"exclude") -> P7 RES BLK-P
A95: France | B95: Richardson | C95: Antoine | D95: SPR_P7 | E95: P7-BLK-P-510 | F95: 5 - Finalize contract | H95: EU | I95: 0.4 | J95: 0 | K95: 0.4 | L95: 0.4 | M95: 0.2 | N95: 0.2 | O95: 0.1 | P95: 0.1 | Q95: 0.1 | X95: PV | Y95: =VLOOKUP(Conso_FCST[[#This Row],[Country]],'Country-Region'!A:D,4,0) -> France and Switzerland Region | Z95: =VLOOKUP(Conso_FCST[[#This Row],[Country]],'Country-Region'!A:D,3,0) -> France | AA95: =IFERROR(VLOOKUP(Conso_FCST[[#This Row],[Model name]],Prod_T6[[#All],[Model name]:[Product Conso]],2,0),"exclude") -> P7 RES BLK-P
A96: France | B96: Ecostal | C96: Antoine | D96: TCL_T_Class | E96: HSM-ND54-DR505 | F96: 6 - Finalize contract | H96: EU | N96: 0.87 | O96: 0.87 | P96: 0.87 | Q96: 0.87 | X96: PV | Y96: =VLOOKUP(Conso_FCST[[#This Row],[Country]],'Country-Region'!A:D,4,0) -> France and Switzerland Region | Z96: =VLOOKUP(Conso_FCST[[#This Row],[Country]],'Country-Region'!A:D,3,0) -> France | AA96: =IFERROR(VLOOKUP(Conso_FCST[[#This Row],[Model name]],Prod_T6[[#All],[Model name]:[Product Conso]],2,0),"exclude") -> HSM-ND54-DR
A97: France | B97: Voltaneo | C97: Antoine | D97: SPR_P7 | E97: P7-BLK-P-510 | F97: 5 - Finalize contract | H97: EU | I97: 0.6 | J97: 0 | K97: 0.6 | L97: 0.6 | M97: 0.6 | N97: 0.6 | O97: 0.4 | P97: 0.4 | Q97: 0.4 | X97: PV | Y97: =VLOOKUP(Conso_FCST[[#This Row],[Country]],'Country-Region'!A:D,4,0) -> France and Switzerland Region | Z97: =VLOOKUP(Conso_FCST[[#This Row],[Country]],'Country-Region'!A:D,3,0) -> France | AA97: =IFERROR(VLOOKUP(Conso_FCST[[#This Row],[Model name]],Prod_T6[[#All],[Model name]:[Product Conso]],2,0),"exclude") -> P7 RES BLK-P
A98: France | B98: Voltaneo | C98: Antoine | D98: SPR_P7 | E98: P7-COM-S CFP | F98: 5 - Finalize contract | H98: EU | I98: 0.3 | J98: 0.3 | K98: 0.5 | O98: 0 | P98: 0 | Q98: 0 | X98: PV | Y98: =VLOOKUP(Conso_FCST[[#This Row],[Country]],'Country-Region'!A:D,4,0) -> France and Switzerland Region | Z98: =VLOOKUP(Conso_FCST[[#This Row],[Country]],'Country-Region'!A:D,3,0) -> France | AA98: =IFERROR(VLOOKUP(Conso_FCST[[#This Row],[Model name]],Prod_T6[[#All],[Model name]:[Product Conso]],2,0),"exclude") -> P7 COM S BF CFP
A99: France | B99: VIVARAIS ENERGIES SARL | D99: SPR_P7 | E99: P7-COM-S CFP | F99: 5 - Finalize contract | H99: EU | J99: 0.3 | X99: PV | Y99: =VLOOKUP(Conso_FCST[[#This Row],[Country]],'Country-Region'!A:D,4,0) -> France and Switzerland Region | Z99: =VLOOKUP(Conso_FCST[[#This Row],[Country]],'Country-Region'!A:D,3,0) -> France | AA99: =IFERROR(VLOOKUP(Conso_FCST[[#This Row],[Model name]],Prod_T6[[#All],[Model name]:[Product Conso]],2,0),"exclude") -> P7 COM S BF CFP
A100: France | B100: REXEL FRANCE SAS | D100: SPR_P7 | E100: P7-COM-S CFP | F100: 5 - Finalize contract | H100: EU | I100: 0.3 | J100: 0.3 | K100: 0.3 | X100: PV | Y100: =VLOOKUP(Conso_FCST[[#This Row],[Country]],'Country-Region'!A:D,4,0) -> France and Switzerland Region | Z100: =VLOOKUP(Conso_FCST[[#This Row],[Country]],'Country-Region'!A:D,3,0) -> France | AA100: =IFERROR(VLOOKUP(Conso_FCST[[#This Row],[Model name]],Prod_T6[[#All],[Model name]:[Product Conso]],2,0),"exclude") -> P7 COM S BF CFP
...

Sheet Country-Region
A1: Country | B1: Market Country | C1: Sales Team | D1: Region
A2: Belgium | B2: Belgium | C2: BeNeLux | D2: Benelux Region
A3: Netherlands | B3: Netherlands | C3: BeNeLux | D3: Benelux Region
A4: Czech Republic | B4: C&E EU | C4: C&E EU | D4: Central and Eastern Europe Region
A5: CZ | B5: C&E EU | C5: C&E EU | D5: Central and Eastern Europe Region
A6: Emerging_Markets | B6: C&E EU | C6: C&E EU | D6: Central and Eastern Europe Region
A7: Hungary | B7: C&E EU | C7: C&E EU | D7: Central and Eastern Europe Region
A8: Lithuania | B8: C&E EU | C8: C&E EU | D8: Central and Eastern Europe Region
A9: Poland | B9: C&E EU | C9: C&E EU | D9: Central and Eastern Europe Region
A10: Poland-Jan | B10: C&E EU | C10: C&E EU | D10: Central and Eastern Europe Region
A11: Romania | B11: C&E EU | C11: C&E EU | D11: Central and Eastern Europe Region
A12: Lithiania | B12: C&E EU | C12: C&E EU | D12: Central and Eastern Europe Region
... A33: UK | B33: UK | C33: UK | D33: UK Region

Sheet Instructions
B2: Go to FCST Tab and fill out each line as follow :
B4: Fill information about Customer
B5: 1- Select Country in Column A
B6: 2- Pick customer from List available. It is adjusted per country selected. (see column B)
B7: 3- Other informations (Tier, CL, etc) will populate automatically
B8: 4- For new customer or unspecified, select "New Customer / Balance of others customer"
B9: 5- if critical conditions to meet, use column K "Comments" to specify
B12: Fill information about Product
B13: 1- Select Product Line to differentiate between BTP, Sunpower P7, TCL Solar, etc. It will narrow list of model name. (column D)
B14: 2- Select Model Name in column E
B15: 3- Other customers will be populated automatically
B18: Fill information of Quantity
... B33: Cells to use are in light blue

Sheet Nordic
E1: TCL_T_Class | G1: Category | J1: mw/qty | K1: mw/qty | L1: mw/qty | M1: mw/qty | N1: mw/qty | O1: mw/qty | P1: mw/qty | Q1: mw/qty | R1: mw/qty | S1: mw/qty | T1: mw/qty | U1: mw/qty | V1: mw/qty | W1: mw/qty | X1: mw/qty | Y1: mw/qty | Z1: mw/qty | AA1: mw/qty | AB1: mw/qty | AC1: mw/qty
G2: ESS | J2: {=SUMPRODUCT((Nordics[Product Category]=$G2)*SUBTOTAL(109,OFFSET(INDEX(Nordics[26M04],1),ROW(Nordics[26M04])-MIN(ROW(Nordics[26M04])),0,1)))} -> 0 | K2: {=SUMPRODUCT((Nordics[Product Category]=$G2)*SUBTOTAL(109,OFFSET(INDEX(Nordics[26M05],1),ROW(Nordics[26M05])-MIN(ROW(Nordics[26M05])),0,1)))} -> 0 | L2: {=SUMPRODUCT((Nordics[Product Category]=$G2)*SUBTOTAL(109,OFFSET(INDEX(Nordics[26M06],1),ROW(Nordics[26M06])-MIN(ROW(Nordics[26M06])),0,1)))} -> 0 | M2: {=SUMPRODUCT((Nordics[Product Category]=$G2)*SUBTOTAL(109,OFFSET(INDEX(Nordics[26M07],1),ROW(Nordics[26M07])-MIN(ROW(Nordics[26M07])),0,1)))} -> 0 | N2: {=SUMPRODUCT((Nordics[Product Category]=$G2)*SUBTOTAL(109,OFFSET(INDEX(Nordics[26M08],1),ROW(Nordics[26M08])-MIN(ROW(Nordics[26M08])),0,1)))} -> 0 | O2: {=SUMPRODUCT((Nordics[Product Category]=$G2)*SUBTOTAL(109,OFFSET(INDEX(Nordics[26M09],1),ROW(Nordics[26M09])-MIN(ROW(Nordics[26M09])),0,1)))} -> 2 | P2: {=SUMPRODUCT((Nordics[Product Category]=$G2)*SUBTOTAL(109,OFFSET(INDEX(Nordics[26M10],1),ROW(Nordics[26M10])-MIN(ROW(Nordics[26M10])),0,1)))} -> 0 | Q2: {=SUMPRODUCT((Nordics[Product Category]=$G2)*SUBTOTAL(109,OFFSET(INDEX(Nordics[26M11],1),ROW(Nordics[26M11])-MIN(ROW(Nordics[26M11])),0,1)))} -> 0 | R2: {=SUMPRODUCT((Nordics[Product Category]=$G2)*SUBTOTAL(109,OFFSET(INDEX(Nordics[26M12],1),ROW(Nordics[26M12])-MIN(ROW(Nordics[26M12])),0,1)))} -> 50 | S2: {=SUMPRODUCT((Nordics[Product Category]=$G2)*SUBTOTAL(109,OFFSET(INDEX(Nordics[26Q2],1),ROW(Nordics[26Q2])-MIN(ROW(Nordics[26Q2])),0,1)))} -> 0 | T2: {=SUMPRODUCT((Nordics[Product Category]=$G2)*SUBTOTAL(109,OFFSET(INDEX(Nordics[26Q3],1),ROW(Nordics[26Q3])-MIN(ROW(Nordics[26Q3])),0,1)))} -> 2 | U2: {=SUMPRODUCT((Nordics[Product Category]=$G2)*SUBTOTAL(109,OFFSET(INDEX(Nordics[26Q4],1),ROW(Nordics[26Q4])-MIN(ROW(Nordics[26Q4])),0,1)))} -> 50 | V2: {=SUMPRODUCT((Nordics[Product Category]=$G2)*SUBTOTAL(109,OFFSET(INDEX(Nordics[27M01],1),ROW(Nordics[27M01])-MIN(ROW(Nordics[27M01])),0,1)))} -> 0 | W2: {=SUMPRODUCT((Nordics[Product Category]=$G2)*SUBTOTAL(109,OFFSET(INDEX(Nordics[27M02],1),ROW(Nordics[27M02])-MIN(ROW(Nordics[27M02])),0,1)))} -> 0 | X2: {=SUMPRODUCT((Nordics[Product Category]=$G2)*SUBTOTAL(109,OFFSET(INDEX(Nordics[27M03],1),ROW(Nordics[27M03])-MIN(ROW(Nordics[27M03])),0,1)))} -> 0 | Y2: {=SUMPRODUCT((Nordics[Product Category]=$G2)*SUBTOTAL(109,OFFSET(INDEX(Nordics[27M04],1),ROW(Nordics[27M04])-MIN(ROW(Nordics[27M04])),0,1)))} -> 0 | Z2: {=SUMPRODUCT((Nordics[Product Category]=$G2)*SUBTOTAL(109,OFFSET(INDEX(Nordics[27M05],1),ROW(Nordics[27M05])-MIN(ROW(Nordics[27M05])),0,1)))} -> 0 | AA2: {=SUMPRODUCT((Nordics[Product Category]=$G2)*SUBTOTAL(109,OFFSET(INDEX(Nordics[27M06],1),ROW(Nordics[27M06])-MIN(ROW(Nordics[27M06])),0,1)))} -> 0 | AB2: {=SUMPRODUCT((Nordics[Product Category]=$G2)*SUBTOTAL(109,OFFSET(INDEX(Nordics[27Q1],1),ROW(Nordics[27Q1])-MIN(ROW(Nordics[27Q1])),0,1)))} -> 0 | AC2: {=SUMPRODUCT((Nordics[Product Category]=$G2)*SUBTOTAL(109,OFFSET(INDEX(Nordics[27Q2],1),ROW(Nordics[27Q2])-MIN(ROW(Nordics[27Q2])),0,1)))} -> 0
G3: HP | J3: {=SUMPRODUCT((Nordics[Product Category]=$G3)*SUBTOTAL(109,OFFSET(INDEX(Nordics[26M04],1),ROW(Nordics[26M04])-MIN(ROW(Nordics[26M04])),0,1)))} -> 0 | K3: {=SUMPRODUCT((Nordics[Product Category]=$G3)*SUBTOTAL(109,OFFSET(INDEX(Nordics[26M05],1),ROW(Nordics[26M05])-MIN(ROW(Nordics[26M05])),0,1)))} -> 0 | L3: {=SUMPRODUCT((Nordics[Product Category]=$G3)*SUBTOTAL(109,OFFSET(INDEX(Nordics[26M06],1),ROW(Nordics[26M06])-MIN(ROW(Nordics[26M06])),0,1)))} -> 0 | M3: {=SUMPRODUCT((Nordics[Product Category]=$G3)*SUBTOTAL(109,OFFSET(INDEX(Nordics[26M07],1),ROW(Nordics[26M07])-MIN(ROW(Nordics[26M07])),0,1)))} -> 2 | N3: {=SUMPRODUCT((Nordics[Product Category]=$G3)*SUBTOTAL(109,OFFSET(INDEX(Nordics[26M08],1),ROW(Nordics[26M08])-MIN(ROW(Nordics[26M08])),0,1)))} -> 0 | O3: {=SUMPRODUCT((Nordics[Product Category]=$G3)*SUBTOTAL(109,OFFSET(INDEX(Nordics[26M09],1),ROW(Nordics[26M09])-MIN(ROW(Nordics[26M09])),0,1)))} -> 0 | P3: {=SUMPRODUCT((Nordics[Product Category]=$G3)*SUBTOTAL(109,OFFSET(INDEX(Nordics[26M10],1),ROW(Nordics[26M10])-MIN(ROW(Nordics[26M10])),0,1)))} -> 0 | Q3: {=SUMPRODUCT((Nordics[Product Category]=$G3)*SUBTOTAL(109,OFFSET(INDEX(Nordics[26M11],1),ROW(Nordics[26M11])-MIN(ROW(Nordics[26M11])),0,1)))} -> 0 | R3: {=SUMPRODUCT((Nordics[Product Category]=$G3)*SUBTOTAL(109,OFFSET(INDEX(Nordics[26M12],1),ROW(Nordics[26M12])-MIN(ROW(Nordics[26M12])),0,1)))} -> 0 | S3: {=SUMPRODUCT((Nordics[Product Category]=$G3)*SUBTOTAL(109,OFFSET(INDEX(Nordics[26Q2],1),ROW(Nordics[26Q2])-MIN(ROW(Nordics[26Q2])),0,1)))} -> 0 | T3: {=SUMPRODUCT((Nordics[Product Category]=$G3)*SUBTOTAL(109,OFFSET(INDEX(Nordics[26Q3],1),ROW(Nordics[26Q3])-MIN(ROW(Nordics[26Q3])),0,1)))} -> 2 | U3: {=SUMPRODUCT((Nordics[Product Category]=$G3)*SUBTOTAL(109,OFFSET(INDEX(Nordics[26Q4],1),ROW(Nordics[26Q4])-MIN(ROW(Nordics[26Q4])),0,1)))} -> 0 | V3: {=SUMPRODUCT((Nordics[Product Category]=$G3)*SUBTOTAL(109,OFFSET(INDEX(Nordics[27M01],1),ROW(Nordics[27M01])-MIN(ROW(Nordics[27M01])),0,1)))} -> 0 | W3: {=SUMPRODUCT((Nordics[Product Category]=$G3)*SUBTOTAL(109,OFFSET(INDEX(Nordics[27M02],1),ROW(Nordics[27M02])-MIN(ROW(Nordics[27M02])),0,1)))} -> 0 | X3: {=SUMPRODUCT((Nordics[Product Category]=$G3)*SUBTOTAL(109,OFFSET(INDEX(Nordics[27M03],1),ROW(Nordics[27M03])-MIN(ROW(Nordics[27M03])),0,1)))} -> 0 | Y3: {=SUMPRODUCT((Nordics[Product Category]=$G3)*SUBTOTAL(109,OFFSET(INDEX(Nordics[27M04],1),ROW(Nordics[27M04])-MIN(ROW(Nordics[27M04])),0,1)))} -> 0 | Z3: {=SUMPRODUCT((Nordics[Product Category]=$G3)*SUBTOTAL(109,OFFSET(INDEX(Nordics[27M05],1),ROW(Nordics[27M05])-MIN(ROW(Nordics[27M05])),0,1)))} -> 0 | AA3: {=SUMPRODUCT((Nordics[Product Category]=$G3)*SUBTOTAL(109,OFFSET(INDEX(Nordics[27M06],1),ROW(Nordics[27M06])-MIN(ROW(Nordics[27M06])),0,1)))} -> 0 | AB3: {=SUMPRODUCT((Nordics[Product Category]=$G3)*SUBTOTAL(109,OFFSET(INDEX(Nordics[27Q1],1),ROW(Nordics[27Q1])-MIN(ROW(Nordics[27Q1])),0,1)))} -> 0 | AC3: {=SUMPRODUCT((Nordics[Product Category]=$G3)*SUBTOTAL(109,OFFSET(INDEX(Nordics[27Q2],1),ROW(Nordics[27Q2])-MIN(ROW(Nordics[27Q2])),0,1)))} -> 0
G4: PV | J4: {=SUMPRODUCT((Nordics[Product Category]=$G4)*SUBTOTAL(109,OFFSET(INDEX(Nordics[26M04],1),ROW(Nordics[26M04])-MIN(ROW(Nordics[26M04])),0,1)))} -> 6.4 | K4: {=SUMPRODUCT((Nordics[Product Category]=$G4)*SUBTOTAL(109,OFFSET(INDEX(Nordics[26M05],1),ROW(Nordics[26M05])-MIN(ROW(Nordics[26M05])),0,1)))} -> 6 | L4: {=SUMPRODUCT((Nordics[Product Category]=$G4)*SUBTOTAL(109,OFFSET(INDEX(Nordics[26M06],1),ROW(Nordics[26M06])-MIN(ROW(Nordics[26M06])),0,1)))} -> 8.4 | M4: {=SUMPRODUCT((Nordics[Product Category]=$G4)*SUBTOTAL(109,OFFSET(INDEX(Nordics[26M07],1),ROW(Nordics[26M07])-MIN(ROW(Nordics[26M07])),0,1)))} -> 6.3 | N4: {=SUMPRODUCT((Nordics[Product Category]=$G4)*SUBTOTAL(109,OFFSET(INDEX(Nordics[26M08],1),ROW(Nordics[26M08])-MIN(ROW(Nordics[26M08])),0,1)))} -> 7.5 | O4: {=SUMPRODUCT((Nordics[Product Category]=$G4)*SUBTOTAL(109,OFFSET(INDEX(Nordics[26M09],1),ROW(Nordics[26M09])-MIN(ROW(Nordics[26M09])),0,1)))} -> 58.3 | P4: {=SUMPRODUCT((Nordics[Product Category]=$G4)*SUBTOTAL(109,OFFSET(INDEX(Nordics[26M10],1),ROW(Nordics[26M10])-MIN(ROW(Nordics[26M10])),0,1)))} -> 20.6 | Q4: {=SUMPRODUCT((Nordics[Product Category]=$G4)*SUBTOTAL(109,OFFSET(INDEX(Nordics[26M11],1),ROW(Nordics[26M11])-MIN(ROW(Nordics[26M11])),0,1)))} -> 16 | R4: {=SUMPRODUCT((Nordics[Product Category]=$G4)*SUBTOTAL(109,OFFSET(INDEX(Nordics[26M12],1),ROW(Nordics[26M12])-MIN(ROW(Nordics[26M12])),0,1)))} -> 4 | S4: {=SUMPRODUCT((Nordics[Product Category]=$G4)*SUBTOTAL(109,OFFSET(INDEX(Nordics[26Q2],1),ROW(Nordics[26Q2])-MIN(ROW(Nordics[26Q2])),0,1)))} -> 16.95 | T4: {=SUMPRODUCT((Nordics[Product Category]=$G4)*SUBTOTAL(109,OFFSET(INDEX(Nordics[26Q3],1),ROW(Nordics[26Q3])-MIN(ROW(Nordics[26Q3])),0,1)))} -> 72.1 | U4: {=SUMPRODUCT((Nordics[Product Category]=$G4)*SUBTOTAL(109,OFFSET(INDEX(Nordics[26Q4],1),ROW(Nordics[26Q4])-MIN(ROW(Nordics[26Q4])),0,1)))} -> 40.6 | V4: {=SUMPRODUCT((Nordics[Product Category]=$G4)*SUBTOTAL(109,OFFSET(INDEX(Nordics[27M01],1),ROW(Nordics[27M01])-MIN(ROW(Nordics[27M01])),0,1)))} -> 0 | W4: {=SUMPRODUCT((Nordics[Product Category]=$G4)*SUBTOTAL(109,OFFSET(INDEX(Nordics[27M02],1),ROW(Nordics[27M02])-MIN(ROW(Nordics[27M02])),0,1)))} -> 0 | X4: {=SUMPRODUCT((Nordics[Product Category]=$G4)*SUBTOTAL(109,OFFSET(INDEX(Nordics[27M03],1),ROW(Nordics[27M03])-MIN(ROW(Nordics[27M03])),0,1)))} -> 0 | Y4: {=SUMPRODUCT((Nordics[Product Category]=$G4)*SUBTOTAL(109,OFFSET(INDEX(Nordics[27M04],1),ROW(Nordics[27M04])-MIN(ROW(Nordics[27M04])),0,1)))} -> 0 | Z4: {=SUMPRODUCT((Nordics[Product Category]=$G4)*SUBTOTAL(109,OFFSET(INDEX(Nordics[27M05],1),ROW(Nordics[27M05])-MIN(ROW(Nordics[27M05])),0,1)))} -> 0 | AA4: {=SUMPRODUCT((Nordics[Product Category]=$G4)*SUBTOTAL(109,OFFSET(INDEX(Nordics[27M06],1),ROW(Nordics[27M06])-MIN(ROW(Nordics[27M06])),0,1)))} -> 0 | AB4: {=SUMPRODUCT((Nordics[Product Category]=$G4)*SUBTOTAL(109,OFFSET(INDEX(Nordics[27Q1],1),ROW(Nordics[27Q1])-MIN(ROW(Nordics[27Q1])),0,1)))} -> 0 | AC4: {=SUMPRODUCT((Nordics[Product Category]=$G4)*SUBTOTAL(109,OFFSET(INDEX(Nordics[27Q2],1),ROW(Nordics[27Q2])-MIN(ROW(Nordics[27Q2])),0,1)))} -> 0
A5: Country | B5: Customer name | C5: RSM | D5: Brand | E5: Product Line | F5: Model name | G5: Stage | H5: Comments (Deal Breaker, spec/requirements, etc) | I5: Supply Chain | J5: 26M04 | K5: 26M05 | L5: 26M06 | M5: 26M07 | N5: 26M08 | O5: 26M09 | P5: 26M10 | Q5: 26M11 | R5: 26M12 | S5: 26Q2 | T5: 26Q3 | U5: 26Q4 | V5: 27M01 | W5: 27M02 | X5: 27M03 | Y5: 27M04 | Z5: 27M05 | AA5: 27M06 | AB5: 27Q1 | AC5: 27Q2 | AD5: Only 2026? | AE5: Product Category
A6: Nordic | B6: Nordic Sun Danmark A/S | C6: Filip Abrahamsson | D6: =VLOOKUP(Nordics[[#This Row],[Product Line]],Prod_T6[],5,0) -> TCL | E6: TCL_T_Class | F6: HSM-ND66-GR620 | G6: 4 - BAFO | H6: Asking for DDP price, Possible Caroline LI, Q2-Q3 Must win - Delayed Q4 due to permits----Long Cable---27Q1 | I6: Offshore/EU? | P6: 7 | Q6: 6 | T6: =SUM(Nordics[[#This Row],[26M07]:[26M09]]) -> 0 | U6: =SUM(Nordics[[#This Row],[26M10]:[26M12]]) -> 13 | AB6: =SUM(Nordics[[#This Row],[27M01]:[27M03]]) -> 0 | AC6: =SUM(Nordics[[#This Row],[27M04]:[27M06]]) -> 0 | AD6: =IF(SUM(Nordics[[#This Row],[26Q2]:[26Q4]])+SUM(Nordics[[#This Row],[27Q1]:[27Q2]])=0,"No FSCT",IF(AND(SUM(Nordics[[#This Row],[26Q2]:[26Q4]])>0,SUM(Nordics[[#This Row],[27Q1]:[27Q2]])=0),"YES","NO")) -> YES | AE6: =VLOOKUP(Nordics[[#This Row],[Product Line]],Prod_T6[],4,0) -> PV | AH6: {=Nordics[Stage]} -> 4 - BAFO
A7: Nordic | B7: Sunny Future AB | C7: Filip Abrahamsson | D7: =VLOOKUP(Nordics[[#This Row],[Product Line]],Prod_T6[],5,0) -> Sunpower | E7: SPR_M_Class | F7: SPR-BE54-DC480 | G7: 7 - Booked | H7: Upgrade to 485 or 480 | I7: EU | K7: 0.2 | S7: =SUM(Nordics[[#This Row],[26M04]:[26M06]]) -> 0.2 | T7: =SUM(Nordics[[#This Row],[26M07]:[26M09]]) -> 0 | U7: =SUM(Nordics[[#This Row],[26M10]:[26M12]]) -> 0 | AB7: =SUM(Nordics[[#This Row],[27M01]:[27M03]]) -> 0 | AC7: =SUM(Nordics[[#This Row],[27M04]:[27M06]]) -> 0 | AD7: =IF(SUM(Nordics[[#This Row],[26Q2]:[26Q4]])+SUM(Nordics[[#This Row],[27Q1]:[27Q2]])=0,"No FSCT",IF(AND(SUM(Nordics[[#This Row],[26Q2]:[26Q4]])>0,SUM(Nordics[[#This Row],[27Q1]:[27Q2]])=0),"YES","NO")) -> YES | AE7: =VLOOKUP(Nordics[[#This Row],[Product Line]],Prod_T6[],4,0) -> PV | AH7: 7 - Booked
A8: Nordic | B8: Solcellespesialisten AS | C8: Filip Abrahamsson | D8: =VLOOKUP(Nordics[[#This Row],[Product Line]],Prod_T6[],5,0) -> Sunpower | E8: SPR_P7 | F8: P7-BLK-P-510 | G8: 0 - Lost | H8: BANKRUPT Reactivation - Special project in portable mounting system EPD! required module can be changed, partner with Nordic Sun 20 MW. MAX 206 cm | I8: Bankrupt | S8: =SUM(Nordics[[#This Row],[26M04]:[26M06]]) -> 0 | T8: =SUM(Nordics[[#This Row],[26M07]:[26M09]]) -> 0 | U8: =SUM(Nordics[[#This Row],[26M10]:[26M12]]) -> 0 | AB8: =SUM(Nordics[[#This Row],[27M01]:[27M03]]) -> 0 | AC8: =SUM(Nordics[[#This Row],[27M04]:[27M06]]) -> 0 | AD8: =IF(SUM(Nordics[[#This Row],[26Q2]:[26Q4]])+SUM(Nordics[[#This Row],[27Q1]:[27Q2]])=0,"No FSCT",IF(AND(SUM(Nordics[[#This Row],[26Q2]:[26Q4]])>0,SUM(Nordics[[#This Row],[27Q1]:[27Q2]])=0),"YES","NO")) -> No FSCT | AE8: =VLOOKUP(Nordics[[#This Row],[Product Line]],Prod_T6[],4,0) -> PV | AH8: 0 - Lost
A9: Nordic | B9: Pareto Alternative investments | C9: Filip Abrahamsson | D9: =VLOOKUP(Nordics[[#This Row],[Product Line]],Prod_T6[],5,0) -> TCL | E9: TCL_T5_Pro | F9: HSM-NT66-GH 640/645 - T5_Pro_L_PP | G9: 1 - Lead qualification | H9: New C&I Norway, compete with AIKO | I9: Offshore | O9: 2 | S9: =SUM(Nordics[[#This Row],[26M04]:[26M06]]) -> 0 | T9: =SUM(Nordics[[#This Row],[26M07]:[26M09]]) -> 2 | U9: =SUM(Nordics[[#This Row],[26M10]:[26M12]]) -> 0 | AB9: =SUM(Nordics[[#This Row],[27M01]:[27M03]]) -> 0 | AC9: =SUM(Nordics[[#This Row],[27M04]:[27M06]]) -> 0 | AD9: =IF(SUM(Nordics[[#This Row],[26Q2]:[26Q4]])+SUM(Nordics[[#This Row],[27Q1]:[27Q2]])=0,"No FSCT",IF(AND(SUM(Nordics[[#This Row],[26Q2]:[26Q4]])>0,SUM(Nordics[[#This Row],[27Q1]:[27Q2]])=0),"YES","NO")) -> YES | AE9: =VLOOKUP(Nordics[[#This Row],[Product Line]],Prod_T6[],4,0) -> PV | AH9: 1 - Lead qualification
A10: Nordic | B10: Nordic Sun Danmark A/S | C10: Filip Abrahamsson | D10: =VLOOKUP(Nordics[[#This Row],[Product Line]],Prod_T6[],5,0) -> TCL | E10: TCL_T_Class | F10: HSM-ND66-GR620 | G10: 4 - BAFO | H10: C&I 10 Containers | I10: Offshore | J10: 2 | S10: =SUM(Nordics[[#This Row],[26M04]:[26M06]]) -> 2 | T10: =SUM(Nordics[[#This Row],[26M07]:[26M09]]) -> 0 | U10: =SUM(Nordics[[#This Row],[26M10]:[26M12]]) -> 0 | AB10: =SUM(Nordics[[#This Row],[27M01]:[27M03]]) -> 0 | AC10: =SUM(Nordics[[#This Row],[27M04]:[27M06]]) -> 0 | AD10: =IF(SUM(Nordics[[#This Row],[26Q2]:[26Q4]])+SUM(Nordics[[#This Row],[27Q1]:[27Q2]])=0,"No FSCT",IF(AND(SUM(Nordics[[#This Row],[26Q2]:[26Q4]])>0,SUM(Nordics[[#This Row],[27Q1]:[27Q2]])=0),"YES","NO")) -> YES | AE10: =VLOOKUP(Nordics[[#This Row],[Product Line]],Prod_T6[],4,0) -> PV | AH10: 4 - BAFO
A11: Nordic | B11: New Customer / Balance of others customers NO | D11: =VLOOKUP(Nordics[[#This Row],[Product Line]],Prod_T6[],5,0) -> TCL | E11: TCL_T_Class | F11: HSM-ND48-DR455 | G11: 6 - Won | I11: Offshore | J11: 2.4 | S11: =SUM(Nordics[[#This Row],[26M04]:[26M06]]) -> 2.4 | T11: =SUM(Nordics[[#This Row],[26M07]:[26M09]]) -> 0 | U11: =SUM(Nordics[[#This Row],[26M10]:[26M12]]) -> 0 | AB11: =SUM(Nordics[[#This Row],[27M01]:[27M03]]) -> 0 | AC11: =SUM(Nordics[[#This Row],[27M04]:[27M06]]) -> 0 | AD11: =IF(SUM(Nordics[[#This Row],[26Q2]:[26Q4]])+SUM(Nordics[[#This Row],[27Q1]:[27Q2]])=0,"No FSCT",IF(AND(SUM(Nordics[[#This Row],[26Q2]:[26Q4]])>0,SUM(Nordics[[#This Row],[27Q1]:[27Q2]])=0),"YES","NO")) -> YES | AE11: =VLOOKUP(Nordics[[#This Row],[Product Line]],Prod_T6[],4,0) -> PV | AH11: 6 - Won
A12: Nordic | B12: New Customer / Balance of others customers NO | D12: =VLOOKUP(Nordics[[#This Row],[Product Line]],Prod_T6[],5,0) -> TCL | E12: TCL_T_Class | F12: HSM-ND54-DR505 | G12: 6 - Won | I12: Offshore | J12: 2 | T12: =SUM(Nordics[[#This Row],[26M07]:[26M09]]) -> 0 | U12: =SUM(Nordics[[#This Row],[26M10]:[26M12]]) -> 0 | AB12: =SUM(Nordics[[#This Row],[27M01]:[27M03]]) -> 0 | AC12: =SUM(Nordics[[#This Row],[27M04]:[27M06]]) -> 0 | AD12: =IF(SUM(Nordics[[#This Row],[26Q2]:[26Q4]])+SUM(Nordics[[#This Row],[27Q1]:[27Q2]])=0,"No FSCT",IF(AND(SUM(Nordics[[#This Row],[26Q2]:[26Q4]])>0,SUM(Nordics[[#This Row],[27Q1]:[27Q2]])=0),"YES","NO")) -> No FSCT | AE12: =VLOOKUP(Nordics[[#This Row],[Product Line]],Prod_T6[],4,0) -> PV | AH12: 6 - Won
A13: Nordic | B13: Rexel Sweden | D13: =VLOOKUP(Nordics[[#This Row],[Product Line]],Prod_T6[],5,0) -> TCL | E13: TCL_T_Class | F13: HSM-ND48-DR455 | G13: 3 - Negotiation | H13: Placement for Q2 | I13: EU | K13: 2 | L13: 2 | N13: 1 | O13: 1 | S13: =SUM(Nordics[[#This Row],[26M04]:[26M06]]) -> 4 | T13: =SUM(Nordics[[#This Row],[26M07]:[26M09]]) -> 2 | U13: =SUM(Nordics[[#This Row],[26M10]:[26M12]]) -> 0 | AB13: =SUM(Nordics[[#This Row],[27M01]:[27M03]]) -> 0 | AC13: =SUM(Nordics[[#This Row],[27M04]:[27M06]]) -> 0 | AD13: =IF(SUM(Nordics[[#This Row],[26Q2]:[26Q4]])+SUM(Nordics[[#This Row],[27Q1]:[27Q2]])=0,"No FSCT",IF(AND(SUM(Nordics[[#This Row],[26Q2]:[26Q4]])>0,SUM(Nordics[[#This Row],[27Q1]:[27Q2]])=0),"YES","NO")) -> YES | AE13: =VLOOKUP(Nordics[[#This Row],[Product Line]],Prod_T6[],4,0) -> PV | AH13: 3 - Negotiation
A14: Nordic | B14: Rexel Sweden | D14: =VLOOKUP(Nordics[[#This Row],[Product Line]],Prod_T6[],5,0) -> TCL | E14: TCL_T_Class | F14: HSM-ND54-DR505 | G14: 7 - Booked | H14: Placement for Q2 | I14: EU | N14: 1 | S14: =SUM(Nordics[[#This Row],[26M04]:[26M06]]) -> 0 | T14: =SUM(Nordics[[#This Row],[26M07]:[26M09]]) -> 1 | U14: =SUM(Nordics[[#This Row],[26M10]:[26M12]]) -> 0 | AB14: =SUM(Nordics[[#This Row],[27M01]:[27M03]]) -> 0 | AC14: =SUM(Nordics[[#This Row],[27M04]:[27M06]]) -> 0 | AD14: =IF(SUM(Nordics[[#This Row],[26Q2]:[26Q4]])+SUM(Nordics[[#This Row],[27Q1]:[27Q2]])=0,"No FSCT",IF(AND(SUM(Nordics[[#This Row],[26Q2]:[26Q4]])>0,SUM(Nordics[[#This Row],[27Q1]:[27Q2]])=0),"YES","NO")) -> YES | AE14: =VLOOKUP(Nordics[[#This Row],[Product Line]],Prod_T6[],4,0) -> PV | AH14: 7 - Booked
A15: Nordic | B15: Rexel Sweden | D15: =VLOOKUP(Nordics[[#This Row],[Product Line]],Prod_T6[],5,0) -> TCL | E15: TCL_T_Class | F15: HSM-ND66-GR620 | G15: 3 - Negotiation | H15: Placement for Q2 | I15: EU | K15: 0.8 | M15: 0.8 | S15: =SUM(Nordics[[#This Row],[26M04]:[26M06]]) -> 0.8 | T15: =SUM(Nordics[[#This Row],[26M07]:[26M09]]) -> 0.8 | U15: =SUM(Nordics[[#This Row],[26M10]:[26M12]]) -> 0 | AB15: =SUM(Nordics[[#This Row],[27M01]:[27M03]]) -> 0 | AC15: =SUM(Nordics[[#This Row],[27M04]:[27M06]]) -> 0 | AD15: =IF(SUM(Nordics[[#This Row],[26Q2]:[26Q4]])+SUM(Nordics[[#This Row],[27Q1]:[27Q2]])=0,"No FSCT",IF(AND(SUM(Nordics[[#This Row],[26Q2]:[26Q4]])>0,SUM(Nordics[[#This Row],[27Q1]:[27Q2]])=0),"YES","NO")) -> YES | AE15: =VLOOKUP(Nordics[[#This Row],[Product Line]],Prod_T6[],4,0) -> PV | AH15: 3 - Negotiation
A16: Nordic | B16: Nordic Sun Danmark A/S | D16: =VLOOKUP(Nordics[[#This Row],[Product Line]],Prod_T6[],5,0) -> TCL | E16: TCL_T_Class | F16: HSM-ND48-DR455 | G16: 1 - Lead qualification | H16: Placement for Q2 | I16: Offshore | L16: 2 | M16: 2 | N16: 2 | O16: 2 | T16: =SUM(Nordics[[#This Row],[26M07]:[26M09]]) -> 6 | U16: =SUM(Nordics[[#This Row],[26M10]:[26M12]]) -> 0 | AB16: =SUM(Nordics[[#This Row],[27M01]:[27M03]]) -> 0 | AC16: =SUM(Nordics[[#This Row],[27M04]:[27M06]]) -> 0 | AD16: =IF(SUM(Nordics[[#This Row],[26Q2]:[26Q4]])+SUM(Nordics[[#This Row],[27Q1]:[27Q2]])=0,"No FSCT",IF(AND(SUM(Nordics[[#This Row],[26Q2]:[26Q4]])>0,SUM(Nordics[[#This Row],[27Q1]:[27Q2]])=0),"YES","NO")) -> YES | AE16: =VLOOKUP(Nordics[[#This Row],[Product Line]],Prod_T6[],4,0) -> PV | AH16: 1 - Lead qualification
A17: Nordic | B17: Nordic Sun Danmark A/S | D17: =VLOOKUP(Nordics[[#This Row],[Product Line]],Prod_T6[],5,0) -> Sunpower | E17: SPR_P7 | F17: P7-BLK-2mm-455 | G17: 1 - Lead qualification | H17: Price ? €0.18 not compatible, DSB project - whitelist against DMEGC - Offer €0.135 | I17: Offshore | L17: 1 | M17: 1 | N17: 1 | S17: =SUM(Nordics[[#This Row],[26M04]:[26M06]]) -> 1 | T17: =SUM(Nordics[[#This Row],[26M07]:[26M09]]) -> 2 | U17: =SUM(Nordics[[#This Row],[26M10]:[26M12]]) -> 0 | AB17: =SUM(Nordics[[#This Row],[27M01]:[27M03]]) -> 0 | AC17: =SUM(Nordics[[#This Row],[27M04]:[27M06]]) -> 0 | AD17: =IF(SUM(Nordics[[#This Row],[26Q2]:[26Q4]])+SUM(Nordics[[#This Row],[27Q1]:[27Q2]])=0,"No FSCT",IF(AND(SUM(Nordics[[#This Row],[26Q2]:[26Q4]])>0,SUM(Nordics[[#This Row],[27Q1]:[27Q2]])=0),"YES","NO")) -> YES | AE17: =VLOOKUP(Nordics[[#This Row],[Product Line]],Prod_T6[],4,0) -> PV | AH17: 1 - Lead qualification
A18: Nordic | B18: Rexel Sweden | D18: =VLOOKUP(Nordics[[#This Row],[Product Line]],Prod_T6[],5,0) -> TCL | E18: TCL_T_Class | F18: HSM-ND66-GR625 | G18: 1 - Lead qualification | H18: C&I Panatoni Warehouse PAN Nordic | I18: EU | M18: 0.5 | N18: 0.5 | O18: 0.5 | S18: =SUM(Nordics[[#This Row],[26M04]:[26M06]]) -> 0 | T18: =SUM(Nordics[[#This Row],[26M07]:[26M09]]) -> 1.5 | U18: =SUM(Nordics[[#This Row],[26M10]:[26M12]]) -> 0 | AB18: =SUM(Nordics[[#This Row],[27M01]:[27M03]]) -> 0 | AC18: =SUM(Nordics[[#This Row],[27M04]:[27M06]]) -> 0 | AD18: =IF(SUM(Nordics[[#This Row],[26Q2]:[26Q4]])+SUM(Nordics[[#This Row],[27Q1]:[27Q2]])=0,"No FSCT",IF(AND(SUM(Nordics[[#This Row],[26Q2]:[26Q4]])>0,SUM(Nordics[[#This Row],[27Q1]:[27Q2]])=0),"YES","NO")) -> YES | AE18: =VLOOKUP(Nordics[[#This Row],[Product Line]],Prod_T6[],4,0) -> PV | AH18: 1 - Lead qualification
A19: Nordic | B19: Rexel Sweden | D19: =VLOOKUP(Nordics[[#This Row],[Product Line]],Prod_T6[],5,0) -> Sunpower | E19: SPR_P7 | F19: P7-BLK-2mm-460 | G19: 1 - Lead qualification | H19: Placement for Q3 | I19: EU | M19: 1 | O19: 1 | S19: =SUM(Nordics[[#This Row],[26M04]:[26M06]]) -> 0 | T19: =SUM(Nordics[[#This Row],[26M07]:[26M09]]) -> 2 | U19: =SUM(Nordics[[#This Row],[26M10]:[26M12]]) -> 0 | AB19: =SUM(Nordics[[#This Row],[27M01]:[27M03]]) -> 0 | AC19: =SUM(Nordics[[#This Row],[27M04]:[27M06]]) -> 0 | AD19: =IF(SUM(Nordics[[#This Row],[26Q2]:[26Q4]])+SUM(Nordics[[#This Row],[27Q1]:[27Q2]])=0,"No FSCT",IF(AND(SUM(Nordics[[#This Row],[26Q2]:[26Q4]])>0,SUM(Nordics[[#This Row],[27Q1]:[27Q2]])=0),"YES","NO")) -> YES | AE19: =VLOOKUP(Nordics[[#This Row],[Product Line]],Prod_T6[],4,0) -> PV | AH19: 1 - Lead qualification
A20: Nordic | B20: Nordic Sun Danmark A/S | D20: =VLOOKUP(Nordics[[#This Row],[Product Line]],Prod_T6[],5,0) -> TCL | E20: TCL_T_Class | F20: HSM-ND66-GK730 | G20: 0 - Lost | H20: Project in Finland Delivery Q3-Q4 | I20: Offshore | O20: 34 | S20: =SUM(Nordics[[#This Row],[26M04]:[26M06]]) -> 0 | T20: =SUM(Nordics[[#This Row],[26M07]:[26M09]]) -> 34 | U20: =SUM(Nordics[[#This Row],[26M10]:[26M12]]) -> 0 | AB20: =SUM(Nordics[[#This Row],[27M01]:[27M03]]) -> 0 | AC20: =SUM(Nordics[[#This Row],[27M04]:[27M06]]) -> 0 | AD20: =IF(SUM(Nordics[[#This Row],[26Q2]:[26Q4]])+SUM(Nordics[[#This Row],[27Q1]:[27Q2]])=0,"No FSCT",IF(AND(SUM(Nordics[[#This Row],[26Q2]:[26Q4]])>0,SUM(Nordics[[#This Row],[27Q1]:[27Q2]])=0),"YES","NO")) -> YES | AE20: =VLOOKUP(Nordics[[#This Row],[Product Line]],Prod_T6[],4,0) -> PV | AH20: 0 - Lost
A21: Nordic | B21: Nordic Sun Danmark A/S | D21: =VLOOKUP(Nordics[[#This Row],[Product Line]],Prod_T6[],5,0) -> TCL | E21: TCL_S_Class | F21: TCL-MG720DT210-68NS | G21: 2 - Initial offer | H21: C&I GM Denmark | I21: Offshore | K21: 3 | L21: 3 | S21: =SUM(Nordics[[#This Row],[26M04]:[26M06]]) -> 6 | T21: =SUM(Nordics[[#This Row],[26M07]:[26M09]]) -> 0 | U21: =SUM(Nordics[[#This Row],[26M10]:[26M12]]) -> 0 | AB21: =SUM(Nordics[[#This Row],[27M01]:[27M03]]) -> 0 | AC21: =SUM(Nordics[[#This Row],[27M04]:[27M06]]) -> 0 | AD21: =IF(SUM(Nordics[[#This Row],[26Q2]:[26Q4]])+SUM(Nordics[[#This Row],[27Q1]:[27Q2]])=0,"No FSCT",IF(AND(SUM(Nordics[[#This Row],[26Q2]:[26Q4]])>0,SUM(Nordics[[#This Row],[27Q1]:[27Q2]])=0),"YES","NO")) -> YES | AE21: =VLOOKUP(Nordics[[#This Row],[Product Line]],Prod_T6[],4,0) -> PV | AH21: 2 - Initial offer
A22: Nordic | B22: Rexel Sweden | D22: =VLOOKUP(Nordics[[#This Row],[Product Line]],Prod_T6[],5,0) -> TCL | E22: TCL_T5_Pro | F22: HSM-NT48-HH 465/470 - T5_Pro_S_Black | G22: 1 - Lead qualification | H22: Offer €0.128 | I22: EU | N22: 1 | O22: 1 | P22: 1 | Q22: 1 | S22: =SUM(Nordics[[#This Row],[26M04]:[26M06]]) -> 0 | T22: =SUM(Nordics[[#This Row],[26M07]:[26M09]]) -> 2 | U22: =SUM(Nordics[[#This Row],[26M10]:[26M12]]) -> 2 | AB22: =SUM(Nordics[[#This Row],[27M01]:[27M03]]) -> 0 | AC22: =SUM(Nordics[[#This Row],[27M04]:[27M06]]) -> 0 | AD22: =IF(SUM(Nordics[[#This Row],[26Q2]:[26Q4]])+SUM(Nordics[[#This Row],[27Q1]:[27Q2]])=0,"No FSCT",IF(AND(SUM(Nordics[[#This Row],[26Q2]:[26Q4]])>0,SUM(Nordics[[#This Row],[27Q1]:[27Q2]])=0),"YES","NO")) -> YES | AE22: =VLOOKUP(Nordics[[#This Row],[Product Line]],Prod_T6[],4,0) -> PV | AH22: 1 - Lead qualification
A23: Nordic | B23: Nordic Sun Danmark A/S | D23: =VLOOKUP(Nordics[[#This Row],[Product Line]],Prod_T6[],5,0) -> TCL | E23: TCL_T5_Pro | F23: HSM-NT48-HH 465/470 - T5_Pro_S_Black | G23: 1 - Lead qualification | H23: Offer €0.128 | I23: offshore | N23: 1 | O23: 1 | P23: 1 | Q23: 1 | S23: =SUM(Nordics[[#This Row],[26M04]:[26M06]]) -> 0 | T23: =SUM(Nordics[[#This Row],[26M07]:[26M09]]) -> 2 | U23: =SUM(Nordics[[#This Row],[26M10]:[26M12]]) -> 2 | AB23: =SUM(Nordics[[#This Row],[27M01]:[27M03]]) -> 0 | AC23: =SUM(Nordics[[#This Row],[27M04]:[27M06]]) -> 0 | AD23: =IF(SUM(Nordics[[#This Row],[26Q2]:[26Q4]])+SUM(Nordics[[#This Row],[27Q1]:[27Q2]])=0,"No FSCT",IF(AND(SUM(Nordics[[#This Row],[26Q2]:[26Q4]])>0,SUM(Nordics[[#This Row],[27Q1]:[27Q2]])=0),"YES","NO")) -> YES | AE23: =VLOOKUP(Nordics[[#This Row],[Product Line]],Prod_T6[],4,0) -> PV | AH23: 1 - Lead qualification
A24: Nordic | B24: Rexel Sweden | D24: =VLOOKUP(Nordics[[#This Row],[Product Line]],Prod_T6[],5,0) -> TCL | E24: TCL_T_Class | F24: HSM-ND66-GR620 | G24: 6 - Won | I24: EU | L24: 0.4 | S24: =SUM(Nordics[[#This Row],[26M04]:[26M06]]) -> 0.4 | T24: =SUM(Nordics[[#This Row],[26M07]:[26M09]]) -> 0 | U24: =SUM(Nordics[[#This Row],[26M10]:[26M12]]) -> 0 | AB24: =SUM(Nordics[[#This Row],[27M01]:[27M03]]) -> 0 | AC24: =SUM(Nordics[[#This Row],[27M04]:[27M06]]) -> 0 | AD24: =IF(SUM(Nordics[[#This Row],[26Q2]:[26Q4]])+SUM(Nordics[[#This Row],[27Q1]:[27Q2]])=0,"No FSCT",IF(AND(SUM(Nordics[[#This Row],[26Q2]:[26Q4]])>0,SUM(Nordics[[#This Row],[27Q1]:[27Q2]])=0),"YES","NO")) -> YES | AE24: =VLOOKUP(Nordics[[#This Row],[Product Line]],Prod_T6[],4,0) -> PV | AH24: 6 - Won
A25: Nordic | B25: Nordic Sun Danmark A/S | D25: =VLOOKUP(Nordics[[#This Row],[Product Line]],Prod_T6[],5,0) -> TCL | E25: TCL_T_Class | F25: HSM-ND66-GR625 | G25: 3 - Negotiation | H25: Special SKU / short cable / HC connect | I25: Offshore | O25: 5 | S25: =SUM(Nordics[[#This Row],[26M04]:[26M06]]) -> 0 | T25: =SUM(Nordics[[#This Row],[26M07]:[26M09]]) -> 5 | U25: =SUM(Nordics[[#This Row],[26M10]:[26M12]]) -> 0 | AB25: =SUM(Nordics[[#This Row],[27M01]:[27M03]]) -> 0 | AC25: =SUM(Nordics[[#This Row],[27M04]:[27M06]]) -> 0 | AD25: =IF(SUM(Nordics[[#This Row],[26Q2]:[26Q4]])+SUM(Nordics[[#This Row],[27Q1]:[27Q2]])=0,"No FSCT",IF(AND(SUM(Nordics[[#This Row],[26Q2]:[26Q4]])>0,SUM(Nordics[[#This Row],[27Q1]:[27Q2]])=0),"YES","NO")) -> YES | AE25: =VLOOKUP(Nordics[[#This Row],[Product Line]],Prod_T6[],4,0) -> PV | AH25: 3 - Negotiation
A26: Nordic | B26: nordic Sun Danmark A/S | D26: =VLOOKUP(Nordics[[#This Row],[Product Line]],Prod_T6[],5,0) -> TCL | E26: TCL_T_Class | F26: HSM-ND66-GR630 | G26: 3 - Negotiation | H26: Special SKU / short cable / HC connect | I26: Offshore | O26: 10 | S26: =SUM(Nordics[[#This Row],[26M04]:[26M06]]) -> 0 | T26: =SUM(Nordics[[#This Row],[26M07]:[26M09]]) -> 10 | U26: =SUM(Nordics[[#This Row],[26M10]:[26M12]]) -> 0 | AB26: =SUM(Nordics[[#This Row],[27M01]:[27M03]]) -> 0 | AC26: =SUM(Nordics[[#This Row],[27M04]:[27M06]]) -> 0 | AD26: =IF(SUM(Nordics[[#This Row],[26Q2]:[26Q4]])+SUM(Nordics[[#This Row],[27Q1]:[27Q2]])=0,"No FSCT",IF(AND(SUM(Nordics[[#This Row],[26Q2]:[26Q4]])>0,SUM(Nordics[[#This Row],[27Q1]:[27Q2]])=0),"YES","NO")) -> YES | AE26: =VLOOKUP(Nordics[[#This Row],[Product Line]],Prod_T6[],4,0) -> PV | AH26: 3 - Negotiation
A27: Nordic | B27: Nordic Sun Danmark A/S | D27: =VLOOKUP(Nordics[[#This Row],[Product Line]],Prod_T6[],5,0) -> TCL | E27: TCL_C2_Series | F27: HSM-BE54-HD485/490 | G27: 4 - BAFO | H27: Offer BC delivered in Sept Q3 / Confirm WW 34 | I27: Offshore | P27: 2 | Q27: 2 | S27: =SUM(Nordics[[#This Row],[26M04]:[26M06]]) -> 0 | T27: =SUM(Nordics[[#This Row],[26M07]:[26M09]]) -> 0 | U27: =SUM(Nordics[[#This Row],[26M10]:[26M12]]) -> 4 | AB27: =SUM(Nordics[[#This Row],[27M01]:[27M03]]) -> 0 | AC27: =SUM(Nordics[[#This Row],[27M04]:[27M06]]) -> 0 | AD27: =IF(SUM(Nordics[[#This Row],[26Q2]:[26Q4]])+SUM(Nordics[[#This Row],[27Q1]:[27Q2]])=0,"No FSCT",IF(AND(SUM(Nordics[[#This Row],[26Q2]:[26Q4]])>0,SUM(Nordics[[#This Row],[27Q1]:[27Q2]])=0),"YES","NO")) -> YES | AE27: =VLOOKUP(Nordics[[#This Row],[Product Line]],Prod_T6[],4,0) -> PV | AH27: 4 - BAFO
A28: Nordic | B28: Rexel Sweden | D28: =VLOOKUP(Nordics[[#This Row],[Product Line]],Prod_T6[],5,0) -> TCL | E28: TCL_C2_Series | F28: HSM-BE54-HD485/490 | G28: 6 - Won | H28: Offer BC delivered in Sept Q3 | I28: Offshore | P28: 1.6 | S28: =SUM(Nordics[[#This Row],[26M04]:[26M06]]) -> 0 | T28: =SUM(Nordics[[#This Row],[26M07]:[26M09]]) -> 0 | U28: =SUM(Nordics[[#This Row],[26M10]:[26M12]]) -> 1.6 | AB28: =SUM(Nordics[[#This Row],[27M01]:[27M03]]) -> 0 | AC28: =SUM(Nordics[[#This Row],[27M04]:[27M06]]) -> 0 | AD28: =IF(SUM(Nordics[[#This Row],[26Q2]:[26Q4]])+SUM(Nordics[[#This Row],[27Q1]:[27Q2]])=0,"No FSCT",IF(AND(SUM(Nordics[[#This Row],[26Q2]:[26Q4]])>0,SUM(Nordics[[#This Row],[27Q1]:[27Q2]])=0),"YES","NO")) -> YES | AE28: =VLOOKUP(Nordics[[#This Row],[Product Line]],Prod_T6[],4,0) -> PV | AH28: 6 - Won
A29: Nordic | B29: Rexel Sweden | D29: =VLOOKUP(Nordics[[#This Row],[Product Line]],Prod_T6[],5,0) -> Sunpower | E29: SPR_P7 | F29: P7-BLK-2mm-460 | G29: 6 - Won | H29: Q3 Order | I29: EU | M29: 0.4 | S29: =SUM(Nordics[[#This Row],[26M04]:[26M06]]) -> 0 | T29: =SUM(Nordics[[#This Row],[26M07]:[26M09]]) -> 0.4 | U29: =SUM(Nordics[[#This Row],[26M10]:[26M12]]) -> 0 | AB29: =SUM(Nordics[[#This Row],[27M01]:[27M03]]) -> 0 | AC29: =SUM(Nordics[[#This Row],[27M04]:[27M06]]) -> 0 | AD29: =IF(SUM(Nordics[[#This Row],[26Q2]:[26Q4]])+SUM(Nordics[[#This Row],[27Q1]:[27Q2]])=0,"No FSCT",IF(AND(SUM(Nordics[[#This Row],[26Q2]:[26Q4]])>0,SUM(Nordics[[#This Row],[27Q1]:[27Q2]])=0),"YES","NO")) -> YES | AE29: =VLOOKUP(Nordics[[#This Row],[Product Line]],Prod_T6[],4,0) -> PV | AH29: 6 - Won
A30: Nordic | B30: Rexel Sweden | D30: =VLOOKUP(Nordics[[#This Row],[Product Line]],Prod_T6[],5,0) -> Sunpower | E30: SPR_P7 | F30: P7-BLK-P-515 | G30: 6 - Won | H30: Q3 Order | I30: EU | M30: 0.4 | S30: =SUM(Nordics[[#This Row],[26M04]:[26M06]]) -> 0 | T30: =SUM(Nordics[[#This Row],[26M07]:[26M09]]) -> 0.4 | U30: =SUM(Nordics[[#This Row],[26M10]:[26M12]]) -> 0 | AB30: =SUM(Nordics[[#This Row],[27M01]:[27M03]]) -> 0 | AC30: =SUM(Nordics[[#This Row],[27M04]:[27M06]]) -> 0 | AD30: =IF(SUM(Nordics[[#This Row],[26Q2]:[26Q4]])+SUM(Nordics[[#This Row],[27Q1]:[27Q2]])=0,"No FSCT",IF(AND(SUM(Nordics[[#This Row],[26Q2]:[26Q4]])>0,SUM(Nordics[[#This Row],[27Q1]:[27Q2]])=0),"YES","NO")) -> YES | AE30: =VLOOKUP(Nordics[[#This Row],[Product Line]],Prod_T6[],4,0) -> PV | AH30: 6 - Won
A31: Nordic | B31: Site Services A/S | D31: =VLOOKUP(Nordics[[#This Row],[Product Line]],Prod_T6[],5,0) -> Sunpower | E31: SPR_MAX_P6 | F31: SPR_MAX_P6 | G31: 6 - Won | H31: New Customer Depletion Maxeon 390-400 COM | I31: EU | M31: 0.2 | T31: =SUM(Nordics[[#This Row],[26M07]:[26M09]]) -> 0.2 | U31: =SUM(Nordics[[#This Row],[26M10]:[26M12]]) -> 0 | AB31: =SUM(Nordics[[#This Row],[27M01]:[27M03]]) -> 0 | AC31: =SUM(Nordics[[#This Row],[27M04]:[27M06]]) -> 0 | AD31: =IF(SUM(Nordics[[#This Row],[26Q2]:[26Q4]])+SUM(Nordics[[#This Row],[27Q1]:[27Q2]])=0,"No FSCT",IF(AND(SUM(Nordics[[#This Row],[26Q2]:[26Q4]])>0,SUM(Nordics[[#This Row],[27Q1]:[27Q2]])=0),"YES","NO")) -> YES | AE31: =VLOOKUP(Nordics[[#This Row],[Product Line]],Prod_T6[],4,0) -> PV | AH31: 6 - Won
A32: Nordic | B32: Nova Solar | D32: =VLOOKUP(Nordics[[#This Row],[Product Line]],Prod_T6[],5,0) -> TCL | E32: Heat_Pump | F32: HB12SP0 | G32: 6 - Won | H32: New Customer 2 Units pilot installation | I32: EU | M32: 2 | S32: =SUM(Nordics[[#This Row],[26M04]:[26M06]]) -> 0 | T32: =SUM(Nordics[[#This Row],[26M07]:[26M09]]) -> 2 | U32: =SUM(Nordics[[#This Row],[26M10]:[26M12]]) -> 0 | AB32: =SUM(Nordics[[#This Row],[27M01]:[27M03]]) -> 0 | AC32: =SUM(Nordics[[#This Row],[27M04]:[27M06]]) -> 0 | AD32: =IF(SUM(Nordics[[#This Row],[26Q2]:[26Q4]])+SUM(Nordics[[#This Row],[27Q1]:[27Q2]])=0,"No FSCT",IF(AND(SUM(Nordics[[#This Row],[26Q2]:[26Q4]])>0,SUM(Nordics[[#This Row],[27Q1]:[27Q2]])=0),"YES","NO")) -> YES | AE32: =VLOOKUP(Nordics[[#This Row],[Product Line]],Prod_T6[],4,0) -> HP | AH32: 6 - Won
A33: Nordic | B33: Rexel Sweden | D33: =VLOOKUP(Nordics[[#This Row],[Product Line]],Prod_T6[],5,0) -> TCL | E33: TCL_T5_Pro | F33: HSM-NT48-HH 465/470 - T5_Pro_S_Black | G33: 6 - Won | H33: Q3 Order | I33: 470 Black | S33: =SUM(Nordics[[#This Row],[26M04]:[26M06]]) -> 0 | T33: =SUM(Nordics[[#This Row],[26M07]:[26M09]]) -> 0 | U33: =SUM(Nordics[[#This Row],[26M10]:[26M12]]) -> 0 | AB33: =SUM(Nordics[[#This Row],[27M01]:[27M03]]) -> 0 | AC33: =SUM(Nordics[[#This Row],[27M04]:[27M06]]) -> 0 | AD33: =IF(SUM(Nordics[[#This Row],[26Q2]:[26Q4]])+SUM(Nordics[[#This Row],[27Q1]:[27Q2]])=0,"No FSCT",IF(AND(SUM(Nordics[[#This Row],[26Q2]:[26Q4]])>0,SUM(Nordics[[#This Row],[27Q1]:[27Q2]])=0),"YES","NO")) -> No FSCT | AE33: =VLOOKUP(Nordics[[#This Row],[Product Line]],Prod_T6[],4,0) -> PV | AH33: 6 - Won
A34: Nordic | B34: Rexel Sweden | D34: =VLOOKUP(Nordics[[#This Row],[Product Line]],Prod_T6[],5,0) -> TCL | E34: ESS_TCL_Res | F34: BlueArk X1-10kW-TP 1*8kWh | G34: 1 - Lead qualification | H34: Rexel Launch of X1 in Sweden | R34: 50 | S34: =SUM(Nordics[[#This Row],[26M04]:[26M06]]) -> 0 | T34: =SUM(Nordics[[#This Row],[26M07]:[26M09]]) -> 0 | U34: =SUM(Nordics[[#This Row],[26M10]:[26M12]]) -> 50 | AB34: =SUM(Nordics[[#This Row],[27M01]:[27M03]]) -> 0 | AC34: =SUM(Nordics[[#This Row],[27M04]:[27M06]]) -> 0 | AD34: =IF(SUM(Nordics[[#This Row],[26Q2]:[26Q4]])+SUM(Nordics[[#This Row],[27Q1]:[27Q2]])=0,"No FSCT",IF(AND(SUM(Nordics[[#This Row],[26Q2]:[26Q4]])>0,SUM(Nordics[[#This Row],[27Q1]:[27Q2]])=0),"YES","NO")) -> YES | AE34: =VLOOKUP(Nordics[[#This Row],[Product Line]],Prod_T6[],4,0) -> ESS | AH34: 1 - Lead qualification
A35: Nordic | B35: Nordic Sun Danmark A/S | D35: =VLOOKUP(Nordics[[#This Row],[Product Line]],Prod_T6[],5,0) -> TCL | E35: ESS_TCL_CI | F35: BlueArk X5-50K-100 | G35: 1 - Lead qualification | H35: Nordic Sun Test Unit - Solinteg whitelist sept | O35: 2 | T35: =SUM(Nordics[[#This Row],[26M07]:[26M09]]) -> 2 | U35: =SUM(Nordics[[#This Row],[26M10]:[26M12]]) -> 0 | AB35: =SUM(Nordics[[#This Row],[27M01]:[27M03]]) -> 0 | AC35: =SUM(Nordics[[#This Row],[27M04]:[27M06]]) -> 0 | AD35: =IF(SUM(Nordics[[#This Row],[26Q2]:[26Q4]])+SUM(Nordics[[#This Row],[27Q1]:[27Q2]])=0,"No FSCT",IF(AND(SUM(Nordics[[#This Row],[26Q2]:[26Q4]])>0,SUM(Nordics[[#This Row],[27Q1]:[27Q2]])=0),"YES","NO")) -> YES | AE35: =VLOOKUP(Nordics[[#This Row],[Product Line]],Prod_T6[],4,0) -> ESS | AH35: 1 - Lead qualification
A36: Nordic | B36: Nordic Sun Danmark A/S | D36: =VLOOKUP(Nordics[[#This Row],[Product Line]],Prod_T6[],5,0) -> TCL | E36: TCL_T5_Pro | F36: HSM-NT48-HH 465/470 - T5_Pro_S_Black | G36: 4 - BAFO | H36: 2 CT Confirmed 260812 @ €0.122 offer €0.126 | I36: 470 Black | O36: 0.8 | S36: =SUM(Nordics[[#This Row],[26M04]:[26M06]]) -> 0 | T36: =SUM(Nordics[[#This Row],[26M07]:[26M09]]) -> 0.8 | U36: =SUM(Nordics[[#This Row],[26M10]:[26M12]]) -> 0 | AB36: =SUM(Nordics[[#This Row],[27M01]:[27M03]]) -> 0 | AC36: =SUM(Nordics[[#This Row],[27M04]:[27M06]]) -> 0 | AD36: =IF(SUM(Nordics[[#This Row],[26Q2]:[26Q4]])+SUM(Nordics[[#This Row],[27Q1]:[27Q2]])=0,"No FSCT",IF(AND(SUM(Nordics[[#This Row],[26Q2]:[26Q4]])>0,SUM(Nordics[[#This Row],[27Q1]:[27Q2]])=0),"YES","NO")) -> YES | AE36: =VLOOKUP(Nordics[[#This Row],[Product Line]],Prod_T6[],4,0) -> PV | AH36: 4 - BAFO
A37: Nordic | B37: Nordic Sun Danmark A/S | D37: =VLOOKUP(Nordics[[#This Row],[Product Line]],Prod_T6[],5,0) -> Sunpower | E37: SPR_P7 | F37: P7-BLK-2mm-460 | G37: 2 - Initial offer | I37: FCA Rotterdam Price | P37: 1 | Q37: 1 | R37: 1 | S37: =SUM(Nordics[[#This Row],[26M04]:[26M06]]) -> 0 | T37: =SUM(Nordics[[#This Row],[26M07]:[26M09]]) -> 0 | U37: =SUM(Nordics[[#This Row],[26M10]:[26M12]]) -> 3 | AB37: =SUM(Nordics[[#This Row],[27M01]:[27M03]]) -> 0 | AC37: =SUM(Nordics[[#This Row],[27M04]:[27M06]]) -> 0 | AD37: =IF(SUM(Nordics[[#This Row],[26Q2]:[26Q4]])+SUM(Nordics[[#This Row],[27Q1]:[27Q2]])=0,"No FSCT",IF(AND(SUM(Nordics[[#This Row],[26Q2]:[26Q4]])>0,SUM(Nordics[[#This Row],[27Q1]:[27Q2]])=0),"YES","NO")) -> YES | AE37: =VLOOKUP(Nordics[[#This Row],[Product Line]],Prod_T6[],4,0) -> PV | AH37: 2 - Initial offer
A38: Nordic | B38: Nordic Sun Danmark A/S | D38: =VLOOKUP(Nordics[[#This Row],[Product Line]],Prod_T6[],5,0) -> Sunpower | E38: SPR_P7 | F38: P7-COM-S | G38: 2 - Initial offer | H38: H2 offer 6 month | I38: FCA Rotterdam Price | P38: 1 | Q38: 1 | R38: 1 | S38: =SUM(Nordics[[#This Row],[26M04]:[26M06]]) -> 0 | T38: =SUM(Nordics[[#This Row],[26M07]:[26M09]]) -> 0 | U38: =SUM(Nordics[[#This Row],[26M10]:[26M12]]) -> 3 | AB38: =SUM(Nordics[[#This Row],[27M01]:[27M03]]) -> 0 | AC38: =SUM(Nordics[[#This Row],[27M04]:[27M06]]) -> 0 | AD38: =IF(SUM(Nordics[[#This Row],[26Q2]:[26Q4]])+SUM(Nordics[[#This Row],[27Q1]:[27Q2]])=0,"No FSCT",IF(AND(SUM(Nordics[[#This Row],[26Q2]:[26Q4]])>0,SUM(Nordics[[#This Row],[27Q1]:[27Q2]])=0),"YES","NO")) -> YES | AE38: =VLOOKUP(Nordics[[#This Row],[Product Line]],Prod_T6[],4,0) -> PV | AH38: 2 - Initial offer
A39: Nordic | B39: Nordic Sun Danmark A/S | D39: =VLOOKUP(Nordics[[#This Row],[Product Line]],Prod_T6[],5,0) -> TCL | E39: TCL_T_Class | F39: HSM-ND66-GR625 | G39: 2 - Initial offer | H39: H2 offer 6 month | I39: FCA Rotterdam Price | P39: 2 | Q39: 2 | R39: 2 | S39: 0.15 | T39: =SUM(Nordics[[#This Row],[26M07]:[26M09]]) -> 0 | U39: =SUM(Nordics[[#This Row],[26M10]:[26M12]]) -> 6 | AB39: =SUM(Nordics[[#This Row],[27M01]:[27M03]]) -> 0 | AC39: =SUM(Nordics[[#This Row],[27M04]:[27M06]]) -> 0 | AD39: =IF(SUM(Nordics[[#This Row],[26Q2]:[26Q4]])+SUM(Nordics[[#This Row],[27Q1]:[27Q2]])=0,"No FSCT",IF(AND(SUM(Nordics[[#This Row],[26Q2]:[26Q4]])>0,SUM(Nordics[[#This Row],[27Q1]:[27Q2]])=0),"YES","NO")) -> YES | AE39: =VLOOKUP(Nordics[[#This Row],[Product Line]],Prod_T6[],4,0) -> PV | AH39: 2 - Initial offer
A40: Nordic | B40: Nordic Sun Danmark A/S | D40: =VLOOKUP(Nordics[[#This Row],[Product Line]],Prod_T6[],5,0) -> TCL | E40: TCL_T5_Pro | F40: HSM-NT48-HH 465/470 - T5_Pro_S_Black | G40: 4 - BAFO | H40: 10 CT | I40: 470 Black | P40: 2 | Q40: 2 | S40: =SUM(Nordics[[#This Row],[26M04]:[26M06]]) -> 0 | T40: =SUM(Nordics[[#This Row],[26M07]:[26M09]]) -> 0 | U40: =SUM(Nordics[[#This Row],[26M10]:[26M12]]) -> 4 | AB40: =SUM(Nordics[[#This Row],[27M01]:[27M03]]) -> 0 | AC40: =SUM(Nordics[[#This Row],[27M04]:[27M06]]) -> 0 | AD40: =IF(SUM(Nordics[[#This Row],[26Q2]:[26Q4]])+SUM(Nordics[[#This Row],[27Q1]:[27Q2]])=0,"No FSCT",IF(AND(SUM(Nordics[[#This Row],[26Q2]:[26Q4]])>0,SUM(Nordics[[#This Row],[27Q1]:[27Q2]])=0),"YES","NO")) -> YES | AE40: =VLOOKUP(Nordics[[#This Row],[Product Line]],Prod_T6[],4,0) -> PV | AH40: 4 - BAFO
A41: Nordic | B41: Rexel Sweden | D41: =VLOOKUP(Nordics[[#This Row],[Product Line]],Prod_T6[],5,0) -> Sunpower | E41: SPR_P7 | F41: P7-BLK-P-515 | H41: Awaiting confirmation | P41: 0.8 | T41: =SUM(Nordics[[#This Row],[26M07]:[26M09]]) -> 0 | U41: =SUM(Nordics[[#This Row],[26M10]:[26M12]]) -> 0.8 | AB41: =SUM(Nordics[[#This Row],[27M01]:[27M03]]) -> 0 | AC41: =SUM(Nordics[[#This Row],[27M04]:[27M06]]) -> 0 | AD41: =IF(SUM(Nordics[[#This Row],[26Q2]:[26Q4]])+SUM(Nordics[[#This Row],[27Q1]:[27Q2]])=0,"No FSCT",IF(AND(SUM(Nordics[[#This Row],[26Q2]:[26Q4]])>0,SUM(Nordics[[#This Row],[27Q1]:[27Q2]])=0),"YES","NO")) -> YES | AE41: =VLOOKUP(Nordics[[#This Row],[Product Line]],Prod_T6[],4,0) -> PV | AH41: 0
A42: Nordic | B42: Solar DK | D42: =VLOOKUP(Nordics[[#This Row],[Product Line]],Prod_T6[],5,0) -> Sunpower | E42: SPR_P7 | F42: P7-BLK-2mm-455 | G42: 5 - Finalize contract | H42: New Dist 2 CT SPR Offer €0.13 - MPO now - Sending distribution contract | P42: 1.2 | S42: =SUM(Nordics[[#This Row],[26M04]:[26M06]]) -> 0 | T42: =SUM(Nordics[[#This Row],[26M07]:[26M09]]) -> 0 | U42: =SUM(Nordics[[#This Row],[26M10]:[26M12]]) -> 1.2 | AB42: =SUM(Nordics[[#This Row],[27M01]:[27M03]]) -> 0 | AC42: =SUM(Nordics[[#This Row],[27M04]:[27M06]]) -> 0 | AD42: =IF(SUM(Nordics[[#This Row],[26Q2]:[26Q4]])+SUM(Nordics[[#This Row],[27Q1]:[27Q2]])=0,"No FSCT",IF(AND(SUM(Nordics[[#This Row],[26Q2]:[26Q4]])>0,SUM(Nordics[[#This Row],[27Q1]:[27Q2]])=0),"YES","NO")) -> YES | AE42: =VLOOKUP(Nordics[[#This Row],[Product Line]],Prod_T6[],4,0) -> PV | AH42: 5 - Finalize contract
A43: Nordic | B43: Rexel Sweden | D43: =VLOOKUP(Nordics[[#This Row],[Product Line]],Prod_T6[],5,0) -> TCL | E43: ESS_TCL_CI | F43: BlueArk X5-50K-100 | G43: 4 - BAFO | H43: 3 Units - Asking price €14.000 to accept - Not accepted from me ---plus freight | S43: =SUM(Nordics[[#This Row],[26M04]:[26M06]]) -> 0 | T43: =SUM(Nordics[[#This Row],[26M07]:[26M09]]) -> 0 | U43: =SUM(Nordics[[#This Row],[26M10]:[26M12]]) -> 0 | AB43: =SUM(Nordics[[#This Row],[27M01]:[27M03]]) -> 0 | AC43: =SUM(Nordics[[#This Row],[27M04]:[27M06]]) -> 0 | AD43: =IF(SUM(Nordics[[#This Row],[26Q2]:[26Q4]])+SUM(Nordics[[#This Row],[27Q1]:[27Q2]])=0,"No FSCT",IF(AND(SUM(Nordics[[#This Row],[26Q2]:[26Q4]])>0,SUM(Nordics[[#This Row],[27Q1]:[27Q2]])=0),"YES","NO")) -> No FSCT | AE43: =VLOOKUP(Nordics[[#This Row],[Product Line]],Prod_T6[],4,0) -> ESS | AH43: 4 - BAFO
A44: Nordic | B44: Rexel Sweden | D44: =VLOOKUP(Nordics[[#This Row],[Product Line]],Prod_T6[],5,0) -> TCL | E44: ESS_TCL_CI | F44: BlueArk W10-125K-261 | G44: 3 - Negotiation | H44: 14 Units - Tender - competition Shanghai ZOE ESS - €91 kWh | S44: =SUM(Nordics[[#This Row],[26M04]:[26M06]]) -> 0 | T44: =SUM(Nordics[[#This Row],[26M07]:[26M09]]) -> 0 | U44: =SUM(Nordics[[#This Row],[26M10]:[26M12]]) -> 0 | AB44: =SUM(Nordics[[#This Row],[27M01]:[27M03]]) -> 0 | AC44: =SUM(Nordics[[#This Row],[27M04]:[27M06]]) -> 0 | AD44: =IF(SUM(Nordics[[#This Row],[26Q2]:[26Q4]])+SUM(Nordics[[#This Row],[27Q1]:[27Q2]])=0,"No FSCT",IF(AND(SUM(Nordics[[#This Row],[26Q2]:[26Q4]])>0,SUM(Nordics[[#This Row],[27Q1]:[27Q2]])=0),"YES","NO")) -> No FSCT | AE44: =VLOOKUP(Nordics[[#This Row],[Product Line]],Prod_T6[],4,0) -> ESS | AH44: 3 - Negotiation
A45: Nordic | B45: Rexel Sweden | D45: =VLOOKUP(Nordics[[#This Row],[Product Line]],Prod_T6[],5,0) -> TCL | E45: TCL_T_Class | F45: HSM-ND48-DR455 | G45: 3 - Negotiation | H45: 2 CT 455W - Price France. | S45: =SUM(Nordics[[#This Row],[26M04]:[26M06]]) -> 0 | T45: =SUM(Nordics[[#This Row],[26M07]:[26M09]]) -> 0 | U45: =SUM(Nordics[[#This Row],[26M10]:[26M12]]) -> 0 | AB45: =SUM(Nordics[[#This Row],[27M01]:[27M03]]) -> 0 | AC45: =SUM(Nordics[[#This Row],[27M04]:[27M06]]) -> 0 | AD45: =IF(SUM(Nordics[[#This Row],[26Q2]:[26Q4]])+SUM(Nordics[[#This Row],[27Q1]:[27Q2]])=0,"No FSCT",IF(AND(SUM(Nordics[[#This Row],[26Q2]:[26Q4]])>0,SUM(Nordics[[#This Row],[27Q1]:[27Q2]])=0),"YES","NO")) -> No FSCT | AE45: =VLOOKUP(Nordics[[#This Row],[Product Line]],Prod_T6[],4,0) -> PV | AH45: 3 - Negotiation
H46: SubTotal => | J46: =SUBTOTAL(9,Nordics[26M04]) -> 6.4 | K46: =SUBTOTAL(9,Nordics[26M05]) -> 6 | L46: =SUBTOTAL(9,Nordics[26M06]) -> 8.4 | M46: =SUBTOTAL(9,Nordics[26M07]) -> 8.3 | N46: =SUBTOTAL(9,Nordics[26M08]) -> 7.5 | O46: =SUBTOTAL(9,Nordics[26M09]) -> 60.3 | P46: =SUBTOTAL(9,Nordics[26M10]) -> 20.6 | Q46: =SUBTOTAL(9,Nordics[26M11]) -> 16 | R46: =SUBTOTAL(9,Nordics[26M12]) -> 54 | S46: =SUBTOTAL(9,Nordics[26Q2]) -> 16.95 | T46: =SUBTOTAL(9,Nordics[26Q3]) -> 76.1 | U46: =SUBTOTAL(9,Nordics[26Q4]) -> 90.6

Sheet BeNeLux
G1: Category | J1: mw/qty | K1: mw/qty | L1: mw/qty | M1: mw/qty | N1: mw/qty | O1: mw/qty | P1: mw/qty | Q1: mw/qty | R1: mw/qty | S1: mw/qty | T1: mw/qty | U1: mw/qty | V1: mw/qty | W1: mw/qty | X1: mw/qty | Y1: mw/qty | Z1: mw/qty | AA1: mw/qty | AB1: mw/qty | AC1: mw/qty
G2: ESS | J2: {=SUMPRODUCT((BE_NL[Product Category]=$G2)*SUBTOTAL(109,OFFSET(INDEX(BE_NL[26M04],1),ROW(BE_NL[26M04])-MIN(ROW(BE_NL[26M04])),0,1)))} -> 0 | K2: {=SUMPRODUCT((BE_NL[Product Category]=$G2)*SUBTOTAL(109,OFFSET(INDEX(BE_NL[26M05],1),ROW(BE_NL[26M05])-MIN(ROW(BE_NL[26M05])),0,1)))} -> 0 | L2: {=SUMPRODUCT((BE_NL[Product Category]=$G2)*SUBTOTAL(109,OFFSET(INDEX(BE_NL[26M06],1),ROW(BE_NL[26M06])-MIN(ROW(BE_NL[26M06])),0,1)))} -> 0 | M2: {=SUMPRODUCT((BE_NL[Product Category]=$G2)*SUBTOTAL(109,OFFSET(INDEX(BE_NL[26M07],1),ROW(BE_NL[26M07])-MIN(ROW(BE_NL[26M07])),0,1)))} -> 0 | N2: {=SUMPRODUCT((BE_NL[Product Category]=$G2)*SUBTOTAL(109,OFFSET(INDEX(BE_NL[26M08],1),ROW(BE_NL[26M08])-MIN(ROW(BE_NL[26M08])),0,1)))} -> 0 | O2: {=SUMPRODUCT((BE_NL[Product Category]=$G2)*SUBTOTAL(109,OFFSET(INDEX(BE_NL[26M09],1),ROW(BE_NL[26M09])-MIN(ROW(BE_NL[26M09])),0,1)))} -> 0 | P2: {=SUMPRODUCT((BE_NL[Product Category]=$G2)*SUBTOTAL(109,OFFSET(INDEX(BE_NL[26M10],1),ROW(BE_NL[26M10])-MIN(ROW(BE_NL[26M10])),0,1)))} -> 0 | Q2: {=SUMPRODUCT((BE_NL[Product Category]=$G2)*SUBTOTAL(109,OFFSET(INDEX(BE_NL[26M11],1),ROW(BE_NL[26M11])-MIN(ROW(BE_NL[26M11])),0,1)))} -> 0 | R2: {=SUMPRODUCT((BE_NL[Product Category]=$G2)*SUBTOTAL(109,OFFSET(INDEX(BE_NL[26M12],1),ROW(BE_NL[26M12])-MIN(ROW(BE_NL[26M12])),0,1)))} -> 0 | S2: {=SUMPRODUCT((BE_NL[Product Category]=$G2)*SUBTOTAL(109,OFFSET(INDEX(BE_NL[26Q2],1),ROW(BE_NL[26Q2])-MIN(ROW(BE_NL[26Q2])),0,1)))} -> 0 | T2: {=SUMPRODUCT((BE_NL[Product Category]=$G2)*SUBTOTAL(109,OFFSET(INDEX(BE_NL[26Q3],1),ROW(BE_NL[26Q3])-MIN(ROW(BE_NL[26Q3])),0,1)))} -> 0 | U2: {=SUMPRODUCT((BE_NL[Product Category]=$G2)*SUBTOTAL(109,OFFSET(INDEX(BE_NL[26Q4],1),ROW(BE_NL[26Q4])-MIN(ROW(BE_NL[26Q4])),0,1)))} -> 0 | V2: {=SUMPRODUCT((BE_NL[Product Category]=$G2)*SUBTOTAL(109,OFFSET(INDEX(BE_NL[27M01],1),ROW(BE_NL[27M01])-MIN(ROW(BE_NL[27M01])),0,1)))} -> 0 | W2: {=SUMPRODUCT((BE_NL[Product Category]=$G2)*SUBTOTAL(109,OFFSET(INDEX(BE_NL[27M02],1),ROW(BE_NL[27M02])-MIN(ROW(BE_NL[27M02])),0,1)))} -> 0 | X2: {=SUMPRODUCT((BE_NL[Product Category]=$G2)*SUBTOTAL(109,OFFSET(INDEX(BE_NL[27M03],1),ROW(BE_NL[27M03])-MIN(ROW(BE_NL[27M03])),0,1)))} -> 0 | Y2: {=SUMPRODUCT((BE_NL[Product Category]=$G2)*SUBTOTAL(109,OFFSET(INDEX(BE_NL[27M04],1),ROW(BE_NL[27M04])-MIN(ROW(BE_NL[27M04])),0,1)))} -> 0 | Z2: {=SUMPRODUCT((BE_NL[Product Category]=$G2)*SUBTOTAL(109,OFFSET(INDEX(BE_NL[27M05],1),ROW(BE_NL[27M05])-MIN(ROW(BE_NL[27M05])),0,1)))} -> 0 | AA2: {=SUMPRODUCT((BE_NL[Product Category]=$G2)*SUBTOTAL(109,OFFSET(INDEX(BE_NL[27M06],1),ROW(BE_NL[27M06])-MIN(ROW(BE_NL[27M06])),0,1)))} -> 0 | AB2: {=SUMPRODUCT((BE_NL[Product Category]=$G2)*SUBTOTAL(109,OFFSET(INDEX(BE_NL[27Q1],1),ROW(BE_NL[27Q1])-MIN(ROW(BE_NL[27Q1])),0,1)))} -> 0 | AC2: {=SUMPRODUCT((BE_NL[Product Category]=$G2)*SUBTOTAL(109,OFFSET(INDEX(BE_NL[27Q2],1),ROW(BE_NL[27Q2])-MIN(ROW(BE_NL[27Q2])),0,1)))} -> 0
G3: HP | J3: {=SUMPRODUCT((BE_NL[Product Category]=$G3)*SUBTOTAL(109,OFFSET(INDEX(BE_NL[26M04],1),ROW(BE_NL[26M04])-MIN(ROW(BE_NL[26M04])),0,1)))} -> 0 | K3: {=SUMPRODUCT((BE_NL[Product Category]=$G3)*SUBTOTAL(109,OFFSET(INDEX(BE_NL[26M05],1),ROW(BE_NL[26M05])-MIN(ROW(BE_NL[26M05])),0,1)))} -> 0 | L3: {=SUMPRODUCT((BE_NL[Product Category]=$G3)*SUBTOTAL(109,OFFSET(INDEX(BE_NL[26M06],1),ROW(BE_NL[26M06])-MIN(ROW(BE_NL[26M06])),0,1)))} -> 0 | M3: {=SUMPRODUCT((BE_NL[Product Category]=$G3)*SUBTOTAL(109,OFFSET(INDEX(BE_NL[26M07],1),ROW(BE_NL[26M07])-MIN(ROW(BE_NL[26M07])),0,1)))} -> 0 | N3: {=SUMPRODUCT((BE_NL[Product Category]=$G3)*SUBTOTAL(109,OFFSET(INDEX(BE_NL[26M08],1),ROW(BE_NL[26M08])-MIN(ROW(BE_NL[26M08])),0,1)))} -> 0 | O3: {=SUMPRODUCT((BE_NL[Product Category]=$G3)*SUBTOTAL(109,OFFSET(INDEX(BE_NL[26M09],1),ROW(BE_NL[26M09])-MIN(ROW(BE_NL[26M09])),0,1)))} -> 0 | P3: {=SUMPRODUCT((BE_NL[Product Category]=$G3)*SUBTOTAL(109,OFFSET(INDEX(BE_NL[26M10],1),ROW(BE_NL[26M10])-MIN(ROW(BE_NL[26M10])),0,1)))} -> 0 | Q3: {=SUMPRODUCT((BE_NL[Product Category]=$G3)*SUBTOTAL(109,OFFSET(INDEX(BE_NL[26M11],1),ROW(BE_NL[26M11])-MIN(ROW(BE_NL[26M11])),0,1)))} -> 0 | R3: {=SUMPRODUCT((BE_NL[Product Category]=$G3)*SUBTOTAL(109,OFFSET(INDEX(BE_NL[26M12],1),ROW(BE_NL[26M12])-MIN(ROW(BE_NL[26M12])),0,1)))} -> 0 | S3: {=SUMPRODUCT((BE_NL[Product Category]=$G3)*SUBTOTAL(109,OFFSET(INDEX(BE_NL[26Q2],1),ROW(BE_NL[26Q2])-MIN(ROW(BE_NL[26Q2])),0,1)))} -> 0 | T3: {=SUMPRODUCT((BE_NL[Product Category]=$G3)*SUBTOTAL(109,OFFSET(INDEX(BE_NL[26Q3],1),ROW(BE_NL[26Q3])-MIN(ROW(BE_NL[26Q3])),0,1)))} -> 0 | U3: {=SUMPRODUCT((BE_NL[Product Category]=$G3)*SUBTOTAL(109,OFFSET(INDEX(BE_NL[26Q4],1),ROW(BE_NL[26Q4])-MIN(ROW(BE_NL[26Q4])),0,1)))} -> 0 | V3: {=SUMPRODUCT((BE_NL[Product Category]=$G3)*SUBTOTAL(109,OFFSET(INDEX(BE_NL[27M01],1),ROW(BE_NL[27M01])-MIN(ROW(BE_NL[27M01])),0,1)))} -> 0 | W3: {=SUMPRODUCT((BE_NL[Product Category]=$G3)*SUBTOTAL(109,OFFSET(INDEX(BE_NL[27M02],1),ROW(BE_NL[27M02])-MIN(ROW(BE_NL[27M02])),0,1)))} -> 0 | X3: {=SUMPRODUCT((BE_NL[Product Category]=$G3)*SUBTOTAL(109,OFFSET(INDEX(BE_NL[27M03],1),ROW(BE_NL[27M03])-MIN(ROW(BE_NL[27M03])),0,1)))} -> 0 | Y3: {=SUMPRODUCT((BE_NL[Product Category]=$G3)*SUBTOTAL(109,OFFSET(INDEX(BE_NL[27M04],1),ROW(BE_NL[27M04])-MIN(ROW(BE_NL[27M04])),0,1)))} -> 0 | Z3: {=SUMPRODUCT((BE_NL[Product Category]=$G3)*SUBTOTAL(109,OFFSET(INDEX(BE_NL[27M05],1),ROW(BE_NL[27M05])-MIN(ROW(BE_NL[27M05])),0,1)))} -> 0 | AA3: {=SUMPRODUCT((BE_NL[Product Category]=$G3)*SUBTOTAL(109,OFFSET(INDEX(BE_NL[27M06],1),ROW(BE_NL[27M06])-MIN(ROW(BE_NL[27M06])),0,1)))} -> 0 | AB3: {=SUMPRODUCT((BE_NL[Product Category]=$G3)*SUBTOTAL(109,OFFSET(INDEX(BE_NL[27Q1],1),ROW(BE_NL[27Q1])-MIN(ROW(BE_NL[27Q1])),0,1)))} -> 0 | AC3: {=SUMPRODUCT((BE_NL[Product Category]=$G3)*SUBTOTAL(109,OFFSET(INDEX(BE_NL[27Q2],1),ROW(BE_NL[27Q2])-MIN(ROW(BE_NL[27Q2])),0,1)))} -> 0
G4: PV | J4: {=SUMPRODUCT((BE_NL[Product Category]=$G4)*SUBTOTAL(109,OFFSET(INDEX(BE_NL[26M04],1),ROW(BE_NL[26M04])-MIN(ROW(BE_NL[26M04])),0,1)))} -> 1.69 | K4: {=SUMPRODUCT((BE_NL[Product Category]=$G4)*SUBTOTAL(109,OFFSET(INDEX(BE_NL[26M05],1),ROW(BE_NL[26M05])-MIN(ROW(BE_NL[26M05])),0,1)))} -> 5.43 | L4: {=SUMPRODUCT((BE_NL[Product Category]=$G4)*SUBTOTAL(109,OFFSET(INDEX(BE_NL[26M06],1),ROW(BE_NL[26M06])-MIN(ROW(BE_NL[26M06])),0,1)))} -> 8.56 | M4: {=SUMPRODUCT((BE_NL[Product Category]=$G4)*SUBTOTAL(109,OFFSET(INDEX(BE_NL[26M07],1),ROW(BE_NL[26M07])-MIN(ROW(BE_NL[26M07])),0,1)))} -> 5.38 | N4: {=SUMPRODUCT((BE_NL[Product Category]=$G4)*SUBTOTAL(109,OFFSET(INDEX(BE_NL[26M08],1),ROW(BE_NL[26M08])-MIN(ROW(BE_NL[26M08])),0,1)))} -> 2.94 | O4: {=SUMPRODUCT((BE_NL[Product Category]=$G4)*SUBTOTAL(109,OFFSET(INDEX(BE_NL[26M09],1),ROW(BE_NL[26M09])-MIN(ROW(BE_NL[26M09])),0,1)))} -> 12.92 | P4: {=SUMPRODUCT((BE_NL[Product Category]=$G4)*SUBTOTAL(109,OFFSET(INDEX(BE_NL[26M10],1),ROW(BE_NL[26M10])-MIN(ROW(BE_NL[26M10])),0,1)))} -> 11.7 | Q4: {=SUMPRODUCT((BE_NL[Product Category]=$G4)*SUBTOTAL(109,OFFSET(INDEX(BE_NL[26M11],1),ROW(BE_NL[26M11])-MIN(ROW(BE_NL[26M11])),0,1)))} -> 11.1 | R4: {=SUMPRODUCT((BE_NL[Product Category]=$G4)*SUBTOTAL(109,OFFSET(INDEX(BE_NL[26M12],1),ROW(BE_NL[26M12])-MIN(ROW(BE_NL[26M12])),0,1)))} -> 11 | S4: {=SUMPRODUCT((BE_NL[Product Category]=$G4)*SUBTOTAL(109,OFFSET(INDEX(BE_NL[26Q2],1),ROW(BE_NL[26Q2])-MIN(ROW(BE_NL[26Q2])),0,1)))} -> 13.73 | T4: {=SUMPRODUCT((BE_NL[Product Category]=$G4)*SUBTOTAL(109,OFFSET(INDEX(BE_NL[26Q3],1),ROW(BE_NL[26Q3])-MIN(ROW(BE_NL[26Q3])),0,1)))} -> 21.24 | U4: {=SUMPRODUCT((BE_NL[Product Category]=$G4)*SUBTOTAL(109,OFFSET(INDEX(BE_NL[26Q4],1),ROW(BE_NL[26Q4])-MIN(ROW(BE_NL[26Q4])),0,1)))} -> 33.8 | V4: {=SUMPRODUCT((BE_NL[Product Category]=$G4)*SUBTOTAL(109,OFFSET(INDEX(BE_NL[27M01],1),ROW(BE_NL[27M01])-MIN(ROW(BE_NL[27M01])),0,1)))} -> 0 | W4: {=SUMPRODUCT((BE_NL[Product Category]=$G4)*SUBTOTAL(109,OFFSET(INDEX(BE_NL[27M02],1),ROW(BE_NL[27M02])-MIN(ROW(BE_NL[27M02])),0,1)))} -> 0 | X4: {=SUMPRODUCT((BE_NL[Product Category]=$G4)*SUBTOTAL(109,OFFSET(INDEX(BE_NL[27M03],1),ROW(BE_NL[27M03])-MIN(ROW(BE_NL[27M03])),0,1)))} -> 0 | Y4: {=SUMPRODUCT((BE_NL[Product Category]=$G4)*SUBTOTAL(109,OFFSET(INDEX(BE_NL[27M04],1),ROW(BE_NL[27M04])-MIN(ROW(BE_NL[27M04])),0,1)))} -> 0 | Z4: {=SUMPRODUCT((BE_NL[Product Category]=$G4)*SUBTOTAL(109,OFFSET(INDEX(BE_NL[27M05],1),ROW(BE_NL[27M05])-MIN(ROW(BE_NL[27M05])),0,1)))} -> 0 | AA4: {=SUMPRODUCT((BE_NL[Product Category]=$G4)*SUBTOTAL(109,OFFSET(INDEX(BE_NL[27M06],1),ROW(BE_NL[27M06])-MIN(ROW(BE_NL[27M06])),0,1)))} -> 0 | AB4: {=SUMPRODUCT((BE_NL[Product Category]=$G4)*SUBTOTAL(109,OFFSET(INDEX(BE_NL[27Q1],1),ROW(BE_NL[27Q1])-MIN(ROW(BE_NL[27Q1])),0,1)))} -> 0 | AC4: {=SUMPRODUCT((BE_NL[Product Category]=$G4)*SUBTOTAL(109,OFFSET(INDEX(BE_NL[27Q2],1),ROW(BE_NL[27Q2])-MIN(ROW(BE_NL[27Q2])),0,1)))} -> 0
A5: Country | B5: Customer name | C5: RSM | D5: Brand | E5: Product Line | F5: Model name | G5: Stage | H5: Comments (Deal Breaker, spec/requirements, etc) | I5: Supply Chain | J5: 26M04 | K5: 26M05 | L5: 26M06 | M5: 26M07 | N5: 26M08 | O5: 26M09 | P5: 26M10 | Q5: 26M11 | R5: 26M12 | S5: 26Q2 | T5: 26Q3 | U5: 26Q4 | V5: 27M01 | W5: 27M02 | X5: 27M03 | Y5: 27M04 | Z5: 27M05 | AA5: 27M06 | AB5: 27Q1 | AC5: 27Q2 | AD5: Only 2026? | AE5: Product Category
A6: Belgium | B6: ECOSTAL SPRL | C6: Romain | D6: =VLOOKUP(BE_NL[[#This Row],[Product Line]],Prod_T6[],5,0) -> TCL | E6: TCL_T_Class | F6: HSM-ND48-DR450 | G6: 7 - Booked | H6: BOOKED | I6: Offshore | K6: 0.84 | L6: 0.84 | M6: 0.84 | N6: 0.84 | T6: =SUM(BE_NL[[#This Row],[26M07]:[26M09]]) -> 1.68 | U6: =SUM(BE_NL[[#This Row],[26M10]:[26M12]]) -> 0 | AB6: =SUM(BE_NL[[#This Row],[27M01]:[27M03]]) -> 0 | AC6: =SUM(BE_NL[[#This Row],[27M04]:[27M06]]) -> 0 | AD6: =IF(SUM(BE_NL[[#This Row],[26Q2]:[26Q4]])+SUM(BE_NL[[#This Row],[27Q1]:[27Q2]])=0,"No FSCT",IF(AND(SUM(BE_NL[[#This Row],[26Q2]:[26Q4]])>0,SUM(BE_NL[[#This Row],[27Q1]:[27Q2]])=0),"YES","NO")) -> YES | AE6: =VLOOKUP(BE_NL[[#This Row],[Product Line]],Prod_T6[],4,0) -> PV | AH6: {=BE_NL[Stage]} -> 7 - Booked
A7: Belgium | B7: ECOSTAL SPRL | D7: =VLOOKUP(BE_NL[[#This Row],[Product Line]],Prod_T6[],5,0) -> TCL | E7: TCL_T_Class | F7: HSM-ND48-DR450 | G7: 7 - Booked | H7: H1-2026 | I7: Offshore | K7: 0.42 | L7: 4 | M7: 2.3 | S7: =SUM(BE_NL[[#This Row],[26M04]:[26M06]]) -> 4.42 | T7: =SUM(BE_NL[[#This Row],[26M07]:[26M09]]) -> 2.3 | U7: =SUM(BE_NL[[#This Row],[26M10]:[26M12]]) -> 0 | AB7: =SUM(BE_NL[[#This Row],[27M01]:[27M03]]) -> 0 | AC7: =SUM(BE_NL[[#This Row],[27M04]:[27M06]]) -> 0 | AD7: =IF(SUM(BE_NL[[#This Row],[26Q2]:[26Q4]])+SUM(BE_NL[[#This Row],[27Q1]:[27Q2]])=0,"No FSCT",IF(AND(SUM(BE_NL[[#This Row],[26Q2]:[26Q4]])>0,SUM(BE_NL[[#This Row],[27Q1]:[27Q2]])=0),"YES","NO")) -> YES | AE7: =VLOOKUP(BE_NL[[#This Row],[Product Line]],Prod_T6[],4,0) -> PV | AH7: 7 - Booked
A8: Belgium | B8: ECOSTAL SPRL | D8: =VLOOKUP(BE_NL[[#This Row],[Product Line]],Prod_T6[],5,0) -> TCL | E8: TCL_T5_Pro | F8: HSM-NT48-HH 465/470-Black | G8: 7 - Booked | H8: BOOKED | I8: Offshore | N8: 2 | O8: 2 | P8: 2 | S8: =SUM(BE_NL[[#This Row],[26M04]:[26M06]]) -> 0 | T8: =SUM(BE_NL[[#This Row],[26M07]:[26M09]]) -> 4 | U8: =SUM(BE_NL[[#This Row],[26M10]:[26M12]]) -> 2 | AB8: =SUM(BE_NL[[#This Row],[27M01]:[27M03]]) -> 0 | AC8: =SUM(BE_NL[[#This Row],[27M04]:[27M06]]) -> 0 | AD8: =IF(SUM(BE_NL[[#This Row],[26Q2]:[26Q4]])+SUM(BE_NL[[#This Row],[27Q1]:[27Q2]])=0,"No FSCT",IF(AND(SUM(BE_NL[[#This Row],[26Q2]:[26Q4]])>0,SUM(BE_NL[[#This Row],[27Q1]:[27Q2]])=0),"YES","NO")) -> YES | AE8: =VLOOKUP(BE_NL[[#This Row],[Product Line]],Prod_T6[],4,0) -> PV | AH8: 7 - Booked
A9: Belgium | B9: ECOSTAL SPRL | D9: =VLOOKUP(BE_NL[[#This Row],[Product Line]],Prod_T6[],5,0) -> TCL | E9: TCL_C2_Series | F9: HSM-BE54-HD485/490 | G9: 3 - Negotiation | H9: AWAITING FORECAST | I9: offshore | P9: 1 | Q9: 1 | R9: 1 | S9: =SUM(BE_NL[[#This Row],[26M04]:[26M06]]) -> 0 | T9: =SUM(BE_NL[[#This Row],[26M07]:[26M09]]) -> 0 | U9: =SUM(BE_NL[[#This Row],[26M10]:[26M12]]) -> 3 | AB9: =SUM(BE_NL[[#This Row],[27M01]:[27M03]]) -> 0 | AC9: =SUM(BE_NL[[#This Row],[27M04]:[27M06]]) -> 0 | AD9: =IF(SUM(BE_NL[[#This Row],[26Q2]:[26Q4]])+SUM(BE_NL[[#This Row],[27Q1]:[27Q2]])=0,"No FSCT",IF(AND(SUM(BE_NL[[#This Row],[26Q2]:[26Q4]])>0,SUM(BE_NL[[#This Row],[27Q1]:[27Q2]])=0),"YES","NO")) -> YES | AE9: =VLOOKUP(BE_NL[[#This Row],[Product Line]],Prod_T6[],4,0) -> PV | AH9: 3 - Negotiation
A10: Belgium | B10: ECOSTAL SPRL | D10: =VLOOKUP(BE_NL[[#This Row],[Product Line]],Prod_T6[],5,0) -> Sunpower | E10: SPR_BC | F10: SPR-BE54-HD490/495 | G10: 4 - BAFO | H10: AWAITING FORECAST | I10: Offshore | Q10: 0.4 | R10: 0.4 | S10: =SUM(BE_NL[[#This Row],[26M04]:[26M06]]) -> 0 | T10: =SUM(BE_NL[[#This Row],[26M07]:[26M09]]) -> 0 | U10: =SUM(BE_NL[[#This Row],[26M10]:[26M12]]) -> 0.8 | AB10: =SUM(BE_NL[[#This Row],[27M01]:[27M03]]) -> 0 | AC10: =SUM(BE_NL[[#This Row],[27M04]:[27M06]]) -> 0 | AD10: =IF(SUM(BE_NL[[#This Row],[26Q2]:[26Q4]])+SUM(BE_NL[[#This Row],[27Q1]:[27Q2]])=0,"No FSCT",IF(AND(SUM(BE_NL[[#This Row],[26Q2]:[26Q4]])>0,SUM(BE_NL[[#This Row],[27Q1]:[27Q2]])=0),"YES","NO")) -> YES | AE10: =VLOOKUP(BE_NL[[#This Row],[Product Line]],Prod_T6[],4,0) -> PV | AH10: 4 - BAFO
A11: Belgium | B11: ECOSTAL SPRL | D11: =VLOOKUP(BE_NL[[#This Row],[Product Line]],Prod_T6[],5,0) -> TCL | E11: TCL_T5_Pro | F11: HSM-NT66-GH 640/645 | G11: 4 - BAFO | H11: AWAITING FORECAST | I11: Offshore | P11: 0.4 | Q11: 0.4 | R11: 0.4 | S11: =SUM(BE_NL[[#This Row],[26M04]:[26M06]]) -> 0 | T11: =SUM(BE_NL[[#This Row],[26M07]:[26M09]]) -> 0 | U11: =SUM(BE_NL[[#This Row],[26M10]:[26M12]]) -> 1.2 | AB11: =SUM(BE_NL[[#This Row],[27M01]:[27M03]]) -> 0 | AC11: =SUM(BE_NL[[#This Row],[27M04]:[27M06]]) -> 0 | AD11: =IF(SUM(BE_NL[[#This Row],[26Q2]:[26Q4]])+SUM(BE_NL[[#This Row],[27Q1]:[27Q2]])=0,"No FSCT",IF(AND(SUM(BE_NL[[#This Row],[26Q2]:[26Q4]])>0,SUM(BE_NL[[#This Row],[27Q1]:[27Q2]])=0),"YES","NO")) -> YES | AE11: =VLOOKUP(BE_NL[[#This Row],[Product Line]],Prod_T6[],4,0) -> PV | AH11: 4 - BAFO
A12: Belgium | B12: ECOSTAL SPRL | C12: Romain | D12: =VLOOKUP(BE_NL[[#This Row],[Product Line]],Prod_T6[],5,0) -> TCL | E12: TCL_T_Class | F12: HSM-ND66-GK725 | G12: 6 - Won | H12: WON | I12: Offshore | O12: 5.7 | T12: =SUM(BE_NL[[#This Row],[26M07]:[26M09]]) -> 5.7 | U12: =SUM(BE_NL[[#This Row],[26M10]:[26M12]]) -> 0 | AB12: =SUM(BE_NL[[#This Row],[27M01]:[27M03]]) -> 0 | AC12: =SUM(BE_NL[[#This Row],[27M04]:[27M06]]) -> 0 | AD12: =IF(SUM(BE_NL[[#This Row],[26Q2]:[26Q4]])+SUM(BE_NL[[#This Row],[27Q1]:[27Q2]])=0,"No FSCT",IF(AND(SUM(BE_NL[[#This Row],[26Q2]:[26Q4]])>0,SUM(BE_NL[[#This Row],[27Q1]:[27Q2]])=0),"YES","NO")) -> YES | AE12: =VLOOKUP(BE_NL[[#This Row],[Product Line]],Prod_T6[],4,0) -> PV | AH12: 6 - Won
A13: Belgium | B13: ECOSTAL SPRL | C13: Romain | D13: =VLOOKUP(BE_NL[[#This Row],[Product Line]],Prod_T6[],5,0) -> TCL | E13: TCL_T_Class | F13: HSM-ND48-DR450 | G13: 0 - Lost | H13: LOST TO UNDERCORE BETTER ASP | I13: Offshore | J13: 1.2 | K13: 1.2 | L13: 1.2 | S13: =SUM(BE_NL[[#This Row],[26M04]:[26M06]]) -> 3.6 | T13: =SUM(BE_NL[[#This Row],[26M07]:[26M09]]) -> 0 | U13: =SUM(BE_NL[[#This Row],[26M10]:[26M12]]) -> 0 | AB13: =SUM(BE_NL[[#This Row],[27M01]:[27M03]]) -> 0 | AC13: =SUM(BE_NL[[#This Row],[27M04]:[27M06]]) -> 0 | AD13: =IF(SUM(BE_NL[[#This Row],[26Q2]:[26Q4]])+SUM(BE_NL[[#This Row],[27Q1]:[27Q2]])=0,"No FSCT",IF(AND(SUM(BE_NL[[#This Row],[26Q2]:[26Q4]])>0,SUM(BE_NL[[#This Row],[27Q1]:[27Q2]])=0),"YES","NO")) -> YES | AE13: =VLOOKUP(BE_NL[[#This Row],[Product Line]],Prod_T6[],4,0) -> PV | AH13: 0 - Lost
A14: Belgium | B14: ECOSTAL SPRL | C14: Romain | D14: =VLOOKUP(BE_NL[[#This Row],[Product Line]],Prod_T6[],5,0) -> TCL | E14: TCL_T5_Pro | F14: HSM-NT48-HH 465/470-Black | G14: 0 - Lost | H14: LOST TO UNDERCORE BETTER ASP | I14: Offshore | M14: 1.2 | N14: 1.2 | O14: 1.2 | S14: =SUM(BE_NL[[#This Row],[26M04]:[26M06]]) -> 0 | T14: =SUM(BE_NL[[#This Row],[26M07]:[26M09]]) -> 3.6 | U14: =SUM(BE_NL[[#This Row],[26M10]:[26M12]]) -> 0 | AB14: =SUM(BE_NL[[#This Row],[27M01]:[27M03]]) -> 0 | AC14: =SUM(BE_NL[[#This Row],[27M04]:[27M06]]) -> 0 | AD14: =IF(SUM(BE_NL[[#This Row],[26Q2]:[26Q4]])+SUM(BE_NL[[#This Row],[27Q1]:[27Q2]])=0,"No FSCT",IF(AND(SUM(BE_NL[[#This Row],[26Q2]:[26Q4]])>0,SUM(BE_NL[[#This Row],[27Q1]:[27Q2]])=0),"YES","NO")) -> YES | AE14: =VLOOKUP(BE_NL[[#This Row],[Product Line]],Prod_T6[],4,0) -> PV | AH14: 0 - Lost
A15: Belgium | B15: ECOSTAL SPRL | D15: =VLOOKUP(BE_NL[[#This Row],[Product Line]],Prod_T6[],5,0) -> TCL | E15: TCL_T_Class | F15: HSM-ND54-DR505 | G15: 7 - Booked | H15: Q1 PROJECT | I15: Offshore | K15: 1.2 | L15: 1.2 | S15: =SUM(BE_NL[[#This Row],[26M04]:[26M06]]) -> 2.4 | T15: =SUM(BE_NL[[#This Row],[26M07]:[26M09]]) -> 0 | U15: =SUM(BE_NL[[#This Row],[26M10]:[26M12]]) -> 0 | AB15: =SUM(BE_NL[[#This Row],[27M01]:[27M03]]) -> 0 | AC15: =SUM(BE_NL[[#This Row],[27M04]:[27M06]]) -> 0 | AD15: =IF(SUM(BE_NL[[#This Row],[26Q2]:[26Q4]])+SUM(BE_NL[[#This Row],[27Q1]:[27Q2]])=0,"No FSCT",IF(AND(SUM(BE_NL[[#This Row],[26Q2]:[26Q4]])>0,SUM(BE_NL[[#This Row],[27Q1]:[27Q2]])=0),"YES","NO")) -> YES | AE15: =VLOOKUP(BE_NL[[#This Row],[Product Line]],Prod_T6[],4,0) -> PV | AH15: 7 - Booked
A16: Belgium | B16: SOLAR DEPOT SARL. | C16: Romain | D16: =VLOOKUP(BE_NL[[#This Row],[Product Line]],Prod_T6[],5,0) -> TCL | E16: TCL_T_Class | F16: HSM-ND48-DR455 | G16: 7 - Booked | H16: AWAITING ORDER | I16: EU | J16: 0.42 | T16: =SUM(BE_NL[[#This Row],[26M07]:[26M09]]) -> 0 | U16: =SUM(BE_NL[[#This Row],[26M10]:[26M12]]) -> 0 | AB16: =SUM(BE_NL[[#This Row],[27M01]:[27M03]]) -> 0 | AC16: =SUM(BE_NL[[#This Row],[27M04]:[27M06]]) -> 0 | AD16: =IF(SUM(BE_NL[[#This Row],[26Q2]:[26Q4]])+SUM(BE_NL[[#This Row],[27Q1]:[27Q2]])=0,"No FSCT",IF(AND(SUM(BE_NL[[#This Row],[26Q2]:[26Q4]])>0,SUM(BE_NL[[#This Row],[27Q1]:[27Q2]])=0),"YES","NO")) -> No FSCT | AE16: =VLOOKUP(BE_NL[[#This Row],[Product Line]],Prod_T6[],4,0) -> PV | AH16: 7 - Booked
A17: Belgium | B17: SOLAR DEPOT SARL. | D17: =VLOOKUP(BE_NL[[#This Row],[Product Line]],Prod_T6[],5,0) -> TCL | E17: TCL_T5_Pro | F17: HSM-NT48-HH 465/470-Black | G17: 7 - Booked | I17: EU | S17: =SUM(BE_NL[[#This Row],[26M04]:[26M06]]) -> 0 | T17: =SUM(BE_NL[[#This Row],[26M07]:[26M09]]) -> 0 | U17: =SUM(BE_NL[[#This Row],[26M10]:[26M12]]) -> 0 | AB17: =SUM(BE_NL[[#This Row],[27M01]:[27M03]]) -> 0 | AC17: =SUM(BE_NL[[#This Row],[27M04]:[27M06]]) -> 0 | AD17: =IF(SUM(BE_NL[[#This Row],[26Q2]:[26Q4]])+SUM(BE_NL[[#This Row],[27Q1]:[27Q2]])=0,"No FSCT",IF(AND(SUM(BE_NL[[#This Row],[26Q2]:[26Q4]])>0,SUM(BE_NL[[#This Row],[27Q1]:[27Q2]])=0),"YES","NO")) -> No FSCT | AE17: =VLOOKUP(BE_NL[[#This Row],[Product Line]],Prod_T6[],4,0) -> PV | AH17: 7 - Booked
A18: Netherlands | B18: VDH Solar Groothandel B.V. | C18: Regis | D18: =VLOOKUP(BE_NL[[#This Row],[Product Line]],Prod_T6[],5,0) -> TCL | E18: TCL_E_Class | F18: HSM-BD54-DA465 | G18: 7 - Booked | H18: CONSIGNEMENT | I18: EU | J18: 0.45 | K18: 0.45 | L18: 0.45 | M18: 0.45 | S18: =SUM(BE_NL[[#This Row],[26M04]:[26M06]]) -> 1.35 | T18: =SUM(BE_NL[[#This Row],[26M07]:[26M09]]) -> 0.45 | U18: =SUM(BE_NL[[#This Row],[26M10]:[26M12]]) -> 0 | AB18: =SUM(BE_NL[[#This Row],[27M01]:[27M03]]) -> 0 | AC18: =SUM(BE_NL[[#This Row],[27M04]:[27M06]]) -> 0 | AD18: =IF(SUM(BE_NL[[#This Row],[26Q2]:[26Q4]])+SUM(BE_NL[[#This Row],[27Q1]:[27Q2]])=0,"No FSCT",IF(AND(SUM(BE_NL[[#This Row],[26Q2]:[26Q4]])>0,SUM(BE_NL[[#This Row],[27Q1]:[27Q2]])=0),"YES","NO")) -> YES | AE18: =VLOOKUP(BE_NL[[#This Row],[Product Line]],Prod_T6[],4,0) -> PV | AH18: 7 - Booked
A19: Netherlands | B19: VDH Solar Groothandel B.V. | D19: =VLOOKUP(BE_NL[[#This Row],[Product Line]],Prod_T6[],5,0) -> TCL | E19: TCL_T5_Pro | F19: HSM-NT48-HH 465/470-Black | G19: 0 - Lost | H19: BANKRUPTCY | I19: EU | S19: =SUM(BE_NL[[#This Row],[26M04]:[26M06]]) -> 0 | T19: =SUM(BE_NL[[#This Row],[26M07]:[26M09]]) -> 0 | U19: =SUM(BE_NL[[#This Row],[26M10]:[26M12]]) -> 0 | AB19: =SUM(BE_NL[[#This Row],[27M01]:[27M03]]) -> 0 | AC19: =SUM(BE_NL[[#This Row],[27M04]:[27M06]]) -> 0 | AD19: =IF(SUM(BE_NL[[#This Row],[26Q2]:[26Q4]])+SUM(BE_NL[[#This Row],[27Q1]:[27Q2]])=0,"No FSCT",IF(AND(SUM(BE_NL[[#This Row],[26Q2]:[26Q4]])>0,SUM(BE_NL[[#This Row],[27Q1]:[27Q2]])=0),"YES","NO")) -> No FSCT | AE19: =VLOOKUP(BE_NL[[#This Row],[Product Line]],Prod_T6[],4,0) -> PV | AH19: 0 - Lost
A20: Netherlands | B20: Natec Sunenergy B.V. | C20: Regis | D20: =VLOOKUP(BE_NL[[#This Row],[Product Line]],Prod_T6[],5,0) -> TCL | E20: TCL_E_Class | F20: HSM-BD54-DA465 | G20: 7 - Booked | H20: CONSIGNEMENT | I20: EU | L20: 0.45 | M20: 0.45 | S20: =SUM(BE_NL[[#This Row],[26M04]:[26M06]]) -> 0.45 | T20: =SUM(BE_NL[[#This Row],[26M07]:[26M09]]) -> 0.45 | U20: =SUM(BE_NL[[#This Row],[26M10]:[26M12]]) -> 0 | AB20: =SUM(BE_NL[[#This Row],[27M01]:[27M03]]) -> 0 | AC20: =SUM(BE_NL[[#This Row],[27M04]:[27M06]]) -> 0 | AD20: =IF(SUM(BE_NL[[#This Row],[26Q2]:[26Q4]])+SUM(BE_NL[[#This Row],[27Q1]:[27Q2]])=0,"No FSCT",IF(AND(SUM(BE_NL[[#This Row],[26Q2]:[26Q4]])>0,SUM(BE_NL[[#This Row],[27Q1]:[27Q2]])=0),"YES","NO")) -> YES | AE20: =VLOOKUP(BE_NL[[#This Row],[Product Line]],Prod_T6[],4,0) -> PV | AH20: 7 - Booked
A21: Netherlands | B21: Natec Sunenergy B.V. | D21: =VLOOKUP(BE_NL[[#This Row],[Product Line]],Prod_T6[],5,0) -> TCL | E21: TCL_E_Class | F21: HSM-BD72-GC650 | G21: 0 - Lost | H21: In competition with Energy 3000 at 0.112/Wp DDP | I21: EU | K21: 1.2 | S21: =SUM(BE_NL[[#This Row],[26M04]:[26M06]]) -> 1.2 | T21: =SUM(BE_NL[[#This Row],[26M07]:[26M09]]) -> 0 | U21: =SUM(BE_NL[[#This Row],[26M10]:[26M12]]) -> 0 | AB21: =SUM(BE_NL[[#This Row],[27M01]:[27M03]]) -> 0 | AC21: =SUM(BE_NL[[#This Row],[27M04]:[27M06]]) -> 0 | AD21: =IF(SUM(BE_NL[[#This Row],[26Q2]:[26Q4]])+SUM(BE_NL[[#This Row],[27Q1]:[27Q2]])=0,"No FSCT",IF(AND(SUM(BE_NL[[#This Row],[26Q2]:[26Q4]])>0,SUM(BE_NL[[#This Row],[27Q1]:[27Q2]])=0),"YES","NO")) -> YES | AE21: =VLOOKUP(BE_NL[[#This Row],[Product Line]],Prod_T6[],4,0) -> PV | AH21: 0 - Lost
A22: Netherlands | B22: Natec Sunenergy B.V. | D22: =VLOOKUP(BE_NL[[#This Row],[Product Line]],Prod_T6[],5,0) -> TCL | E22: TCL_T_Class | F22: HSM-ND48-DR450 | G22: 6 - Won | H22: TRINA Vertex 455 BLK at 0.110 DDP/Longi 460W BLK at 0.108 DDP NEED BETTER ASP 455W | I22: EU | J22: 0.4 | K22: 1.2 | L22: 1.2 | S22: =SUM(BE_NL[[#This Row],[26M04]:[26M06]]) -> 2.8 | T22: =SUM(BE_NL[[#This Row],[26M07]:[26M09]]) -> 0 | U22: =SUM(BE_NL[[#This Row],[26M10]:[26M12]]) -> 0 | AB22: =SUM(BE_NL[[#This Row],[27M01]:[27M03]]) -> 0 | AC22: =SUM(BE_NL[[#This Row],[27M04]:[27M06]]) -> 0 | AD22: =IF(SUM(BE_NL[[#This Row],[26Q2]:[26Q4]])+SUM(BE_NL[[#This Row],[27Q1]:[27Q2]])=0,"No FSCT",IF(AND(SUM(BE_NL[[#This Row],[26Q2]:[26Q4]])>0,SUM(BE_NL[[#This Row],[27Q1]:[27Q2]])=0),"YES","NO")) -> YES | AE22: =VLOOKUP(BE_NL[[#This Row],[Product Line]],Prod_T6[],4,0) -> PV | AH22: 6 - Won
A23: Netherlands | B23: Natec Sunenergy B.V. | D23: =VLOOKUP(BE_NL[[#This Row],[Product Line]],Prod_T6[],5,0) -> TCL | E23: TCL_T5_Pro | F23: HSM-NT48-HH 465/470-Black | G23: 3 - Negotiation | H23: AWAITING FORECAST | I23: EU | O23: 1.2 | P23: 1.2 | Q23: 1.2 | R23: 1.2 | S23: =SUM(BE_NL[[#This Row],[26M04]:[26M06]]) -> 0 | T23: =SUM(BE_NL[[#This Row],[26M07]:[26M09]]) -> 1.2 | U23: =SUM(BE_NL[[#This Row],[26M10]:[26M12]]) -> 3.6 | AB23: =SUM(BE_NL[[#This Row],[27M01]:[27M03]]) -> 0 | AC23: =SUM(BE_NL[[#This Row],[27M04]:[27M06]]) -> 0 | AD23: =IF(SUM(BE_NL[[#This Row],[26Q2]:[26Q4]])+SUM(BE_NL[[#This Row],[27Q1]:[27Q2]])=0,"No FSCT",IF(AND(SUM(BE_NL[[#This Row],[26Q2]:[26Q4]])>0,SUM(BE_NL[[#This Row],[27Q1]:[27Q2]])=0),"YES","NO")) -> YES | AE23: =VLOOKUP(BE_NL[[#This Row],[Product Line]],Prod_T6[],4,0) -> PV | AH23: 3 - Negotiation
A24: Netherlands | B24: Natec Sunenergy B.V. | D24: =VLOOKUP(BE_NL[[#This Row],[Product Line]],Prod_T6[],5,0) -> TCL | E24: TCL_C2_Series | F24: HSM-BE54-HD485/490 | G24: 3 - Negotiation | H24: AWAITING FORECAST | I24: EU | P24: 0.4 | Q24: 0.4 | R24: 0.4 | S24: =SUM(BE_NL[[#This Row],[26M04]:[26M06]]) -> 0 | T24: =SUM(BE_NL[[#This Row],[26M07]:[26M09]]) -> 0 | U24: =SUM(BE_NL[[#This Row],[26M10]:[26M12]]) -> 1.2 | AB24: =SUM(BE_NL[[#This Row],[27M01]:[27M03]]) -> 0 | AC24: =SUM(BE_NL[[#This Row],[27M04]:[27M06]]) -> 0 | AD24: =IF(SUM(BE_NL[[#This Row],[26Q2]:[26Q4]])+SUM(BE_NL[[#This Row],[27Q1]:[27Q2]])=0,"No FSCT",IF(AND(SUM(BE_NL[[#This Row],[26Q2]:[26Q4]])>0,SUM(BE_NL[[#This Row],[27Q1]:[27Q2]])=0),"YES","NO")) -> YES | AE24: =VLOOKUP(BE_NL[[#This Row],[Product Line]],Prod_T6[],4,0) -> PV | AH24: 3 - Negotiation
A25: Netherlands | B25: Natec Sunenergy B.V. | D25: =VLOOKUP(BE_NL[[#This Row],[Product Line]],Prod_T6[],5,0) -> TCL | E25: TCL_T_Class | F25: HSM-ND66-GK725 | G25: 0 - Lost | H25: PROJECT 6.85 MW Proposed at 0.122 DPP Delivery Q3 | I25: EU | N25: 3.25 | O25: 3.25 | S25: =SUM(BE_NL[[#This Row],[26M04]:[26M06]]) -> 0 | T25: =SUM(BE_NL[[#This Row],[26M07]:[26M09]]) -> 6.5 | U25: =SUM(BE_NL[[#This Row],[26M10]:[26M12]]) -> 0 | AB25: =SUM(BE_NL[[#This Row],[27M01]:[27M03]]) -> 0 | AC25: =SUM(BE_NL[[#This Row],[27M04]:[27M06]]) -> 0 | AD25: =IF(SUM(BE_NL[[#This Row],[26Q2]:[26Q4]])+SUM(BE_NL[[#This Row],[27Q1]:[27Q2]])=0,"No FSCT",IF(AND(SUM(BE_NL[[#This Row],[26Q2]:[26Q4]])>0,SUM(BE_NL[[#This Row],[27Q1]:[27Q2]])=0),"YES","NO")) -> YES | AE25: =VLOOKUP(BE_NL[[#This Row],[Product Line]],Prod_T6[],4,0) -> PV | AH25: 0 - Lost
A26: Netherlands | B26: Natec Sunenergy B.V. | D26: =VLOOKUP(BE_NL[[#This Row],[Product Line]],Prod_T6[],5,0) -> TCL | E26: TCL_T_Class | F26: HSM-ND66-GR625 | G26: 0 - Lost | H26: Offer at 0.117 EUR/Wp | I26: EU | K26: 0.42 | S26: =SUM(BE_NL[[#This Row],[26M04]:[26M06]]) -> 0.42 | T26: =SUM(BE_NL[[#This Row],[26M07]:[26M09]]) -> 0 | U26: =SUM(BE_NL[[#This Row],[26M10]:[26M12]]) -> 0 | AB26: =SUM(BE_NL[[#This Row],[27M01]:[27M03]]) -> 0 | AC26: =SUM(BE_NL[[#This Row],[27M04]:[27M06]]) -> 0 | AD26: =IF(SUM(BE_NL[[#This Row],[26Q2]:[26Q4]])+SUM(BE_NL[[#This Row],[27Q1]:[27Q2]])=0,"No FSCT",IF(AND(SUM(BE_NL[[#This Row],[26Q2]:[26Q4]])>0,SUM(BE_NL[[#This Row],[27Q1]:[27Q2]])=0),"YES","NO")) -> YES | AE26: =VLOOKUP(BE_NL[[#This Row],[Product Line]],Prod_T6[],4,0) -> PV | AH26: 0 - Lost
A27: Belgium | B27: Reno.Energy SA | D27: =VLOOKUP(BE_NL[[#This Row],[Product Line]],Prod_T6[],5,0) -> TCL | E27: TCL_T5_Pro | F27: HSM-NT48-HH 465/470-Black | G27: 3 - Negotiation | H27: AWAITING FORECAST | I27: EU | O27: 0.8 | P27: 0.8 | Q27: 0.8 | R27: 0.8 | S27: =SUM(BE_NL[[#This Row],[26M04]:[26M06]]) -> 0 | T27: =SUM(BE_NL[[#This Row],[26M07]:[26M09]]) -> 0.8 | U27: =SUM(BE_NL[[#This Row],[26M10]:[26M12]]) -> 2.4 | AB27: =SUM(BE_NL[[#This Row],[27M01]:[27M03]]) -> 0 | AC27: =SUM(BE_NL[[#This Row],[27M04]:[27M06]]) -> 0 | AD27: =IF(SUM(BE_NL[[#This Row],[26Q2]:[26Q4]])+SUM(BE_NL[[#This Row],[27Q1]:[27Q2]])=0,"No FSCT",IF(AND(SUM(BE_NL[[#This Row],[26Q2]:[26Q4]])>0,SUM(BE_NL[[#This Row],[27Q1]:[27Q2]])=0),"YES","NO")) -> YES | AE27: =VLOOKUP(BE_NL[[#This Row],[Product Line]],Prod_T6[],4,0) -> PV | AH27: 3 - Negotiation
A28: Belgium | B28: Reno.Energy SA | D28: =VLOOKUP(BE_NL[[#This Row],[Product Line]],Prod_T6[],5,0) -> TCL | E28: TCL_C2_Series | F28: HSM-BE54-HD485/490 | G28: 3 - Negotiation | H28: AWAITING FORECAST | I28: EU | O28: 0.4 | P28: 0.4 | Q28: 0.4 | R28: 0.4 | S28: =SUM(BE_NL[[#This Row],[26M04]:[26M06]]) -> 0 | T28: =SUM(BE_NL[[#This Row],[26M07]:[26M09]]) -> 0.4 | U28: =SUM(BE_NL[[#This Row],[26M10]:[26M12]]) -> 1.2 | AB28: =SUM(BE_NL[[#This Row],[27M01]:[27M03]]) -> 0 | AC28: =SUM(BE_NL[[#This Row],[27M04]:[27M06]]) -> 0 | AD28: =IF(SUM(BE_NL[[#This Row],[26Q2]:[26Q4]])+SUM(BE_NL[[#This Row],[27Q1]:[27Q2]])=0,"No FSCT",IF(AND(SUM(BE_NL[[#This Row],[26Q2]:[26Q4]])>0,SUM(BE_NL[[#This Row],[27Q1]:[27Q2]])=0),"YES","NO")) -> YES | AE28: =VLOOKUP(BE_NL[[#This Row],[Product Line]],Prod_T6[],4,0) -> PV | AH28: 3 - Negotiation
A29: Belgium | B29: Reno.Energy SA | D29: =VLOOKUP(BE_NL[[#This Row],[Product Line]],Prod_T6[],5,0) -> Sunpower | E29: SPR_BC | F29: SPR-BE54-HD490/495 | G29: 3 - Negotiation | H29: AWAITING FORECAST | I29: EU | O29: 1 | S29: =SUM(BE_NL[[#This Row],[26M04]:[26M06]]) -> 0 | T29: =SUM(BE_NL[[#This Row],[26M07]:[26M09]]) -> 1 | U29: =SUM(BE_NL[[#This Row],[26M10]:[26M12]]) -> 0 | AB29: =SUM(BE_NL[[#This Row],[27M01]:[27M03]]) -> 0 | AC29: =SUM(BE_NL[[#This Row],[27M04]:[27M06]]) -> 0 | AD29: =IF(SUM(BE_NL[[#This Row],[26Q2]:[26Q4]])+SUM(BE_NL[[#This Row],[27Q1]:[27Q2]])=0,"No FSCT",IF(AND(SUM(BE_NL[[#This Row],[26Q2]:[26Q4]])>0,SUM(BE_NL[[#This Row],[27Q1]:[27Q2]])=0),"YES","NO")) -> YES | AE29: =VLOOKUP(BE_NL[[#This Row],[Product Line]],Prod_T6[],4,0) -> PV | AH29: 3 - Negotiation
A30: Belgium | B30: bvba BeliVert | C30: Regis | D30: =VLOOKUP(BE_NL[[#This Row],[Product Line]],Prod_T6[],5,0) -> Sunpower | E30: SPR_P7 | F30: P7-BLK-2mm-455 | G30: 7 - Booked | H30: AWAITING ORDER | I30: EU | J30: 0.42 | K30: 0.42 | L30: 0.42 | M30: 0.42 | O30: 0.42 | S30: =SUM(BE_NL[[#This Row],[26M04]:[26M06]]) -> 1.26 | T30: =SUM(BE_NL[[#This Row],[26M07]:[26M09]]) -> 0.84 | U30: =SUM(BE_NL[[#This Row],[26M10]:[26M12]]) -> 0 | AB30: =SUM(BE_NL[[#This Row],[27M01]:[27M03]]) -> 0 | AC30: =SUM(BE_NL[[#This Row],[27M04]:[27M06]]) -> 0 | AD30: =IF(SUM(BE_NL[[#This Row],[26Q2]:[26Q4]])+SUM(BE_NL[[#This Row],[27Q1]:[27Q2]])=0,"No FSCT",IF(AND(SUM(BE_NL[[#This Row],[26Q2]:[26Q4]])>0,SUM(BE_NL[[#This Row],[27Q1]:[27Q2]])=0),"YES","NO")) -> YES | AE30: =VLOOKUP(BE_NL[[#This Row],[Product Line]],Prod_T6[],4,0) -> PV | AH30: 7 - Booked
A31: Belgium | B31: bvba BeliVert | D31: =VLOOKUP(BE_NL[[#This Row],[Product Line]],Prod_T6[],5,0) -> Sunpower | E31: SPR_BC | F31: SPR-BE54-HD490/495 | G31: 3 - Negotiation | I31: EU | Q31: 0.9 | R31: 0.9 | T31: =SUM(BE_NL[[#This Row],[26M07]:[26M09]]) -> 0 | U31: =SUM(BE_NL[[#This Row],[26M10]:[26M12]]) -> 1.8 | AB31: =SUM(BE_NL[[#This Row],[27M01]:[27M03]]) -> 0 | AC31: =SUM(BE_NL[[#This Row],[27M04]:[27M06]]) -> 0 | AD31: =IF(SUM(BE_NL[[#This Row],[26Q2]:[26Q4]])+SUM(BE_NL[[#This Row],[27Q1]:[27Q2]])=0,"No FSCT",IF(AND(SUM(BE_NL[[#This Row],[26Q2]:[26Q4]])>0,SUM(BE_NL[[#This Row],[27Q1]:[27Q2]])=0),"YES","NO")) -> YES | AE31: =VLOOKUP(BE_NL[[#This Row],[Product Line]],Prod_T6[],4,0) -> PV | AH31: 3 - Negotiation
A32: Belgium | B32: SOLARPRO BVBA | C32: Regis | D32: =VLOOKUP(BE_NL[[#This Row],[Product Line]],Prod_T6[],5,0) -> Sunpower | E32: SPR_P7 | F32: P7-BLK-2mm-460 | G32: 7 - Booked | I32: EU | K32: 0.1 | M32: 0.1 | N32: 0.1 | O32: 0.1 | S32: =SUM(BE_NL[[#This Row],[26M04]:[26M06]]) -> 0.1 | T32: =SUM(BE_NL[[#This Row],[26M07]:[26M09]]) -> 0.3 | U32: =SUM(BE_NL[[#This Row],[26M10]:[26M12]]) -> 0 | AB32: =SUM(BE_NL[[#This Row],[27M01]:[27M03]]) -> 0 | AC32: =SUM(BE_NL[[#This Row],[27M04]:[27M06]]) -> 0 | AD32: =IF(SUM(BE_NL[[#This Row],[26Q2]:[26Q4]])+SUM(BE_NL[[#This Row],[27Q1]:[27Q2]])=0,"No FSCT",IF(AND(SUM(BE_NL[[#This Row],[26Q2]:[26Q4]])>0,SUM(BE_NL[[#This Row],[27Q1]:[27Q2]])=0),"YES","NO")) -> YES | AE32: =VLOOKUP(BE_NL[[#This Row],[Product Line]],Prod_T6[],4,0) -> PV | AH32: 7 - Booked
A33: Belgium | B33: SOLARPRO | D33: =VLOOKUP(BE_NL[[#This Row],[Product Line]],Prod_T6[],5,0) -> Sunpower | E33: SPR_BC | F33: SPR-BE54-HD490/495 | G33: 3 - Negotiation | I33: EU | P33: 0.2 | Q33: 0.2 | R33: 0.2 | S33: =SUM(BE_NL[[#This Row],[26M04]:[26M06]]) -> 0 | T33: =SUM(BE_NL[[#This Row],[26M07]:[26M09]]) -> 0 | U33: =SUM(BE_NL[[#This Row],[26M10]:[26M12]]) -> 0.6 | AB33: =SUM(BE_NL[[#This Row],[27M01]:[27M03]]) -> 0 | AC33: =SUM(BE_NL[[#This Row],[27M04]:[27M06]]) -> 0 | AD33: =IF(SUM(BE_NL[[#This Row],[26Q2]:[26Q4]])+SUM(BE_NL[[#This Row],[27Q1]:[27Q2]])=0,"No FSCT",IF(AND(SUM(BE_NL[[#This Row],[26Q2]:[26Q4]])>0,SUM(BE_NL[[#This Row],[27Q1]:[27Q2]])=0),"YES","NO")) -> YES | AE33: =VLOOKUP(BE_NL[[#This Row],[Product Line]],Prod_T6[],4,0) -> PV | AH33: 3 - Negotiation
A34: Belgium | B34: RENA SOLAR & CHARGE | C34: Regis | D34: =VLOOKUP(BE_NL[[#This Row],[Product Line]],Prod_T6[],5,0) -> Sunpower | E34: SPR_P7 | F34: P7-BLK-2mm-460 | G34: 7 - Booked | I34: EU | K34: 0.1 | M34: 0.1 | O34: 0.1 | Q34: 0.1 | S34: =SUM(BE_NL[[#This Row],[26M04]:[26M06]]) -> 0.1 | T34: =SUM(BE_NL[[#This Row],[26M07]:[26M09]]) -> 0.2 | U34: =SUM(BE_NL[[#This Row],[26M10]:[26M12]]) -> 0.1 | AB34: =SUM(BE_NL[[#This Row],[27M01]:[27M03]]) -> 0 | AC34: =SUM(BE_NL[[#This Row],[27M04]:[27M06]]) -> 0 | AD34: =IF(SUM(BE_NL[[#This Row],[26Q2]:[26Q4]])+SUM(BE_NL[[#This Row],[27Q1]:[27Q2]])=0,"No FSCT",IF(AND(SUM(BE_NL[[#This Row],[26Q2]:[26Q4]])>0,SUM(BE_NL[[#This Row],[27Q1]:[27Q2]])=0),"YES","NO")) -> YES | AE34: =VLOOKUP(BE_NL[[#This Row],[Product Line]],Prod_T6[],4,0) -> PV | AH34: 7 - Booked
A35: Belgium | B35: RENA SOLAR & CHARGE | D35: =VLOOKUP(BE_NL[[#This Row],[Product Line]],Prod_T6[],5,0) -> TCL | E35: TCL_C2_Series | F35: SPR-BE54-HD490/495 | G35: 3 - Negotiation | I35: EU | P35: 0.1 | Q35: 0.1 | R35: 0.1 | T35: =SUM(BE_NL[[#This Row],[26M07]:[26M09]]) -> 0 | U35: =SUM(BE_NL[[#This Row],[26M10]:[26M12]]) -> 0.3 | AB35: =SUM(BE_NL[[#This Row],[27M01]:[27M03]]) -> 0 | AC35: =SUM(BE_NL[[#This Row],[27M04]:[27M06]]) -> 0 | AD35: =IF(SUM(BE_NL[[#This Row],[26Q2]:[26Q4]])+SUM(BE_NL[[#This Row],[27Q1]:[27Q2]])=0,"No FSCT",IF(AND(SUM(BE_NL[[#This Row],[26Q2]:[26Q4]])>0,SUM(BE_NL[[#This Row],[27Q1]:[27Q2]])=0),"YES","NO")) -> YES | AE35: =VLOOKUP(BE_NL[[#This Row],[Product Line]],Prod_T6[],4,0) -> PV | AH35: 3 - Negotiation
A36: Belgium | B36: Neopower | C36: Romain | D36: =VLOOKUP(BE_NL[[#This Row],[Product Line]],Prod_T6[],5,0) -> Sunpower | E36: SPR_P7 | F36: P7-BLK-2mm-460 | G36: 7 - Booked | I36: EU | K36: 0.1 | M36: 0.1 | O36: 0.1 | S36: =SUM(BE_NL[[#This Row],[26M04]:[26M06]]) -> 0.1 | T36: =SUM(BE_NL[[#This Row],[26M07]:[26M09]]) -> 0.2 | U36: =SUM(BE_NL[[#This Row],[26M10]:[26M12]]) -> 0 | AB36: =SUM(BE_NL[[#This Row],[27M01]:[27M03]]) -> 0 | AC36: =SUM(BE_NL[[#This Row],[27M04]:[27M06]]) -> 0 | AD36: =IF(SUM(BE_NL[[#This Row],[26Q2]:[26Q4]])+SUM(BE_NL[[#This Row],[27Q1]:[27Q2]])=0,"No FSCT",IF(AND(SUM(BE_NL[[#This Row],[26Q2]:[26Q4]])>0,SUM(BE_NL[[#This Row],[27Q1]:[27Q2]])=0),"YES","NO")) -> YES | AE36: =VLOOKUP(BE_NL[[#This Row],[Product Line]],Prod_T6[],4,0) -> PV | AH36: 7 - Booked
A37: Belgium | B37: Neopower | D37: =VLOOKUP(BE_NL[[#This Row],[Product Line]],Prod_T6[],5,0) -> Sunpower | E37: SPR_BC | F37: SPR-BE54-HD490/495 | G37: 3 - Negotiation | I37: EU | P37: 0.1 | Q37: 0.1 | R37: 0.1 | S37: =SUM(BE_NL[[#This Row],[26M04]:[26M06]]) -> 0 | T37: =SUM(BE_NL[[#This Row],[26M07]:[26M09]]) -> 0 | U37: =SUM(BE_NL[[#This Row],[26M10]:[26M12]]) -> 0.3 | AB37: =SUM(BE_NL[[#This Row],[27M01]:[27M03]]) -> 0 | AC37: =SUM(BE_NL[[#This Row],[27M04]:[27M06]]) -> 0 | AD37: =IF(SUM(BE_NL[[#This Row],[26Q2]:[26Q4]])+SUM(BE_NL[[#This Row],[27Q1]:[27Q2]])=0,"No FSCT",IF(AND(SUM(BE_NL[[#This Row],[26Q2]:[26Q4]])>0,SUM(BE_NL[[#This Row],[27Q1]:[27Q2]])=0),"YES","NO")) -> YES | AE37: =VLOOKUP(BE_NL[[#This Row],[Product Line]],Prod_T6[],4,0) -> PV | AH37: 3 - Negotiation
A38: Belgium | B38: ENR Lux | D38: =VLOOKUP(BE_NL[[#This Row],[Product Line]],Prod_T6[],5,0) -> Sunpower | E38: SPR_P7 | F38: P7-BLK-2mm-460 | G38: 7 - Booked | I38: EU | K38: 0.2 | M38: 0.2 | O38: 0.2 | S38: =SUM(BE_NL[[#This Row],[26M04]:[26M06]]) -> 0.2 | T38: =SUM(BE_NL[[#This Row],[26M07]:[26M09]]) -> 0.4 | U38: =SUM(BE_NL[[#This Row],[26M10]:[26M12]]) -> 0 | AB38: =SUM(BE_NL[[#This Row],[27M01]:[27M03]]) -> 0 | AC38: =SUM(BE_NL[[#This Row],[27M04]:[27M06]]) -> 0 | AD38: =IF(SUM(BE_NL[[#This Row],[26Q2]:[26Q4]])+SUM(BE_NL[[#This Row],[27Q1]:[27Q2]])=0,"No FSCT",IF(AND(SUM(BE_NL[[#This Row],[26Q2]:[26Q4]])>0,SUM(BE_NL[[#This Row],[27Q1]:[27Q2]])=0),"YES","NO")) -> YES | AE38: =VLOOKUP(BE_NL[[#This Row],[Product Line]],Prod_T6[],4,0) -> PV | AH38: 7 - Booked
A39: Belgium | B39: ENR Lux | D39: =VLOOKUP(BE_NL[[#This Row],[Product Line]],Prod_T6[],5,0) -> Sunpower | E39: SPR_BC | F39: SPR-BE54-HD490/495 | G39: 7 - Booked | I39: EU | P39: 0.2 | Q39: 0.2 | R39: 0.2 | S39: 0.15 | T39: =SUM(BE_NL[[#This Row],[26M07]:[26M09]]) -> 0 | U39: =SUM(BE_NL[[#This Row],[26M10]:[26M12]]) -> 0.6 | AB39: =SUM(BE_NL[[#This Row],[27M01]:[27M03]]) -> 0 | AC39: =SUM(BE_NL[[#This Row],[27M04]:[27M06]]) -> 0 | AD39: =IF(SUM(BE_NL[[#This Row],[26Q2]:[26Q4]])+SUM(BE_NL[[#This Row],[27Q1]:[27Q2]])=0,"No FSCT",IF(AND(SUM(BE_NL[[#This Row],[26Q2]:[26Q4]])>0,SUM(BE_NL[[#This Row],[27Q1]:[27Q2]])=0),"YES","NO")) -> YES | AE39: =VLOOKUP(BE_NL[[#This Row],[Product Line]],Prod_T6[],4,0) -> PV | AH39: 7 - Booked
A40: Belgium | B40: MR group | D40: =VLOOKUP(BE_NL[[#This Row],[Product Line]],Prod_T6[],5,0) -> TCL | E40: TCL_T5_Pro | F40: HSM-NT60-GH 580/585 | G40: 2 - Initial offer | I40: EU | P40: 0.9 | Q40: 0.9 | R40: 0.9 | S40: =SUM(BE_NL[[#This Row],[26M04]:[26M06]]) -> 0 | T40: =SUM(BE_NL[[#This Row],[26M07]:[26M09]]) -> 0 | U40: =SUM(BE_NL[[#This Row],[26M10]:[26M12]]) -> 2.7 | AB40: =SUM(BE_NL[[#This Row],[27M01]:[27M03]]) -> 0 | AC40: =SUM(BE_NL[[#This Row],[27M04]:[27M06]]) -> 0 | AD40: =IF(SUM(BE_NL[[#This Row],[26Q2]:[26Q4]])+SUM(BE_NL[[#This Row],[27Q1]:[27Q2]])=0,"No FSCT",IF(AND(SUM(BE_NL[[#This Row],[26Q2]:[26Q4]])>0,SUM(BE_NL[[#This Row],[27Q1]:[27Q2]])=0),"YES","NO")) -> YES | AE40: =VLOOKUP(BE_NL[[#This Row],[Product Line]],Prod_T6[],4,0) -> PV | AH40: 2 - Initial offer
A41: Belgium | B41: MR group | D41: =VLOOKUP(BE_NL[[#This Row],[Product Line]],Prod_T6[],5,0) -> TCL | E41: TCL_C2_Series | F41: SPR-BE54-HD490/495 | G41: 3 - Negotiation | I41: EU | O41: 0.9 | P41: 0.9 | Q41: 0.9 | R41: 0.9 | T41: =SUM(BE_NL[[#This Row],[26M07]:[26M09]]) -> 0.9 | U41: =SUM(BE_NL[[#This Row],[26M10]:[26M12]]) -> 2.7 | AB41: =SUM(BE_NL[[#This Row],[27M01]:[27M03]]) -> 0 | AC41: =SUM(BE_NL[[#This Row],[27M04]:[27M06]]) -> 0 | AD41: =IF(SUM(BE_NL[[#This Row],[26Q2]:[26Q4]])+SUM(BE_NL[[#This Row],[27Q1]:[27Q2]])=0,"No FSCT",IF(AND(SUM(BE_NL[[#This Row],[26Q2]:[26Q4]])>0,SUM(BE_NL[[#This Row],[27Q1]:[27Q2]])=0),"YES","NO")) -> YES | AE41: =VLOOKUP(BE_NL[[#This Row],[Product Line]],Prod_T6[],4,0) -> PV | AH41: 3 - Negotiation
A42: Netherlands | B42: SO Products B.V. | C42: Paul | D42: =VLOOKUP(BE_NL[[#This Row],[Product Line]],Prod_T6[],5,0) -> Sunpower | E42: SPR_P7 | F42: P7-COM-S | G42: 7 - Booked | I42: EU | K42: 0.4 | S42: =SUM(BE_NL[[#This Row],[26M04]:[26M06]]) -> 0.4 | T42: =SUM(BE_NL[[#This Row],[26M07]:[26M09]]) -> 0 | U42: =SUM(BE_NL[[#This Row],[26M10]:[26M12]]) -> 0 | AB42: =SUM(BE_NL[[#This Row],[27M01]:[27M03]]) -> 0 | AC42: =SUM(BE_NL[[#This Row],[27M04]:[27M06]]) -> 0 | AD42: =IF(SUM(BE_NL[[#This Row],[26Q2]:[26Q4]])+SUM(BE_NL[[#This Row],[27Q1]:[27Q2]])=0,"No FSCT",IF(AND(SUM(BE_NL[[#This Row],[26Q2]:[26Q4]])>0,SUM(BE_NL[[#This Row],[27Q1]:[27Q2]])=0),"YES","NO")) -> YES | AE42: =VLOOKUP(BE_NL[[#This Row],[Product Line]],Prod_T6[],4,0) -> PV | AH42: 7 - Booked
A43: Netherlands | B43: SO Products B.V. | C43: Paul | D43: =VLOOKUP(BE_NL[[#This Row],[Product Line]],Prod_T6[],5,0) -> TCL | E43: TCL_T5_Pro | F43: HSM-NT66-GH 640/645 | G43: 2 - Initial offer | I43: EU | N43: 0.82 | S43: =SUM(BE_NL[[#This Row],[26M04]:[26M06]]) -> 0 | T43: =SUM(BE_NL[[#This Row],[26M07]:[26M09]]) -> 0.82 | U43: =SUM(BE_NL[[#This Row],[26M10]:[26M12]]) -> 0 | AB43: =SUM(BE_NL[[#This Row],[27M01]:[27M03]]) -> 0 | AC43: =SUM(BE_NL[[#This Row],[27M04]:[27M06]]) -> 0 | AD43: =IF(SUM(BE_NL[[#This Row],[26Q2]:[26Q4]])+SUM(BE_NL[[#This Row],[27Q1]:[27Q2]])=0,"No FSCT",IF(AND(SUM(BE_NL[[#This Row],[26Q2]:[26Q4]])>0,SUM(BE_NL[[#This Row],[27Q1]:[27Q2]])=0),"YES","NO")) -> YES | AE43: =VLOOKUP(BE_NL[[#This Row],[Product Line]],Prod_T6[],4,0) -> PV | AH43: 2 - Initial offer
A44: Netherlands | B44: Zonnepaneel Kampioen B.V | D44: =VLOOKUP(BE_NL[[#This Row],[Product Line]],Prod_T6[],5,0) -> TCL | E44: TCL_E_Class | F44: HSM-BD54-DA465 | G44: 0 - Lost | H44: GIVEN TO GERMAN DISTR. | I44: EU | M44: 1 | S44: =SUM(BE_NL[[#This Row],[26M04]:[26M06]]) -> 0 | T44: =SUM(BE_NL[[#This Row],[26M07]:[26M09]]) -> 1 | U44: =SUM(BE_NL[[#This Row],[26M10]:[26M12]]) -> 0 | AB44: =SUM(BE_NL[[#This Row],[27M01]:[27M03]]) -> 0 | AC44: =SUM(BE_NL[[#This Row],[27M04]:[27M06]]) -> 0 | AD44: =IF(SUM(BE_NL[[#This Row],[26Q2]:[26Q4]])+SUM(BE_NL[[#This Row],[27Q1]:[27Q2]])=0,"No FSCT",IF(AND(SUM(BE_NL[[#This Row],[26Q2]:[26Q4]])>0,SUM(BE_NL[[#This Row],[27Q1]:[27Q2]])=0),"YES","NO")) -> YES | AE44: =VLOOKUP(BE_NL[[#This Row],[Product Line]],Prod_T6[],4,0) -> PV | AH44: 0 - Lost
A45: Netherlands | B45: Zonnepaneel Kampioen B.V | C45: Paul | D45: =VLOOKUP(BE_NL[[#This Row],[Product Line]],Prod_T6[],5,0) -> TCL | E45: TCL_T5_Pro | F45: HSM-NT48-HH 465/470-Black | G45: 0 - Lost | H45: LOST | I45: EU | S45: =SUM(BE_NL[[#This Row],[26M04]:[26M06]]) -> 0 | T45: =SUM(BE_NL[[#This Row],[26M07]:[26M09]]) -> 0 | U45: =SUM(BE_NL[[#This Row],[26M10]:[26M12]]) -> 0 | AB45: =SUM(BE_NL[[#This Row],[27M01]:[27M03]]) -> 0 | AC45: =SUM(BE_NL[[#This Row],[27M04]:[27M06]]) -> 0 | AD45: =IF(SUM(BE_NL[[#This Row],[26Q2]:[26Q4]])+SUM(BE_NL[[#This Row],[27Q1]:[27Q2]])=0,"No FSCT",IF(AND(SUM(BE_NL[[#This Row],[26Q2]:[26Q4]])>0,SUM(BE_NL[[#This Row],[27Q1]:[27Q2]])=0),"YES","NO")) -> No FSCT | AE45: =VLOOKUP(BE_NL[[#This Row],[Product Line]],Prod_T6[],4,0) -> PV | AH45: 0 - Lost
A46: Netherlands | B46: New Customer / Balance of others customers BNL | D46: =VLOOKUP(BE_NL[[#This Row],[Product Line]],Prod_T6[],5,0) -> TCL | E46: TCL_E_Class | F46: HSM-BD54-DA465 | G46: 7 - Booked | H46: BOOKED SOA SEND | I46: EU | M46: 0.42 | S46: =SUM(BE_NL[[#This Row],[26M04]:[26M06]]) -> 0 | T46: =SUM(BE_NL[[#This Row],[26M07]:[26M09]]) -> 0.42 | U46: =SUM(BE_NL[[#This Row],[26M10]:[26M12]]) -> 0 | AB46: =SUM(BE_NL[[#This Row],[27M01]:[27M03]]) -> 0 | AC46: =SUM(BE_NL[[#This Row],[27M04]:[27M06]]) -> 0 | AD46: =IF(SUM(BE_NL[[#This Row],[26Q2]:[26Q4]])+SUM(BE_NL[[#This Row],[27Q1]:[27Q2]])=0,"No FSCT",IF(AND(SUM(BE_NL[[#This Row],[26Q2]:[26Q4]])>0,SUM(BE_NL[[#This Row],[27Q1]:[27Q2]])=0),"YES","NO")) -> YES | AE46: =VLOOKUP(BE_NL[[#This Row],[Product Line]],Prod_T6[],4,0) -> PV | AH46: 7 - Booked
A47: Netherlands | B47: New Customer / Balance of others customers BNL | D47: =VLOOKUP(BE_NL[[#This Row],[Product Line]],Prod_T6[],5,0) -> TCL | E47: TCL_C2_Series | F47: HSM-BE54-HD485/490 | G47: 3 - Negotiation | H47: NEW ACCOUNTS | I47: EU | P47: 2 | Q47: 2 | R47: 2 | S47: =SUM(BE_NL[[#This Row],[26M04]:[26M06]]) -> 0 | T47: =SUM(BE_NL[[#This Row],[26M07]:[26M09]]) -> 0 | U47: =SUM(BE_NL[[#This Row],[26M10]:[26M12]]) -> 6 | AB47: =SUM(BE_NL[[#This Row],[27M01]:[27M03]]) -> 0 | AC47: =SUM(BE_NL[[#This Row],[27M04]:[27M06]]) -> 0 | AD47: =IF(SUM(BE_NL[[#This Row],[26Q2]:[26Q4]])+SUM(BE_NL[[#This Row],[27Q1]:[27Q2]])=0,"No FSCT",IF(AND(SUM(BE_NL[[#This Row],[26Q2]:[26Q4]])>0,SUM(BE_NL[[#This Row],[27Q1]:[27Q2]])=0),"YES","NO")) -> YES | AE47: =VLOOKUP(BE_NL[[#This Row],[Product Line]],Prod_T6[],4,0) -> PV | AH47: 3 - Negotiation
A48: Netherlands | B48: New Customer / Balance of others customers BNL | D48: =VLOOKUP(BE_NL[[#This Row],[Product Line]],Prod_T6[],5,0) -> Sunpower | E48: SPR_BC | F48: SPR-BE54-HD490/495 | G48: 3 - Negotiation | H48: REVIVE DORMANT ACCOUNT | I48: EU | P48: 2 | Q48: 2 | R48: 2 | S48: =SUM(BE_NL[[#This Row],[26M04]:[26M06]]) -> 0 | T48: =SUM(BE_NL[[#This Row],[26M07]:[26M09]]) -> 0 | U48: =SUM(BE_NL[[#This Row],[26M10]:[26M12]]) -> 6 | AB48: =SUM(BE_NL[[#This Row],[27M01]:[27M03]]) -> 0 | AC48: =SUM(BE_NL[[#This Row],[27M04]:[27M06]]) -> 0 | AD48: =IF(SUM(BE_NL[[#This Row],[26Q2]:[26Q4]])+SUM(BE_NL[[#This Row],[27Q1]:[27Q2]])=0,"No FSCT",IF(AND(SUM(BE_NL[[#This Row],[26Q2]:[26Q4]])>0,SUM(BE_NL[[#This Row],[27Q1]:[27Q2]])=0),"YES","NO")) -> YES | AE48: =VLOOKUP(BE_NL[[#This Row],[Product Line]],Prod_T6[],4,0) -> PV | AH48: 3 - Negotiation
A49: Netherlands | B49: New Customer / Balance of others customers BNL | D49: =VLOOKUP(BE_NL[[#This Row],[Product Line]],Prod_T6[],5,0) -> TCL | E49: TCL_T5_Pro | F49: HSM-NT66-GH 640/645 | G49: 2 - Initial offer | H49: NEW C&I KEY ACCOUNT | I49: EU | P49: 2 | Q49: 2 | R49: 2 | S49: =SUM(BE_NL[[#This Row],[26M04]:[26M06]]) -> 0 | T49: =SUM(BE_NL[[#This Row],[26M07]:[26M09]]) -> 0 | U49: =SUM(BE_NL[[#This Row],[26M10]:[26M12]]) -> 6 | AB49: =SUM(BE_NL[[#This Row],[27M01]:[27M03]]) -> 0 | AC49: =SUM(BE_NL[[#This Row],[27M04]:[27M06]]) -> 0 | AD49: =IF(SUM(BE_NL[[#This Row],[26Q2]:[26Q4]])+SUM(BE_NL[[#This Row],[27Q1]:[27Q2]])=0,"No FSCT",IF(AND(SUM(BE_NL[[#This Row],[26Q2]:[26Q4]])>0,SUM(BE_NL[[#This Row],[27Q1]:[27Q2]])=0),"YES","NO")) -> YES | AE49: =VLOOKUP(BE_NL[[#This Row],[Product Line]],Prod_T6[],4,0) -> PV | AH49: 2 - Initial offer
A50: Netherlands | B50: New Customer / Balance of others customers BNL | D50: =VLOOKUP(BE_NL[[#This Row],[Product Line]],Prod_T6[],5,0) -> TCL | E50: TCL_T5_Pro | F50: HSM-NT60-GH 580/585 | G50: 2 - Initial offer | H50: NEW C&I KEY ACCOUNT | I50: EU | P50: 3 | Q50: 3 | R50: 3 | S50: =SUM(BE_NL[[#This Row],[26M04]:[26M06]]) -> 0 | T50: =SUM(BE_NL[[#This Row],[26M07]:[26M09]]) -> 0 | U50: =SUM(BE_NL[[#This Row],[26M10]:[26M12]]) -> 9 | AB50: =SUM(BE_NL[[#This Row],[27M01]:[27M03]]) -> 0 | AC50: =SUM(BE_NL[[#This Row],[27M04]:[27M06]]) -> 0 | AD50: =IF(SUM(BE_NL[[#This Row],[26Q2]:[26Q4]])+SUM(BE_NL[[#This Row],[27Q1]:[27Q2]])=0,"No FSCT",IF(AND(SUM(BE_NL[[#This Row],[26Q2]:[26Q4]])>0,SUM(BE_NL[[#This Row],[27Q1]:[27Q2]])=0),"YES","NO")) -> YES | AE50: =VLOOKUP(BE_NL[[#This Row],[Product Line]],Prod_T6[],4,0) -> PV | AH50: 2 - Initial offer
A51: Netherlands | B51: New Customer / Balance of others customers BNL | D51: =VLOOKUP(BE_NL[[#This Row],[Product Line]],Prod_T6[],5,0) -> Sunpower | E51: SPR_P7 | F51: P7-BLK-2mm-460 | G51: 2 - Initial offer | H51: NEW C&I KEY ACCOUNT | I51: EU | P51: 1 | Q51: 1 | R51: 1 | S51: =SUM(BE_NL[[#This Row],[26M04]:[26M06]]) -> 0 | T51: =SUM(BE_NL[[#This Row],[26M07]:[26M09]]) -> 0 | U51: =SUM(BE_NL[[#This Row],[26M10]:[26M12]]) -> 3 | AB51: =SUM(BE_NL[[#This Row],[27M01]:[27M03]]) -> 0 | AC51: =SUM(BE_NL[[#This Row],[27M04]:[27M06]]) -> 0 | AD51: =IF(SUM(BE_NL[[#This Row],[26Q2]:[26Q4]])+SUM(BE_NL[[#This Row],[27Q1]:[27Q2]])=0,"No FSCT",IF(AND(SUM(BE_NL[[#This Row],[26Q2]:[26Q4]])>0,SUM(BE_NL[[#This Row],[27Q1]:[27Q2]])=0),"YES","NO")) -> YES | AE51: =VLOOKUP(BE_NL[[#This Row],[Product Line]],Prod_T6[],4,0) -> PV | AH51: 2 - Initial offer
A52: Netherlands | B52: New Customer / Balance of others customers BNL | D52: =VLOOKUP(BE_NL[[#This Row],[Product Line]],Prod_T6[],5,0) -> TCL | E52: TCL_T5_Pro | F52: HSM-NT48-JH 470/475-White | G52: 2 - Initial offer | H52: NEW C&I KEY ACCOUNT | I52: EU | P52: 0.8 | Q52: 0.8 | R52: 0.8 | S52: =SUM(BE_NL[[#This Row],[26M04]:[26M06]]) -> 0 | T52: =SUM(BE_NL[[#This Row],[26M07]:[26M09]]) -> 0 | U52: =SUM(BE_NL[[#This Row],[26M10]:[26M12]]) -> 2.4 | AB52: =SUM(BE_NL[[#This Row],[27M01]:[27M03]]) -> 0 | AC52: =SUM(BE_NL[[#This Row],[27M04]:[27M06]]) -> 0 | AD52: =IF(SUM(BE_NL[[#This Row],[26Q2]:[26Q4]])+SUM(BE_NL[[#This Row],[27Q1]:[27Q2]])=0,"No FSCT",IF(AND(SUM(BE_NL[[#This Row],[26Q2]:[26Q4]])>0,SUM(BE_NL[[#This Row],[27Q1]:[27Q2]])=0),"YES","NO")) -> YES | AE52: =VLOOKUP(BE_NL[[#This Row],[Product Line]],Prod_T6[],4,0) -> PV | AH52: 2 - Initial offer
A53: Belgium | B53: ECOSTAL SPRL | D53: =VLOOKUP(BE_NL[[#This Row],[Product Line]],Prod_T6[],5,0) -> TCL | E53: ESS_TCL_CI | F53: BlueArk X5-50K-100 | G53: 2 - Initial offer | H53: AWAITING FEEDBACK NEW ASP | I53: Offshore | P53: 2 | Q53: 2 | R53: 2 | S53: =SUM(BE_NL[[#This Row],[26M04]:[26M06]]) -> 0 | T53: =SUM(BE_NL[[#This Row],[26M07]:[26M09]]) -> 0 | U53: =SUM(BE_NL[[#This Row],[26M10]:[26M12]]) -> 6 | AB53: =SUM(BE_NL[[#This Row],[27M01]:[27M03]]) -> 0 | AC53: =SUM(BE_NL[[#This Row],[27M04]:[27M06]]) -> 0 | AD53: =IF(SUM(BE_NL[[#This Row],[26Q2]:[26Q4]])+SUM(BE_NL[[#This Row],[27Q1]:[27Q2]])=0,"No FSCT",IF(AND(SUM(BE_NL[[#This Row],[26Q2]:[26Q4]])>0,SUM(BE_NL[[#This Row],[27Q1]:[27Q2]])=0),"YES","NO")) -> YES | AE53: =VLOOKUP(BE_NL[[#This Row],[Product Line]],Prod_T6[],4,0) -> ESS | AH53: 2 - Initial offer
A54: Belgium | B54: ECOSTAL SPRL | D54: =VLOOKUP(BE_NL[[#This Row],[Product Line]],Prod_T6[],5,0) -> TCL | E54: ESS_TCL_CI | F54: BlueArk W10-125K-261 | G54: 2 - Initial offer | H54: AWAITING FEEDBACK NEW ASP | I54: Offshore | P54: 2 | Q54: 3 | R54: 3 | S54: =SUM(BE_NL[[#This Row],[26M04]:[26M06]]) -> 0 | T54: =SUM(BE_NL[[#This Row],[26M07]:[26M09]]) -> 0 | U54: =SUM(BE_NL[[#This Row],[26M10]:[26M12]]) -> 8 | AB54: =SUM(BE_NL[[#This Row],[27M01]:[27M03]]) -> 0 | AC54: =SUM(BE_NL[[#This Row],[27M04]:[27M06]]) -> 0 | AD54: =IF(SUM(BE_NL[[#This Row],[26Q2]:[26Q4]])+SUM(BE_NL[[#This Row],[27Q1]:[27Q2]])=0,"No FSCT",IF(AND(SUM(BE_NL[[#This Row],[26Q2]:[26Q4]])>0,SUM(BE_NL[[#This Row],[27Q1]:[27Q2]])=0),"YES","NO")) -> YES | AE54: =VLOOKUP(BE_NL[[#This Row],[Product Line]],Prod_T6[],4,0) -> ESS | AH54: 2 - Initial offer
A55: Netherlands | B55: Natec Sunenergy B.V. | D55: =VLOOKUP(BE_NL[[#This Row],[Product Line]],Prod_T6[],5,0) -> TCL | E55: ESS_TCL_CI | F55: BlueArk X5-50K-100 | G55: 2 - Initial offer | H55: AWAITING FEEDBACK NEW ASP | I55: EU | P55: 1 | Q55: 3 | R55: 3 | S55: =SUM(BE_NL[[#This Row],[26M04]:[26M06]]) -> 0 | T55: =SUM(BE_NL[[#This Row],[26M07]:[26M09]]) -> 0 | U55: =SUM(BE_NL[[#This Row],[26M10]:[26M12]]) -> 7 | AB55: =SUM(BE_NL[[#This Row],[27M01]:[27M03]]) -> 0 | AC55: =SUM(BE_NL[[#This Row],[27M04]:[27M06]]) -> 0 | AD55: =IF(SUM(BE_NL[[#This Row],[26Q2]:[26Q4]])+SUM(BE_NL[[#This Row],[27Q1]:[27Q2]])=0,"No FSCT",IF(AND(SUM(BE_NL[[#This Row],[26Q2]:[26Q4]])>0,SUM(BE_NL[[#This Row],[27Q1]:[27Q2]])=0),"YES","NO")) -> YES | AE55: =VLOOKUP(BE_NL[[#This Row],[Product Line]],Prod_T6[],4,0) -> ESS | AH55: 2 - Initial offer
A56: Netherlands | B56: Natec Sunenergy B.V. | D56: =VLOOKUP(BE_NL[[#This Row],[Product Line]],Prod_T6[],5,0) -> TCL | E56: ESS_TCL_CI | F56: BlueArk W10-125K-261 | G56: 2 - Initial offer | H56: AWAITING FEEDBACK NEW ASP | I56: EU | P56: 1 | Q56: 2 | R56: 2 | S56: =SUM(BE_NL[[#This Row],[26M04]:[26M06]]) -> 0 | T56: =SUM(BE_NL[[#This Row],[26M07]:[26M09]]) -> 0 | U56: =SUM(BE_NL[[#This Row],[26M10]:[26M12]]) -> 5 | AB56: =SUM(BE_NL[[#This Row],[27M01]:[27M03]]) -> 0 | AC56: =SUM(BE_NL[[#This Row],[27M04]:[27M06]]) -> 0 | AD56: =IF(SUM(BE_NL[[#This Row],[26Q2]:[26Q4]])+SUM(BE_NL[[#This Row],[27Q1]:[27Q2]])=0,"No FSCT",IF(AND(SUM(BE_NL[[#This Row],[26Q2]:[26Q4]])>0,SUM(BE_NL[[#This Row],[27Q1]:[27Q2]])=0),"YES","NO")) -> YES | AE56: =VLOOKUP(BE_NL[[#This Row],[Product Line]],Prod_T6[],4,0) -> ESS | AH56: 2 - Initial offer
A57: Belgium | B57: Reno.Energy SA | D57: =VLOOKUP(BE_NL[[#This Row],[Product Line]],Prod_T6[],5,0) -> TCL | E57: ESS_TCL_CI | F57: BlueArk X5-50K-100 | G57: 2 - Initial offer | H57: AWAITING FEEDBACK NEW ASP | I57: EU | P57: 1 | Q57: 1 | R57: 1 | S57: =SUM(BE_NL[[#This Row],[26M04]:[26M06]]) -> 0 | T57: =SUM(BE_NL[[#This Row],[26M07]:[26M09]]) -> 0 | U57: =SUM(BE_NL[[#This Row],[26M10]:[26M12]]) -> 3 | AB57: =SUM(BE_NL[[#This Row],[27M01]:[27M03]]) -> 0 | AC57: =SUM(BE_NL[[#This Row],[27M04]:[27M06]]) -> 0 | AD57: =IF(SUM(BE_NL[[#This Row],[26Q2]:[26Q4]])+SUM(BE_NL[[#This Row],[27Q1]:[27Q2]])=0,"No FSCT",IF(AND(SUM(BE_NL[[#This Row],[26Q2]:[26Q4]])>0,SUM(BE_NL[[#This Row],[27Q1]:[27Q2]])=0),"YES","NO")) -> YES | AE57: =VLOOKUP(BE_NL[[#This Row],[Product Line]],Prod_T6[],4,0) -> ESS | AH57: 2 - Initial offer
A58: Belgium | B58: Reno.Energy SA | D58: =VLOOKUP(BE_NL[[#This Row],[Product Line]],Prod_T6[],5,0) -> TCL | E58: ESS_TCL_CI | F58: BlueArk W10-125K-261 | G58: 2 - Initial offer | H58: AWAITING FEEDBACK NEW ASP | I58: EU | P58: 1 | Q58: 1 | R58: 1 | S58: =SUM(BE_NL[[#This Row],[26M04]:[26M06]]) -> 0 | T58: =SUM(BE_NL[[#This Row],[26M07]:[26M09]]) -> 0 | U58: =SUM(BE_NL[[#This Row],[26M10]:[26M12]]) -> 3 | AB58: =SUM(BE_NL[[#This Row],[27M01]:[27M03]]) -> 0 | AC58: =SUM(BE_NL[[#This Row],[27M04]:[27M06]]) -> 0 | AD58: =IF(SUM(BE_NL[[#This Row],[26Q2]:[26Q4]])+SUM(BE_NL[[#This Row],[27Q1]:[27Q2]])=0,"No FSCT",IF(AND(SUM(BE_NL[[#This Row],[26Q2]:[26Q4]])>0,SUM(BE_NL[[#This Row],[27Q1]:[27Q2]])=0),"YES","NO")) -> YES | AE58: =VLOOKUP(BE_NL[[#This Row],[Product Line]],Prod_T6[],4,0) -> ESS | AH58: 2 - Initial offer
A59: Netherlands | B59: New Customer / Balance of others customers BNL | C59: Regis | D59: =VLOOKUP(BE_NL[[#This Row],[Product Line]],Prod_T6[],5,0) -> TCL | E59: Heat_Pump | F59: HB12SP0 | G59: 2 - Initial offer | H59: BETA TEST SCHEDULED | I59: EU | J59: 0 | K59: 0 | L59: 0 | M59: 1 | N59: 1 | O59: 1 | P59: 1 | Q59: 10 | R59: 20 | S59: =SUM(BE_NL[[#This Row],[26M04]:[26M06]]) -> 0 | T59: =SUM(BE_NL[[#This Row],[26M07]:[26M09]]) -> 3 | U59: =SUM(BE_NL[[#This Row],[26M10]:[26M12]]) -> 31 | AB59: =SUM(BE_NL[[#This Row],[27M01]:[27M03]]) -> 0 | AC59: =SUM(BE_NL[[#This Row],[27M04]:[27M06]]) -> 0 | AD59: =IF(SUM(BE_NL[[#This Row],[26Q2]:[26Q4]])+SUM(BE_NL[[#This Row],[27Q1]:[27Q2]])=0,"No FSCT",IF(AND(SUM(BE_NL[[#This Row],[26Q2]:[26Q4]])>0,SUM(BE_NL[[#This Row],[27Q1]:[27Q2]])=0),"YES","NO")) -> YES | AE59: =VLOOKUP(BE_NL[[#This Row],[Product Line]],Prod_T6[],4,0) -> HP | AH59: 2 - Initial offer
H60: SubTotal => | J60: =SUBTOTAL(9,BE_NL[26M04]) -> 1.69 | K60: =SUBTOTAL(9,BE_NL[26M05]) -> 5.43 | L60: =SUBTOTAL(9,BE_NL[26M06]) -> 8.56 | M60: =SUBTOTAL(9,BE_NL[26M07]) -> 5.38 | N60: =SUBTOTAL(9,BE_NL[26M08]) -> 2.94 | O60: =SUBTOTAL(9,BE_NL[26M09]) -> 12.92 | P60: =SUBTOTAL(9,BE_NL[26M10]) -> 11.7 | Q60: =SUBTOTAL(9,BE_NL[26M11]) -> 11.1 | R60: =SUBTOTAL(9,BE_NL[26M12]) -> 11 | S60: =SUBTOTAL(9,BE_NL[26Q2]) -> 13.73 | T60: =SUBTOTAL(9,BE_NL[26Q3]) -> 21.24 | U60: =SUBTOTAL(9,BE_NL[26Q4]) -> 33.8

Sheet UK
G1: Category | J1: mw/qty | K1: mw/qty | L1: mw/qty | M1: mw/qty | N1: mw/qty | O1: mw/qty | P1: mw/qty | Q1: mw/qty | R1: mw/qty | S1: mw/qty | T1: mw/qty | U1: mw/qty | V1: mw/qty | W1: mw/qty | X1: mw/qty | Y1: mw/qty | Z1: mw/qty | AA1: mw/qty | AB1: mw/qty | AC1: mw/qty
G2: ESS | J2: {=SUMPRODUCT((UK_NO[Product Category]=$G2)*SUBTOTAL(109,OFFSET(INDEX(UK_NO[26M04],1),ROW(UK_NO[26M04])-MIN(ROW(UK_NO[26M04])),0,1)))} -> 0 | K2: {=SUMPRODUCT((UK_NO[Product Category]=$G2)*SUBTOTAL(109,OFFSET(INDEX(UK_NO[26M05],1),ROW(UK_NO[26M05])-MIN(ROW(UK_NO[26M05])),0,1)))} -> 0.397 | L2: {=SUMPRODUCT((UK_NO[Product Category]=$G2)*SUBTOTAL(109,OFFSET(INDEX(UK_NO[26M06],1),ROW(UK_NO[26M06])-MIN(ROW(UK_NO[26M06])),0,1)))} -> 0 | M2: {=SUMPRODUCT((UK_NO[Product Category]=$G2)*SUBTOTAL(109,OFFSET(INDEX(UK_NO[26M07],1),ROW(UK_NO[26M07])-MIN(ROW(UK_NO[26M07])),0,1)))} -> 3 | N2: {=SUMPRODUCT((UK_NO[Product Category]=$G2)*SUBTOTAL(109,OFFSET(INDEX(UK_NO[26M08],1),ROW(UK_NO[26M08])-MIN(ROW(UK_NO[26M08])),0,1)))} -> 2 | O2: {=SUMPRODUCT((UK_NO[Product Category]=$G2)*SUBTOTAL(109,OFFSET(INDEX(UK_NO[26M09],1),ROW(UK_NO[26M09])-MIN(ROW(UK_NO[26M09])),0,1)))} -> 9 | P2: {=SUMPRODUCT((UK_NO[Product Category]=$G2)*SUBTOTAL(109,OFFSET(INDEX(UK_NO[26M10],1),ROW(UK_NO[26M10])-MIN(ROW(UK_NO[26M10])),0,1)))} -> 41 | Q2: {=SUMPRODUCT((UK_NO[Product Category]=$G2)*SUBTOTAL(109,OFFSET(INDEX(UK_NO[26M11],1),ROW(UK_NO[26M11])-MIN(ROW(UK_NO[26M11])),0,1)))} -> 41 | R2: {=SUMPRODUCT((UK_NO[Product Category]=$G2)*SUBTOTAL(109,OFFSET(INDEX(UK_NO[26M12],1),ROW(UK_NO[26M12])-MIN(ROW(UK_NO[26M12])),0,1)))} -> 15 | S2: {=SUMPRODUCT((UK_NO[Product Category]=$G2)*SUBTOTAL(109,OFFSET(INDEX(UK_NO[26Q2],1),ROW(UK_NO[26Q2])-MIN(ROW(UK_NO[26Q2])),0,1)))} -> 0.397 | T2: {=SUMPRODUCT((UK_NO[Product Category]=$G2)*SUBTOTAL(109,OFFSET(INDEX(UK_NO[26Q3],1),ROW(UK_NO[26Q3])-MIN(ROW(UK_NO[26Q3])),0,1)))} -> 14 | U2: {=SUMPRODUCT((UK_NO[Product Category]=$G2)*SUBTOTAL(109,OFFSET(INDEX(UK_NO[26Q4],1),ROW(UK_NO[26Q4])-MIN(ROW(UK_NO[26Q4])),0,1)))} -> 97 | V2: {=SUMPRODUCT((UK_NO[Product Category]=$G2)*SUBTOTAL(109,OFFSET(INDEX(UK_NO[27M01],1),ROW(UK_NO[27M01])-MIN(ROW(UK_NO[27M01])),0,1)))} -> 0 | W2: {=SUMPRODUCT((UK_NO[Product Category]=$G2)*SUBTOTAL(109,OFFSET(INDEX(UK_NO[27M02],1),ROW(UK_NO[27M02])-MIN(ROW(UK_NO[27M02])),0,1)))} -> 0 | X2: {=SUMPRODUCT((UK_NO[Product Category]=$G2)*SUBTOTAL(109,OFFSET(INDEX(UK_NO[27M03],1),ROW(UK_NO[27M03])-MIN(ROW(UK_NO[27M03])),0,1)))} -> 0 | Y2: {=SUMPRODUCT((UK_NO[Product Category]=$G2)*SUBTOTAL(109,OFFSET(INDEX(UK_NO[27M04],1),ROW(UK_NO[27M04])-MIN(ROW(UK_NO[27M04])),0,1)))} -> 0 | Z2: {=SUMPRODUCT((UK_NO[Product Category]=$G2)*SUBTOTAL(109,OFFSET(INDEX(UK_NO[27M05],1),ROW(UK_NO[27M05])-MIN(ROW(UK_NO[27M05])),0,1)))} -> 0 | AA2: {=SUMPRODUCT((UK_NO[Product Category]=$G2)*SUBTOTAL(109,OFFSET(INDEX(UK_NO[27M06],1),ROW(UK_NO[27M06])-MIN(ROW(UK_NO[27M06])),0,1)))} -> 0 | AB2: {=SUMPRODUCT((UK_NO[Product Category]=$G2)*SUBTOTAL(109,OFFSET(INDEX(UK_NO[27Q1],1),ROW(UK_NO[27Q1])-MIN(ROW(UK_NO[27Q1])),0,1)))} -> 0 | AC2: {=SUMPRODUCT((UK_NO[Product Category]=$G2)*SUBTOTAL(109,OFFSET(INDEX(UK_NO[27Q2],1),ROW(UK_NO[27Q2])-MIN(ROW(UK_NO[27Q2])),0,1)))} -> 0
G3: HP | J3: {=SUMPRODUCT((UK_NO[Product Category]=$G3)*SUBTOTAL(109,OFFSET(INDEX(UK_NO[26M04],1),ROW(UK_NO[26M04])-MIN(ROW(UK_NO[26M04])),0,1)))} -> 0 | K3: {=SUMPRODUCT((UK_NO[Product Category]=$G3)*SUBTOTAL(109,OFFSET(INDEX(UK_NO[26M05],1),ROW(UK_NO[26M05])-MIN(ROW(UK_NO[26M05])),0,1)))} -> 0 | L3: {=SUMPRODUCT((UK_NO[Product Category]=$G3)*SUBTOTAL(109,OFFSET(INDEX(UK_NO[26M06],1),ROW(UK_NO[26M06])-MIN(ROW(UK_NO[26M06])),0,1)))} -> 0 | M3: {=SUMPRODUCT((UK_NO[Product Category]=$G3)*SUBTOTAL(109,OFFSET(INDEX(UK_NO[26M07],1),ROW(UK_NO[26M07])-MIN(ROW(UK_NO[26M07])),0,1)))} -> 0 | N3: {=SUMPRODUCT((UK_NO[Product Category]=$G3)*SUBTOTAL(109,OFFSET(INDEX(UK_NO[26M08],1),ROW(UK_NO[26M08])-MIN(ROW(UK_NO[26M08])),0,1)))} -> 0 | O3: {=SUMPRODUCT((UK_NO[Product Category]=$G3)*SUBTOTAL(109,OFFSET(INDEX(UK_NO[26M09],1),ROW(UK_NO[26M09])-MIN(ROW(UK_NO[26M09])),0,1)))} -> 0 | P3: {=SUMPRODUCT((UK_NO[Product Category]=$G3)*SUBTOTAL(109,OFFSET(INDEX(UK_NO[26M10],1),ROW(UK_NO[26M10])-MIN(ROW(UK_NO[26M10])),0,1)))} -> 0 | Q3: {=SUMPRODUCT((UK_NO[Product Category]=$G3)*SUBTOTAL(109,OFFSET(INDEX(UK_NO[26M11],1),ROW(UK_NO[26M11])-MIN(ROW(UK_NO[26M11])),0,1)))} -> 0 | R3: {=SUMPRODUCT((UK_NO[Product Category]=$G3)*SUBTOTAL(109,OFFSET(INDEX(UK_NO[26M12],1),ROW(UK_NO[26M12])-MIN(ROW(UK_NO[26M12])),0,1)))} -> 0 | S3: {=SUMPRODUCT((UK_NO[Product Category]=$G3)*SUBTOTAL(109,OFFSET(INDEX(UK_NO[26Q2],1),ROW(UK_NO[26Q2])-MIN(ROW(UK_NO[26Q2])),0,1)))} -> 0 | T3: {=SUMPRODUCT((UK_NO[Product Category]=$G3)*SUBTOTAL(109,OFFSET(INDEX(UK_NO[26Q3],1),ROW(UK_NO[26Q3])-MIN(ROW(UK_NO[26Q3])),0,1)))} -> 0 | U3: {=SUMPRODUCT((UK_NO[Product Category]=$G3)*SUBTOTAL(109,OFFSET(INDEX(UK_NO[26Q4],1),ROW(UK_NO[26Q4])-MIN(ROW(UK_NO[26Q4])),0,1)))} -> 0 | V3: {=SUMPRODUCT((UK_NO[Product Category]=$G3)*SUBTOTAL(109,OFFSET(INDEX(UK_NO[27M01],1),ROW(UK_NO[27M01])-MIN(ROW(UK_NO[27M01])),0,1)))} -> 0 | W3: {=SUMPRODUCT((UK_NO[Product Category]=$G3)*SUBTOTAL(109,OFFSET(INDEX(UK_NO[27M02],1),ROW(UK_NO[27M02])-MIN(ROW(UK_NO[27M02])),0,1)))} -> 0 | X3: {=SUMPRODUCT((UK_NO[Product Category]=$G3)*SUBTOTAL(109,OFFSET(INDEX(UK_NO[27M03],1),ROW(UK_NO[27M03])-MIN(ROW(UK_NO[27M03])),0,1)))} -> 0 | Y3: {=SUMPRODUCT((UK_NO[Product Category]=$G3)*SUBTOTAL(109,OFFSET(INDEX(UK_NO[27M04],1),ROW(UK_NO[27M04])-MIN(ROW(UK_NO[27M04])),0,1)))} -> 0 | Z3: {=SUMPRODUCT((UK_NO[Product Category]=$G3)*SUBTOTAL(109,OFFSET(INDEX(UK_NO[27M05],1),ROW(UK_NO[27M05])-MIN(ROW(UK_NO[27M05])),0,1)))} -> 0 | AA3: {=SUMPRODUCT((UK_NO[Product Category]=$G3)*SUBTOTAL(109,OFFSET(INDEX(UK_NO[27M06],1),ROW(UK_NO[27M06])-MIN(ROW(UK_NO[27M06])),0,1)))} -> 0 | AB3: {=SUMPRODUCT((UK_NO[Product Category]=$G3)*SUBTOTAL(109,OFFSET(INDEX(UK_NO[27Q1],1),ROW(UK_NO[27Q1])-MIN(ROW(UK_NO[27Q1])),0,1)))} -> 0 | AC3: {=SUMPRODUCT((UK_NO[Product Category]=$G3)*SUBTOTAL(109,OFFSET(INDEX(UK_NO[27Q2],1),ROW(UK_NO[27Q2])-MIN(ROW(UK_NO[27Q2])),0,1)))} -> 0
G4: PV | J4: {=SUMPRODUCT((UK_NO[Product Category]=$G4)*SUBTOTAL(109,OFFSET(INDEX(UK_NO[26M04],1),ROW(UK_NO[26M04])-MIN(ROW(UK_NO[26M04])),0,1)))} -> 25.3864 | K4: {=SUMPRODUCT((UK_NO[Product Category]=$G4)*SUBTOTAL(109,OFFSET(INDEX(UK_NO[26M05],1),ROW(UK_NO[26M05])-MIN(ROW(UK_NO[26M05])),0,1)))} -> 31.48 | L4: {=SUMPRODUCT((UK_NO[Product Category]=$G4)*SUBTOTAL(109,OFFSET(INDEX(UK_NO[26M06],1),ROW(UK_NO[26M06])-MIN(ROW(UK_NO[26M06])),0,1)))} -> 44.501 | M4: {=SUMPRODUCT((UK_NO[Product Category]=$G4)*SUBTOTAL(109,OFFSET(INDEX(UK_NO[26M07],1),ROW(UK_NO[26M07])-MIN(ROW(UK_NO[26M07])),0,1)))} -> 47.093 | N4: {=SUMPRODUCT((UK_NO[Product Category]=$G4)*SUBTOTAL(109,OFFSET(INDEX(UK_NO[26M08],1),ROW(UK_NO[26M08])-MIN(ROW(UK_NO[26M08])),0,1)))} -> 19.656 | O4: {=SUMPRODUCT((UK_NO[Product Category]=$G4)*SUBTOTAL(109,OFFSET(INDEX(UK_NO[26M09],1),ROW(UK_NO[26M09])-MIN(ROW(UK_NO[26M09])),0,1)))} -> 23.874 | P4: {=SUMPRODUCT((UK_NO[Product Category]=$G4)*SUBTOTAL(109,OFFSET(INDEX(UK_NO[26M10],1),ROW(UK_NO[26M10])-MIN(ROW(UK_NO[26M10])),0,1)))} -> 16.732 | Q4: {=SUMPRODUCT((UK_NO[Product Category]=$G4)*SUBTOTAL(109,OFFSET(INDEX(UK_NO[26M11],1),ROW(UK_NO[26M11])-MIN(ROW(UK_NO[26M11])),0,1)))} -> 18.853 | R4: {=SUMPRODUCT((UK_NO[Product Category]=$G4)*SUBTOTAL(109,OFFSET(INDEX(UK_NO[26M12],1),ROW(UK_NO[26M12])-MIN(ROW(UK_NO[26M12])),0,1)))} -> 6.517 | S4: {=SUMPRODUCT((UK_NO[Product Category]=$G4)*SUBTOTAL(109,OFFSET(INDEX(UK_NO[26Q2],1),ROW(UK_NO[26Q2])-MIN(ROW(UK_NO[26Q2])),0,1)))} -> 98.7374 | T4: {=SUMPRODUCT((UK_NO[Product Category]=$G4)*SUBTOTAL(109,OFFSET(INDEX(UK_NO[26Q3],1),ROW(UK_NO[26Q3])-MIN(ROW(UK_NO[26Q3])),0,1)))} -> 90.623 | U4: {=SUMPRODUCT((UK_NO[Product Category]=$G4)*SUBTOTAL(109,OFFSET(INDEX(UK_NO[26Q4],1),ROW(UK_NO[26Q4])-MIN(ROW(UK_NO[26Q4])),0,1)))} -> 42.102 | V4: {=SUMPRODUCT((UK_NO[Product Category]=$G4)*SUBTOTAL(109,OFFSET(INDEX(UK_NO[27M01],1),ROW(UK_NO[27M01])-MIN(ROW(UK_NO[27M01])),0,1)))} -> 0 | W4: {=SUMPRODUCT((UK_NO[Product Category]=$G4)*SUBTOTAL(109,OFFSET(INDEX(UK_NO[27M02],1),ROW(UK_NO[27M02])-MIN(ROW(UK_NO[27M02])),0,1)))} -> 0 | X4: {=SUMPRODUCT((UK_NO[Product Category]=$G4)*SUBTOTAL(109,OFFSET(INDEX(UK_NO[27M03],1),ROW(UK_NO[27M03])-MIN(ROW(UK_NO[27M03])),0,1)))} -> 0 | Y4: {=SUMPRODUCT((UK_NO[Product Category]=$G4)*SUBTOTAL(109,OFFSET(INDEX(UK_NO[27M04],1),ROW(UK_NO[27M04])-MIN(ROW(UK_NO[27M04])),0,1)))} -> 0 | Z4: {=SUMPRODUCT((UK_NO[Product Category]=$G4)*SUBTOTAL(109,OFFSET(INDEX(UK_NO[27M05],1),ROW(UK_NO[27M05])-MIN(ROW(UK_NO[27M05])),0,1)))} -> 0 | AA4: {=SUMPRODUCT((UK_NO[Product Category]=$G4)*SUBTOTAL(109,OFFSET(INDEX(UK_NO[27M06],1),ROW(UK_NO[27M06])-MIN(ROW(UK_NO[27M06])),0,1)))} -> 0 | AB4: {=SUMPRODUCT((UK_NO[Product Category]=$G4)*SUBTOTAL(109,OFFSET(INDEX(UK_NO[27Q1],1),ROW(UK_NO[27Q1])-MIN(ROW(UK_NO[27Q1])),0,1)))} -> 0 | AC4: {=SUMPRODUCT((UK_NO[Product Category]=$G4)*SUBTOTAL(109,OFFSET(INDEX(UK_NO[27Q2],1),ROW(UK_NO[27Q2])-MIN(ROW(UK_NO[27Q2])),0,1)))} -> 0
A5: Country | B5: Customer name | C5: RSM | D5: Brand | E5: Product Line | F5: Model name | G5: Stage | H5: Comments (Deal Breaker, spec/requirements, etc) | I5: Supply Chain | J5: 26M04 | K5: 26M05 | L5: 26M06 | M5: 26M07 | N5: 26M08 | O5: 26M09 | P5: 26M10 | Q5: 26M11 | R5: 26M12 | S5: 26Q2 | T5: 26Q3 | U5: 26Q4 | V5: 27M01 | W5: 27M02 | X5: 27M03 | Y5: 27M04 | Z5: 27M05 | AA5: 27M06 | AB5: 27Q1 | AC5: 27Q2 | AD5: Only 2026? | AE5: Product Category
A6: UK | B6: AES Limited | C6: Jon Juxon | D6: =VLOOKUP(UK_NO[[#This Row],[Product Line]],Prod_T6[],5,0) -> Sunpower | E6: SPR_BC | F6: SPR-BE54-HD490/495 | G6: 2 - Initial offer | H6: Long-standing, loyal SunPower Partner with decent run-rate on P7 | I6: EU | J6: 0.085 | K6: 0.085 | L6: 0.085 | Q6: 0.072 | R6: 0.072 | T6: =SUM(UK_NO[[#This Row],[26M07]:[26M09]]) -> 0 | U6: =SUM(UK_NO[[#This Row],[26M10]:[26M12]]) -> 0.144 | AB6: =SUM(UK_NO[[#This Row],[27M01]:[27M03]]) -> 0 | AC6: =SUM(UK_NO[[#This Row],[27M04]:[27M06]]) -> 0 | AD6: =IF(SUM(UK_NO[[#This Row],[26Q2]:[26Q4]])+SUM(UK_NO[[#This Row],[27Q1]:[27Q2]])=0,"No FSCT",IF(AND(SUM(UK_NO[[#This Row],[26Q2]:[26Q4]])>0,SUM(UK_NO[[#This Row],[27Q1]:[27Q2]])=0),"YES","NO")) -> YES | AE6: =VLOOKUP(UK_NO[[#This Row],[Product Line]],Prod_T6[],4,0) -> PV | AH6: {=UK_NO[Stage]} -> 2 - Initial offer
A7: UK | B7: AES Limited | C7: Jon Juxon | D7: =VLOOKUP(UK_NO[[#This Row],[Product Line]],Prod_T6[],5,0) -> Sunpower | E7: SPR_P7 | F7: P7-BLK-2mm-460 | G7: 7 - Booked | H7: Long-standing, loyal SunPower Partner with decent run-rate on P7 | I7: EU | J7: 0.085 | K7: 0.085 | L7: 0.085 | M7: 0.085 | N7: 0.085 | O7: 0.085 | P7: 0.085 | Q7: 0.085 | R7: 0.085 | S7: =SUM(UK_NO[[#This Row],[26M04]:[26M06]]) -> 0.255 | T7: =SUM(UK_NO[[#This Row],[26M07]:[26M09]]) -> 0.255 | U7: =SUM(UK_NO[[#This Row],[26M10]:[26M12]]) -> 0.255 | AB7: =SUM(UK_NO[[#This Row],[27M01]:[27M03]]) -> 0 | AC7: =SUM(UK_NO[[#This Row],[27M04]:[27M06]]) -> 0 | AD7: =IF(SUM(UK_NO[[#This Row],[26Q2]:[26Q4]])+SUM(UK_NO[[#This Row],[27Q1]:[27Q2]])=0,"No FSCT",IF(AND(SUM(UK_NO[[#This Row],[26Q2]:[26Q4]])>0,SUM(UK_NO[[#This Row],[27Q1]:[27Q2]])=0),"YES","NO")) -> YES | AE7: =VLOOKUP(UK_NO[[#This Row],[Product Line]],Prod_T6[],4,0) -> PV | AH7: 7 - Booked
A8: UK | B8: Bimble Solar Limited | C8: Nicholas Paget | D8: =VLOOKUP(UK_NO[[#This Row],[Product Line]],Prod_T6[],5,0) -> TCL | E8: ESS_TCL_CI | F8: BlueArk X5-50K-100 | G8: 6 - Won | H8: Initial project damand potential far higher | I8: EU | K8: 0.397 | M8: 2 | P8: 4 | Q8: 4 | R8: 4 | S8: =SUM(UK_NO[[#This Row],[26M04]:[26M06]]) -> 0.397 | T8: =SUM(UK_NO[[#This Row],[26M07]:[26M09]]) -> 2 | U8: =SUM(UK_NO[[#This Row],[26M10]:[26M12]]) -> 12 | AB8: =SUM(UK_NO[[#This Row],[27M01]:[27M03]]) -> 0 | AC8: =SUM(UK_NO[[#This Row],[27M04]:[27M06]]) -> 0 | AD8: =IF(SUM(UK_NO[[#This Row],[26Q2]:[26Q4]])+SUM(UK_NO[[#This Row],[27Q1]:[27Q2]])=0,"No FSCT",IF(AND(SUM(UK_NO[[#This Row],[26Q2]:[26Q4]])>0,SUM(UK_NO[[#This Row],[27Q1]:[27Q2]])=0),"YES","NO")) -> YES | AE8: =VLOOKUP(UK_NO[[#This Row],[Product Line]],Prod_T6[],4,0) -> ESS | AH8: 6 - Won
A9: UK | B9: Bimble Solar Limited | C9: Nicholas Paget | D9: =VLOOKUP(UK_NO[[#This Row],[Product Line]],Prod_T6[],5,0) -> TCL | E9: ESS_TCL_CI | F9: BlueArk W10-125K-261 | G9: 2 - Initial offer | I9: EU | P9: 2 | S9: =SUM(UK_NO[[#This Row],[26M04]:[26M06]]) -> 0 | T9: =SUM(UK_NO[[#This Row],[26M07]:[26M09]]) -> 0 | U9: =SUM(UK_NO[[#This Row],[26M10]:[26M12]]) -> 2 | AB9: =SUM(UK_NO[[#This Row],[27M01]:[27M03]]) -> 0 | AC9: =SUM(UK_NO[[#This Row],[27M04]:[27M06]]) -> 0 | AD9: =IF(SUM(UK_NO[[#This Row],[26Q2]:[26Q4]])+SUM(UK_NO[[#This Row],[27Q1]:[27Q2]])=0,"No FSCT",IF(AND(SUM(UK_NO[[#This Row],[26Q2]:[26Q4]])>0,SUM(UK_NO[[#This Row],[27Q1]:[27Q2]])=0),"YES","NO")) -> YES | AE9: =VLOOKUP(UK_NO[[#This Row],[Product Line]],Prod_T6[],4,0) -> ESS | AH9: 2 - Initial offer
A10: UK | B10: Bimble Solar Limited | C10: Nicholas Paget | D10: =VLOOKUP(UK_NO[[#This Row],[Product Line]],Prod_T6[],5,0) -> TCL | E10: TCL_C2_Series | F10: HSM-BE54-DD485/490 | G10: 6 - Won | I10: EU | O10: 0.431 | S10: =SUM(UK_NO[[#This Row],[26M04]:[26M06]]) -> 0 | T10: =SUM(UK_NO[[#This Row],[26M07]:[26M09]]) -> 0.431 | U10: =SUM(UK_NO[[#This Row],[26M10]:[26M12]]) -> 0 | AB10: =SUM(UK_NO[[#This Row],[27M01]:[27M03]]) -> 0 | AC10: =SUM(UK_NO[[#This Row],[27M04]:[27M06]]) -> 0 | AD10: =IF(SUM(UK_NO[[#This Row],[26Q2]:[26Q4]])+SUM(UK_NO[[#This Row],[27Q1]:[27Q2]])=0,"No FSCT",IF(AND(SUM(UK_NO[[#This Row],[26Q2]:[26Q4]])>0,SUM(UK_NO[[#This Row],[27Q1]:[27Q2]])=0),"YES","NO")) -> YES | AE10: =VLOOKUP(UK_NO[[#This Row],[Product Line]],Prod_T6[],4,0) -> PV | AH10: 6 - Won
A11: UK | B11: Bimble Solar Limited | C11: Nicholas Paget | D11: =VLOOKUP(UK_NO[[#This Row],[Product Line]],Prod_T6[],5,0) -> TCL | E11: TCL_T5_Pro | F11: HSM-NT48-HH 465/470-Black | G11: 6 - Won | I11: EU | N11: 0.431 | S11: =SUM(UK_NO[[#This Row],[26M04]:[26M06]]) -> 0 | T11: =SUM(UK_NO[[#This Row],[26M07]:[26M09]]) -> 0.431 | U11: =SUM(UK_NO[[#This Row],[26M10]:[26M12]]) -> 0 | AB11: =SUM(UK_NO[[#This Row],[27M01]:[27M03]]) -> 0 | AC11: =SUM(UK_NO[[#This Row],[27M04]:[27M06]]) -> 0 | AD11: =IF(SUM(UK_NO[[#This Row],[26Q2]:[26Q4]])+SUM(UK_NO[[#This Row],[27Q1]:[27Q2]])=0,"No FSCT",IF(AND(SUM(UK_NO[[#This Row],[26Q2]:[26Q4]])>0,SUM(UK_NO[[#This Row],[27Q1]:[27Q2]])=0),"YES","NO")) -> YES | AE11: =VLOOKUP(UK_NO[[#This Row],[Product Line]],Prod_T6[],4,0) -> PV | AH11: 6 - Won
A12: UK | B12: Ceiba Renewables Limited | C12: Jon Juxon | D12: =VLOOKUP(UK_NO[[#This Row],[Product Line]],Prod_T6[],5,0) -> Sunpower | E12: SPR_BC | F12: SPR-BE54-HD490/495 | G12: 2 - Initial offer | I12: EU | J12: 0.03 | K12: 0.03 | L12: 0.03 | R12: 0.03 | T12: =SUM(UK_NO[[#This Row],[26M07]:[26M09]]) -> 0 | U12: =SUM(UK_NO[[#This Row],[26M10]:[26M12]]) -> 0.03 | AB12: =SUM(UK_NO[[#This Row],[27M01]:[27M03]]) -> 0 | AC12: =SUM(UK_NO[[#This Row],[27M04]:[27M06]]) -> 0 | AD12: =IF(SUM(UK_NO[[#This Row],[26Q2]:[26Q4]])+SUM(UK_NO[[#This Row],[27Q1]:[27Q2]])=0,"No FSCT",IF(AND(SUM(UK_NO[[#This Row],[26Q2]:[26Q4]])>0,SUM(UK_NO[[#This Row],[27Q1]:[27Q2]])=0),"YES","NO")) -> YES | AE12: =VLOOKUP(UK_NO[[#This Row],[Product Line]],Prod_T6[],4,0) -> PV | AH12: 2 - Initial offer
A13: UK | B13: Ceiba Renewables Limited | C13: Jon Juxon | D13: =VLOOKUP(UK_NO[[#This Row],[Product Line]],Prod_T6[],5,0) -> Sunpower | E13: SPR_P7 | F13: P7-BLK-2mm-460 | G13: 7 - Booked | I13: EU | J13: 0.03 | K13: 0.03 | L13: 0.03 | M13: 0.03 | N13: 0.03 | O13: 0.03 | P13: 0.03 | Q13: 0.03 | R13: 0.03 | S13: =SUM(UK_NO[[#This Row],[26M04]:[26M06]]) -> 0.09 | T13: =SUM(UK_NO[[#This Row],[26M07]:[26M09]]) -> 0.09 | U13: =SUM(UK_NO[[#This Row],[26M10]:[26M12]]) -> 0.09 | AB13: =SUM(UK_NO[[#This Row],[27M01]:[27M03]]) -> 0 | AC13: =SUM(UK_NO[[#This Row],[27M04]:[27M06]]) -> 0 | AD13: =IF(SUM(UK_NO[[#This Row],[26Q2]:[26Q4]])+SUM(UK_NO[[#This Row],[27Q1]:[27Q2]])=0,"No FSCT",IF(AND(SUM(UK_NO[[#This Row],[26Q2]:[26Q4]])>0,SUM(UK_NO[[#This Row],[27Q1]:[27Q2]])=0),"YES","NO")) -> YES | AE13: =VLOOKUP(UK_NO[[#This Row],[Product Line]],Prod_T6[],4,0) -> PV | AH13: 7 - Booked
A14: UK | B14: Eco Greenenergy Solutions Ltd | C14: Jon Juxon | D14: =VLOOKUP(UK_NO[[#This Row],[Product Line]],Prod_T6[],5,0) -> Sunpower | E14: SPR_P7 | F14: P7-BLK-2mm-460 | G14: 3 - Negotiation | H14: Credit/payment issues | I14: EU | J14: 0 | K14: 0 | L14: 0 | M14: 0 | N14: 0 | O14: 0 | P14: 0 | Q14: 0 | R14: 0 | S14: =SUM(UK_NO[[#This Row],[26M04]:[26M06]]) -> 0 | T14: =SUM(UK_NO[[#This Row],[26M07]:[26M09]]) -> 0 | U14: =SUM(UK_NO[[#This Row],[26M10]:[26M12]]) -> 0 | AB14: =SUM(UK_NO[[#This Row],[27M01]:[27M03]]) -> 0 | AC14: =SUM(UK_NO[[#This Row],[27M04]:[27M06]]) -> 0 | AD14: =IF(SUM(UK_NO[[#This Row],[26Q2]:[26Q4]])+SUM(UK_NO[[#This Row],[27Q1]:[27Q2]])=0,"No FSCT",IF(AND(SUM(UK_NO[[#This Row],[26Q2]:[26Q4]])>0,SUM(UK_NO[[#This Row],[27Q1]:[27Q2]])=0),"YES","NO")) -> No FSCT | AE14: =VLOOKUP(UK_NO[[#This Row],[Product Line]],Prod_T6[],4,0) -> PV | AH14: 3 - Negotiation
A15: UK | B15: Eco NRG Ltd. | C15: Nicholas Paget | D15: =VLOOKUP(UK_NO[[#This Row],[Product Line]],Prod_T6[],5,0) -> Sunpower | E15: SPR_P7 | F15: P7-BLK-2mm-460 | G15: 6 - Won | I15: EU | J15: 0.066 | K15: 0.066 | L15: 0.033 | M15: 0.066 | N15: 0.066 | O15: 0.066 | P15: 0.066 | Q15: 0.066 | R15: 0.066 | S15: =SUM(UK_NO[[#This Row],[26M04]:[26M06]]) -> 0.165 | T15: =SUM(UK_NO[[#This Row],[26M07]:[26M09]]) -> 0.198 | U15: =SUM(UK_NO[[#This Row],[26M10]:[26M12]]) -> 0.198 | AB15: =SUM(UK_NO[[#This Row],[27M01]:[27M03]]) -> 0 | AC15: =SUM(UK_NO[[#This Row],[27M04]:[27M06]]) -> 0 | AD15: =IF(SUM(UK_NO[[#This Row],[26Q2]:[26Q4]])+SUM(UK_NO[[#This Row],[27Q1]:[27Q2]])=0,"No FSCT",IF(AND(SUM(UK_NO[[#This Row],[26Q2]:[26Q4]])>0,SUM(UK_NO[[#This Row],[27Q1]:[27Q2]])=0),"YES","NO")) -> YES | AE15: =VLOOKUP(UK_NO[[#This Row],[Product Line]],Prod_T6[],4,0) -> PV | AH15: 6 - Won
A16: UK | B16: Evo Energy | C16: Jon Juxon | D16: =VLOOKUP(UK_NO[[#This Row],[Product Line]],Prod_T6[],5,0) -> Sunpower | E16: SPR_P7 | F16: P7-BLK-2mm-460 | G16: 3 - Negotiation | H16: Aiming to convert from Trina to TCL T/S-Class for C&I business | I16: EU | J16: 0 | K16: 0 | L16: 0.5 | M16: 0 | N16: 0 | O16: 0 | P16: 0 | Q16: 0.2 | R16: 0 | T16: =SUM(UK_NO[[#This Row],[26M07]:[26M09]]) -> 0 | U16: =SUM(UK_NO[[#This Row],[26M10]:[26M12]]) -> 0.2 | AB16: =SUM(UK_NO[[#This Row],[27M01]:[27M03]]) -> 0 | AC16: =SUM(UK_NO[[#This Row],[27M04]:[27M06]]) -> 0 | AD16: =IF(SUM(UK_NO[[#This Row],[26Q2]:[26Q4]])+SUM(UK_NO[[#This Row],[27Q1]:[27Q2]])=0,"No FSCT",IF(AND(SUM(UK_NO[[#This Row],[26Q2]:[26Q4]])>0,SUM(UK_NO[[#This Row],[27Q1]:[27Q2]])=0),"YES","NO")) -> YES | AE16: =VLOOKUP(UK_NO[[#This Row],[Product Line]],Prod_T6[],4,0) -> PV | AH16: 3 - Negotiation
A17: UK | B17: Failte Solar | C17: Matt | D17: =VLOOKUP(UK_NO[[#This Row],[Product Line]],Prod_T6[],5,0) -> Sunpower | E17: SPR_M_Class | F17: SPR-BD54-DC490/495 | G17: 7 - Booked | I17: Offshore | J17: 1.274 | S17: =SUM(UK_NO[[#This Row],[26M04]:[26M06]]) -> 1.274 | T17: =SUM(UK_NO[[#This Row],[26M07]:[26M09]]) -> 0 | U17: =SUM(UK_NO[[#This Row],[26M10]:[26M12]]) -> 0 | AB17: =SUM(UK_NO[[#This Row],[27M01]:[27M03]]) -> 0 | AC17: =SUM(UK_NO[[#This Row],[27M04]:[27M06]]) -> 0 | AD17: =IF(SUM(UK_NO[[#This Row],[26Q2]:[26Q4]])+SUM(UK_NO[[#This Row],[27Q1]:[27Q2]])=0,"No FSCT",IF(AND(SUM(UK_NO[[#This Row],[26Q2]:[26Q4]])>0,SUM(UK_NO[[#This Row],[27Q1]:[27Q2]])=0),"YES","NO")) -> YES | AE17: =VLOOKUP(UK_NO[[#This Row],[Product Line]],Prod_T6[],4,0) -> PV | AH17: 7 - Booked
A18: UK | B18: Failte Solar | C18: Matt | D18: =VLOOKUP(UK_NO[[#This Row],[Product Line]],Prod_T6[],5,0) -> Sunpower | E18: SPR_P7 | F18: P7-BLK-2mm-455 | G18: 6 - Won | H18: Ireland only | I18: Offshore | K18: 4.3 | S18: =SUM(UK_NO[[#This Row],[26M04]:[26M06]]) -> 4.3 | T18: =SUM(UK_NO[[#This Row],[26M07]:[26M09]]) -> 0 | U18: =SUM(UK_NO[[#This Row],[26M10]:[26M12]]) -> 0 | AB18: =SUM(UK_NO[[#This Row],[27M01]:[27M03]]) -> 0 | AC18: =SUM(UK_NO[[#This Row],[27M04]:[27M06]]) -> 0 | AD18: =IF(SUM(UK_NO[[#This Row],[26Q2]:[26Q4]])+SUM(UK_NO[[#This Row],[27Q1]:[27Q2]])=0,"No FSCT",IF(AND(SUM(UK_NO[[#This Row],[26Q2]:[26Q4]])>0,SUM(UK_NO[[#This Row],[27Q1]:[27Q2]])=0),"YES","NO")) -> YES | AE18: =VLOOKUP(UK_NO[[#This Row],[Product Line]],Prod_T6[],4,0) -> PV | AH18: 6 - Won
A19: UK | B19: Failte Solar | C19: Matt | D19: =VLOOKUP(UK_NO[[#This Row],[Product Line]],Prod_T6[],5,0) -> Sunpower | E19: SPR_P7 | F19: P7-BLK-2mm-460 | G19: 2 - Initial offer | I19: Offshore | M19: 4.1 | O19: 4.1 | S19: =SUM(UK_NO[[#This Row],[26M04]:[26M06]]) -> 0 | T19: =SUM(UK_NO[[#This Row],[26M07]:[26M09]]) -> 8.2 | U19: =SUM(UK_NO[[#This Row],[26M10]:[26M12]]) -> 0 | AB19: =SUM(UK_NO[[#This Row],[27M01]:[27M03]]) -> 0 | AC19: =SUM(UK_NO[[#This Row],[27M04]:[27M06]]) -> 0 | AD19: =IF(SUM(UK_NO[[#This Row],[26Q2]:[26Q4]])+SUM(UK_NO[[#This Row],[27Q1]:[27Q2]])=0,"No FSCT",IF(AND(SUM(UK_NO[[#This Row],[26Q2]:[26Q4]])>0,SUM(UK_NO[[#This Row],[27Q1]:[27Q2]])=0),"YES","NO")) -> YES | AE19: =VLOOKUP(UK_NO[[#This Row],[Product Line]],Prod_T6[],4,0) -> PV | AH19: 2 - Initial offer
A20: UK | B20: Failte Solar | C20: Matt | D20: =VLOOKUP(UK_NO[[#This Row],[Product Line]],Prod_T6[],5,0) -> TCL | E20: TCL_S_Class | F20: TCL-MR460DT182-58NS | G20: 0 - Lost | H20: Failte Solar UK / lost to alternergy | I20: Offshore | L20: =0.397*6 -> 2.382 | S20: =SUM(UK_NO[[#This Row],[26M04]:[26M06]]) -> 2.382 | T20: =SUM(UK_NO[[#This Row],[26M07]:[26M09]]) -> 0 | U20: =SUM(UK_NO[[#This Row],[26M10]:[26M12]]) -> 0 | AB20: =SUM(UK_NO[[#This Row],[27M01]:[27M03]]) -> 0 | AC20: =SUM(UK_NO[[#This Row],[27M04]:[27M06]]) -> 0 | AD20: =IF(SUM(UK_NO[[#This Row],[26Q2]:[26Q4]])+SUM(UK_NO[[#This Row],[27Q1]:[27Q2]])=0,"No FSCT",IF(AND(SUM(UK_NO[[#This Row],[26Q2]:[26Q4]])>0,SUM(UK_NO[[#This Row],[27Q1]:[27Q2]])=0),"YES","NO")) -> YES | AE20: =VLOOKUP(UK_NO[[#This Row],[Product Line]],Prod_T6[],4,0) -> PV | AH20: 0 - Lost
A21: UK | B21: Failte Solar | C21: Matt | D21: =VLOOKUP(UK_NO[[#This Row],[Product Line]],Prod_T6[],5,0) -> TCL | E21: TCL_S_Class | F21: TCL-MR470DT182-58NS | G21: 2 - Initial offer | I21: Offshore | N21: 2.382 | S21: =SUM(UK_NO[[#This Row],[26M04]:[26M06]]) -> 0 | T21: =SUM(UK_NO[[#This Row],[26M07]:[26M09]]) -> 2.382 | U21: =SUM(UK_NO[[#This Row],[26M10]:[26M12]]) -> 0 | AB21: =SUM(UK_NO[[#This Row],[27M01]:[27M03]]) -> 0 | AC21: =SUM(UK_NO[[#This Row],[27M04]:[27M06]]) -> 0 | AD21: =IF(SUM(UK_NO[[#This Row],[26Q2]:[26Q4]])+SUM(UK_NO[[#This Row],[27Q1]:[27Q2]])=0,"No FSCT",IF(AND(SUM(UK_NO[[#This Row],[26Q2]:[26Q4]])>0,SUM(UK_NO[[#This Row],[27Q1]:[27Q2]])=0),"YES","NO")) -> YES | AE21: =VLOOKUP(UK_NO[[#This Row],[Product Line]],Prod_T6[],4,0) -> PV | AH21: 2 - Initial offer
A22: UK | B22: Failte Solar | C22: Matt | D22: =VLOOKUP(UK_NO[[#This Row],[Product Line]],Prod_T6[],5,0) -> TCL | E22: TCL_T5_Pro | F22: HSM-NT48-HH 465/470-Black | G22: 1 - Lead qualification | H22: need indicative pricing | I22: Offshore | K22: =0.43*4 -> 1.72 | L22: =0.43*4 -> 1.72 | N22: 3.44 | S22: =SUM(UK_NO[[#This Row],[26M04]:[26M06]]) -> 3.44 | T22: =SUM(UK_NO[[#This Row],[26M07]:[26M09]]) -> 3.44 | U22: =SUM(UK_NO[[#This Row],[26M10]:[26M12]]) -> 0 | AB22: =SUM(UK_NO[[#This Row],[27M01]:[27M03]]) -> 0 | AC22: =SUM(UK_NO[[#This Row],[27M04]:[27M06]]) -> 0 | AD22: =IF(SUM(UK_NO[[#This Row],[26Q2]:[26Q4]])+SUM(UK_NO[[#This Row],[27Q1]:[27Q2]])=0,"No FSCT",IF(AND(SUM(UK_NO[[#This Row],[26Q2]:[26Q4]])>0,SUM(UK_NO[[#This Row],[27Q1]:[27Q2]])=0),"YES","NO")) -> YES | AE22: =VLOOKUP(UK_NO[[#This Row],[Product Line]],Prod_T6[],4,0) -> PV | AH22: 1 - Lead qualification
A23: UK | B23: Failte Solar | C23: Matt | D23: =VLOOKUP(UK_NO[[#This Row],[Product Line]],Prod_T6[],5,0) -> TCL | E23: TCL_T_Class | F23: HSM-ND48-DR455 | G23: 1 - Lead qualification | I23: Offshore | M23: 2.66 | N23: 2.66 | O23: 2.66 | S23: =SUM(UK_NO[[#This Row],[26M04]:[26M06]]) -> 0 | T23: =SUM(UK_NO[[#This Row],[26M07]:[26M09]]) -> 7.98 | U23: =SUM(UK_NO[[#This Row],[26M10]:[26M12]]) -> 0 | AB23: =SUM(UK_NO[[#This Row],[27M01]:[27M03]]) -> 0 | AC23: =SUM(UK_NO[[#This Row],[27M04]:[27M06]]) -> 0 | AD23: =IF(SUM(UK_NO[[#This Row],[26Q2]:[26Q4]])+SUM(UK_NO[[#This Row],[27Q1]:[27Q2]])=0,"No FSCT",IF(AND(SUM(UK_NO[[#This Row],[26Q2]:[26Q4]])>0,SUM(UK_NO[[#This Row],[27Q1]:[27Q2]])=0),"YES","NO")) -> YES | AE23: =VLOOKUP(UK_NO[[#This Row],[Product Line]],Prod_T6[],4,0) -> PV | AH23: 1 - Lead qualification
A24: UK | B24: Failte Solar | C24: Matt | D24: =VLOOKUP(UK_NO[[#This Row],[Product Line]],Prod_T6[],5,0) -> TCL | E24: TCL_T_Class | F24: HSM-ND48-DR450 | G24: 1 - Lead qualification | I24: Offshore | K24: 5.04 | S24: =SUM(UK_NO[[#This Row],[26M04]:[26M06]]) -> 5.04 | T24: =SUM(UK_NO[[#This Row],[26M07]:[26M09]]) -> 0 | U24: =SUM(UK_NO[[#This Row],[26M10]:[26M12]]) -> 0 | AB24: =SUM(UK_NO[[#This Row],[27M01]:[27M03]]) -> 0 | AC24: =SUM(UK_NO[[#This Row],[27M04]:[27M06]]) -> 0 | AD24: =IF(SUM(UK_NO[[#This Row],[26Q2]:[26Q4]])+SUM(UK_NO[[#This Row],[27Q1]:[27Q2]])=0,"No FSCT",IF(AND(SUM(UK_NO[[#This Row],[26Q2]:[26Q4]])>0,SUM(UK_NO[[#This Row],[27Q1]:[27Q2]])=0),"YES","NO")) -> YES | AE24: =VLOOKUP(UK_NO[[#This Row],[Product Line]],Prod_T6[],4,0) -> PV | AH24: 1 - Lead qualification
A25: UK | B25: Failte SOlar | C25: Matt | D25: =VLOOKUP(UK_NO[[#This Row],[Product Line]],Prod_T6[],5,0) -> Sunpower | E25: SPR_P7 | F25: P7-BLK-2mm-460 | G25: 7 - Booked | I25: Offshore | J25: 3.9744 | S25: =SUM(UK_NO[[#This Row],[26M04]:[26M06]]) -> 3.9744 | T25: =SUM(UK_NO[[#This Row],[26M07]:[26M09]]) -> 0 | U25: =SUM(UK_NO[[#This Row],[26M10]:[26M12]]) -> 0 | AB25: =SUM(UK_NO[[#This Row],[27M01]:[27M03]]) -> 0 | AC25: =SUM(UK_NO[[#This Row],[27M04]:[27M06]]) -> 0 | AD25: =IF(SUM(UK_NO[[#This Row],[26Q2]:[26Q4]])+SUM(UK_NO[[#This Row],[27Q1]:[27Q2]])=0,"No FSCT",IF(AND(SUM(UK_NO[[#This Row],[26Q2]:[26Q4]])>0,SUM(UK_NO[[#This Row],[27Q1]:[27Q2]])=0),"YES","NO")) -> YES | AE25: =VLOOKUP(UK_NO[[#This Row],[Product Line]],Prod_T6[],4,0) -> PV | AH25: 7 - Booked
A26: UK | B26: Failte Solar | C26: Matt | D26: =VLOOKUP(UK_NO[[#This Row],[Product Line]],Prod_T6[],5,0) -> Sunpower | E26: SPR_P7 | F26: P7-BLK-P-510 | G26: 7 - Booked | H26: Ireland only P7-510 | I26: Offshore | K26: 2.05 | M26: 2.05 | O26: 2.05 | S26: =SUM(UK_NO[[#This Row],[26M04]:[26M06]]) -> 2.05 | T26: =SUM(UK_NO[[#This Row],[26M07]:[26M09]]) -> 4.1 | U26: =SUM(UK_NO[[#This Row],[26M10]:[26M12]]) -> 0 | AB26: =SUM(UK_NO[[#This Row],[27M01]:[27M03]]) -> 0 | AC26: =SUM(UK_NO[[#This Row],[27M04]:[27M06]]) -> 0 | AD26: =IF(SUM(UK_NO[[#This Row],[26Q2]:[26Q4]])+SUM(UK_NO[[#This Row],[27Q1]:[27Q2]])=0,"No FSCT",IF(AND(SUM(UK_NO[[#This Row],[26Q2]:[26Q4]])>0,SUM(UK_NO[[#This Row],[27Q1]:[27Q2]])=0),"YES","NO")) -> YES | AE26: =VLOOKUP(UK_NO[[#This Row],[Product Line]],Prod_T6[],4,0) -> PV | AH26: 7 - Booked
A27: UK | B27: Failte Solar | C27: Matt | D27: =VLOOKUP(UK_NO[[#This Row],[Product Line]],Prod_T6[],5,0) -> TCL | E27: TCL_T_Class | F27: HSM-ND48-DR450 | G27: 7 - Booked | I27: Offshore | J27: 6.318 | S27: =SUM(UK_NO[[#This Row],[26M04]:[26M06]]) -> 6.318 | T27: =SUM(UK_NO[[#This Row],[26M07]:[26M09]]) -> 0 | U27: =SUM(UK_NO[[#This Row],[26M10]:[26M12]]) -> 0 | AB27: =SUM(UK_NO[[#This Row],[27M01]:[27M03]]) -> 0 | AC27: =SUM(UK_NO[[#This Row],[27M04]:[27M06]]) -> 0 | AD27: =IF(SUM(UK_NO[[#This Row],[26Q2]:[26Q4]])+SUM(UK_NO[[#This Row],[27Q1]:[27Q2]])=0,"No FSCT",IF(AND(SUM(UK_NO[[#This Row],[26Q2]:[26Q4]])>0,SUM(UK_NO[[#This Row],[27Q1]:[27Q2]])=0),"YES","NO")) -> YES | AE27: =VLOOKUP(UK_NO[[#This Row],[Product Line]],Prod_T6[],4,0) -> PV | AH27: 7 - Booked
A28: UK | B28: Failte Solar Ireland | C28: Matt | D28: =VLOOKUP(UK_NO[[#This Row],[Product Line]],Prod_T6[],5,0) -> Sunpower | E28: SPR_BC | F28: SPR-BE54-HD490/495 | G28: 3 - Negotiation | I28: EU | S28: =SUM(UK_NO[[#This Row],[26M04]:[26M06]]) -> 0 | T28: =SUM(UK_NO[[#This Row],[26M07]:[26M09]]) -> 0 | U28: =SUM(UK_NO[[#This Row],[26M10]:[26M12]]) -> 0 | AB28: =SUM(UK_NO[[#This Row],[27M01]:[27M03]]) -> 0 | AC28: =SUM(UK_NO[[#This Row],[27M04]:[27M06]]) -> 0 | AD28: =IF(SUM(UK_NO[[#This Row],[26Q2]:[26Q4]])+SUM(UK_NO[[#This Row],[27Q1]:[27Q2]])=0,"No FSCT",IF(AND(SUM(UK_NO[[#This Row],[26Q2]:[26Q4]])>0,SUM(UK_NO[[#This Row],[27Q1]:[27Q2]])=0),"YES","NO")) -> No FSCT | AE28: =VLOOKUP(UK_NO[[#This Row],[Product Line]],Prod_T6[],4,0) -> PV | AH28: 3 - Negotiation
A29: UK | B29: Failte Solar UK | C29: Matt | D29: =VLOOKUP(UK_NO[[#This Row],[Product Line]],Prod_T6[],5,0) -> TCL | E29: TCL_C2_Series | F29: HSM-BE54-HD485/490 | G29: 3 - Negotiation | H29: Forward orders | I29: EU | Q29: 4.5 | S29: =SUM(UK_NO[[#This Row],[26M04]:[26M06]]) -> 0 | T29: =SUM(UK_NO[[#This Row],[26M07]:[26M09]]) -> 0 | U29: =SUM(UK_NO[[#This Row],[26M10]:[26M12]]) -> 4.5 | AB29: =SUM(UK_NO[[#This Row],[27M01]:[27M03]]) -> 0 | AC29: =SUM(UK_NO[[#This Row],[27M04]:[27M06]]) -> 0 | AD29: =IF(SUM(UK_NO[[#This Row],[26Q2]:[26Q4]])+SUM(UK_NO[[#This Row],[27Q1]:[27Q2]])=0,"No FSCT",IF(AND(SUM(UK_NO[[#This Row],[26Q2]:[26Q4]])>0,SUM(UK_NO[[#This Row],[27Q1]:[27Q2]])=0),"YES","NO")) -> YES | AE29: =VLOOKUP(UK_NO[[#This Row],[Product Line]],Prod_T6[],4,0) -> PV | AH29: 3 - Negotiation
A30: UK | B30: FES Support Services | C30: Jon Juxon | D30: =VLOOKUP(UK_NO[[#This Row],[Product Line]],Prod_T6[],5,0) -> Sunpower | E30: SPR_P7 | F30: P7-BLK-2mm-460 | G30: 7 - Booked | H30: 14yr relationship with SunPower on Stirling Borough Council and COM projects | I30: EU | J30: 0 | K30: 0 | L30: 0.125 | M30: 0 | N30: 0.145 | O30: 0.231 | P30: 0 | Q30: 0.125 | R30: 0.25 | S30: =SUM(UK_NO[[#This Row],[26M04]:[26M06]]) -> 0.125 | T30: =SUM(UK_NO[[#This Row],[26M07]:[26M09]]) -> 0.376 | U30: =SUM(UK_NO[[#This Row],[26M10]:[26M12]]) -> 0.375 | AB30: =SUM(UK_NO[[#This Row],[27M01]:[27M03]]) -> 0 | AC30: =SUM(UK_NO[[#This Row],[27M04]:[27M06]]) -> 0 | AD30: =IF(SUM(UK_NO[[#This Row],[26Q2]:[26Q4]])+SUM(UK_NO[[#This Row],[27Q1]:[27Q2]])=0,"No FSCT",IF(AND(SUM(UK_NO[[#This Row],[26Q2]:[26Q4]])>0,SUM(UK_NO[[#This Row],[27Q1]:[27Q2]])=0),"YES","NO")) -> YES | AE30: =VLOOKUP(UK_NO[[#This Row],[Product Line]],Prod_T6[],4,0) -> PV | AH30: 7 - Booked
A31: UK | B31: FES Support Services | C31: Jon Juxon | D31: =VLOOKUP(UK_NO[[#This Row],[Product Line]],Prod_T6[],5,0) -> Sunpower | E31: SPR_BC | F31: SPR-BE54-HD490/495 | G31: 2 - Initial offer | H31: 14yr relationship with SunPower on Stirling Borough Council and COM projects | I31: EU | J31: 0 | K31: 0 | L31: 0.125 | M31: 0 | N31: 0 | O31: 0 | P31: 0 | Q31: 0 | R31: 0.175 | T31: =SUM(UK_NO[[#This Row],[26M07]:[26M09]]) -> 0 | U31: =SUM(UK_NO[[#This Row],[26M10]:[26M12]]) -> 0.175 | AB31: =SUM(UK_NO[[#This Row],[27M01]:[27M03]]) -> 0 | AC31: =SUM(UK_NO[[#This Row],[27M04]:[27M06]]) -> 0 | AD31: =IF(SUM(UK_NO[[#This Row],[26Q2]:[26Q4]])+SUM(UK_NO[[#This Row],[27Q1]:[27Q2]])=0,"No FSCT",IF(AND(SUM(UK_NO[[#This Row],[26Q2]:[26Q4]])>0,SUM(UK_NO[[#This Row],[27Q1]:[27Q2]])=0),"YES","NO")) -> YES | AE31: =VLOOKUP(UK_NO[[#This Row],[Product Line]],Prod_T6[],4,0) -> PV | AH31: 2 - Initial offer
A32: UK | B32: Geo Green Power Ltd | C32: Nicholas Paget | D32: =VLOOKUP(UK_NO[[#This Row],[Product Line]],Prod_T6[],5,0) -> Sunpower | E32: SPR_P7 | F32: P7-BLK-P-510 | G32: 6 - Won | H32: Product proposed for MoD Project | I32: EU | L32: 0.3 | N32: 0.3 | O32: 0.3 | P32: 0.3 | Q32: 0.3 | S32: =SUM(UK_NO[[#This Row],[26M04]:[26M06]]) -> 0.3 | T32: =SUM(UK_NO[[#This Row],[26M07]:[26M09]]) -> 0.6 | U32: =SUM(UK_NO[[#This Row],[26M10]:[26M12]]) -> 0.6 | AB32: =SUM(UK_NO[[#This Row],[27M01]:[27M03]]) -> 0 | AC32: =SUM(UK_NO[[#This Row],[27M04]:[27M06]]) -> 0 | AD32: =IF(SUM(UK_NO[[#This Row],[26Q2]:[26Q4]])+SUM(UK_NO[[#This Row],[27Q1]:[27Q2]])=0,"No FSCT",IF(AND(SUM(UK_NO[[#This Row],[26Q2]:[26Q4]])>0,SUM(UK_NO[[#This Row],[27Q1]:[27Q2]])=0),"YES","NO")) -> YES | AE32: =VLOOKUP(UK_NO[[#This Row],[Product Line]],Prod_T6[],4,0) -> PV | AH32: 6 - Won
A33: UK | B33: Geo Green Power Ltd | C33: Nicholas Paget | D33: =VLOOKUP(UK_NO[[#This Row],[Product Line]],Prod_T6[],5,0) -> Sunpower | E33: SPR_P7 | F33: P7-BLK-2mm-460 | G33: 6 - Won | I33: EU | J33: 0.066 | K33: 0.066 | L33: 0.066 | M33: 0.066 | N33: 0.066 | O33: 0.066 | P33: 0.066 | Q33: 0.066 | R33: 0.066 | S33: =SUM(UK_NO[[#This Row],[26M04]:[26M06]]) -> 0.198 | T33: =SUM(UK_NO[[#This Row],[26M07]:[26M09]]) -> 0.198 | U33: =SUM(UK_NO[[#This Row],[26M10]:[26M12]]) -> 0.198 | AB33: =SUM(UK_NO[[#This Row],[27M01]:[27M03]]) -> 0 | AC33: =SUM(UK_NO[[#This Row],[27M04]:[27M06]]) -> 0 | AD33: =IF(SUM(UK_NO[[#This Row],[26Q2]:[26Q4]])+SUM(UK_NO[[#This Row],[27Q1]:[27Q2]])=0,"No FSCT",IF(AND(SUM(UK_NO[[#This Row],[26Q2]:[26Q4]])>0,SUM(UK_NO[[#This Row],[27Q1]:[27Q2]])=0),"YES","NO")) -> YES | AE33: =VLOOKUP(UK_NO[[#This Row],[Product Line]],Prod_T6[],4,0) -> PV | AH33: 6 - Won
A34: UK | B34: Geo Green Power Ltd | C34: Nicholas Paget | D34: =VLOOKUP(UK_NO[[#This Row],[Product Line]],Prod_T6[],5,0) -> TCL | E34: TCL_T5_Pro | F34: HSM-NT48-HH 465/470-Black | G34: 2 - Initial offer | H34: SUPPLY VIA UK GREENTECH - negotiations underway | I34: EU | O34: 1 | P34: 1 | Q34: 1 | S34: =SUM(UK_NO[[#This Row],[26M04]:[26M06]]) -> 0 | T34: =SUM(UK_NO[[#This Row],[26M07]:[26M09]]) -> 1 | U34: =SUM(UK_NO[[#This Row],[26M10]:[26M12]]) -> 2 | AB34: =SUM(UK_NO[[#This Row],[27M01]:[27M03]]) -> 0 | AC34: =SUM(UK_NO[[#This Row],[27M04]:[27M06]]) -> 0 | AD34: =IF(SUM(UK_NO[[#This Row],[26Q2]:[26Q4]])+SUM(UK_NO[[#This Row],[27Q1]:[27Q2]])=0,"No FSCT",IF(AND(SUM(UK_NO[[#This Row],[26Q2]:[26Q4]])>0,SUM(UK_NO[[#This Row],[27Q1]:[27Q2]])=0),"YES","NO")) -> YES | AE34: =VLOOKUP(UK_NO[[#This Row],[Product Line]],Prod_T6[],4,0) -> PV | AH34: 2 - Initial offer
A35: UK | B35: Greenscape Energy | C35: Jon Juxon | D35: =VLOOKUP(UK_NO[[#This Row],[Product Line]],Prod_T6[],5,0) -> Sunpower | E35: SPR_BC | F35: SPR-BE54-HD490/495 | G35: 2 - Initial offer | H35: Supply problem on 510w: Long-term supply deal potentially, (460 & 510) | I35: EU | J35: 0.175 | K35: 0 | L35: 0.445 | M35: 0 | N35: 0 | O35: 0 | P35: 0 | Q35: 0 | R35: 0.3 | T35: =SUM(UK_NO[[#This Row],[26M07]:[26M09]]) -> 0 | U35: =SUM(UK_NO[[#This Row],[26M10]:[26M12]]) -> 0.3 | AB35: =SUM(UK_NO[[#This Row],[27M01]:[27M03]]) -> 0 | AC35: =SUM(UK_NO[[#This Row],[27M04]:[27M06]]) -> 0 | AD35: =IF(SUM(UK_NO[[#This Row],[26Q2]:[26Q4]])+SUM(UK_NO[[#This Row],[27Q1]:[27Q2]])=0,"No FSCT",IF(AND(SUM(UK_NO[[#This Row],[26Q2]:[26Q4]])>0,SUM(UK_NO[[#This Row],[27Q1]:[27Q2]])=0),"YES","NO")) -> YES | AE35: =VLOOKUP(UK_NO[[#This Row],[Product Line]],Prod_T6[],4,0) -> PV | AH35: 2 - Initial offer
A36: UK | B36: Greenscape Energy | C36: Jon Juxon | D36: =VLOOKUP(UK_NO[[#This Row],[Product Line]],Prod_T6[],5,0) -> Sunpower | E36: SPR_P7 | F36: P7-BLK-P-515 | G36: 7 - Booked | H36: Supply problem on 510w: Long-term supply deal potentially, (460 & 510) | I36: EU | J36: 0.175 | K36: 0 | L36: 0.445 | M36: 0.445 | N36: 0.445 | O36: 0.445 | P36: 0.445 | Q36: 0.445 | R36: 0.075 | S36: =SUM(UK_NO[[#This Row],[26M04]:[26M06]]) -> 0.62 | T36: =SUM(UK_NO[[#This Row],[26M07]:[26M09]]) -> 1.335 | U36: =SUM(UK_NO[[#This Row],[26M10]:[26M12]]) -> 0.965 | AB36: =SUM(UK_NO[[#This Row],[27M01]:[27M03]]) -> 0 | AC36: =SUM(UK_NO[[#This Row],[27M04]:[27M06]]) -> 0 | AD36: =IF(SUM(UK_NO[[#This Row],[26Q2]:[26Q4]])+SUM(UK_NO[[#This Row],[27Q1]:[27Q2]])=0,"No FSCT",IF(AND(SUM(UK_NO[[#This Row],[26Q2]:[26Q4]])>0,SUM(UK_NO[[#This Row],[27Q1]:[27Q2]])=0),"YES","NO")) -> YES | AE36: =VLOOKUP(UK_NO[[#This Row],[Product Line]],Prod_T6[],4,0) -> PV | AH36: 7 - Booked
A37: UK | B37: Greenshop Solar Ltd | C37: Nicholas Paget | D37: =VLOOKUP(UK_NO[[#This Row],[Product Line]],Prod_T6[],5,0) -> Sunpower | E37: SPR_P7 | F37: P7-BLK-2mm-460 | G37: 6 - Won | I37: EU | L37: 0.033 | N37: 0.033 | P37: 0.033 | R37: 0.033 | S37: =SUM(UK_NO[[#This Row],[26M04]:[26M06]]) -> 0.033 | T37: =SUM(UK_NO[[#This Row],[26M07]:[26M09]]) -> 0.033 | U37: =SUM(UK_NO[[#This Row],[26M10]:[26M12]]) -> 0.066 | AB37: =SUM(UK_NO[[#This Row],[27M01]:[27M03]]) -> 0 | AC37: =SUM(UK_NO[[#This Row],[27M04]:[27M06]]) -> 0 | AD37: =IF(SUM(UK_NO[[#This Row],[26Q2]:[26Q4]])+SUM(UK_NO[[#This Row],[27Q1]:[27Q2]])=0,"No FSCT",IF(AND(SUM(UK_NO[[#This Row],[26Q2]:[26Q4]])>0,SUM(UK_NO[[#This Row],[27Q1]:[27Q2]])=0),"YES","NO")) -> YES | AE37: =VLOOKUP(UK_NO[[#This Row],[Product Line]],Prod_T6[],4,0) -> PV | AH37: 6 - Won
A38: UK | B38: Guernsey - Little Green | C38: Jon Juxon | D38: =VLOOKUP(UK_NO[[#This Row],[Product Line]],Prod_T6[],5,0) -> Sunpower | E38: SPR_P7 | F38: P7-BLK-P-515 | G38: 7 - Booked | H38: Elite Partner, steady business across both RES & COM | I38: EU | J38: 0 | K38: 0 | L38: 0.13 | M38: 0 | N38: 0.252 | Q38: 0.072 | S38: =SUM(UK_NO[[#This Row],[26M04]:[26M06]]) -> 0.13 | T38: =SUM(UK_NO[[#This Row],[26M07]:[26M09]]) -> 0.252 | U38: =SUM(UK_NO[[#This Row],[26M10]:[26M12]]) -> 0.072 | AB38: =SUM(UK_NO[[#This Row],[27M01]:[27M03]]) -> 0 | AC38: =SUM(UK_NO[[#This Row],[27M04]:[27M06]]) -> 0 | AD38: =IF(SUM(UK_NO[[#This Row],[26Q2]:[26Q4]])+SUM(UK_NO[[#This Row],[27Q1]:[27Q2]])=0,"No FSCT",IF(AND(SUM(UK_NO[[#This Row],[26Q2]:[26Q4]])>0,SUM(UK_NO[[#This Row],[27Q1]:[27Q2]])=0),"YES","NO")) -> YES | AE38: =VLOOKUP(UK_NO[[#This Row],[Product Line]],Prod_T6[],4,0) -> PV | AH38: 7 - Booked
A39: UK | B39: Guernsey - Little Green | C39: Jon Juxon | D39: =VLOOKUP(UK_NO[[#This Row],[Product Line]],Prod_T6[],5,0) -> Sunpower | E39: SPR_BC | F39: SPR-BE54-HD490/495 | G39: 2 - Initial offer | H39: Elite Partner, steady business across both RES & COM | I39: EU | J39: 0 | K39: 0 | L39: 0.15 | M39: 0 | R39: 0.143 | S39: 0.15 | T39: =SUM(UK_NO[[#This Row],[26M07]:[26M09]]) -> 0 | U39: =SUM(UK_NO[[#This Row],[26M10]:[26M12]]) -> 0.143 | AB39: =SUM(UK_NO[[#This Row],[27M01]:[27M03]]) -> 0 | AC39: =SUM(UK_NO[[#This Row],[27M04]:[27M06]]) -> 0 | AD39: =IF(SUM(UK_NO[[#This Row],[26Q2]:[26Q4]])+SUM(UK_NO[[#This Row],[27Q1]:[27Q2]])=0,"No FSCT",IF(AND(SUM(UK_NO[[#This Row],[26Q2]:[26Q4]])>0,SUM(UK_NO[[#This Row],[27Q1]:[27Q2]])=0),"YES","NO")) -> YES | AE39: =VLOOKUP(UK_NO[[#This Row],[Product Line]],Prod_T6[],4,0) -> PV | AH39: 2 - Initial offer
A40: UK | B40: In2gr8ted Solutions Ltd | C40: Jon Juxon | D40: =VLOOKUP(UK_NO[[#This Row],[Product Line]],Prod_T6[],5,0) -> Sunpower | E40: SPR_P7 | F40: P7-BLK-2mm-460 | G40: 7 - Booked | H40: Private landlord properties and standard domestic | I40: EU | J40: 0 | K40: 0.13 | L40: 0.13 | M40: 0.13 | N40: 0 | O40: 0.13 | P40: 0 | Q40: 0.13 | R40: 0 | S40: =SUM(UK_NO[[#This Row],[26M04]:[26M06]]) -> 0.26 | T40: =SUM(UK_NO[[#This Row],[26M07]:[26M09]]) -> 0.26 | U40: =SUM(UK_NO[[#This Row],[26M10]:[26M12]]) -> 0.13 | AB40: =SUM(UK_NO[[#This Row],[27M01]:[27M03]]) -> 0 | AC40: =SUM(UK_NO[[#This Row],[27M04]:[27M06]]) -> 0 | AD40: =IF(SUM(UK_NO[[#This Row],[26Q2]:[26Q4]])+SUM(UK_NO[[#This Row],[27Q1]:[27Q2]])=0,"No FSCT",IF(AND(SUM(UK_NO[[#This Row],[26Q2]:[26Q4]])>0,SUM(UK_NO[[#This Row],[27Q1]:[27Q2]])=0),"YES","NO")) -> YES | AE40: =VLOOKUP(UK_NO[[#This Row],[Product Line]],Prod_T6[],4,0) -> PV | AH40: 7 - Booked
