Workbook
Name date_end_horizon: DATE(2026,11,15)
Name fx_qty: SUMIFS('H2-2025 PV DATA'!A:A,'H2-2025 PV DATA'!$C:$C,'H2-2025 PV DATA'!$A1)
Name fx_qty: SUMIFS('PV SUPPLY DATA'!A:A,'PV SUPPLY DATA'!$C:$C,'PV SUPPLY DATA'!$A1)

Sheet H1-2026 PV DATA
A1: TCL REFERENCE | B1: Factory Location | C1: FX_QTY criteria | D1: CHANNEL | E1: New Ark PO Type | F1: New Ark WH | G1: TCL-HK PO INCOTERM Requested | H1: B/L Consignee | I1: Priority Level | J1: ALLOCATION Planning | K1: SPWR SO Number | L1: SPWR SO Line | M1: G2G / Planning | N1: Factory Available Date | O1: PRODUCT TYPE | P1: New Ark SKU | Q1: Model | R1: Connector | S1: Cable Length | T1: WATT | U1: QUANTITY | V1: MW | W1: PALLETS | X1: CONTAINERS | Y1: STATUS | Z1: COMPLETED or IN-TRANSIT | AA1: ETR | AB1: Pick-Up Date | AC1: Pick-Up Week | AD1: SPTN-PVHK New Ark PO# | AE1: SPTN-HKPV ORacle PO# | AF1: PORT OF LOADING | AG1: POL | AH1: PORT DESTINATION | AI1: ETD On S/O | AJ1: ETD Update | AK1: ATD PORT | AL1: ETA On S/O | AM1: ETA Update | AN1: ATA PORT | AO1: Incoterm | AP1: REFERENCE V.V | AQ1: Carrier | AR1: TCL Invoice# or PO# | AS1: MBL/HBL# | AT1: BOOKING# | AU1: Leg2 leadtime On S/O | AV1: Telex released | AW1: ODP ETA Port | AX1: New Ark PO status | AY1: NewArk ETA PO | AZ1: Customs/Leg3 Assumption | BA1: ETA for New Ark update | BB1: ETA Year | BC1: ETA Month | BD1: ETA Week | BE1: Qty/Pallet | BF1: Qty/CT | BG1: Back Glass | BH1: Shipping Line
A2: OCT009.05 | B2: Tianjin | C2: OCT009 | D2: CORE DG | E2: Internal | F2: Arrival Plan-SPTN | G2: DAP | H2: SunPower Energy Solutions France SAS | I2: n/a | J2: Local WH | M2: n/a | N2: n/a | O2: Half Cut | P2: GF0700000071 | Q2: HSM-ND54-DR500 | R2: EVO2A | S2: ±1200mm | T2: 500 | U2: 2592 | V2: 1.296 | W2: 72 | X2: 3 | Y2: COMPLETED | Z2: COMPLETED | AB2: 46003 | AC2: 50 | AD2: POPV260114015 | AE2: 371009290 | AF2: TIANJIN | AG2: Tianjin | AH2: FOS SUR MER | AI2: 46009 | AJ2: 46009 | AK2: 46012 | AL2: 46076 | AM2: 46098 | AN2: 46099 | AO2: DAP | AP2: COSCO SHIPPING CAPRICORN/039W | AQ2: COSCO | AR2: TPVB20251205009 | AS2: COSU6437850520 | AT2: COSU6437850520 | AU2: 87 | AV2: SWB | AW2: 46099 | AX2: In Stock-Approved | AY2: 46112 | AZ2: 8 | BA2: 46107 | BB2: 2026 | BC2: 3 | BD2: 13 | BE2: 36 | BF2: 864 | BG2: Black glazing | BH2: AEM
A3: NOV008.04 | B3: Tianjin | C3: NOV008 | D3: CORE DG | E3: Internal | F3: Arrival Plan-SPTN | G3: DAP | H3: SunPower Energy Solutions France SAS | I3: n/a | J3: SPTN / NED | K3: 46010796 / FR0125122900758 | M3: n/a | N3: n/a | O3: Half Cut | P3: GF0700000080 | Q3: HSM-ND48-DR450_CFP | R3: EVO2A | S3: ±1200mm | T3: 450 | U3: 936 | V3: 0.421 | W3: 26 | X3: 1 | Y3: COMPLETED | Z3: COMPLETED | AB3: 46003 | AC3: 50 | AD3: POPV260114013 | AE3: 371009297 | AF3: TIANJIN | AG3: Tianjin | AH3: FOS SUR MER | AI3: 46009 | AJ3: 46009 | AK3: 46012 | AL3: 46076 | AM3: 46098 | AN3: 46099 | AO3: DAP | AP3: COSCO SHIPPING CAPRICORN/039W | AQ3: COSCO | AR3: TPVB20251205009 | AS3: COSU6437850520 | AT3: COSU6437850520 | AU3: 87 | AV3: SWB | AW3: 46099 | AX3: In Stock-Approved | AY3: 46112 | AZ3: 8 | BA3: 46107 | BB3: 2026 | BC3: 3 | BD3: 13 | BE3: 36 | BF3: 936 | BG3: Transparent | BH3: AEM
A4: NOV008.07 | B4: Tianjin | C4: NOV008 | D4: CORE DG | E4: Internal | F4: Arrival Plan-SPTN | G4: DAP | H4: SunPower Energy Solutions France SAS | I4: n/a | J4: Local WH | M4: n/a | N4: n/a | O4: Half Cut | P4: GF0700000080 | Q4: HSM-ND48-DR450_CFP | R4: EVO2A | S4: ±1200mm | T4: 450 | U4: 2808 | V4: 1.264 | W4: 78 | X4: 3 | Y4: COMPLETED | Z4: COMPLETED | AB4: 46003 | AC4: 50 | AD4: POPV260114014 | AE4: 371009298 | AF4: TIANJIN | AG4: Tianjin | AH4: FOS SUR MER | AI4: 46009 | AJ4: 46009 | AK4: 46012 | AL4: 46076 | AM4: 46098 | AN4: 46099 | AO4: DAP | AP4: COSCO SHIPPING CAPRICORN/039W | AQ4: COSCO | AR4: TPVB20251205009 | AS4: COSU6437850520 | AT4: COSU6437850520 | AU4: 87 | AV4: SWB | AW4: 46099 | AX4: In Stock-Approved | AY4: 46112 | AZ4: 8 | BA4: 46107 | BB4: 2026 | BC4: 3 | BD4: 13 | BE4: 36 | BF4: 936 | BG4: Transparent | BH4: AEM
A5: OCT012.02 | B5: Tianjin | C5: OCT012 | D5: CORE DG | E5: Internal | F5: Arrival Plan-SPNL | G5: DAP | H5: SunPower Energy Solutions France SAS | I5: n/a | J5: Distributors Italy - W72 | M5: n/a | N5: n/a | O5: Half Cut | P5: GF0101010095 | Q5: HSM-ND66-GR620 | R5: EVO2A | S5: ±1200mm | T5: 620 | U5: 4320 | V5: 2.678 | W5: 120 | X5: 6 | Y5: COMPLETED | Z5: COMPLETED | AB5: 46000 | AC5: 50 | AD5: POPV260224025 | AE5: 371009291 | AF5: TIANJIN | AG5: Tianjin | AH5: ROTTERDAM | AI5: 46009 | AJ5: 46009 | AK5: 46012 | AL5: 46061 | AM5: 46111 | AN5: 46111 | AO5: DAP | AP5: COSCO SHIPPING CAPRICORN/039W | AQ5: COSCO | AR5: TPVB20251205010 | AS5: COSU6437850970 | AT5: COSU6437850970 | AU5: 99 | AV5: SWB | AW5: 46111 | AX5: In Stock-Approved | AY5: 46125 | AZ5: 7 | BA5: 46118 | BB5: 2026 | BC5: 4 | BD5: 15 | BE5: 36 | BF5: 720 | BG5: White glazing | BH5: AEU
A6: DEC003.09 | B6: Yixing | C6: DEC003 | D6: UPP | E6: Internal | F6: Arrival Plan-SPES | G6: DAP | H6: Sunpower Energy Systems Spain, S.L.U. | I6: n/a | J6: SPES / Total Portugal | K6: PT0125122900789 | M6: n/a | N6: n/a | O6: Half Cut | P6: GF0700001575 | Q6: HSM-ND78-GF640 | R6: EVO2A | S6: ±1400mm | T6: 640 | U6: 2304 | V6: 1.475 | W6: 64 | X6: 4 | Y6: COMPLETED | Z6: COMPLETED | AB6: 46015 | AC6: 52 | AD6: POPV260115029 | AF6: SHANGHAI | AG6: Shanghai | AH6: VALENCIA | AI6: 46020 | AJ6: 46030 | AK6: 46030 | AL6: 46072 | AM6: 46092 | AN6: 46094 | AO6: DAP | AP6: COSCO SHIPPING PISCES 031W | AQ6: COSCO | AR6: TPVB20251212006 | AS6: COSU6438488340 | AT6: COSU6438488340 | AU6: 64 | AW6: 46094 | AX6: In Stock-Approved | AY6: 46104 | AZ6: 9 | BA6: 46103 | BB6: 2026 | BC6: 3 | BD6: 12 | BE6: 36 | BF6: 576 | BG6: Redirection Film | BH6: AEM
A7: DEC012.04 | B7: Yixing | C7: DEC012 | D7: CORE DG | E7: Internal | F7: Arrival Plan-SPTN | G7: DAP | H7: SunPower Energy Solutions France SAS | I7: n/a | J7: Local WH - SPTN W74 (Italy) | M7: n/a | N7: n/a | O7: Shingle | P7: GF0700000811 | Q7: TCL-MG720DT210-68NS | R7: EVO2A | S7: ±1400mm | T7: 720 | U7: 1782 | V7: 1.283 | W7: 54 | X7: 3 | Y7: COMPLETED | Z7: COMPLETED | AB7: 46012 | AC7: 51 | AD7: POPV260224037 | AF7: SHANGHAI | AG7: Shanghai | AH7: FOS SUR MER | AI7: 46020 | AJ7: 46030 | AK7: 46030 | AL7: 46064 | AM7: 46098 | AN7: 46099 | AO7: DAP | AP7: COSCO SHIPPING PISCES 031W | AQ7: COSCO | AR7: TPVB20251212007 | AS7: COSU6438902550 | AT7: COSU6438902550 | AU7: 69 | AW7: 46099 | AX7: In Stock-Approved | AY7: 46112 | AZ7: 8 | BA7: 46107 | BB7: 2026 | BC7: 3 | BD7: 13 | BE7: 33 | BF7: 594 | BG7: White glazing | BH7: AEM
A8: DEC012.01 | B8: Yixing | C8: DEC012 | D8: CORE DG | E8: Internal | F8: Arrival Plan-SPNL | G8: DAP | H8: SunPower Energy Solutions France SAS | I8: n/a | J8: Distributors Italy - W72 | M8: n/a | N8: n/a | O8: Shingle | P8: GF0700000811 | Q8: TCL-MG720DT210-68NS | R8: EVO2A | S8: ±1400mm | T8: 720 | U8: 1782 | V8: 1.283 | W8: 54 | X8: 3 | Y8: COMPLETED | Z8: COMPLETED | AB8: 46008 | AC8: 51 | AD8: POPV260217050 | AF8: SHANGHAI | AG8: Shanghai | AH8: ROTTERDAM | AI8: 46014 | AJ8: 46018 | AK8: 46017 | AL8: 46073 | AM8: 46090 | AN8: 46090 | AO8: DAP | AP8: COSCO SHIPPING KILIMANJARO 043W | AQ8: COSCO | AR8: TPVB20251212008 | AS8: COSU6438512470 | AT8: COSU6438512470 | AU8: 73 | AW8: 46090 | AX8: In Stock-Approved | AY8: 46104 | AZ8: 7 | BA8: 46097 | BB8: 2026 | BC8: 3 | BD8: 12 | BE8: 33 | BF8: 594 | BG8: White glazing | BH8: AEU
A9: NOV008.01 | B9: Tianjin | C9: NOV008 | D9: CORE DG | E9: Offshore | F9: SPTN Offstore in Transit WH | G9: CIP | H9: Ecostal France | I9: n/a | J9: Ecostal France | K9: 46010731 | M9: n/a | N9: n/a | O9: Half Cut | P9: GF0700000080 | Q9: HSM-ND48-DR450_CFP | R9: EVO2A | S9: ±1200mm | T9: 450 | U9: 936 | V9: 0.421 | W9: 26 | X9: 1 | Y9: COMPLETED | Z9: COMPLETED | AB9: 46009 | AC9: 51 | AD9: POPV260104138 | AE9: 371009343 | AF9: TIANJIN | AG9: Tianjin | AH9: FOS SUR MER | AI9: 46017 | AJ9: 46018 | AK9: 46018 | AL9: 46077 | AM9: 46090 | AN9: 46090 | AO9: CIP | AP9: COSCO SHIPPING VIRGO 034W | AQ9: COSCO | AR9: 46010731&817 | AS9: COSU9505137680 | AT9: COSU9505137680 | AU9: 72 | AV9: SWB | AW9: 46090 | AX9: In Stock-Approved | AY9: 46026 | AZ9: - | BA9: 46090 | BB9: 2026 | BC9: 3 | BD9: 11 | BE9: 36 | BF9: 936 | BG9: Transparent | BH9: AEM
A10: NOV008.02 | B10: Tianjin | C10: NOV008 | D10: CORE DG | E10: Offshore | F10: SPTN Offstore in Transit WH | G10: CIP | H10: Ecostal France | I10: n/a | J10: Ecostal France | K10: 46010817 | M10: n/a | N10: n/a | O10: Half Cut | P10: GF0700000080 | Q10: HSM-ND48-DR450_CFP | R10: EVO2A | S10: ±1200mm | T10: 450 | U10: 936 | V10: 0.421 | W10: 26 | X10: 1 | Y10: COMPLETED | Z10: COMPLETED | AB10: 46009 | AC10: 51 | AD10: POPV260104116 | AE10: 371009344 | AF10: TIANJIN | AG10: Tianjin | AH10: FOS SUR MER | AI10: 46017 | AJ10: 46018 | AK10: 46018 | AL10: 46077 | AM10: 46090 | AN10: 46090 | AO10: CIP | AP10: COSCO SHIPPING VIRGO 034W | AQ10: COSCO | AR10: 46010731&817 | AS10: COSU9505137680 | AT10: COSU9505137680 | AU10: 72 | AV10: SWB | AW10: 46090 | AX10: In Stock-Approved | AY10: 46026 | AZ10: - | BA10: 46090 | BB10: 2026 | BC10: 3 | BD10: 11 | BE10: 36 | BF10: 936 | BG10: Transparent | BH10: AEM
A11: OCT009.06 | B11: Tianjin | C11: OCT009 | D11: CORE DG | E11: Offshore | F11: SPTN Offstore in Transit WH | G11: FOB | H11: UAB Elmitra | I11: n/a | J11: UAB Elmitra | K11: 46011026 | M11: n/a | N11: n/a | O11: Half Cut | P11: GF0700000071 | Q11: HSM-ND54-DR500 | R11: EVO2A | S11: ±1200mm | T11: 500 | U11: 2592 | V11: 1.296 | W11: 72 | X11: 3 | Y11: COMPLETED | Z11: COMPLETED | AB11: 46011 | AC11: 51 | AD11: POPV260104081 | AE11: 371009338 | AF11: TIANJIN | AG11: Tianjin | AH11: KLAIPEDA | AI11: 46020 | AJ11: 46022 | AK11: 46020 | AL11: 46088 | AM11: 46106 | AN11: 46106 | AO11: FOB | AP11: MSC CARMELA/GA552W | AQ11: OTHER | AR11: 46011026 | AS11: 1071458212 | AT11: 177KKNPPXTNN5247 | AU11: 86 | AW11: 46106 | AX11: In Stock-Approved | AY11: 46026 | AZ11: - | BA11: 46106 | BB11: 2026 | BC11: 3 | BD11: 13 | BE11: 36 | BF11: 864 | BG11: Black glazing | BH11: AEU
A12: OCT012.03 | B12: Tianjin | C12: OCT012 | D12: CORE DG | E12: Internal | F12: Arrival Plan-SPNL | G12: DAP | H12: SunPower Energy Solutions France SAS | I12: n/a | J12: Distributors Italy - W72 | M12: n/a | N12: n/a | O12: Half Cut | P12: GF0101010095 | Q12: HSM-ND66-GR620 | R12: EVO2A | S12: ±1200mm | T12: 620 | U12: 4320 | V12: 2.678 | W12: 120 | X12: 6 | Y12: COMPLETED | Z12: COMPLETED | AB12: 46009 | AC12: 51 | AD12: POPV260224026 | AF12: TIANJIN | AG12: Tianjin | AH12: ROTTERDAM | AI12: 46017 | AJ12: 46018 | AK12: 46018 | AL12: 46078 | AM12: 46111 | AN12: 46111 | AO12: DAP | AP12: COSCO SHIPPING VIRGO 034W | AQ12: COSCO | AR12: TPVB20251212011 | AS12: COSU6438568500 | AT12: COSU6438568500 | AU12: 93 | AV12: SWB | AW12: 46111 | AX12: In Stock-Approved | AY12: 46125 | AZ12: 7 | BA12: 46118 | BB12: 2026 | BC12: 4 | BD12: 15 | BE12: 36 | BF12: 720 | BG12: White glazing | BH12: AEU
A13: DEC009.02 | B13: Yixing | C13: DEC009 | D13: CORE DG | E13: Internal | F13: Arrival Plan-SPNL | G13: DAP | H13: SunPower Energy Solutions France SAS | I13: n/a | J13: Local WH - W72 (Italy) | M13: n/a | N13: n/a | O13: P7 COM S BF IT | P13: GF0700000769 | Q13: PVM, SPR-P7-555-COM-S, I BF-G M4.3D EVO2Z6NL 1.5KV IT | R13: EVO2A | S13: ±1400mm | T13: 555 | U13: 1320 | V13: 0.733 | W13: 40 | X13: 2 | Y13: COMPLETED | Z13: COMPLETED | AB13: 46013 | AC13: 52 | AD13: POPV260217038 | AF13: SHANGHAI | AG13: Shanghai | AH13: ROTTERDAM | AI13: 46021 | AJ13: 46031 | AK13: 46030 | AL13: 46075 | AM13: 46111 | AN13: 46111 | AO13: DAP | AP13: CSCL URANUS 107W | AQ13: COSCO | AR13: TPVB20251219006 | AS13: COSU6439187330 | AT13: COSU6439187330 | AU13: 81 | AW13: 46111 | AX13: In Stock-Approved | AY13: 46125 | AZ13: 7 | BA13: 46118 | BB13: 2026 | BC13: 4 | BD13: 15 | BE13: 33 | BF13: 660 | BG13: White glazing | BH13: AEU
A14: DEC003.04 | B14: Yixing | C14: DEC003 | D14: UPP | E14: Internal | F14: Arrival Plan-SPES | G14: DAP | H14: Sunpower Energy Systems Spain, S.L.U. | I14: n/a | J14: SPES / Total Portugal | K14: PT0125122900789 | M14: n/a | N14: n/a | O14: Half Cut | P14: GF0700001575 | Q14: HSM-ND78-GF640 | R14: EVO2A | S14: ±1400mm | T14: 640 | U14: 1152 | V14: 0.737 | W14: 32 | X14: 2 | Y14: COMPLETED | Z14: COMPLETED | AB14: 46018 | AC14: 52 | AD14: POPV260115034 | AF14: SHANGHAI | AG14: Shanghai | AH14: VALENCIA | AI14: 46021 | AJ14: 46031 | AK14: 46030 | AL14: 46065 | AM14: 46088 | AN14: 46089 | AO14: DAP | AP14: CSCL URANUS 107W | AQ14: COSCO | AR14: TPVB20251219004 | AS14: COSU6439185140 | AT14: COSU6439185140 | AU14: 59 | AW14: 46089 | AX14: In Stock-Approved | AY14: 46100 | AZ14: 9 | BA14: 46098 | BB14: 2026 | BC14: 3 | BD14: 12 | BE14: 36 | BF14: 576 | BG14: Redirection Film | BH14: AEM
A15: DEC012.05 | B15: Yixing | C15: DEC012 | D15: CORE DG | E15: Internal | F15: Arrival Plan-SPTN | G15: DAP | H15: SunPower Energy Solutions France SAS | I15: n/a | J15: Local WH - SPTN W74 (Italy) | M15: n/a | N15: n/a | O15: Shingle | P15: GF0700000811 | Q15: TCL-MG720DT210-68NS | R15: EVO2A | S15: ±1400mm | T15: 720 | U15: 4752 | V15: 3.421 | W15: 144 | X15: 8 | Y15: COMPLETED | Z15: COMPLETED | AB15: 46021 | AC15: 1 | AD15: POPV260224033 | AF15: SHANGHAI | AG15: Shanghai | AH15: FOS SUR MER | AI15: 46027 | AJ15: 46029 | AK15: 46030 | AL15: 46073 | AM15: 46098 | AN15: 46099 | AO15: DAP | AP15: EVER GOLDEN 0733-031W | AQ15: COSCO | AR15: TPVB20251219005 | AS15: COSU6440016030 | AT15: COSU6440016030 | AU15: 69 | AW15: 46099 | AX15: In Stock-Approved | AY15: 46112 | AZ15: 8 | BA15: 46107 | BB15: 2026 | BC15: 3 | BD15: 13 | BE15: 33 | BF15: 594 | BG15: White glazing | BH15: AEM
A16: NOV005.02 | B16: Yixing | C16: NOV005 | D16: CORE DG | E16: Internal | F16: Arrival Plan-SPTN | G16: DAP | H16: SunPower Energy Solutions France SAS | I16: n/a | J16: Distributors Italy - SPTN W74 | M16: n/a | N16: n/a | O16: Shingle | P16: GF0700001578 | Q16: TCL-MR465DT182-58NS | R16: EVO2A | S16: ±1200mm | T16: 465 | U16: 4320 | V16: 2.009 | W16: 120 | X16: 5 | Y16: COMPLETED | Z16: COMPLETED | AB16: 46021 | AC16: 1 | AD16: POPV260224034 | AF16: SHANGHAI | AG16: Shanghai | AH16: FOS SUR MER | AI16: 46027 | AJ16: 46029 | AK16: 46030 | AL16: 46073 | AM16: 46098 | AN16: 46099 | AO16: DAP | AP16: EVER GOLDEN 0733-031W | AQ16: COSCO | AR16: TPVB20251219005 | AS16: COSU6440016030 | AT16: COSU6440016030 | AU16: 69 | AW16: 46099 | AX16: In Stock-Approved | AY16: 46112 | AZ16: 8 | BA16: 46107 | BB16: 2026 | BC16: 3 | BD16: 13 | BE16: 36 | BF16: 864 | BG16: White glazing | BH16: AEM
A17: OCT007.08 | B17: Tianjin | C17: OCT007 | D17: CORE DG | E17: Internal | F17: Arrival Plan-SPNL | G17: DAP | H17: SunPower Energy Solutions France SAS | I17: n/a | J17: SPTN // Baltsolar | K17: 46011059 | M17: n/a | N17: n/a | O17: Half Cut | P17: GF0700000078 | Q17: HSM-ND48-DR450 | R17: EVO2A | S17: ±1200mm | T17: 450 | U17: 1872 | V17: 0.842 | W17: 52 | X17: 2 | Y17: COMPLETED | Z17: COMPLETED | AB17: 46016 | AC17: 52 | AD17: POPV260115023 | AF17: TIANJIN | AG17: Tianjin | AH17: ROTTERDAM | AI17: 46027 | AJ17: 46027 | AK17: 46027 | AL17: 46081 | AM17: 46094 | AN17: 46094 | AO17: DAP | AP17: COSCO SHIPPING GALAXY 028W | AQ17: COSCO | AR17: TPVB20251219008 | AS17: COSU9505242760 | AT17: COSU9505242760 | AU17: 67 | AV17: SWB | AW17: 46094 | AX17: In Stock-Approved | AY17: 46097 | AZ17: 7 | BA17: 46101 | BB17: 2026 | BC17: 3 | BD17: 12 | BE17: 36 | BF17: 936 | BG17: Black glazing | BH17: AEU
A18: NOV009 | B18: Tianjin | C18: Main Line | D18: CORE DG | E18: Internal | F18: Arrival Plan-SPTN | G18: DAP | H18: SunPower Energy Solutions France SAS | I18: n/a | J18: Local WH | M18: n/a | N18: n/a | O18: Half Cut | P18: GF0700001603 | Q18: HSM-ND48-DR455_CFP | R18: EVO2A | S18: ±1200mm | T18: 455 | U18: 5616 | V18: 2.555 | W18: 156 | X18: 6 | Y18: COMPLETED | Z18: COMPLETED | AB18: 46016 | AC18: 52 | AD18: POPV260204032 | AF18: TIANJIN | AG18: Tianjin | AH18: FOS SUR MER | AI18: 46027 | AJ18: 46027 | AK18: 46027 | AL18: 46090 | AM18: 46101 | AN18: 46102 | AO18: DAP | AP18: COSCO SHIPPING GALAXY 028W | AQ18: COSCO | AR18: TPVB20251219009 | AS18: COSU6439291780 | AT18: COSU6439291780 | AU18: 75 | AV18: SWB | AW18: 46102 | AX18: In Stock-Approved | AY18: 46115 | AZ18: 8 | BA18: 46110 | BB18: 2026 | BC18: 3 | BD18: 13 | BE18: 36 | BF18: 936 | BG18: Transparent | BH18: AEM
A19: DEC009.10 | B19: Yixing | C19: DEC009 | D19: CORE DG | E19: Internal | F19: Arrival Plan-SPNL | G19: DAP | H19: SunPower Energy Solutions France SAS | I19: n/a | J19: Local WH | M19: n/a | N19: n/a | O19: P7 COM S BF IT | P19: GF0700000769 | Q19: PVM, SPR-P7-555-COM-S, I BF-G M4.3D EVO2Z6NL 1.5KV IT | R19: EVO2A | S19: ±1400mm | T19: 555 | U19: 660 | V19: 0.366 | W19: 20 | X19: 1 | Y19: COMPLETED | Z19: COMPLETED | AB19: 46028 | AC19: 2 | AD19: POPV260126026 | AF19: SHANGHAI | AG19: Shanghai | AH19: ROTTERDAM | AI19: 46031 | AJ19: 46036 | AK19: 46035 | AL19: 46069 | AM19: 46087 | AN19: 46087 | AO19: DAP | AP19: COSCO NETHERLANDS 075W | AQ19: COSCO | AR19: TPVB20260102009 | AS19: COSU6440379730 | AT19: COSU6440379730 | AU19: 52 | AW19: 46087 | AX19: In Stock-Approved | AY19: 46101 | AZ19: 7 | BA19: 46094 | BB19: 2026 | BC19: 3 | BD19: 11 | BE19: 33 | BF19: 660 | BG19: White glazing | BH19: AEU
A20: NOV017.11 | B20: Yixing | C20: NOV017 | D20: UPP | E20: Internal | F20: Arrival Plan-SPNL | G20: DAP | H20: SunPower Energy Solutions France SAS | I20: n/a | J20: SPTN / Elements Montredon | K20: FR0125122900699 | M20: n/a | N20: n/a | O20: Half Cut | P20: GF0700000313 | Q20: HSM-ND66-GR625 CFP | R20: EVO2A | S20: ±1400mm | T20: 625 | U20: 2880 | V20: 1.8 | W20: 80 | X20: 4 | Y20: COMPLETED | Z20: COMPLETED | AB20: 46028 | AC20: 2 | AD20: POPV260126028 | AF20: SHANGHAI | AG20: Shanghai | AH20: ROTTERDAM | AI20: 46033 | AJ20: 46033 | AK20: 46032 | AL20: 46070 | AM20: 46074 | AN20: 46078 | AO20: DAP | AP20: CMA CGM SAINT GERMAIN 0FMLKW1MA | AQ20: OTHER | AR20: TPVB20260102001 | AS20: CHN2962495 | AT20: CHN2962495 | AU20: 46 | AW20: 46078 | AX20: In Stock-Approved | AY20: 46090 | AZ20: 7 | BA20: 46085 | BB20: 2026 | BC20: 3 | BD20: 10 | BE20: 36 | BF20: 720 | BG20: Redirection Film | BH20: AEU
A21: NOV017.09 | B21: Yixing | C21: NOV017 | D21: UPP | E21: Internal | F21: Arrival Plan-SPNL | G21: DAP | H21: SunPower Energy Solutions France SAS | I21: n/a | J21: SPTN / Elements Montredon | K21: FR0125122900699 | M21: n/a | N21: n/a | O21: Half Cut | P21: GF0700000313 | Q21: HSM-ND66-GR625 CFP | R21: EVO2A | S21: ±1400mm | T21: 625 | U21: 5040 | V21: 3.15 | W21: 140 | X21: 7 | Y21: COMPLETED | Z21: COMPLETED | AB21: 46028 | AC21: 2 | AD21: POPV260126029 | AF21: SHANGHAI | AG21: Shanghai | AH21: ROTTERDAM | AI21: 46033 | AJ21: 46033 | AK21: 46032 | AL21: 46070 | AM21: 46074 | AN21: 46078 | AO21: DAP | AP21: CMA CGM SAINT GERMAIN 0FMLKW1MA | AQ21: OTHER | AR21: TPVB20260102001 | AS21: CHN2962495 | AT21: CHN2962495 | AU21: 46 | AW21: 46078 | AX21: In Stock-Approved | AY21: 46090 | AZ21: 7 | BA21: 46085 | BB21: 2026 | BC21: 3 | BD21: 10 | BE21: 36 | BF21: 720 | BG21: Redirection Film | BH21: AEU
A22: DEC009.01 | B22: Yixing | C22: DEC009 | D22: CORE DG | E22: Internal | F22: Arrival Plan-SPTN | G22: DAP | H22: SunPower Energy Solutions France SAS | I22: n/a | J22: Local WH | M22: n/a | N22: n/a | O22: P7 COM S BF IT | P22: GF0700000769 | Q22: PVM, SPR-P7-555-COM-S, I BF-G M4.3D EVO2Z6NL 1.5KV IT | R22: EVO2A | S22: ±1400mm | T22: 555 | U22: 1320 | V22: 0.733 | W22: 40 | X22: 2 | Y22: COMPLETED | Z22: COMPLETED | AB22: 46024 | AC22: 1 | AD22: POPV260126033 | AF22: SHANGHAI | AG22: Shanghai | AH22: FOS SUR MER | AI22: 46028 | AJ22: 46029 | AK22: 46029 | AL22: 46077 | AM22: 46083 | AN22: 46083 | AO22: DAP | AP22: CMA CGM BIG SUR 0MEMRW1MA | AQ22: COSCO | AR22: TPVB20260102003 | AS22: COSU6440380050 | AT22: COSU6440380050 | AU22: 54 | AW22: 46083 | AX22: In Stock-Approved | AY22: 46097 | AZ22: 8 | BA22: 46091 | BB22: 2026 | BC22: 3 | BD22: 11 | BE22: 33 | BF22: 660 | BG22: White glazing | BH22: AEM
A23: DEC009.06 | B23: Yixing | C23: DEC009 | D23: CORE DG | E23: Internal | F23: Arrival Plan-SPTN | G23: DAP | H23: SunPower Energy Solutions France SAS | I23: n/a | J23: Local WH - SPTN W74 | M23: n/a | N23: n/a | O23: P7 COM S BF IT | P23: GF0700000769 | Q23: PVM, SPR-P7-555-COM-S, I BF-G M4.3D EVO2Z6NL 1.5KV IT | R23: EVO2A | S23: ±1400mm | T23: 555 | U23: 1320 | V23: 0.733 | W23: 40 | X23: 2 | Y23: COMPLETED | Z23: COMPLETED | AB23: 46024 | AC23: 1 | AD23: POPV260127044 | AF23: SHANGHAI | AG23: Shanghai | AH23: FOS SUR MER | AI23: 46028 | AJ23: 46029 | AK23: 46029 | AL23: 46077 | AM23: 46083 | AN23: 46083 | AO23: DAP | AP23: CMA CGM BIG SUR | AQ23: COSCO | AR23: TPVB20260102003 | AS23: COSU6440380050 | AT23: COSU6440380050 | AU23: 54 | AW23: 46083 | AX23: In Stock-Approved | AY23: 46097 | AZ23: 8 | BA23: 46091 | BB23: 2026 | BC23: 3 | BD23: 11 | BE23: 33 | BF23: 660 | BG23: White glazing | BH23: AEM
A24: DEC003.11 | B24: Yixing | C24: DEC003 | D24: UPP | E24: Internal | F24: Arrival Plan-SPES | G24: DAP | H24: Sunpower Energy Systems Spain, S.L.U. | I24: n/a | J24: SPES / Total Portugal | K24: PT0125122900789 | M24: n/a | N24: n/a | O24: Half Cut | P24: GF0700001575 | Q24: HSM-ND78-GF640 | R24: EVO2A | S24: ±1400mm | T24: 640 | U24: 1152 | V24: 0.737 | W24: 32 | X24: 2 | Y24: COMPLETED | Z24: COMPLETED | AB24: 46024 | AC24: 1 | AD24: POPV260126030 | AF24: SHANGHAI | AG24: Shanghai | AH24: VALENCIA | AI24: 46028 | AJ24: 46029 | AK24: 46029 | AL24: 46072 | AM24: 46072 | AN24: 46075 | AO24: DAP | AP24: CMA CGM BIG SUR 0MEMRW1MA | AQ24: COSCO | AR24: TPVB20260102004 | AS24: COSU6440380240 | AT24: COSU6440380240 | AU24: 46 | AW24: 46075 | AX24: In Stock-Approved | AY24: 46086 | AZ24: 9 | BA24: 46084 | BB24: 2026 | BC24: 3 | BD24: 10 | BE24: 36 | BF24: 576 | BG24: Redirection Film | BH24: AEM
A25: DEC003.12.01 | B25: Yixing | C25: DEC003 | D25: UPP | E25: Internal | F25: Arrival Plan-SPES | G25: DAP | H25: Sunpower Energy Systems Spain, S.L.U. | I25: n/a | J25: SPES / Total Portugal | K25: PT0125122900789 | M25: n/a | N25: n/a | O25: Half Cut | P25: GF0700001575 | Q25: HSM-ND78-GF640 | R25: EVO2A | S25: ±1400mm | T25: 640 | U25: 967 | V25: 0.619 | W25: 26.9 | X25: 1.7 | Y25: COMPLETED | Z25: COMPLETED | AB25: 46027 | AC25: 2 | AD25: POPV260126032 | AF25: SHANGHAI | AG25: Shanghai | AH25: VALENCIA | AI25: 46032 | AJ25: 45670 | AK25: 46035 | AL25: 46072 | AM25: 46076 | AN25: 46078 | AO25: DAP | AP25: CSCL MERCURY 098W | AQ25: COSCO | AR25: TPVB20260102005 | AS25: COSU6440381610 | AT25: COSU6440381610 | AU25: 43 | AW25: 46078 | AX25: In Stock-Approved | AY25: 46092 | AZ25: 9 | BA25: 46087 | BB25: 2026 | BC25: 3 | BD25: 10 | BE25: 36 | BF25: 576 | BG25: Redirection Film | BH25: AEM
A26: DEC003.12 | B26: Yixing | C26: DEC003 | D26: UPP | E26: Internal | F26: Arrival Plan-SPES | G26: DAP | H26: Sunpower Energy Systems Spain, S.L.U. | I26: n/a | J26: SPES / Total Portugal | K26: PT0125122900789 | M26: n/a | N26: n/a | O26: Half Cut | P26: GF0700001575 | Q26: HSM-ND78-GF640 | R26: EVO2A | S26: ±1400mm | T26: 640 | U26: 761 | V26: 0.487 | W26: 21.1 | X26: 1.3 | Y26: COMPLETED | Z26: COMPLETED | AB26: 46027 | AC26: 2 | AD26: POPV260126032 | AF26: SHANGHAI | AG26: Shanghai | AH26: VALENCIA | AI26: 46032 | AJ26: 45670 | AK26: 46035 | AL26: 46072 | AM26: 46076 | AN26: 46078 | AO26: DAP | AP26: CSCL MERCURY 098W | AQ26: COSCO | AR26: TPVB20260102005 | AS26: COSU6440381610 | AT26: COSU6440381610 | AU26: 43 | AW26: 46078 | AX26: In Stock-Approved | AY26: 46092 | AZ26: 9 | BA26: 46087 | BB26: 2026 | BC26: 3 | BD26: 10 | BE26: 36 | BF26: 576 | BG26: Redirection Film | BH26: AEM
A27: DEC003.13 | B27: Yixing | C27: DEC003 | D27: UPP | E27: Internal | F27: Arrival Plan-SPES | G27: DAP | H27: Sunpower Energy Systems Spain, S.L.U. | I27: n/a | J27: SPES / Total Portugal | K27: PT0125122900789 | M27: n/a | N27: n/a | O27: Half Cut | P27: GF0700001575 | Q27: HSM-ND78-GF640 | R27: EVO2A | S27: ±1400mm | T27: 640 | U27: 1728 | V27: 1.106 | W27: 48 | X27: 3 | Y27: COMPLETED | Z27: COMPLETED | AB27: 46026 | AC27: 1 | AD27: POPV260206008 | AF27: SHANGHAI | AG27: Shanghai | AH27: VALENCIA | AI27: 46031 | AK27: 46030 | AL27: 46086 | AM27: 46088 | AN27: 46089 | AO27: DAP | AP27: COSCO SHIPPING SCORPIO 033W | AQ27: COSCO | AR27: TPVB20260102006 | AS27: COSU6440381320 | AT27: COSU6440381320 | AU27: 59 | AW27: 46089 | AX27: In Stock-Approved | AY27: 46100 | AZ27: 9 | BA27: 46098 | BB27: 2026 | BC27: 3 | BD27: 12 | BE27: 36 | BF27: 576 | BG27: Redirection Film | BH27: AEM
A28: NOV005.03 | B28: Yixing | C28: NOV005 | D28: CORE DG | E28: Internal | F28: Arrival Plan-SPTN | G28: DAP | H28: SunPower Energy Solutions France SAS | I28: n/a | J28: Distributors Italy - SPTN W74 | M28: n/a | N28: n/a | O28: Shingle | P28: GF0700001578 | Q28: TCL-MR465DT182-58NS | R28: EVO2A | S28: ±1200mm | T28: 465 | U28: 1728 | V28: 0.804 | W28: 48 | X28: 2 | Y28: COMPLETED | Z28: COMPLETED | AB28: 46026 | AC28: 1 | AD28: POPV260224032 | AF28: SHANGHAI | AG28: Shanghai | AH28: FOS SUR MER | AI28: 46031 | AK28: 46030 | AL28: 46078 | AM28: 46083 | AN28: 46084 | AO28: DAP | AP28: COSCO SHIPPING SCORPIO 033W | AQ28: COSCO | AR28: TPVB20260102007 | AS28: COSU6440242670 | AT28: COSU6440242670 | AU28: 54 | AW28: 46084 | AX28: In Stock-Approved | AY28: 46097 | AZ28: 8 | BA28: 46092 | BB28: 2026 | BC28: 3 | BD28: 11 | BE28: 36 | BF28: 864 | BG28: White glazing | BH28: AEM
A29: NOV005.04 | B29: Yixing | C29: NOV005 | D29: CORE DG | E29: Internal | F29: Arrival Plan-SPNL | G29: DAP | H29: SunPower Energy Solutions France SAS | I29: n/a | J29: Distributors Italy - W72 | M29: n/a | N29: n/a | O29: Shingle | P29: GF0700001578 | Q29: TCL-MR465DT182-58NS | R29: EVO2A | S29: ±1200mm | T29: 465 | U29: 864 | V29: 0.402 | W29: 24 | X29: 1 | Y29: COMPLETED | Z29: COMPLETED | AB29: 46026 | AC29: 1 | AD29: POPV260417059 | AF29: SHANGHAI | AG29: Shanghai | AH29: ROTTERDAM | AI29: 46031 | AK29: 46030 | AL29: 46080 | AM29: 46111 | AN29: 46111 | AO29: DAP | AP29: COSCO SHIPPING SCORPIO 033W | AQ29: COSCO | AR29: TPVB20260102008 | AS29: COSU6440242960 | AT29: COSU6440242960 | AU29: 81 | AW29: 46111 | AX29: In Stock-Approved | AY29: 46146 | AZ29: 7 | BA29: 46118 | BB29: 2026 | BC29: 4 | BD29: 15 | BE29: 36 | BF29: 864 | BG29: White glazing | BH29: AEU
A30: DEC009.04 | B30: Yixing | C30: DEC009 | D30: CORE DG | E30: Internal | F30: Arrival Plan-SPNL | G30: DAP | H30: SunPower Energy Solutions France SAS | I30: n/a | J30: Local WH - W72 (Italy) | M30: n/a | N30: n/a | O30: P7 COM S BF IT | P30: GF0700000769 | Q30: PVM, SPR-P7-555-COM-S, I BF-G M4.3D EVO2Z6NL 1.5KV IT | R30: EVO2A | S30: ±1400mm | T30: 555 | U30: 660 | V30: 0.366 | W30: 20 | X30: 1 | Y30: COMPLETED | Z30: COMPLETED | AB30: 46026 | AC30: 1 | AD30: POPV260217039 | AF30: SHANGHAI | AG30: Shanghai | AH30: ROTTERDAM | AI30: 46031 | AK30: 46030 | AL30: 46080 | AM30: 46111 | AN30: 46111 | AO30: DAP | AP30: COSCO SHIPPING SCORPIO 033W | AQ30: COSCO | AR30: TPVB20260102008 | AS30: COSU6440242960 | AT30: COSU6440242960 | AU30: 81 | AW30: 46111 | AX30: In Stock-Approved | AY30: 46125 | AZ30: 7 | BA30: 46118 | BB30: 2026 | BC30: 4 | BD30: 15 | BE30: 33 | BF30: 660 | BG30: White glazing | BH30: AEU
A31: DEC009.11 | B31: Yixing | C31: DEC009 | D31: CORE DG | E31: Internal | F31: Arrival Plan-SPNL | G31: DAP | H31: SunPower Energy Solutions France SAS | I31: n/a | J31: Local WH | M31: n/a | N31: n/a | O31: P7 COM S BF IT | P31: GF0700000769 | Q31: PVM, SPR-P7-555-COM-S, I BF-G M4.3D EVO2Z6NL 1.5KV IT | R31: EVO2A | S31: ±1400mm | T31: 555 | U31: 1320 | V31: 0.733 | W31: 40 | X31: 2 | Y31: COMPLETED | Z31: COMPLETED | AB31: 46029 | AC31: 2 | AD31: POPV260126031 | AF31: SHANGHAI | AG31: Shanghai | AH31: ROTTERDAM | AI31: 46035 | AJ31: 46037 | AK31: 46037 | AL31: 46071 | AM31: 46083 | AN31: 46083 | AO31: DAP | AP31: EVER APEX 1383-013W | AQ31: COSCO | AR31: TPVB20260109002 | AS31: COSU6441128810 | AT31: COSU6441128810 | AU31: 46 | AW31: 46083 | AX31: In Stock-Approved | AY31: 46097 | AZ31: 7 | BA31: 46090 | BB31: 2026 | BC31: 3 | BD31: 11 | BE31: 33 | BF31: 660 | BG31: White glazing | BH31: AEU
A32: DEC003.06 | B32: Yixing | C32: DEC003 | D32: UPP | E32: Internal | F32: Arrival Plan-SPES | G32: DAP | H32: Sunpower Energy Systems Spain, S.L.U. | I32: n/a | J32: SPES / Total Portugal | K32: PT0125122900795 | M32: n/a | N32: n/a | O32: Half Cut | P32: GF0700001575 | Q32: HSM-ND78-GF640 | R32: EVO2A | S32: ±1400mm | T32: 640 | U32: 1152 | V32: 0.737 | W32: 32 | X32: 2 | Y32: COMPLETED | Z32: COMPLETED | AB32: 46034 | AC32: 3 | AD32: POPV260206007 | AF32: SHANGHAI | AG32: Shanghai | AH32: VALENCIA | AI32: 46042 | AJ32: 46044 | AK32: 46044 | AL32: 46081 | AM32: 46083 | AN32: 46084 | AO32: DAP | AP32: CSCL SATURN 087W | AQ32: COSCO | AR32: TPVB20260109003 | AS32: COSU6441114300 | AT32: COSU6441114300 | AU32: 40 | AW32: 46084 | AX32: In Stock-Approved | AY32: 46095 | AZ32: 9 | BA32: 46093 | BB32: 2026 | BC32: 3 | BD32: 11 | BE32: 36 | BF32: 576 | BG32: Redirection Film | BH32: AEM
A33: DEC003.05 | B33: Yixing | C33: DEC003 | D33: UPP | E33: Internal | F33: Arrival Plan-SPES | G33: DAP | H33: Sunpower Energy Systems Spain, S.L.U. | I33: n/a | J33: SPES / Total Portugal | K33: PT0125122900789 | M33: n/a | N33: n/a | O33: Half Cut | P33: GF0700001575 | Q33: HSM-ND78-GF640 | R33: EVO2A | S33: ±1400mm | T33: 640 | U33: 2124 | V33: 1.359 | W33: 59 | X33: 3.7 | Y33: COMPLETED | Z33: COMPLETED | AB33: 46029 | AC33: 2 | AD33: POPV260129005 | AF33: SHANGHAI | AG33: Shanghai | AH33: VALENCIA | AI33: 46035 | AJ33: 46041 | AK33: 46041 | AL33: 46079 | AM33: 46079 | AN33: 46079 | AO33: DAP | AP33: CMA CGM CEDRUS 0MEMTW1MA | AQ33: COSCO | AR33: TPVB20260109004 | AS33: COSU6440662920 | AT33: COSU6440662920 | AU33: 38 | AW33: 46079 | AX33: In Stock-Approved | AY33: 46093 | AZ33: 9 | BA33: 46088 | BB33: 2026 | BC33: 3 | BD33: 10 | BE33: 36 | BF33: 576 | BG33: Redirection Film | BH33: AEM
A34: DEC003.10 | B34: Yixing | C34: DEC003 | D34: UPP | E34: Internal | F34: Arrival Plan-SPES | G34: DAP | H34: Sunpower Energy Systems Spain, S.L.U. | I34: n/a | J34: SPES / Total Portugal | K34: PT0125122900795 | M34: n/a | N34: n/a | O34: Half Cut | P34: GF0700001575 | Q34: HSM-ND78-GF640 | R34: EVO2A | S34: ±1400mm | T34: 640 | U34: 180 | V34: 0.115 | W34: 5 | X34: 0.3 | Y34: COMPLETED | Z34: COMPLETED | AB34: 46029 | AC34: 2 | AD34: POPV260129004 | AF34: SHANGHAI | AG34: Shanghai | AH34: VALENCIA | AI34: 46035 | AJ34: 46041 | AK34: 46041 | AL34: 46079 | AM34: 46079 | AN34: 46079 | AO34: DAP | AP34: CMA CGM CEDRUS 0MEMTW1MA | AQ34: COSCO | AR34: TPVB20260109004 | AS34: COSU6440662920 | AT34: COSU6440662920 | AU34: 38 | AW34: 46079 | AX34: In Stock-Approved | AY34: 46093 | AZ34: 9 | BA34: 46088 | BB34: 2026 | BC34: 3 | BD34: 10 | BE34: 36 | BF34: 576 | BG34: Redirection Film | BH34: AEM
A35: DEC003.15 | B35: Yixing | C35: DEC003 | D35: UPP | E35: Internal | F35: Arrival Plan-SPES | G35: DAP | H35: Sunpower Energy Systems Spain, S.L.U. | I35: n/a | J35: SPES / Total Portugal | K35: PT0125122900795 | M35: n/a | N35: n/a | O35: Half Cut | P35: GF0700001575 | Q35: HSM-ND78-GF640 | R35: EVO2A | S35: ±1400mm | T35: 640 | U35: 1152 | V35: 0.737 | W35: 32 | X35: 2 | Y35: COMPLETED | Z35: COMPLETED | AB35: 46029 | AC35: 2 | AD35: POPV260129012 | AF35: SHANGHAI | AG35: Shanghai | AH35: VALENCIA | AI35: 46035 | AJ35: 46041 | AK35: 46041 | AL35: 46079 | AM35: 46079 | AN35: 46079 | AO35: DAP | AP35: CMA CGM CEDRUS 0MEMTW1MA | AQ35: COSCO | AR35: TPVB20260109004 | AS35: COSU6440662920 | AT35: COSU6440662920 | AU35: 38 | AW35: 46079 | AX35: In Stock-Approved | AY35: 46093 | AZ35: 9 | BA35: 46088 | BB35: 2026 | BC35: 3 | BD35: 10 | BE35: 36 | BF35: 576 | BG35: Redirection Film | BH35: AEM
A36: JUNE001.09 | B36: zhuhai -> Shenzhen | C36: JUNE001 | D36: CORE DG | E36: Internal | F36: Arrival Plan-SPNL | G36: DAP | H36: SunPower Energy Solutions France SAS | I36: n/a | J36: SPTN / Grosshandelsunion | M36: n/a | N36: n/a | O36: BC | P36: GF0700000075 | Q36: HSM-BD54-DA460 | R36: EVO2A | S36: ±1400mm | T36: 460 | U36: 962 | V36: 0.443 | W36: 26 | X36: 1 | Y36: COMPLETED | Z36: COMPLETED | AB36: 46030 | AC36: 2 | AD36: POPV260126025 | AF36: SHENZHEN | AG36: Shenzhen | AH36: ROTTERDAM | AI36: 46038 | AJ36: 46041 | AK36: 46041 | AL36: 46069 | AM36: 46087 | AN36: 46087 | AO36: DAP | AP36: COSCO NETHERLANDS 075W | AQ36: COSCO | AR36: TPVB20260109005 | AS36: COSU6440518510 | AT36: COSU6440518510 | AU36: 46 | AV36: SWB | AW36: 46087 | AX36: In Stock-Approved | AY36: 46094 | AZ36: 7 | BA36: 46094 | BB36: 2026 | BC36: 3 | BD36: 11 | BE36: 37 | BF36: 962 | BG36: Black glazing | BH36: AEU
A37: JUNE001.11 | B37: zhuhai -> Shenzhen | C37: JUNE001 | D37: CORE DG | E37: Internal | F37: Arrival Plan-SPNL | G37: DAP | H37: SunPower Energy Solutions France SAS | I37: n/a | J37: SPTN / Energy3000 | M37: n/a | N37: n/a | O37: BC | P37: GF0700000075 | Q37: HSM-BD54-DA460 | R37: EVO2A | S37: ±1400mm | T37: 460 | U37: 4810 | V37: 2.213 | W37: 130 | X37: 5 | Y37: COMPLETED | Z37: COMPLETED | AB37: 46030 | AC37: 2 | AD37: POPV260126022 | AF37: SHENZHEN | AG37: Shenzhen | AH37: ROTTERDAM | AI37: 46038 | AJ37: 46041 | AK37: 46041 | AL37: 46069 | AM37: 46087 | AN37: 46087 | AO37: DAP | AP37: COSCO NETHERLANDS 075W | AQ37: COSCO | AR37: TPVB20260109005 | AS37: COSU6440518510 | AT37: COSU6440518510 | AU37: 46 | AV37: SWB | AW37: 46087 | AX37: In Stock-Approved | AY37: 46094 | AZ37: 7 | BA37: 46094 | BB37: 2026 | BC37: 3 | BD37: 11 | BE37: 37 | BF37: 962 | BG37: Black glazing | BH37: AEU
A38: DEC001.01 | B38: Zhuhai | C38: DEC001 | D38: CORE DG | E38: Internal | F38: Arrival Plan-SPNL | G38: DAP | H38: SunPower Energy Solutions France SAS | I38: n/a | J38: Local WH | M38: n/a | N38: n/a | O38: M Class | P38: GF0700000804 | Q38: SPR-BE54-DC480 | R38: EVO2A | S38: ±1200mm | T38: 480 | U38: 1924 | V38: 0.924 | W38: 52 | X38: 2 | Y38: COMPLETED | Z38: COMPLETED | AB38: 46031 | AC38: 2 | AD38: POPV260126023 | AF38: SHENZHEN | AG38: Shenzhen | AH38: ROTTERDAM | AI38: 46038 | AJ38: 46041 | AK38: 46041 | AL38: 46069 | AM38: 46087 | AN38: 46087 | AO38: DAP | AP38: COSCO NETHERLANDS 075W | AQ38: COSCO | AR38: TPVB20260109006 | AS38: COSU6440518511 | AT38: COSU6440518511 | AU38: 46 | AV38: SWB | AW38: 46087 | AX38: In Stock-Approved | AY38: 46101 | AZ38: 7 | BA38: 46094 | BB38: 2026 | BC38: 3 | BD38: 11 | BE38: 37 | BF38: 962 | BG38: Black glazing | BH38: AEU
A39: DEC002.01 | B39: Zhuhai | C39: DEC002 | D39: CORE DG | E39: Internal | F39: Arrival Plan-SPNL | G39: DAP | H39: SunPower Energy Solutions France SAS | I39: n/a | J39: Local WH | M39: n/a | N39: n/a | O39: M Class | P39: GF0700000805 | Q39: SPR-BE54-DC485 | R39: EVO2A | S39: ±1200mm | T39: 485 | U39: 2886 | V39: 1.4 | W39: 78 | X39: 3 | Y39: COMPLETED | Z39: COMPLETED | AB39: 46031 | AC39: 2 | AD39: POPV260126027 | AF39: SHENZHEN | AG39: Shenzhen | AH39: ROTTERDAM | AI39: 46038 | AJ39: 46041 | AK39: 46041 | AL39: 46069 | AM39: 46087 | AN39: 46087 | AO39: DAP | AP39: COSCO NETHERLANDS 075W | AQ39: COSCO | AR39: TPVB20260109006 | AS39: COSU6440518511 | AT39: COSU6440518511 | AU39: 46 | AV39: SWB | AW39: 46087 | AX39: In Stock-Approved | AY39: 46101 | AZ39: 7 | BA39: 46094 | BB39: 2026 | BC39: 3 | BD39: 11 | BE39: 37 | BF39: 962 | BG39: Black glazing | BH39: AEU
A40: DEC001.02 | B40: Zhuhai | C40: DEC001 | D40: CORE DG | E40: Internal | F40: Arrival Plan-SPIT | G40: DAP | H40: Sunpower Italia S.R.L. | I40: n/a | J40: Local WH - POD to be updated vs. W81 | M40: n/a | N40: n/a | O40: M Class | P40: GF0700000804 | Q40: SPR-BE54-DC480 | R40: EVO2A | S40: ±1200mm | T40: 480 | U40: 1924 | V40: 0.924 | W40: 52 | X40: 2 | Y40: COMPLETED | Z40: COMPLETED | AB40: 46034 | AC40: 3 | AD40: POPV260129008 | AF40: SHENZHEN | AG40: Shenzhen | AH40: GENOA | AI40: 46037 | AJ40: 46037 | AK40: 46038 | AL40: 46078 | AM40: 46078 | AN40: 46078 | AO40: DAP | AP40: COSCO SHIPPING SCORPIO 033W | AQ40: COSCO | AR40: TPVB20260109007 | AS40: COSU6440775660 | AT40: COSU6440775660 | AU40: 40 | AV40: SWB | AW40: 46078 | AX40: In Stock-Approved | AY40: 46092 | AZ40: 13 | BA40: 46091 | BB40: 2026 | BC40: 3 | BD40: 11 | BE40: 37 | BF40: 962 | BG40: Black glazing | BH40: AEM
A41: DEC002.02 | B41: Zhuhai | C41: DEC002 | D41: CORE DG | E41: Internal | F41: Arrival Plan-SPIT | G41: DAP | H41: Sunpower Italia S.R.L. | I41: n/a | J41: Local WH - POD to be updated vs. W81 | M41: n/a | N41: n/a | O41: M Class | P41: GF0700000805 | Q41: SPR-BE54-DC485 | R41: EVO2A | S41: ±1200mm | T41: 485 | U41: 1924 | V41: 0.933 | W41: 52 | X41: 2 | Y41: COMPLETED | Z41: COMPLETED | AB41: 46034 | AC41: 3 | AD41: POPV260129021 | AF41: SHENZHEN | AG41: Shenzhen | AH41: GENOA | AI41: 46037 | AJ41: 46037 | AK41: 46038 | AL41: 46078 | AM41: 46078 | AN41: 46078 | AO41: DAP | AP41: COSCO SHIPPING SCORPIO 033W | AQ41: COSCO | AR41: TPVB20260109007 | AS41: COSU6440775660 | AT41: COSU6440775660 | AU41: 40 | AV41: SWB | AW41: 46078 | AX41: In Stock-Approved | AY41: 46092 | AZ41: 13 | BA41: 46091 | BB41: 2026 | BC41: 3 | BD41: 11 | BE41: 37 | BF41: 962 | BG41: Black glazing | BH41: AEM
A42: DEC002.03 | B42: Zhuhai | C42: DEC002 | D42: CORE DG | E42: Internal | F42: Arrival Plan-SPNL | G42: DAP | H42: SunPower Energy Solutions France SAS | I42: n/a | J42: Local WH - W72 (Italy) | M42: n/a | N42: n/a | O42: M Class | P42: GF0700000805 | Q42: SPR-BE54-DC485 | R42: EVO2A | S42: ±1200mm | T42: 485 | U42: 962 | V42: 0.467 | W42: 26 | X42: 1 | Y42: COMPLETED | Z42: COMPLETED | AB42: 46031 | AC42: 2 | AD42: POPV260211003 | AF42: SHENZHEN | AG42: Shenzhen | AH42: ROTTERDAM | AI42: 46041 | AJ42: 46042 | AK42: 46042 | AL42: 46090 | AM42: 46111 | AN42: 46111 | AO42: DAP | AP42: CSCL MERCURY 098W | AQ42: COSCO | AR42: TPVB20260109008 | AS42: COSU6440772870 | AT42: COSU6440772870 | AU42: 69 | AW42: 46111 | AX42: In Stock-Approved | AY42: 46125 | AZ42: 7 | BA42: 46118 | BB42: 2026 | BC42: 4 | BD42: 15 | BE42: 37 | BF42: 962 | BG42: Black glazing | BH42: AEU
A43: DEC001.03 | B43: Zhuhai | C43: DEC001 | D43: CORE DG | E43: Internal | F43: Arrival Plan-SPNL | G43: DAP | H43: SunPower Energy Solutions France SAS | I43: n/a | J43: Local WH - W72 (Italy) | M43: n/a | N43: n/a | O43: M Class | P43: GF0700000804 | Q43: SPR-BE54-DC480 | R43: EVO2A | S43: ±1200mm | T43: 480 | U43: 962 | V43: 0.462 | W43: 26 | X43: 1 | Y43: COMPLETED | Z43: COMPLETED | AB43: 46031 | AC43: 2 | AD43: POPV260211019 | AF43: SHENZHEN | AG43: Shenzhen | AH43: ROTTERDAM | AI43: 46041 | AJ43: 46042 | AK43: 46042 | AL43: 46090 | AM43: 46111 | AN43: 46111 | AO43: DAP | AP43: CSCL MERCURY 098W | AQ43: COSCO | AR43: TPVB20260109008 | AS43: COSU6440772870 | AT43: COSU6440772870 | AU43: 69 | AW43: 46111 | AX43: In Stock-Approved | AY43: 46125 | AZ43: 7 | BA43: 46118 | BB43: 2026 | BC43: 4 | BD43: 15 | BE43: 37 | BF43: 962 | BG43: Black glazing | BH43: AEU
A44: DEC018.03 | B44: Tianjin | C44: DEC018 | D44: UPP | E44: Internal | F44: Arrival Plan-SPNL | G44: DAP | H44: SunPower Energy Solutions France SAS | I44: n/a | J44: SPTN / Qair SP Uebigau-Wahrenbrück GmbH & Co. KG | K44: tbc | M44: n/a | N44: n/a | O44: Half Cut | P44: GF0700000346 | Q44: HSM-ND66-GR625 | R44: H4(Com) | S44: ±1400mm | T44: 625 | U44: 7200 | V44: 4.5 | W44: 200 | X44: 10 | Y44: COMPLETED | Z44: COMPLETED | AB44: 46030 | AC44: 2 | AD44: POPV260126034 | AF44: TIANJIN | AG44: Tianjin | AH44: ROTTERDAM | AI44: 46036 | AJ44: 46038 | AK44: 46038 | AL44: 46077 | AM44: 46094 | AN44: 46094 | AO44: DAP | AP44: COSCO SHIPPING SOLAR / 0FAM7W1MA/035W | AQ44: OTHER | AR44: TPVB20260109009 | AS44: TJN0838410 | AT44: TJN0838410 | AU44: 56 | AW44: 46094 | AX44: In Stock-Approved | AY44: 46104 | AZ44: 7 | BA44: 46101 | BB44: 2026 | BC44: 3 | BD44: 12 | BE44: 36 | BF44: 720 | BG44: Redirection Film | BH44: AEU
A45: OCT007.06 | B45: Tianjin | C45: OCT007 | D45: CORE DG | E45: Internal | F45: Arrival Plan-SPNL | G45: DAP | H45: SunPower Energy Solutions France SAS | I45: n/a | J45: SPTN / Grosshandelsunion | M45: n/a | N45: n/a | O45: Half Cut | P45: GF0700000078 | Q45: HSM-ND48-DR450 | R45: EVO2A | S45: ±1200mm | T45: 450 | U45: 936 | V45: 0.421 | W45: 26 | X45: 1 | Y45: COMPLETED | Z45: COMPLETED | AB45: 46030 | AC45: 2 | AD45: POPV260126021 | AF45: TIANJIN | AG45: Tianjin | AH45: ROTTERDAM | AI45: 46036 | AJ45: 46038 | AK45: 46038 | AL45: 46077 | AM45: 46094 | AN45: 46094 | AO45: DAP | AP45: COSCO SHIPPING SOLAR 035W | AQ45: COSCO | AR45: TPVB20260109010 | AS45: COSU6441103270 | AT45: COSU6441103270 | AU45: 56 | AW45: 46094 | AX45: In Stock-Approved | AY45: 46107 | AZ45: 7 | BA45: 46101 | BB45: 2026 | BC45: 3 | BD45: 12 | BE45: 36 | BF45: 936 | BG45: Black glazing | BH45: AEU
A46: DEC018.02 | B46: Tianjin | C46: DEC018 | D46: UPP | E46: Internal | F46: Arrival Plan-SPNL | G46: DAP | H46: SunPower Energy Solutions France SAS | I46: n/a | J46: SPTN / Qair SP Uebigau-Wahrenbrück GmbH & Co. KG | K46: tbc | M46: n/a | N46: n/a | O46: Half Cut | P46: GF0700000346 | Q46: HSM-ND66-GR625 | R46: H4(Com) | S46: ±1400mm | T46: 625 | U46: 7200 | V46: 4.5 | W46: 200 | X46: 10 | Y46: COMPLETED | Z46: COMPLETED | AB46: 46026 | AC46: 1 | AD46: POPV260126020 | AF46: TIANJIN | AG46: Tianjin | AH46: ROTTERDAM | AI46: 46036 | AJ46: 46038 | AK46: 46038 | AL46: 46077 | AM46: 46094 | AN46: 46094 | AO46: DAP | AP46: COSCO SHIPPING SOLAR / 0FAM7W1MA/035W | AQ46: OTHER | AR46: TPVB20260109001 | AS46: TJN0838400 | AT46: TJN0838400 | AU46: 56 | AW46: 46094 | AX46: In Stock-Approved | AY46: 46107 | AZ46: 7 | BA46: 46101 | BB46: 2026 | BC46: 3 | BD46: 12 | BE46: 36 | BF46: 720 | BG46: Redirection Film | BH46: AEU
A47: OCT009.03 | B47: Tianjin | C47: OCT009 | D47: CORE DG | E47: Offshore | F47: SPTN Offstore in Transit WH | G47: CIP | H47: Ecostal France | I47: n/a | J47: Ecostal France | K47: FR0125122900715 | M47: n/a | N47: n/a | O47: Half Cut | P47: GF0700000071 | Q47: HSM-ND54-DR500 | R47: EVO2A | S47: ±1200mm | T47: 500 | U47: 864 | V47: 0.432 | W47: 24 | X47: 1 | Y47: COMPLETED | Z47: COMPLETED | AB47: 46027 | AC47: 2 | AD47: POPV260129006 | AF47: TIANJIN | AG47: Tianjin | AH47: FOS SUR MER | AI47: 46032 | AJ47: 46034 | AK47: 46034 | AL47: 46091 | AM47: 46095 | AN47: 46096 | AO47: CIP | AP47: COSCO SHIPPING LIBRA 034W | AQ47: COSCO | AR47: 46010942-4.1 | AS47: COSU6440567860 | AT47: COSU6440567860 | AU47: 62 | AW47: 46096 | AX47: In Stock-Approved | AY47: 46105 | AZ47: - | BA47: 46096 | BB47: 2026 | BC47: 3 | BD47: 11 | BE47: 36 | BF47: 864 | BG47: Black glazing | BH47: AEM
A48: DEC021.02 | B48: Yixing | C48: DEC021 | D48: UPP | E48: Internal | F48: Arrival Plan-SPTN | G48: DAP | H48: SunPower Energy Solutions France SAS | I48: n/a | J48: SPTN / Unite Chauvigny | K48: 46011022 -> FR0125122900833 | M48: n/a | N48: n/a | O48: Half Cut | P48: GF0700000313 | Q48: HSM-ND66-GR625 CFP | R48: EVO2A | S48: ±1400mm | T48: 625 | U48: 2880 | V48: 1.8 | W48: 80 | X48: 4 | Y48: COMPLETED | Z48: COMPLETED | AB48: 46035 | AC48: 3 | AD48: POPV260129013 | AF48: SHANGHAI | AG48: Shanghai | AH48: LE HAVRE | AI48: 46040 | AJ48: 46045 | AK48: 46043 | AL48: 46077 | AM48: 46077 | AN48: 46079 | AO48: DAP | AP48: CMA CGM ZHENG HE / 0FMLMW1MA | AQ48: OTHER | AR48: TPVB20260116002 | AS48: CHN2966579 | AT48: CHN2966579 | AU48: 36 | AW48: 46079 | AX48: In Stock-Approved | AY48: 46091 | AZ48: 8 | BA48: 46087 | BB48: 2026 | BC48: 3 | BD48: 10 | BE48: 36 | BF48: 720 | BG48: Redirection Film | BH48: AEU
A49: NOV017.06 | B49: Yixing | C49: NOV017 | D49: UPP | E49: Internal | F49: Arrival Plan-SPTN | G49: DAP | H49: SunPower Energy Solutions France SAS | I49: n/a | J49: SPTN / Unite Chauvigny | K49: 46011022 -> FR0125122900833 | M49: n/a | N49: n/a | O49: Half Cut | P49: GF0700000313 | Q49: HSM-ND66-GR625 CFP | R49: EVO2A | S49: ±1400mm | T49: 625 | U49: 1440 | V49: 0.9 | W49: 40 | X49: 2 | Y49: COMPLETED | Z49: COMPLETED | AB49: 46035 | AC49: 3 | AD49: POPV260129014 | AF49: SHANGHAI | AG49: Shanghai | AH49: LE HAVRE | AI49: 46040 | AJ49: 46045 | AK49: 46043 | AL49: 46077 | AM49: 46077 | AN49: 46079 | AO49: DAP | AP49: CMA CGM ZHENG HE / 0FMLMW1MA | AQ49: OTHER | AR49: TPVB20260116002 | AS49: CHN2966579 | AT49: CHN2966579 | AU49: 36 | AW49: 46079 | AX49: In Stock-Approved | AY49: 46091 | AZ49: 8 | BA49: 46087 | BB49: 2026 | BC49: 3 | BD49: 10 | BE49: 36 | BF49: 720 | BG49: Redirection Film | BH49: AEU
A50: NOV017.07 | B50: Yixing | C50: NOV017 | D50: UPP | E50: Internal | F50: Arrival Plan-SPTN | G50: DAP | H50: SunPower Energy Solutions France SAS | I50: n/a | J50: SPTN / Unite Beauchêne | K50: 46011021 -> FR0125122900835 | M50: n/a | N50: n/a | O50: Half Cut | P50: GF0700000313 | Q50: HSM-ND66-GR625 CFP | R50: EVO2A | S50: ±1400mm | T50: 625 | U50: 2880 | V50: 1.8 | W50: 80 | X50: 4 | Y50: COMPLETED | Z50: COMPLETED | AB50: 46035 | AC50: 3 | AD50: POPV260129016 | AF50: SHANGHAI | AG50: Shanghai | AH50: LE HAVRE | AI50: 46040 | AJ50: 46045 | AK50: 46043 | AL50: 46077 | AM50: 46077 | AN50: 46079 | AO50: DAP | AP50: CMA CGM ZHENG HE / 0FMLMW1MA | AQ50: OTHER | AR50: TPVB20260116002 | AS50: CHN2966579 | AT50: CHN2966579 | AU50: 36 | AW50: 46079 | AX50: In Stock-Approved | AY50: 46091 | AZ50: 8 | BA50: 46087 | BB50: 2026 | BC50: 3 | BD50: 10 | BE50: 36 | BF50: 720 | BG50: Redirection Film | BH50: AEU
A51: NOV017.12 | B51: Yixing | C51: NOV017 | D51: UPP | E51: Internal | F51: Arrival Plan-SPTN | G51: DAP | H51: SunPower Energy Solutions France SAS | I51: n/a | J51: SPTN / Unite Beauchêne | K51: 46011021 -> FR0125122900835 | M51: n/a | N51: n/a | O51: Half Cut | P51: GF0700000313 | Q51: HSM-ND66-GR625 CFP | R51: EVO2A | S51: ±1400mm | T51: 625 | U51: 1440 | V51: 0.9 | W51: 40 | X51: 2 | Y51: COMPLETED | Z51: COMPLETED | AB51: 46035 | AC51: 3 | AD51: POPV260129015 | AF51: SHANGHAI | AG51: Shanghai | AH51: LE HAVRE | AI51: 46040 | AJ51: 46045 | AK51: 46043 | AL51: 46077 | AM51: 46077 | AN51: 46079 | AO51: DAP | AP51: CMA CGM ZHENG HE / 0FMLMW1MA | AQ51: OTHER | AR51: TPVB20260116002 | AS51: CHN2966579 | AT51: CHN2966579 | AU51: 36 | AW51: 46079 | AX51: In Stock-Approved | AY51: 46091 | AZ51: 8 | BA51: 46087 | BB51: 2026 | BC51: 3 | BD51: 10 | BE51: 36 | BF51: 720 | BG51: Redirection Film | BH51: AEU
A52: NOV017.08 | B52: Yixing | C52: NOV017 | D52: UPP | E52: Internal | F52: Arrival Plan-SPTN | G52: DAP | H52: SunPower Energy Solutions France SAS | I52: n/a | J52: SPTN / Elements Montredon | K52: FR0125122900699 | M52: n/a | N52: n/a | O52: Half Cut | P52: GF0700000313 | Q52: HSM-ND66-GR625 CFP | R52: EVO2A | S52: ±1400mm | T52: 625 | U52: 72 | V52: 0.045 | W52: 2 | X52: 0.1 | Y52: COMPLETED | Z52: COMPLETED | AB52: 46035 | AC52: 3 | AD52: POPV260129017 | AF52: SHANGHAI | AG52: Shanghai | AH52: LE HAVRE | AI52: 46040 | AJ52: 46043 | AK52: 46043 | AL52: 46077 | AM52: 46077 | AN52: 46078 | AO52: DAP | AP52: CMA CGM ZHENG HE 0FMLMW1MA | AQ52: COSCO | AR52: TPVB20260116004 | AS52: COSU6441393600 | AT52: COSU6441393600 | AU52: 35 | AW52: 46078 | AX52: In Stock-Approved | AY52: 46091 | AZ52: 8 | BA52: 46086 | BB52: 2026 | BC52: 3 | BD52: 10 | BE52: 36 | BF52: 720 | BG52: Redirection Film | BH52: AEU
A53: NOV017.13 | B53: Yixing | C53: NOV017 | D53: UPP | E53: Internal | F53: Arrival Plan-SPTN | G53: DAP | H53: SunPower Energy Solutions France SAS | I53: n/a | J53: SPTN / Unite Beauchêne | K53: 46011021 -> FR0125122900835 | M53: n/a | N53: n/a | O53: Half Cut | P53: GF0700000313 | Q53: HSM-ND66-GR625 CFP | R53: EVO2A | S53: ±1400mm | T53: 625 | U53: 324 | V53: 0.203 | W53: 9 | X53: 0.5 | Y53: COMPLETED | Z53: COMPLETED | AB53: 46035 | AC53: 3 | AD53: POPV260129018 | AF53: SHANGHAI | AG53: Shanghai | AH53: LE HAVRE | AI53: 46040 | AJ53: 46043 | AK53: 46043 | AL53: 46077 | AM53: 46077 | AN53: 46078 | AO53: DAP | AP53: CMA CGM ZHENG HE 0FMLMW1MA | AQ53: COSCO | AR53: TPVB20260116004 | AS53: COSU6441393600 | AT53: COSU6441393600 | AU53: 35 | AW53: 46078 | AX53: In Stock-Approved | AY53: 46091 | AZ53: 8 | BA53: 46086 | BB53: 2026 | BC53: 3 | BD53: 10 | BE53: 36 | BF53: 720 | BG53: Redirection Film | BH53: AEU
A54: NOV016.01 | B54: Yixing | C54: NOV016 | D54: UPP | E54: Internal | F54: Arrival Plan-SPTN | G54: DAP | H54: SunPower Energy Solutions France SAS | I54: n/a | J54: SPTN / Soregies Dange II | K54: tbc | M54: n/a | N54: n/a | O54: Half Cut | P54: GF0700000885 | Q54: HSM-ND66-GR620 CFP | R54: EVO2A | S54: ±1400mm | T54: 620 | U54: 324 | V54: 0.201 | W54: 9 | X54: 0.5 | Y54: COMPLETED | Z54: COMPLETED | AB54: 46035 | AC54: 3 | AD54: POPV260129019 | AF54: SHANGHAI | AG54: Shanghai | AH54: LE HAVRE | AI54: 46040 | AJ54: 46043 | AK54: 46043 | AL54: 46077 | AM54: 46077 | AN54: 46078 | AO54: DAP | AP54: CMA CGM ZHENG HE 0FMLMW1MA | AQ54: COSCO | AR54: TPVB20260116004 | AS54: COSU6441393600 | AT54: COSU6441393600 | AU54: 35 | AW54: 46078 | AX54: In Stock-Approved | AY54: 46091 | AZ54: 8 | BA54: 46086 | BB54: 2026 | BC54: 3 | BD54: 10 | BE54: 36 | BF54: 720 | BG54: Redirection Film | BH54: AEU
A55: NOV005.08 | B55: Yixing | C55: NOV005 | D55: CORE DG | E55: Internal | F55: Arrival Plan-SPTN | G55: DAP | H55: SunPower Energy Solutions France SAS | I55: n/a | J55: Distributors Italy - SPTN W74 | M55: n/a | N55: n/a | O55: Shingle | P55: GF0700001578 | Q55: TCL-MR465DT182-58NS | R55: EVO2A | S55: ±1200mm | T55: 465 | U55: 1728 | V55: 0.804 | W55: 48 | X55: 2 | Y55: COMPLETED | Z55: COMPLETED | AB55: 46033 | AC55: 2 | AD55: POPV260225024 | AF55: SHANGHAI | AG55: Shanghai | AH55: FOS SUR MER | AI55: 46042 | AJ55: 46044 | AK55: 46044 | AL55: 46085 | AM55: 46101 | AN55: 46102 | AO55: DAP | AP55: OOCL HONG KONG 038W | AQ55: COSCO | AR55: TPVB20260116005 | AS55: COSU6441367620 | AT55: COSU6441367620 | AU55: 58 | AW55: 46102 | AX55: In Stock-Approved | AY55: 46115 | AZ55: 8 | BA55: 46110 | BB55: 2026 | BC55: 3 | BD55: 13 | BE55: 36 | BF55: 864 | BG55: White glazing | BH55: AEM
A56: DEC011.08 | B56: Yixing | C56: DEC011 | D56: CORE DG | E56: Internal | F56: Arrival Plan-SPTN | G56: DAP | H56: SunPower Energy Solutions France SAS | I56: n/a | J56: Distributors Italy - SPTN W74 | M56: n/a | N56: n/a | O56: Shingle | P56: GF0700001578 | Q56: TCL-MR465DT182-58NS | R56: EVO2A | S56: ±1200mm | T56: 465 | U56: 2592 | V56: 1.205 | W56: 72 | X56: 3 | Y56: COMPLETED | Z56: COMPLETED | AB56: 46033 | AC56: 2 | AD56: POPV260225023 | AF56: SHANGHAI | AG56: Shanghai | AH56: FOS SUR MER | AI56: 46042 | AJ56: 46044 | AK56: 46044 | AL56: 46085 | AM56: 46101 | AN56: 46102 | AO56: DAP | AP56: OOCL HONG KONG 038W | AQ56: COSCO | AR56: TPVB20260116005 | AS56: COSU6441367620 | AT56: COSU6441367620 | AU56: 58 | AW56: 46102 | AX56: In Stock-Approved | AY56: 46115 | AZ56: 8 | BA56: 46110 | BB56: 2026 | BC56: 3 | BD56: 13 | BE56: 36 | BF56: 864 | BG56: White glazing | BH56: AEM
A57: DEC011.02 | B57: Yixing | C57: DEC011 | D57: CORE DG | E57: Internal | F57: Arrival Plan-SPTN | G57: DAP | H57: SunPower Energy Solutions France SAS | I57: n/a | J57: Distributors Italy - SPTN W74 | M57: n/a | N57: n/a | O57: Shingle | P57: GF0700001578 | Q57: TCL-MR465DT182-58NS | R57: EVO2A | S57: ±1200mm | T57: 465 | U57: 1728 | V57: 0.804 | W57: 48 | X57: 2 | Y57: COMPLETED | Z57: COMPLETED | AB57: 46033 | AC57: 2 | AD57: POPV260225022 | AF57: SHANGHAI | AG57: Shanghai | AH57: FOS SUR MER | AI57: 46042 | AJ57: 46044 | AK57: 46044 | AL57: 46085 | AM57: 46101 | AN57: 46102 | AO57: DAP | AP57: OOCL HONG KONG 038W | AQ57: COSCO | AR57: TPVB20260116005 | AS57: COSU6441367620 | AT57: COSU6441367620 | AU57: 58 | AW57: 46102 | AX57: In Stock-Approved | AY57: 46115 | AZ57: 8 | BA57: 46110 | BB57: 2026 | BC57: 3 | BD57: 13 | BE57: 36 | BF57: 864 | BG57: White glazing | BH57: AEM
A58: NOV005.05 | B58: Yixing | C58: NOV005 | D58: CORE DG | E58: Internal | F58: Arrival Plan-SPNL | G58: DAP | H58: SunPower Energy Solutions France SAS | I58: n/a | J58: Distributors Italy - W72 | M58: n/a | N58: n/a | O58: Shingle | P58: GF0700001578 | Q58: TCL-MR465DT182-58NS | R58: EVO2A | S58: ±1200mm | T58: 465 | U58: 1728 | V58: 0.804 | W58: 48 | X58: 2 | Y58: COMPLETED | Z58: COMPLETED | AB58: 46039 | AC58: 3 | AD58: POPV260211018 | AF58: SHANGHAI | AG58: Shanghai | AH58: ROTTERDAM | AI58: 46045 | AJ58: 46047 | AK58: 46047 | AL58: 46096 | AM58: 46111 | AN58: 46116 | AO58: DAP | AP58: EVER LIFTING 062W | AQ58: COSCO | AR58: TPVB20260116006 | AS58: COSU6441367700 | AT58: COSU6441367700 | AU58: 69 | AW58: 46116 | AX58: In Stock-Approved | AY58: 46129 | AZ58: 7 | BA58: 46123 | BB58: 2026 | BC58: 4 | BD58: 15 | BE58: 36 | BF58: 864 | BG58: White glazing | BH58: AEU
A59: DEC003.16 | B59: Yixing | C59: DEC003 | D59: UPP | E59: Internal | F59: Arrival Plan-SPES | G59: DAP | H59: Sunpower Energy Systems Spain, S.L.U. | I59: n/a | J59: SPES / Total Portugal | K59: PT0125122900795 | M59: n/a | N59: n/a | O59: Half Cut | P59: GF0700001575 | Q59: HSM-ND78-GF640 | R59: EVO2A | S59: ±1400mm | T59: 640 | U59: 1152 | V59: 0.737 | W59: 32 | X59: 2 | Y59: COMPLETED | Z59: COMPLETED | AB59: 46039 | AC59: 3 | AD59: POPV260129007 | AF59: SHANGHAI | AG59: Shanghai | AH59: VALENCIA | AI59: 46043 | AJ59: 46046 | AK59: 46046 | AL59: 46081 | AM59: 46091 | AN59: 46092 | AO59: DAP | AP59: ANE MAERSK 604W | AQ59: OTHER | AR59: TPVB20260116003 | AS59: 263794612 | AT59: 263794612 | AU59: 46 | AW59: 46092 | AX59: In Stock-Approved | AY59: 46097 | AZ59: 9 | BA59: 46101 | BB59: 2026 | BC59: 3 | BD59: 12 | BE59: 36 | BF59: 576 | BG59: Redirection Film | BH59: AEM
A60: MAY010.03 | B60: Yixing | C60: MAY010 | D60: CORE DG | E60: Offshore | F60: SPTN Offstore in Transit WH | G60: CIF | H60: SUMINISTROS ORDUÑA | I60: n/a | J60: SUMINISTROS ORDUÑA // ES0125122900527 | M60: n/a | N60: n/a | O60: Shingle | P60: GF0700000024 | Q60: TCL-MR510DT182-64NS | R60: EVO2A | S60: ±1400mm | T60: 510 | U60: 2376 | V60: 1.212 | W60: 66 | X60: 3 | Y60: COMPLETED | Z60: COMPLETED | AB60: 46035 | AC60: 3 | AD60: POPV260123004 | AF60: SHANGHAI | AG60: Shanghai | AH60: VALENCIA | AI60: 46042 | AJ60: 46041 | AK60: 46041 | AL60: 46086 | AM60: 46079 | AN60: 46079 | AO60: CIF | AP60: CMA CGM JULES VERNE 0MEMVW1MA | AQ60: COSCO | AR60: TPVB20260116007 | AS60: COSU6441765780 | AT60: COSU6441765780 | AU60: 38 | AW60: 46079 | AX60: In Stock-Approved | AY60: 46086 | AZ60: - | BA60: 46079 | BB60: 2026 | BC60: 2 | BD60: 9 | BE60: 36 | BF60: 792 | BG60: White glazing | BH60: AEM
A61: DEC009.07 | B61: Yixing | C61: DEC009 | D61: CORE DG | E61: Internal | F61: Arrival Plan-SPTN | G61: DAP | H61: SunPower Energy Solutions France SAS | I61: n/a | J61: Local WH - SPTN W74 | M61: n/a | N61: n/a | O61: P7 COM S BF IT | P61: GF0700000769 | Q61: PVM, SPR-P7-555-COM-S, I BF-G M4.3D EVO2Z6NL 1.5KV IT | R61: EVO2A | S61: ±1400mm | T61: 555 | U61: 660 | V61: 0.366 | W61: 20 | X61: 1 | Y61: COMPLETED | Z61: COMPLETED | AB61: 46035 | AC61: 3 | AD61: POPV260205017 | AF61: SHANGHAI | AG61: Shanghai | AH61: FOS SUR MER | AI61: 46042 | AJ61: 46041 | AK61: 46041 | AL61: 46091 | AM61: 46090 | AN61: 46090 | AO61: DAP | AP61: CMA CGM JULES VERNE 0MEMVW1MA | AQ61: COSCO | AR61: TPVB20260116008 | AS61: COSU6441963530 | AT61: COSU6441963530 | AU61: 49 | AW61: 46090 | AX61: In Stock-Approved | AY61: 46104 | AZ61: 8 | BA61: 46098 | BB61: 2026 | BC61: 3 | BD61: 12 | BE61: 33 | BF61: 660 | BG61: White glazing | BH61: AEM
A62: DEC009.08 | B62: Yixing | C62: DEC009 | D62: CORE DG | E62: Internal | F62: Arrival Plan-SPTN | G62: DAP | H62: SunPower Energy Solutions France SAS | I62: n/a | J62: Local WH - SPTN W74 | M62: n/a | N62: n/a | O62: P7 COM S BF IT | P62: GF0700000769 | Q62: PVM, SPR-P7-555-COM-S, I BF-G M4.3D EVO2Z6NL 1.5KV IT | R62: EVO2A | S62: ±1400mm | T62: 555 | U62: 1320 | V62: 0.733 | W62: 40 | X62: 2 | Y62: COMPLETED | Z62: COMPLETED | AB62: 46035 | AC62: 3 | AD62: POPV260205015 | AF62: SHANGHAI | AG62: Shanghai | AH62: FOS SUR MER | AI62: 46042 | AJ62: 46041 | AK62: 46041 | AL62: 46091 | AM62: 46090 | AN62: 46090 | AO62: DAP | AP62: CMA CGM JULES VERNE 0MEMVW1MA | AQ62: COSCO | AR62: TPVB20260116008 | AS62: COSU6441963530 | AT62: COSU6441963530 | AU62: 49 | AW62: 46090 | AX62: In Stock-Approved | AY62: 46104 | AZ62: 8 | BA62: 46098 | BB62: 2026 | BC62: 3 | BD62: 12 | BE62: 33 | BF62: 660 | BG62: White glazing | BH62: AEM
A63: OCT010.01 | B63: Tianjin | C63: OCT010 | D63: CORE DG | E63: Internal | F63: Arrival Plan-SPNL | G63: DAP | H63: SunPower Energy Solutions France SAS | I63: n/a | J63: SPTN / Rexel Sweden | M63: n/a | N63: n/a | O63: Half Cut | P63: GF0700000842 | Q63: HSM-ND54-DR505 | R63: EVO2A | S63: ±1400mm | T63: 505 | U63: 1728 | V63: 0.873 | W63: 48 | X63: 2 | Y63: COMPLETED | Z63: COMPLETED | AB63: 46031 | AC63: 2 | AD63: POPV260129020 | AF63: TIANJIN | AG63: Tianjin | AH63: ROTTERDAM | AI63: 46036 | AJ63: 46038 | AK63: 46038 | AL63: 46077 | AM63: 46094 | AN63: 46094 | AO63: DAP | AP63: COSCO SHIPPING SOLAR 035W | AQ63: COSCO | AR63: TPVB20260109011 | AS63: COSU6441563290 | AT63: COSU6441563290 | AU63: 56 | AW63: 46094 | AX63: In Stock-Approved | AY63: 46104 | AZ63: 7 | BA63: 46101 | BB63: 2026 | BC63: 3 | BD63: 12 | BE63: 36 | BF63: 864 | BG63: Black glazing | BH63: AEU
A64: DEC018.04 | B64: Tianjin | C64: DEC018 | D64: UPP | E64: Internal | F64: Arrival Plan-SPNL | G64: DAP | H64: SunPower Energy Solutions France SAS | I64: n/a | J64: SPTN / Qair SP Uebigau-Wahrenbrück GmbH & Co. KG | K64: tbc | M64: n/a | N64: n/a | O64: Half Cut | P64: GF0700000346 | Q64: HSM-ND66-GR625 | R64: H4(Com) | S64: ±1400mm | T64: 625 | U64: 7200 | V64: 4.5 | W64: 200 | X64: 10 | Y64: COMPLETED | Z64: COMPLETED | AB64: 46034 | AC64: 3 | AD64: POPV260202005 | AF64: TIANJIN | AG64: Tianjin | AH64: ROTTERDAM | AI64: 46040 | AJ64: 46040 | AK64: 46040 | AL64: 46084 | AM64: 46103 | AN64: 46103 | AO64: DAP | AP64: COSCO SHIPPING UNIVERSE/0FAM9W1MA/034W | AQ64: OTHER | AR64: TPVB20260116001 | AS64: TJN0838416 | AT64: TJN0838416 | AU64: 63 | AW64: 46103 | AX64: In Stock-Approved | AY64: 46118 | AZ64: 7 | BA64: 46110 | BB64: 2026 | BC64: 3 | BD64: 13 | BE64: 36 | BF64: 720 | BG64: Redirection Film | BH64: AEU
A65: DEC021.01 | B65: Yixing | C65: DEC021 | D65: UPP | E65: Internal | F65: Arrival Plan-SPTN | G65: DAP | H65: SunPower Energy Solutions France SAS | I65: n/a | J65: SPTN / Unite Chauvigny | K65: 46011022 -> FR0125122900833 | M65: n/a | N65: n/a | O65: Half Cut | P65: GF0700000313 | Q65: HSM-ND66-GR625 CFP | R65: EVO2A | S65: ±1400mm | T65: 625 | U65: 2880 | V65: 1.8 | W65: 80 | X65: 4 | Y65: COMPLETED | Z65: COMPLETED | AB65: 46041 | AC65: 4 | AD65: POPV260202006 | AF65: SHANGHAI | AG65: Shanghai | AH65: LE HAVRE | AI65: 46047 | AJ65: 46045 | AK65: 46045 | AL65: 46084 | AM65: 46092 | AN65: 46092 | AO65: DAP | AP65: CMA CGM JACQUES SAADE/0FMLOW1MA | AQ65: OTHER | AR65: TPVB20260123005 | AS65: CHN3007423 | AT65: CHN3007423 | AU65: 47 | AW65: 46092 | AX65: In Stock-Approved | AY65: 46105 | AZ65: 8 | BA65: 46100 | BB65: 2026 | BC65: 3 | BD65: 12 | BE65: 36 | BF65: 720 | BG65: Redirection Film | BH65: AEU
A66: DEC021.03 | B66: Yixing | C66: DEC021 | D66: UPP | E66: Internal | F66: Arrival Plan-SPTN | G66: DAP | H66: SunPower Energy Solutions France SAS | I66: n/a | J66: SPTN / Unite Chauvigny | K66: 46011022 -> FR0125122900833 | M66: n/a | N66: n/a | O66: Half Cut | P66: GF0700000313 | Q66: HSM-ND66-GR625 CFP | R66: EVO2A | S66: ±1400mm | T66: 625 | U66: 1440 | V66: 0.9 | W66: 40 | X66: 2 | Y66: COMPLETED | Z66: COMPLETED | AB66: 46041 | AC66: 4 | AD66: POPV260202008 | AF66: SHANGHAI | AG66: Shanghai | AH66: LE HAVRE | AI66: 46047 | AJ66: 46045 | AK66: 46045 | AL66: 46084 | AM66: 46092 | AN66: 46092 | AO66: DAP | AP66: CMA CGM JACQUES SAADE/0FMLOW1MA | AQ66: OTHER | AR66: TPVB20260123005 | AS66: CHN3007423 | AT66: CHN3007423 | AU66: 47 | AW66: 46092 | AX66: In Stock-Approved | AY66: 46105 | AZ66: 8 | BA66: 46100 | BB66: 2026 | BC66: 3 | BD66: 12 | BE66: 36 | BF66: 720 | BG66: Redirection Film | BH66: AEU
A67: NOV017.10 | B67: Yixing | C67: NOV017 | D67: UPP | E67: Internal | F67: Arrival Plan-SPTN | G67: DAP | H67: SunPower Energy Solutions France SAS | I67: n/a | J67: SPTN / Unite Chauvigny | K67: FR0125122900833 | M67: n/a | N67: n/a | O67: Half Cut | P67: GF0700000313 | Q67: HSM-ND66-GR625 CFP | R67: EVO2A | S67: ±1400mm | T67: 625 | U67: 2592 | V67: 1.62 | W67: 72 | X67: 3.6 | Y67: COMPLETED | Z67: COMPLETED | AB67: 46041 | AC67: 4 | AD67: POPV260202007 | AF67: SHANGHAI | AG67: Shanghai | AH67: LE HAVRE | AI67: 46047 | AJ67: 46045 | AK67: 46045 | AL67: 46084 | AM67: 46092 | AN67: 46092 | AO67: DAP | AP67: CMA CGM JACQUES SAADE/0FMLOW1MA | AQ67: OTHER | AR67: TPVB20260123005 | AS67: CHN3007423 | AT67: CHN3007423 | AU67: 47 | AW67: 46092 | AX67: In Stock-Approved | AY67: 46105 | AZ67: 8 | BA67: 46100 | BB67: 2026 | BC67: 3 | BD67: 12 | BE67: 36 | BF67: 720 | BG67: Redirection Film | BH67: AEU
A68: DEC021.04 | B68: Yixing | C68: DEC021 | D68: UPP | E68: Internal | F68: Arrival Plan-SPTN | G68: DAP | H68: SunPower Energy Solutions France SAS | I68: n/a | J68: SPTN / Unite Chauvigny | K68: FR0125122900833 | M68: n/a | N68: n/a | O68: Half Cut | P68: GF0700000313 | Q68: HSM-ND66-GR625 CFP | R68: EVO2A | S68: ±1400mm | T68: 625 | U68: 72 | V68: 0.045 | W68: 2 | X68: 0.1 | Y68: COMPLETED | Z68: COMPLETED | AB68: 46041 | AC68: 4 | AD68: POPV260202009 | AF68: SHANGHAI | AG68: Shanghai | AH68: LE HAVRE | AI68: 45682 | AJ68: 46045 | AK68: 46045 | AL68: 46084 | AM68: 46092 | AN68: 46092 | AO68: DAP | AP68: CMA CGM JACQUES SAADE | AQ68: OTHER | AR68: TPVB20260123005 | AS68: CHN3007423 | AT68: CHN3007423 | AU68: 47 | AW68: 46092 | AX68: In Stock-Approved | AY68: 46105 | AZ68: 8 | BA68: 46100 | BB68: 2026 | BC68: 3 | BD68: 12 | BE68: 36 | BF68: 720 | BG68: Redirection Film | BH68: AEU
A69: NOV016.04 | B69: Yixing | C69: NOV016 | D69: UPP | E69: Internal | F69: Arrival Plan-SPTN | G69: DAP | H69: SunPower Energy Solutions France SAS | I69: n/a | J69: SPTN / Soregies Dange II | K69: tbc | M69: n/a | N69: n/a | O69: Half Cut | P69: GF0700000885 | Q69: HSM-ND66-GR620 CFP | R69: EVO2A | S69: ±1400mm | T69: 620 | U69: 216 | V69: 0.134 | W69: 6 | X69: 0.3 | Y69: COMPLETED | Z69: COMPLETED | AB69: 46041 | AC69: 4 | AD69: POPV260202010 | AF69: SHANGHAI | AG69: Shanghai | AH69: LE HAVRE | AI69: 45682 | AJ69: 46045 | AK69: 46045 | AL69: 46084 | AM69: 46092 | AN69: 46092 | AO69: DAP | AP69: CMA CGM JACQUES SAADE | AQ69: OTHER | AR69: TPVB20260123005 | AS69: CHN3007423 | AT69: CHN3007423 | AU69: 47 | AW69: 46092 | AX69: In Stock-Approved | AY69: 46105 | AZ69: 8 | BA69: 46100 | BB69: 2026 | BC69: 3 | BD69: 12 | BE69: 36 | BF69: 720 | BG69: Redirection Film | BH69: AEU
A70: DEC021 | B70: Yixing | C70: Main Line | D70: UPP | E70: Internal | F70: Arrival Plan-SPTN | G70: DAP | H70: SunPower Energy Solutions France SAS | I70: n/a | J70: SPTN / Unite Chauvigny | K70: FR0125122900833 | M70: n/a | N70: n/a | O70: Half Cut | P70: GF0700000313 | Q70: HSM-ND66-GR625 CFP | R70: EVO2A | S70: ±1400mm | T70: 625 | U70: 720 | V70: 0.45 | W70: 20 | X70: 1 | Y70: COMPLETED | Z70: COMPLETED | AB70: 46041 | AC70: 4 | AD70: POPV260202004 | AF70: SHANGHAI | AG70: Shanghai | AH70: LE HAVRE | AI70: 45682 | AJ70: 46045 | AK70: 46045 | AL70: 46084 | AM70: 46086 | AN70: 46086 | AO70: DAP | AP70: CMA CGM JACQUES SAADE | AQ70: COSCO | AR70: TPVB20260123022 | AS70: COSU6442049520 | AT70: COSU6442049520 | AU70: 41 | AW70: 46086 | AX70: In Stock-Approved | AY70: 46099 | AZ70: 8 | BA70: 46094 | BB70: 2026 | BC70: 3 | BD70: 11 | BE70: 36 | BF70: 720 | BG70: Redirection Film | BH70: AEU
A71: DEC010.01 | B71: Yixing | C71: DEC010 | D71: CORE DG | E71: Internal | F71: Arrival Plan-SPUK | G71: DAP | H71: Sunpower Corporation UK Limited | I71: n/a | J71: SPGB / Solarsense UK ltd | K71: 20519249 | M71: n/a | N71: n/a | O71: Shingle | P71: GF0700000025 | Q71: TCL-MR460DT182-58NS | R71: EVO2A | S71: ±1200mm | T71: 460 | U71: 1728 | V71: 0.795 | W71: 48 | X71: 2 | Y71: COMPLETED | Z71: COMPLETED | AB71: 46042 | AC71: 4 | AD71: POPV260205018 | AF71: SHANGHAI | AG71: Shanghai | AH71: FELIXSTOWE | AI71: 46050 | AJ71: 46053 | AK71: 46053 | AL71: 46089 | AM71: 46108 | AN71: 46108 | AO71: DAP | AP71: EVER AIM 1385-016W | AQ71: COSCO | AR71: TPVB20260123008 | AS71: COSU6441764750 | AT71: COSU6441764750 | AU71: 55 | AW71: 46108 | AX71: In Stock-Approved | AY71: 46120 | AZ71: 7 | BA71: 46115 | BB71: 2026 | BC71: 4 | BD71: 14 | BE71: 36 | BF71: 864 | BG71: White glazing | BH71: AEU
A72: DEC008.02 | B72: Yixing | C72: DEC008 | D72: CORE DG | E72: Internal | F72: Arrival Plan-SPTN | G72: DAP | H72: SunPower Energy Solutions France SAS | I72: n/a | J72: Local WH - SPTN W74 | M72: n/a | N72: n/a | O72: P7 COM S BF IT | P72: GF0700000766 | Q72: PVM, SPR-P7-550-COM-S, I BF-G M4.3D EVO2Z6NL 1.5KV IT | R72: EVO2A | S72: ±1500mm | T72: 550 | U72: 660 | V72: 0.363 | W72: 20 | X72: 1 | Y72: COMPLETED | Z72: COMPLETED | AB72: 46044 | AC72: 4 | AD72: POPV260205033 | AF72: SHANGHAI | AG72: Shanghai | AH72: FOS SUR MER | AI72: 46049 | AJ72: 46055 | AK72: 46056 | AL72: 46098 | AM72: 46101 | AN72: 46103 | AO72: DAP | AP72: CMA CGM APOLLON 0MEMXW1MA | AQ72: COSCO | AR72: TPVB20260123009 | AS72: COSU6442048090 | AT72: COSU6442048090 | AU72: 47 | AW72: 46103 | AX72: In Stock-Approved | AY72: 46115 | AZ72: 8 | BA72: 46111 | BB72: 2026 | BC72: 3 | BD72: 14 | BE72: 33 | BF72: 660 | BG72: White glazing | BH72: AEM
A73: DEC008.03 | B73: Yixing | C73: DEC008 | D73: CORE DG | E73: Internal | F73: Arrival Plan-SPTN | G73: DAP | H73: SunPower Energy Solutions France SAS | I73: n/a | J73: Local WH - SPTN W74 | M73: n/a | N73: n/a | O73: P7 COM S BF IT | P73: GF0700000766 | Q73: PVM, SPR-P7-550-COM-S, I BF-G M4.3D EVO2Z6NL 1.5KV IT | R73: EVO2A | S73: ±1500mm | T73: 550 | U73: 1320 | V73: 0.726 | W73: 40 | X73: 2 | Y73: COMPLETED | Z73: COMPLETED | AB73: 46044 | AC73: 4 | AD73: POPV260205032 | AF73: SHANGHAI | AG73: Shanghai | AH73: FOS SUR MER | AI73: 46049 | AJ73: 46055 | AK73: 46056 | AL73: 46098 | AM73: 46101 | AN73: 46103 | AO73: DAP | AP73: CMA CGM APOLLON 0MEMXW1MA | AQ73: COSCO | AR73: TPVB20260123009 | AS73: COSU6442048090 | AT73: COSU6442048090 | AU73: 47 | AW73: 46103 | AX73: In Stock-Approved | AY73: 46115 | AZ73: 8 | BA73: 46111 | BB73: 2026 | BC73: 3 | BD73: 14 | BE73: 33 | BF73: 660 | BG73: White glazing | BH73: AEM
A74: DEC007.01 | B74: Yixing | C74: DEC007 | D74: CORE DG | E74: Internal | F74: Arrival Plan-SPTN | G74: DAP | H74: SunPower Energy Solutions France SAS | I74: n/a | J74: Local WH - SPTN W74 | M74: n/a | N74: n/a | O74: P7 RES BLK 2.0 | P74: GF0700000797 | Q74: PVM, SPR-P7-460-BLK-1500, I BF-G AR-SA M4.4F EVO2Z1NL IT P39 | R74: EVO2A | S74: ±1200mm | T74: 460 | U74: 2592 | V74: 1.192 | W74: 72 | X74: 3 | Y74: COMPLETED | Z74: COMPLETED | AB74: 46044 | AC74: 4 | AD74: POPV260205030 | AF74: SHANGHAI | AG74: Shanghai | AH74: FOS SUR MER | AI74: 46049 | AJ74: 46055 | AK74: 46056 | AL74: 46098 | AM74: 46101 | AN74: 46103 | AO74: DAP | AP74: CMA CGM APOLLON 0MEMXW1MA | AQ74: COSCO | AR74: TPVB20260123009 | AS74: COSU6442048090 | AT74: COSU6442048090 | AU74: 47 | AW74: 46103 | AX74: In Stock-Approved | AY74: 46115 | AZ74: 8 | BA74: 46111 | BB74: 2026 | BC74: 3 | BD74: 14 | BE74: 36 | BF74: 864 | BG74: Black glazing | BH74: AEM
A75: DEC008.07 | B75: Yixing | C75: DEC008 | D75: CORE DG | E75: Internal | F75: Arrival Plan-SPTN | G75: DAP | H75: SunPower Energy Solutions France SAS | I75: n/a | J75: Local WH - SPTN W74 | M75: n/a | N75: n/a | O75: P7 COM S BF IT | P75: GF0700000766 | Q75: PVM, SPR-P7-550-COM-S, I BF-G M4.3D EVO2Z6NL 1.5KV IT | R75: EVO2A | S75: ±1500mm | T75: 550 | U75: 660 | V75: 0.363 | W75: 20 | X75: 1 | Y75: COMPLETED | Z75: COMPLETED | AB75: 46040 | AC75: 3 | AD75: POPV260205034 | AF75: SHANGHAI | AG75: Shanghai | AH75: FOS SUR MER | AI75: 46045 | AJ75: 46047 | AK75: 46047 | AL75: 46097 | AM75: 46111 | AN75: 46111 | AO75: DAP | AP75: EVER GIFTED 0736-028W | AQ75: COSCO | AR75: TPVB20260123010 | AS75: COSU6442107220 | AT75: COSU6442107220 | AU75: 64 | AW75: 46111 | AX75: In Stock-Approved | AY75: 46120 | AZ75: 8 | BA75: 46119 | BB75: 2026 | BC75: 4 | BD75: 15 | BE75: 33 | BF75: 660 | BG75: White glazing | BH75: AEM
A76: DEC011.09 | B76: Yixing | C76: DEC011 | D76: CORE DG | E76: Internal | F76: Arrival Plan-SPNL | G76: DAP | H76: SunPower Energy Solutions France SAS | I76: n/a | J76: Local WH - W72 | M76: n/a | N76: n/a | O76: Shingle | P76: GF0700001578 | Q76: TCL-MR465DT182-58NS | R76: EVO2A | S76: ±1200mm | T76: 465 | U76: 864 | V76: 0.402 | W76: 24 | X76: 1 | Y76: COMPLETED | Z76: COMPLETED | AB76: 46042 | AC76: 4 | AD76: POPV260211017 | AF76: SHANGHAI | AG76: Shanghai | AH76: ROTTERDAM | AI76: 46050 | AJ76: 46053 | AK76: 46054 | AL76: 46101 | AM76: 46116 | AN76: 46118 | AO76: DAP | AP76: COSCO SHIPPING SAKURA 034W | AQ76: COSCO | AR76: TPVB20260123011 | AS76: COSU6441766300 | AT76: COSU6441766300 | AU76: 64 | AW76: 46118 | AX76: In Stock-Approved | AY76: 46132 | AZ76: 7 | BA76: 46125 | BB76: 2026 | BC76: 4 | BD76: 16 | BE76: 36 | BF76: 864 | BG76: White glazing | BH76: AEU
A77: NOV005.06 | B77: Yixing | C77: NOV005 | D77: CORE DG | E77: Internal | F77: Arrival Plan-SPNL | G77: DAP | H77: SunPower Energy Solutions France SAS | I77: n/a | J77: Local WH - W72 | M77: n/a | N77: n/a | O77: Shingle | P77: GF0700001578 | Q77: TCL-MR465DT182-58NS | R77: EVO2A | S77: ±1200mm | T77: 465 | U77: 1728 | V77: 0.804 | W77: 48 | X77: 2 | Y77: COMPLETED | Z77: COMPLETED | AB77: 46042 | AC77: 4 | AD77: POPV260211014 | AF77: SHANGHAI | AG77: Shanghai | AH77: ROTTERDAM | AI77: 46050 | AJ77: 46053 | AK77: 46054 | AL77: 46101 | AM77: 46116 | AN77: 46118 | AO77: DAP | AP77: COSCO SHIPPING SAKURA 034W | AQ77: COSCO | AR77: TPVB20260123011 | AS77: COSU6441766300 | AT77: COSU6441766300 | AU77: 64 | AW77: 46118 | AX77: In Stock-Approved | AY77: 46132 | AZ77: 7 | BA77: 46125 | BB77: 2026 | BC77: 4 | BD77: 16 | BE77: 36 | BF77: 864 | BG77: White glazing | BH77: AEU
A78: DEC011.05 | B78: Yixing | C78: DEC011 | D78: CORE DG | E78: Internal | F78: Arrival Plan-SPNL | G78: DAP | H78: SunPower Energy Solutions France SAS | I78: n/a | J78: Distributors Italy - W72 | M78: n/a | N78: n/a | O78: Shingle | P78: GF0700001578 | Q78: TCL-MR465DT182-58NS | R78: EVO2A | S78: ±1200mm | T78: 465 | U78: 1728 | V78: 0.804 | W78: 48 | X78: 2 | Y78: COMPLETED | Z78: COMPLETED | AB78: 46040 | AC78: 3 | AD78: POPV260211016 | AF78: SHANGHAI | AG78: Shanghai | AH78: ROTTERDAM | AI78: 46045 | AJ78: 46047 | AK78: 46047 | AL78: 46089 | AM78: 46111 | AN78: 46111 | AO78: DAP | AP78: EVER GIFTED 0736-028W | AQ78: COSCO | AR78: TPVB20260123012 | AS78: COSU6442108070 | AT78: COSU6442108070 | AU78: 64 | AW78: 46111 | AX78: In Stock-Approved | AY78: 46125 | AZ78: 7 | BA78: 46118 | BB78: 2026 | BC78: 4 | BD78: 15 | BE78: 36 | BF78: 864 | BG78: White glazing | BH78: AEU
A79: DEC011.06 | B79: Yixing | C79: DEC011 | D79: CORE DG | E79: Internal | F79: Arrival Plan-SPNL | G79: DAP | H79: SunPower Energy Solutions France SAS | I79: n/a | J79: Distributors Italy - W72 | M79: n/a | N79: n/a | O79: Shingle | P79: GF0700001578 | Q79: TCL-MR465DT182-58NS | R79: EVO2A | S79: ±1200mm | T79: 465 | U79: 864 | V79: 0.402 | W79: 24 | X79: 1 | Y79: COMPLETED | Z79: COMPLETED | AB79: 46040 | AC79: 3 | AD79: POPV260211015 | AF79: SHANGHAI | AG79: Shanghai | AH79: ROTTERDAM | AI79: 46045 | AJ79: 46047 | AK79: 46047 | AL79: 46089 | AM79: 46111 | AN79: 46111 | AO79: DAP | AP79: EVER GIFTED 0736-028W | AQ79: COSCO | AR79: TPVB20260123012 | AS79: COSU6442108070 | AT79: COSU6442108070 | AU79: 64 | AW79: 46111 | AX79: In Stock-Approved | AY79: 46125 | AZ79: 7 | BA79: 46118 | BB79: 2026 | BC79: 4 | BD79: 15 | BE79: 36 | BF79: 864 | BG79: White glazing | BH79: AEU
A80: DEC008.01 | B80: Yixing | C80: DEC008 | D80: CORE DG | E80: Internal | F80: Arrival Plan-SPNL | G80: DAP | H80: SunPower Energy Solutions France SAS | I80: n/a | J80: Local WH - W72 (Italy) | M80: n/a | N80: n/a | O80: P7 COM S BF IT | P80: GF0700000766 | Q80: PVM, SPR-P7-550-COM-S, I BF-G M4.3D EVO2Z6NL 1.5KV IT | R80: EVO2A | S80: ±1500mm | T80: 550 | U80: 660 | V80: 0.363 | W80: 20 | X80: 1 | Y80: COMPLETED | Z80: COMPLETED | AB80: 46040 | AC80: 3 | AD80: POPV260211013 | AF80: SHANGHAI | AG80: Shanghai | AH80: ROTTERDAM | AI80: 46045 | AJ80: 46047 | AK80: 46047 | AL80: 46089 | AM80: 46111 | AN80: 46111 | AO80: DAP | AP80: EVER GIFTED 0736-028W | AQ80: COSCO | AR80: TPVB20260123012 | AS80: COSU6442108070 | AT80: COSU6442108070 | AU80: 64 | AW80: 46111 | AX80: In Stock-Approved | AY80: 46125 | AZ80: 7 | BA80: 46118 | BB80: 2026 | BC80: 4 | BD80: 15 | BE80: 33 | BF80: 660 | BG80: White glazing | BH80: AEU
A81: DEC008.05 | B81: Yixing | C81: DEC008 | D81: CORE DG | E81: Internal | F81: Arrival Plan-SPNL | G81: DAP | H81: SunPower Energy Solutions France SAS | I81: n/a | J81: Local WH - W72 (Italy) | M81: n/a | N81: n/a | O81: P7 COM S BF IT | P81: GF0700000766 | Q81: PVM, SPR-P7-550-COM-S, I BF-G M4.3D EVO2Z6NL 1.5KV IT | R81: EVO2A | S81: ±1500mm | T81: 550 | U81: 660 | V81: 0.363 | W81: 20 | X81: 1 | Y81: COMPLETED | Z81: COMPLETED | AB81: 46040 | AC81: 3 | AD81: POPV260211012 | AF81: SHANGHAI | AG81: Shanghai | AH81: ROTTERDAM | AI81: 46045 | AJ81: 46047 | AK81: 46047 | AL81: 46089 | AM81: 46111 | AN81: 46111 | AO81: DAP | AP81: EVER GIFTED 0736-028W | AQ81: COSCO | AR81: TPVB20260123012 | AS81: COSU6442108070 | AT81: COSU6442108070 | AU81: 64 | AW81: 46111 | AX81: In Stock-Approved | AY81: 46125 | AZ81: 7 | BA81: 46118 | BB81: 2026 | BC81: 4 | BD81: 15 | BE81: 33 | BF81: 660 | BG81: White glazing | BH81: AEU
A82: DEC011.03 | B82: Yixing | C82: DEC011 | D82: CORE DG | E82: Internal | F82: Arrival Plan-SPTN | G82: DAP | H82: SunPower Energy Solutions France SAS | I82: n/a | J82: Distributors Italy - SPTN W74 | M82: n/a | N82: n/a | O82: Shingle | P82: GF0700001578 | Q82: TCL-MR465DT182-58NS | R82: EVO2A | S82: ±1200mm | T82: 465 | U82: 1728 | V82: 0.804 | W82: 48 | X82: 2 | Y82: COMPLETED | Z82: COMPLETED | AB82: 46038 | AC82: 3 | AD82: POPV260225020 | AF82: SHANGHAI | AG82: Shanghai | AH82: FOS SUR MER | AI82: 46045 | AJ82: 46047 | AK82: 46047 | AL82: 46092 | AM82: 46111 | AN82: 46111 | AO82: DAP | AP82: EVER GIFTED 0736-028W | AQ82: COSCO | AR82: TPVB20260123013 | AS82: COSU6442054300 | AT82: COSU6442054300 | AU82: 64 | AW82: 46111 | AX82: In Stock-Approved | AY82: 46120 | AZ82: 8 | BA82: 46119 | BB82: 2026 | BC82: 4 | BD82: 15 | BE82: 36 | BF82: 864 | BG82: White glazing | BH82: AEM
A83: DEC012.06 | B83: Yixing | C83: DEC012 | D83: CORE DG | E83: Internal | F83: Arrival Plan-SPTN | G83: DAP | H83: SunPower Energy Solutions France SAS | I83: n/a | J83: Distributors Italy - SPTN W74 | M83: n/a | N83: n/a | O83: Shingle | P83: GF0700000811 | Q83: TCL-MG720DT210-68NS | R83: EVO2A | S83: ±1400mm | T83: 720 | U83: 594 | V83: 0.428 | W83: 18 | X83: 1 | Y83: COMPLETED | Z83: COMPLETED | AB83: 46038 | AC83: 3 | AD83: POPV260225016 | AF83: SHANGHAI | AG83: Shanghai | AH83: FOS SUR MER | AI83: 46045 | AJ83: 46047 | AK83: 46047 | AL83: 46092 | AM83: 46111 | AN83: 46111 | AO83: DAP | AP83: EVER GIFTED 0736-028W | AQ83: COSCO | AR83: TPVB20260123013 | AS83: COSU6442054300 | AT83: COSU6442054300 | AU83: 64 | AW83: 46111 | AX83: In Stock-Approved | AY83: 46120 | AZ83: 8 | BA83: 46119 | BB83: 2026 | BC83: 4 | BD83: 15 | BE83: 33 | BF83: 594 | BG83: White glazing | BH83: AEM
... A86: DEC012.03 | B86: Yixing | C86: DEC012 | D86: CORE DG | E86: Internal | F86: Arrival Plan-SPTN | G86: DAP | H86: SunPower Energy Solutions France SAS | I86: n/a | J86: Distributors Italy - SPTN W74 | M86: n/a | N86: n/a | O86: Shingle | P86: GF0700000811 | Q86: TCL-MG720DT210-68NS | R86: EVO2A | S86: ±1400mm | T86: 720 | U86: 2376 | V86: 1.711 | W86: 72 | X86: 4 | Y86: COMPLETED | Z86: COMPLETED | AB86: 46039 | AC86: 3 | AD86: POPV260226006 | AF86: SHANGHAI | AG86: Shanghai | AH86: FOS SUR MER | AI86: 46045 | AJ86: 46047 | AK86: 46047 | AL86: 46092 | AM86: 46111 | AN86: 46111 | AO86: DAP | AP86: EVER GIFTED 0736-028W | AQ86: COSCO | AR86: TPVB20260123014 | AS86: COSU6442107610 | AT86: COSU6442107610 | AU86: 64 | AW86: 46111 | AX86: In Stock-Approved | AY86: 46120 | AZ86: 8 | BA86: 46119 | BB86: 2026 | BC86: 4 | BD86: 15 | BE86: 33 | BF86: 594 | BG86: White glazing | BH86: AEM
A87: DEC003.19 | B87: Yixing | C87: DEC003 | D87: UPP | E87: Internal | F87: Arrival Plan-SPES | G87: DAP | H87: Sunpower Energy Systems Spain, S.L.U. | I87: n/a | J87: SPES / Total Portugal | K87: PT0125122900795 | M87: n/a | N87: n/a | O87: Half Cut | P87: GF0700001575 | Q87: HSM-ND78-GF640 | R87: EVO2A | S87: ±1400mm | T87: 640 | V87: - | W87: - | X87: 0 | Y87: COMPLETED | Z87: COMPLETED | AB87: 46040 | AC87: 3 | AD87: POPV260206005 | AF87: SHANGHAI | AG87: Shanghai | AH87: VALENCIA | AI87: 46045 | AJ87: 46047 | AK87: 46047 | AL87: 46100 | AM87: 46114 | AN87: 46117 | AO87: DAP | AP87: EVER GIFTED 0736-028W | AQ87: COSCO | AR87: TPVB20260123015 | AS87: COSU6442105900 | AT87: COSU6442105900 | AU87: 70 | AW87: 46117 | AX87: In Stock-Approved | AY87: 46120 | AZ87: 9 | BA87: 46126 | BB87: 2026 | BC87: 4 | BD87: 16 | BE87: 36 | BF87: 576 | BG87: Redirection Film | BH87: AEM
A88: DEC003.14 | B88: Yixing | C88: DEC003 | D88: UPP | E88: Internal | F88: Arrival Plan-SPES | G88: DAP | H88: Sunpower Energy Systems Spain, S.L.U. | I88: n/a | J88: SPES / Total Portugal | K88: PT0125122900795 | M88: n/a | N88: n/a | O88: Half Cut | P88: GF0700001575 | Q88: HSM-ND78-GF640 | R88: EVO2A | S88: ±1400mm | T88: 640 | U88: 1152 | V88: 0.737 | W88: 32 | X88: 2 | Y88: COMPLETED | Z88: COMPLETED | AB88: 46042 | AC88: 4 | AD88: POPV260206006 | AF88: SHANGHAI | AG88: Shanghai | AH88: VALENCIA | AI88: 46051 | AJ88: 46053 | AK88: 46054 | AL88: 46093 | AM88: 46095 | AN88: 46095 | AO88: DAP | AP88: COSCO SHIPPING SAKURA 034W | AQ88: COSCO | AR88: TPVB20260123031 | AS88: COSU6441765320 | AT88: COSU6441765320 | AU88: 41 | AW88: 46095 | AX88: In Stock-Approved | AY88: 46107 | AZ88: 9 | BA88: 46104 | BB88: 2026 | BC88: 3 | BD88: 13 | BE88: 36 | BF88: 576 | BG88: Redirection Film | BH88: AEM
A89: DEC006.01 | B89: Yixing | C89: DEC006 | D89: CORE DG | E89: Offshore | F89: SPTN Offstore in Transit WH | G89: CIF | H89: Nordic Sun Danmark A/S | I89: n/a | J89: NordicSun | K89: 46010947 -> DK0125122900520 | M89: n/a | N89: n/a | O89: P7 RES BLK 2.0 | P89: GF0700000798 | Q89: PVM, SPR-P7-455-BLK-1500, I BF-G AR-SA M4.4F EVO2Z1NL IT P39 | R89: EVO2A | S89: ±1200mm | T89: 455 | U89: 4320 | V89: 1.966 | W89: 120 | X89: 5 | Y89: COMPLETED | Z89: COMPLETED | AB89: 46049 | AC89: 5 | AD89: POPV260130034 | AF89: SHANGHAI | AG89: Shanghai | AH89: AARHUS | AI89: 46055 | AJ89: 46059 | AK89: 46059 | AL89: 46106 | AM89: 46121 | AN89: 46122 | AO89: CIF | AP89: MSC CRISTINA/FW604W | AQ89: OTHER | AR89: TPVB20260123001 | AS89: MEDUWK500504 | AT89: 177FCLCLS0689421 | AU89: 63 | AW89: 46122 | AX89: In Stock-Approved | AY89: 46120 | AZ89: - | BA89: 46122 | BB89: 2026 | BC89: 4 | BD89: 15 | BE89: 36 | BF89: 864 | BG89: Black glazing | BH89: AEU
A90: OCT002 | B90: Yixing | C90: Main Line | D90: CORE DG | E90: Offshore | F90: SPTN Offstore in Transit WH | G90: CIF | H90: Failte Solar | I90: n/a | J90: Failte Solar | K90: 46010980 -> IE0125122900800 | M90: n/a | N90: n/a | O90: P7 RES BLK 2.0 | P90: GF0700000798 | Q90: PVM, SPR-P7-455-BLK-1500, I BF-G AR-SA M4.4F EVO2Z1NL IT P39 | R90: EVO2A | S90: ±1200mm | T90: 455 | U90: 1728 | V90: 0.786 | W90: 48 | X90: 2 | Y90: COMPLETED | Z90: COMPLETED | AB90: 46040 | AC90: 3 | AD90: POPV260123005 | AF90: SHANGHAI | AG90: Shanghai | AH90: CORK | AI90: 46047 | AJ90: 46054 | AK90: 46054 | AL90: 46093 | AM90: 46107 | AN90: 46107 | AO90: CIF | AP90: CMA CGM JACQUES SAADE / 0FMLOW1MA/0FMLOW | AQ90: OTHER | AR90: TPVB20260123002 | AS90: CHN2988980 | AT90: CHN2988980 | AU90: 53 | AW90: 46107 | AX90: In Stock-Approved | AY90: 46104 | AZ90: - | BA90: 46107 | BB90: 2026 | BC90: 3 | BD90: 13 | BE90: 36 | BF90: 864 | BG90: Black glazing | BH90: AEU
A91: NOV002 | B91: Yixing | C91: Main Line | D91: CORE DG | E91: Offshore | F91: SPTN Offstore in Transit WH | G91: CIF | H91: Failte Solar | I91: n/a | J91: Failte Solar | K91: 46010980 -> IE0125122900800 | M91: n/a | N91: n/a | O91: P7 RES BLK 2.0 | P91: GF0700000798 | Q91: PVM, SPR-P7-455-BLK-1500, I BF-G AR-SA M4.4F EVO2Z1NL IT P39 | R91: EVO2A | S91: ±1200mm | T91: 455 | U91: 2592 | V91: 1.179 | W91: 72 | X91: 3 | Y91: COMPLETED | Z91: COMPLETED | AB91: 46040 | AC91: 3 | AD91: POPV260123007 | AF91: SHANGHAI | AG91: Shanghai | AH91: CORK | AI91: 46047 | AJ91: 46054 | AK91: 46054 | AL91: 46093 | AM91: 46107 | AN91: 46107 | AO91: CIF | AP91: CMA CGM JACQUES SAADE / 0FMLOW1MA/0FMLOW | AQ91: OTHER | AR91: TPVB20260123002 | AS91: CHN2988980 | AT91: CHN2988980 | AU91: 53 | AW91: 46107 | AX91: In Stock-Approved | AY91: 46104 | AZ91: - | BA91: 46107 | BB91: 2026 | BC91: 3 | BD91: 13 | BE91: 36 | BF91: 864 | BG91: Black glazing | BH91: AEU
A92: AUG004.11 | B92: Yixing | C92: AUG004 | D92: CORE DG | E92: Offshore | F92: SPTN Offstore in Transit WH | G92: CIF | H92: Failte Solar | I92: n/a | J92: Failte Solar | K92: 46010979 -> IE0125122900792 | M92: n/a | N92: n/a | O92: P7 RES BLK P | P92: GF0700000795 | Q92: PVM, SPR-P7-510-BLK-P, I BF-G AR-SA M4.4F EVO2Z7NL | R92: EVO2A | S92: ±1350mm | T92: 510 | U92: 2376 | V92: 1.212 | W92: 66 | X92: 3 | Y92: COMPLETED | Z92: COMPLETED | AB92: 46040 | AC92: 3 | AD92: POPV260123003 | AF92: SHANGHAI | AG92: Shanghai | AH92: CORK | AI92: 46047 | AJ92: 46054 | AK92: 46054 | AL92: 46093 | AM92: 46107 | AN92: 46107 | AO92: CIF | AP92: CMA CGM JACQUES SAADE / 0FMLOW1MA/0FMLOW | AQ92: OTHER | AR92: TPVB20260123002 | AS92: CHN2988980 | AT92: CHN2988980 | AU92: 53 | AW92: 46107 | AX92: In Stock-Approved | AY92: 46104 | AZ92: - | BA92: 46107 | BB92: 2026 | BC92: 3 | BD92: 13 | BE92: 36 | BF92: 792 | BG92: Black glazing | BH92: AEU
A93: DEC006.02 | B93: Yixing | C93: DEC006 | D93: CORE DG | E93: Offshore | F93: SPTN Offstore in Transit WH | G93: CIF | H93: Failte Solar | I93: n/a | J93: Failte Solar | K93: 46010979 -> IE0125122900792 | M93: n/a | N93: n/a | O93: P7 RES BLK 2.0 | P93: GF0700000798 | Q93: PVM, SPR-P7-455-BLK-1500, I BF-G AR-SA M4.4F EVO2Z1NL IT P39 | R93: EVO2A | S93: ±1200mm | T93: 455 | U93: 5184 | V93: 2.359 | W93: 144 | X93: 6 | Y93: COMPLETED | Z93: COMPLETED | AB93: 46040 | AC93: 3 | AD93: POPV260123006 | AF93: SHANGHAI | AG93: Shanghai | AH93: CORK | AI93: 46047 | AJ93: 46054 | AK93: 46054 | AL93: 46093 | AM93: 46107 | AN93: 46107 | AO93: CIF | AP93: CMA CGM JACQUES SAADE / 0FMLOW1MA/0FMLOW | AQ93: OTHER | AR93: TPVB20260123002 | AS93: CHN2988980 | AT93: CHN2988980 | AU93: 53 | AW93: 46107 | AX93: In Stock-Approved | AY93: 46104 | AZ93: - | BA93: 46107 | BB93: 2026 | BC93: 3 | BD93: 13 | BE93: 36 | BF93: 864 | BG93: Black glazing | BH93: AEU
A94: SEPT013.01 | B94: Tianjin | C94: SEPT013 | D94: CORE DG | E94: Offshore | F94: SPTN Offstore in Transit WH | G94: CIF | H94: Failte Solar | I94: n/a | J94: Failte Solar | K94: 46010978 -> IE0126011200030 | M94: n/a | N94: n/a | O94: Half Cut | P94: GF0700001591 | Q94: HSM-ND48-DR450 | R94: EVO2A | S94: ±1400mm | T94: 450 | U94: 1872 | V94: 0.842 | W94: 52 | X94: 2 | Y94: COMPLETED | Z94: COMPLETED | AB94: 46044 | AC94: 4 | AD94: POPV260123016 | AF94: TIANJIN | AG94: Tianjin | AH94: CORK | AI94: 46050 | AJ94: 46051 | AK94: 46051 | AL94: 46119 | AM94: 46128 | AN94: 46128 | AO94: CIF | AP94: CMA CGM MONTE CRISTO / 0BEMXW1MA | AQ94: OTHER | AR94: TPVB20260123003 | AS94: TJN0856710 | AT94: TJN0856710 | AU94: 77 | AW94: 46128 | AX94: In Stock-Approved | AY94: 46118 | AZ94: - | BA94: 46128 | BB94: 2026 | BC94: 4 | BD94: 16 | BE94: 36 | BF94: 936 | BG94: Transparent | BH94: AEU
A95: SEPT013.02 | B95: Tianjin | C95: SEPT013 | D95: CORE DG | E95: Offshore | F95: SPTN Offstore in Transit WH | G95: CIF | H95: Failte Solar | I95: n/a | J95: Failte Solar | K95: 46010978 -> IE0126011200030 | M95: n/a | N95: n/a | O95: Half Cut | P95: GF0700001591 | Q95: HSM-ND48-DR450 | R95: EVO2A | S95: ±1400mm | T95: 450 | U95: 1872 | V95: 0.842 | W95: 52 | X95: 2 | Y95: COMPLETED | Z95: COMPLETED | AB95: 46044 | AC95: 4 | AD95: POPV260123017 | AF95: TIANJIN | AG95: Tianjin | AH95: CORK | AI95: 46050 | AJ95: 46051 | AK95: 46051 | AL95: 46119 | AM95: 46128 | AN95: 46128 | AO95: CIF | AP95: CMA CGM MONTE CRISTO / 0BEMXW1MA | AQ95: OTHER | AR95: TPVB20260123003 | AS95: TJN0856710 | AT95: TJN0856710 | AU95: 77 | AW95: 46128 | AX95: In Stock-Approved | AY95: 46118 | AZ95: - | BA95: 46128 | BB95: 2026 | BC95: 4 | BD95: 16 | BE95: 36 | BF95: 936 | BG95: Transparent | BH95: AEU
A96: MAY016.06 | B96: Tianjin | C96: MAY016 | D96: CORE DG | E96: Offshore | F96: SPTN Offstore in Transit WH | G96: CIF | H96: Failte Solar | I96: n/a | J96: Failte Solar | K96: 46010978 -> IE0126011200030 | M96: n/a | N96: n/a | O96: Half Cut | P96: GF0700001592 | Q96: HSM-ND48-DR445 | R96: EVO2A | S96: ±1400mm | T96: 445 | U96: 3744 | V96: 1.666 | W96: 104 | X96: 4 | Y96: COMPLETED | Z96: COMPLETED | AB96: 46044 | AC96: 4 | AD96: POPV260123018 | AF96: TIANJIN | AG96: Tianjin | AH96: CORK | AI96: 46050 | AJ96: 46051 | AK96: 46051 | AL96: 46119 | AM96: 46128 | AN96: 46128 | AO96: CIF | AP96: CMA CGM MONTE CRISTO / 0BEMXW1MA | AQ96: OTHER | AR96: TPVB20260123003 | AS96: TJN0856710 | AT96: TJN0856710 | AU96: 77 | AW96: 46128 | AX96: In Stock-Approved | AY96: 46118 | AZ96: - | BA96: 46128 | BB96: 2026 | BC96: 4 | BD96: 16 | BE96: 36 | BF96: 936 | BG96: Transparent | BH96: AEU
A97: MAY016.07 | B97: Tianjin | C97: MAY016 | D97: CORE DG | E97: Offshore | F97: SPTN Offstore in Transit WH | G97: CIF | H97: Failte Solar | I97: n/a | J97: Failte Solar | K97: 46011008 -> IE0125122900502 | M97: n/a | N97: n/a | O97: Half Cut | P97: GF0700001592 | Q97: HSM-ND48-DR445 | R97: EVO2A | S97: ±1400mm | T97: 445 | U97: 4680 | V97: 2.083 | W97: 130 | X97: 5 | Y97: COMPLETED | Z97: COMPLETED | AB97: 46044 | AC97: 4 | AD97: POPV260123015 | AF97: TIANJIN | AG97: Tianjin | AH97: CORK | AI97: 46050 | AJ97: 46051 | AK97: 46051 | AL97: 46119 | AM97: 46128 | AN97: 46128 | AO97: CIF | AP97: CMA CGM MONTE CRISTO / 0BEMXW1MA | AQ97: OTHER | AR97: TPVB20260123003 | AS97: TJN0856710 | AT97: TJN0856710 | AU97: 77 | AW97: 46128 | AX97: In Stock-Approved | AY97: 46118 | AZ97: - | BA97: 46128 | BB97: 2026 | BC97: 4 | BD97: 16 | BE97: 36 | BF97: 936 | BG97: Transparent | BH97: AEU
A98: NOV010.01 | B98: Tianjin | C98: NOV010 | D98: CORE DG | E98: Internal | F98: Arrival Plan-SPNL | G98: DAP | H98: SunPower Energy Solutions France SAS | I98: n/a | J98: SPTN / Yuma | K98: tbc | M98: n/a | N98: n/a | O98: Half Cut | P98: GF0700000071 | Q98: HSM-ND54-DR500 | R98: EVO2A | S98: ±1200mm | T98: 500 | U98: 8640 | V98: 4.32 | W98: 240 | X98: 10 | Y98: COMPLETED | Z98: COMPLETED | AB98: 46045 | AC98: 4 | AD98: POPV260205040 | AF98: TIANJIN | AG98: Tianjin | AH98: ROTTERDAM | AI98: 46054 | AJ98: 46054 | AK98: 46055 | AL98: 46094 | AM98: 46116 | AN98: 46118 | AO98: DAP | AP98: COSCO SHIPPING ARIES 036W | AQ98: COSCO | AR98: TPVB20260123021 | AS98: COSU6442391530 | AT98: COSU6442391530 | AU98: 63 | AW98: 46118 | AX98: In Stock-Approved | AY98: 46129 | AZ98: 7 | BA98: 46125 | BB98: 2026 | BC98: 4 | BD98: 16 | BE98: 36 | BF98: 864 | BG98: Black glazing | BH98: AEU
A99: DEC022.01 | B99: Tianjin | C99: DEC022 | D99: CORE DG | E99: Internal | F99: Arrival Plan-SPIT | G99: DAP | H99: Sunpower Italia S.R.L. | I99: n/a | J99: Distributors Italy - SPTN W74 | M99: n/a | N99: n/a | O99: Half Cut | P99: GF0700000348 | Q99: HSM-ND66-GR620 | R99: H4(Com) | S99: ±1400mm | T99: 620 | U99: 1440 | V99: 0.893 | W99: 40 | X99: 2 | Y99: COMPLETED | Z99: COMPLETED | AB99: 46044 | AC99: 4 | AD99: POPV260331025 | AF99: TIANJIN | AG99: Tianjin | AH99: GENOA | AI99: 46048 | AJ99: 46049 | AK99: 46049 | AL99: 46106 | AM99: 46120 | AN99: 46120 | AO99: DAP | AP99: OOCL VALENCIA 008W | AQ99: COSCO | AR99: TPVB20260123006 | AS99: COSU6442058120 | AT99: COSU6442058120 | AU99: 71 | AW99: 46120 | AX99: In Stock-Approved | AY99: 46132 | AZ99: 13 | BA99: 46133 | BB99: 2026 | BC99: 4 | BD99: 17 | BE99: 36 | BF99: 720 | BG99: Redirection Film | BH99: AEM
A100: OCT010.02 | B100: Tianjin | C100: OCT010 | D100: CORE DG | E100: Internal | F100: Arrival Plan-SPIT | G100: DAP | H100: Sunpower Italia S.R.L. | I100: n/a | J100: Distributors Italy - SPTN W74 | M100: n/a | N100: n/a | O100: Half Cut | P100: GF0700000842 | Q100: HSM-ND54-DR505 | R100: EVO2A | S100: ±1400mm | T100: 505 | U100: 2592 | V100: 1.309 | W100: 72 | X100: 3 | Y100: COMPLETED | Z100: COMPLETED | AB100: 46044 | AC100: 4 | AD100: POPV260331024 | AF100: TIANJIN | AG100: Tianjin | AH100: GENOA | AI100: 46048 | AJ100: 46049 | AK100: 46049 | AL100: 46106 | AM100: 46120 | AN100: 46120 | AO100: DAP | AP100: OOCL VALENCIA 008W | AQ100: COSCO | AR100: TPVB20260123006 | AS100: COSU6442058120 | AT100: COSU6442058120 | AU100: 71 | AW100: 46120 | AX100: In Stock-Approved | AY100: 46133 | AZ100: 13 | BA100: 46133 | BB100: 2026 | BC100: 4 | BD100: 17 | BE100: 36 | BF100: 864 | BG100: Black glazing | BH100: AEM
A101: OCT007.07 | B101: Tianjin | C101: OCT007 | D101: CORE DG | E101: Offshore | F101: SPTN Offstore in Transit WH | G101: CIF | H101: LM Eight Solar Renewables Energies S.L. | I101: n/a | J101: LM Eight | K101: ES0126011200034 | M101: n/a | N101: n/a | O101: Half Cut | P101: GF0700000078 | Q101: HSM-ND48-DR450 | R101: EVO2A | S101: ±1200mm | T101: 450 | U101: 1872 | V101: 0.842 | W101: 52 | X101: 2 | Y101: COMPLETED | Z101: COMPLETED | AB101: 46041 | AC101: 4 | AD101: POPV260126008 | AF101: TIANJIN | AG101: Tianjin | AH101: VALENCIA | AI101: 46048 | AJ101: 46049 | AK101: 46049 | AL101: 46114 | AN101: 46112 | AO101: CIF | AP101: OOCL VALENCIA 008W | AQ101: COSCO | AR101: TPVB20260123007 | AS101: COSU6442057020 | AT101: COSU6442057020 | AU101: 63 | AW101: 46112 | AX101: In Stock-Approved | AY101: 46114 | AZ101: - | BA101: 46112 | BB101: 2026 | BC101: 3 | BD101: 14 | BE101: 36 | BF101: 936 | BG101: Black glazing | BH101: AEM
A102: JUNE003.06 | B102: zhuhai -> Shenzhen | C102: JUNE003 | D102: CORE DG | E102: Internal | F102: Arrival Plan-SPNL | G102: DAP | H102: SunPower Energy Solutions France SAS | I102: n/a | J102: SPTN / Energy3000 | M102: n/a | N102: n/a | O102: BC | P102: GF0700000838 | Q102: HSM-BD54-GA465 | R102: EVO2A | S102: ±1400mm | T102: 465 | U102: 14430 | V102: 6.71 | W102: 390 | X102: 15 | Y102: COMPLETED | Z102: COMPLETED | AB102: 46043 | AC102: 4 | AD102: POPV260205020 | AF102: SHENZHEN | AG102: Shenzhen | AH102: ROTTERDAM | AI102: 46050 | AJ102: 46050 | AK102: 46050 | AL102: 46087 | AM102: 46102 | AN102: 46102 | AO102: DAP | AP102: MSC AZRA / QB604W | AQ102: OTHER | AR102: TPVB20260123023 | AS102: PLISZ4H01365 | AT102: 181AY0263403359S1 | AU102: 52 | AW102: 46102 | AX102: In Stock-Approved | AY102: 46114 | AZ102: 7 | BA102: 46109 | BB102: 2026 | BC102: 3 | BD102: 13 | BE102: 37 | BF102: 962 | BG102: White glazing | BH102: AEU
...

Sheet H2-2025 PV DATA
A1: TCL REFERENCE NO. | B1: Factory Location | C1: FX_QTY criteria | D1: CHANNEL | E1: New Ark PO Type | F1: New Ark WH | G1: B/L Consignee | H1: TCL-HK PO INCOTERM Requested | I1: ALLOCATION Planning | J1: Priority Level | K1: SPWR SO Number | L1: Region | M1: G2G ? | N1: Factory Available Date | O1: ATP Status | P1: PRODUCT TYPE | Q1: New Ark SKU | R1: Oracle SKU | S1: DESCRIPTION | T1: WATT | U1: QUANTITY | V1: MW | W1: PALLETS | X1: CONTAINERS | Y1: STATUS | Z1: ship before 4.1? | AA1: Back Glass | AB1: Cable Length | AC1: Pick-Up Date | AD1: Pick-Up Week | AE1: SPTN-PVHK New Ark PO# | AF1: SPTN-HKPV ORacle PO# | AG1: PORT OF LOADING | AH1: PORT DESTINATION | AI1: ETD On S/O | AJ1: ETD Update | AK1: ATD PORT | AL1: ETA On S/O | AM1: ETA Update | AN1: ATA PORT | AO1: incoterm | AP1: REFERENCE V.V | AQ1: Carrier | AR1: TCL Invoice# or PO# | AS1: MBL/HBL# | AT1: Booking # | AU1: Leg2 leadtime On S/O | AV1: Telex released | AW1: TBA - 1 | AX1: LT (pick-up to ETA) | AY1: ETD Conso | AZ1: ODP Available Port | BA1: New Ark PO status | BB1: New Ark ETA | BC1: ETA WH / Port for New Ark | BD1: ETA WH Year | BE1: ETA WH Month | BF1: ETA WH Week | BG1: Qty/Pallet | BH1: Qty/CT
A2: MAY006.17 | C2: MAY006 | D2: CORE DG | E2: Internal | F2: Arrival Plan-SPTN | G2: SunPower Energy Solutions France SAS | H2: DAP | I2: Local WH | J2: n/a | L2: All | M2: n/a | O2: Check Availability in New Ark | P2: P7 COM S BF IT | Q2: GF0700000769 | R2: 552045 | S2: PVM, SPR-P7-555-COM-S, I BF-G M4.3D EVO2Z6NL 1.5KV IT | T2: 555 | U2: 1980 | V2: 1.0989 | W2: 60 | X2: 3 | Y2: COMPLETED | AA2: White glazing | AB2: ±1400mm | AC2: 45814 | AD2: 23 | AE2: POPV251231059 | AF2: 371008554 | AG2: SHANGHAI | AH2: FOS SUR MER | AI2: 45822 | AJ2: 45822 | AK2: 45822 | AL2: 45872 | AM2: 45873 | AN2: 45872 | AO2: DAP | AP2: CMA CGM KIMBERLEY/0MEL3W1MA | AR2: TPVB20250529001 | AS2: COSU6419461300 | AT2: COSU6419461300 | AU2: 51 | AV2: SWB | AW2: 11 | AX2: 58 | AY2: 45822 | AZ2: 45872 | BA2: #N/A | BC2: 45886 | BD2: 2025 | BE2: 8 | BF2: 33 | BG2: 33 | BH2: 660
A3: MAY006.18 | C3: MAY006 | D3: CORE DG | E3: n/a | F3: n/a | H3: DAP | I3: Local WH | J3: n/a | L3: lberia Region | M3: n/a | O3: Check Availability in New Ark | P3: P7 COM S BF IT | Q3: GF0700000769 | R3: 552045 | S3: PVM, SPR-P7-555-COM-S, I BF-G M4.3D EVO2Z6NL 1.5KV IT | T3: 555 | U3: 660 | V3: 0.3663 | W3: 20 | X3: 1 | Y3: COMPLETED | AA3: White glazing | AB3: ±1400mm | AC3: 45814 | AD3: 23 | AE3: POPV251231053 | AF3: 371008559 | AG3: SHANGHAI | AH3: VALENCIA | AI3: 45819 | AJ3: 45819 | AK3: 45819 | AL3: 45866 | AM3: 45866 | AN3: 45866 | AO3: DAP | AP3: CSCL MERCURY/096W | AR3: TPVB20250529008 | AS3: COSU6419474470 | AT3: COSU6419474470 | AU3: 48 | AV3: SWB | AW3: 11 | AX3: 52 | AY3: 45819 | AZ3: 45866 | BA3: #N/A | BC3: 45880 | BD3: 2025 | BE3: 8 | BF3: 33 | BG3: 33 | BH3: 660
A4: MAY006.19 | C4: MAY006 | D4: CORE DG | E4: n/a | F4: n/a | H4: CIP | I4: Reenpro | J4: n/a | L4: Emerging Market | M4: n/a | O4: Check Availability in New Ark | P4: P7 COM S BF IT | Q4: GF0700000769 | R4: 552045 | S4: PVM, SPR-P7-555-COM-S, I BF-G M4.3D EVO2Z6NL 1.5KV IT | T4: 555 | U4: 1980 | V4: 1.0989 | W4: 60 | X4: 3 | Y4: COMPLETED | AA4: White glazing | AB4: ±1400mm | AC4: 45815 | AD4: 23 | AE4: POPV251231056 | AF4: 371008556 | AG4: SHANGHAI | AH4: KLAIPEDA | AI4: 45821 | AJ4: 45821 | AK4: 45821 | AL4: 45883 | AM4: 45872 | AN4: 45883 | AO4: CIP | AP4: WILHELMSHAVEN EXPR524W | AR4: 46010580-1 | AS4: 254396324 | AT4: 254396324 | AU4: 63 | AV4: Y | AW4: 11 | AX4: 68 | AY4: 45821 | AZ4: 45883 | BA4: #N/A | BC4: 45897 | BD4: 2025 | BE4: 8 | BF4: 35 | BG4: 33 | BH4: 660
A5: MAY009.01 | C5: MAY009 | D5: CORE DG | E5: n/a | F5: n/a | H5: DAP | I5: Italy Distrib. | J5: n/a | L5: Italy & Adriatics Region | M5: n/a | O5: Check Availability in New Ark | P5: Shingle | Q5: GF0700000025 | R5: 554541 | S5: TCL-MR460DT182-58NS | T5: 460 | U5: 2592 | V5: 1.19232 | W5: 72 | X5: 3 | Y5: COMPLETED | AA5: White glazing | AB5: ±1200mm | AC5: 45814 | AD5: 23 | AE5: POPV251231062 | AF5: 371008562 | AG5: SHANGHAI | AH5: GENOA | AI5: 45821 | AJ5: 45821 | AK5: 45821 | AL5: 45877 | AM5: 45872 | AN5: 45877 | AO5: DAP | AP5: EVER GENTLE/0704-025W | AR5: TPVB20250529002 | AS5: COSU6419461600 | AT5: COSU6419461600 | AU5: 57 | AV5: SWB | AW5: 6 | AX5: 63 | AY5: 45821 | AZ5: 45877 | BA5: #N/A | BC5: 45891 | BD5: 2025 | BE5: 8 | BF5: 34 | BG5: 36 | BH5: 864
A6: MAY008.01 | B6: Yixing | C6: MAY008 | D6: CORE DG | E6: n/a | F6: n/a | H6: DAP | I6: SPIT / MARINI-PANDOLFI | J6: n/a | K6: 19142931 | L6: Italy & Adriatics Region | M6: n/a | O6: Check Availability in New Ark | P6: Shingle | Q6: GF0700001780 | R6: 554431 | S6: TCL-MR455DT182-58NS | T6: 455 | U6: 1728 | V6: 0.78624 | W6: 48 | X6: 2 | Y6: COMPLETED | AA6: White glazing | AB6: ±1400mm | AC6: 45816 | AD6: 23 | AE6: POPV251231067 | AF6: 371008573 | AG6: SHANGHAI | AH6: GENOA | AI6: 45821 | AJ6: 45821 | AK6: 45821 | AL6: 45877 | AM6: 45872 | AN6: 45877 | AO6: DAP | AP6: EVER GENTLE/0704-025W | AR6: TPVB20250529007 | AS6: COSU6420662030 | AT6: COSU6420662030 | AU6: 57 | AV6: SWB | AW6: 4 | AX6: 61 | AY6: 45821 | AZ6: 45877 | BA6: #N/A | BC6: 45891 | BD6: 2025 | BE6: 8 | BF6: 34 | BG6: 36 | BH6: 864
A7: JULY004.08 | B7: Yixing | C7: JULY004 | D7: CORE DG | E7: Internal | F7: Arrival Plan-SPTN | G7: SunPower Energy Solutions France SAS | H7: DAP | I7: Local WH | J7: n/a | L7: All | M7: n/a | O7: Check Availability in New Ark | P7: Shingle | Q7: GF0700000766 | R7: 552026 | S7: PVM, SPR-P7-550-COM-S, I BF-G M4.3D EVO2Z6NL 1.5KV IT | T7: 550 | U7: 660 | V7: 0.363 | W7: 20 | X7: 1 | Y7: COMPLETED | AA7: White glazing | AB7: ±1500mm | AC7: 45814 | AD7: 23 | AE7: POPV251231059 | AF7: 371008554 | AG7: SHANGHAI | AH7: FOS SUR MER | AI7: 45822 | AJ7: 45822 | AK7: 45822 | AL7: 45872 | AM7: 45873 | AN7: 45872 | AO7: DAP | AP7: CMA CGM KIMBERLEY/0MEL3W1MA | AR7: TPVB20250529001 | AS7: COSU6419461300 | AT7: COSU6419461300 | AU7: 51 | AV7: SWB | AW7: 8 | AX7: 58 | AY7: 45822 | AZ7: 45872 | BA7: #N/A | BC7: 45886 | BD7: 2025 | BE7: 8 | BF7: 33 | BG7: 33 | BH7: 660
A8: MAY006.20 | C8: MAY006 | D8: CORE DG | E8: n/a | F8: n/a | H8: DAP | I8: Local WH - SPIT W81 | J8: n/a | L8: Italy & Adriatics Region | M8: n/a | O8: Check Availability in New Ark | P8: P7 COM S BF IT | Q8: GF0700000769 | R8: 552045 | S8: PVM, SPR-P7-555-COM-S, I BF-G M4.3D EVO2Z6NL 1.5KV IT | T8: 555 | U8: 1980 | V8: 1.0989 | W8: 60 | X8: 3 | Y8: COMPLETED | AA8: White glazing | AB8: ±1400mm | AC8: 45822 | AD8: 24 | AE8: POPV251231058 | AF8: 371008563 | AG8: SHANGHAI | AH8: GENOA | AI8: 45831 | AJ8: 45831 | AK8: 45831 | AL8: 45887 | AM8: 45886 | AN8: 45887 | AO8: DAP | AP8: COSCO SHIPPING SOLAR/033W | AR8: TPVB20250605001 | AS8: COSU6420263970 | AT8: COSU6420263970 | AU8: 57 | AV8: SWB | AW8: 11 | AX8: 65 | AY8: 45831 | AZ8: 45887 | BA8: #N/A | BC8: 45901 | BD8: 2025 | BE8: 9 | BF8: 36 | BG8: 33 | BH8: 660
A9: MAY006.21 | C9: MAY006 | D9: CORE DG | E9: n/a | F9: n/a | H9: CIP | I9: Reenpro | J9: n/a | L9: Emerging Market | M9: n/a | O9: Check Availability in New Ark | P9: P7 COM S BF IT | Q9: GF0700000769 | R9: 552045 | S9: PVM, SPR-P7-555-COM-S, I BF-G M4.3D EVO2Z6NL 1.5KV IT | T9: 555 | U9: 1320 | V9: 0.7326 | W9: 40 | X9: 2 | Y9: COMPLETED | AA9: White glazing | AB9: ±1400mm | AC9: 45822 | AD9: 24 | AE9: POPV251231072 | AF9: 371008564 | AG9: SHANGHAI | AH9: KLAIPEDA | AI9: 45828 | AJ9: 45828 | AK9: 45828 | AL9: 45883 | AM9: 45879 | AN9: 45883 | AO9: CIP | AP9: TIHAMA 525W | AR9: 46010580-2 | AS9: 255195702 | AT9: 254738544 | AU9: 56 | AV9: Y | AW9: 11 | AX9: 61 | AY9: 45828 | AZ9: 45883 | BA9: #N/A | BC9: 45897 | BD9: 2025 | BE9: 8 | BF9: 35 | BG9: 33 | BH9: 660
A10: MAY009.05 | C10: MAY009 | D10: CORE DG | E10: n/a | F10: n/a | H10: DAP | I10: Italy Distrib. | J10: n/a | L10: Italy & Adriatics Region | M10: n/a | O10: Check Availability in New Ark | P10: Shingle | Q10: GF0700000025 | R10: 554541 | S10: TCL-MR460DT182-58NS | T10: 460 | U10: 1728 | V10: 0.79488 | W10: 48 | X10: 2 | Y10: COMPLETED | AA10: White glazing | AB10: ±1200mm | AC10: 45817 | AD10: 24 | AE10: POPV251231075 | AF10: 371008571 | AG10: SHANGHAI | AH10: GENOA | AI10: 45821 | AJ10: 45821 | AK10: 45821 | AL10: 45877 | AM10: 45872 | AN10: 45877 | AO10: DAP | AP10: EVER GENTLE/0704-025W | AR10: TPVB20250529006 | AS10: COSU6420591050 | AT10: COSU6420591050 | AU10: 57 | AV10: SWB | AW10: 6 | AX10: 60 | AY10: 45821 | AZ10: 45877 | BA10: #N/A | BC10: 45891 | BD10: 2025 | BE10: 8 | BF10: 34 | BG10: 36 | BH10: 864
A11: MAY009.07 | C11: MAY009 | D11: CORE DG | E11: n/a | F11: n/a | H11: DAP | I11: Local WH - SPIT W82 | J11: n/a | L11: Italy & Adriatics Region | M11: n/a | O11: Check Availability in New Ark | P11: Shingle | Q11: GF0700000025 | R11: 554541 | S11: TCL-MR460DT182-58NS | T11: 460 | U11: 3456 | V11: 1.58976 | W11: 96 | X11: 4 | Y11: COMPLETED | AA11: White glazing | AB11: ±1200mm | AC11: 45823 | AD11: 24 | AE11: POPV251231095 | AF11: 371008572 | AG11: SHANGHAI | AH11: NAPLES | AI11: 45831 | AJ11: 45831 | AK11: 45831 | AL11: 45878 | AM11: 45878 | AN11: 45878 | AO11: DAP | AP11: COSCO SHIPPING SOLAR/033W | AR11: TPVB20250605002 | AS11: COSU6420264270 | AT11: COSU6420264270 | AU11: 48 | AV11: SWB | AW11: 6 | AX11: 55 | AY11: 45831 | AZ11: 45878 | BA11: #N/A | BC11: 45892 | BD11: 2025 | BE11: 8 | BF11: 34 | BG11: 36 | BH11: 864
A12: MAY011.01 | C12: MAY011 | D12: CORE DG | E12: n/a | F12: n/a | H12: CIF | I12: LM Eight | J12: n/a | L12: Iberia Region | M12: n/a | O12: Not Available | P12: Shingle | Q12: GF0700000023 | R12: 554542 | S12: TCL-MR515DT182-64NS | T12: 515 | U12: 1584 | V12: 0.81576 | W12: 44 | X12: 2 | Y12: COMPLETED | AA12: White glazing | AB12: ±1400mm | AC12: 45821 | AD12: 24 | AE12: n/a - 2025 legacy | AF12: TPVO2025061617 | AG12: SHANGHAI | AH12: VALENCIA | AI12: 45825 | AJ12: 45825 | AK12: 45825 | AL12: 45869 | AM12: 45869 | AN12: 45869 | AO12: CIF | AP12: COSCO SHIPPING HIMALAYAS/044W | AR12: TPVB20250605003 | AS12: COSU6420290820 | AT12: COSU6420290820 | AU12: 45 | AV12: Y | AW12: 5 | AX12: 48 | AY12: 45825 | AZ12: 45869 | BA12: #N/A | BC12: 45883 | BD12: 2025 | BE12: 8 | BF12: 33 | BG12: 36 | BH12: 792
A13: MAY011.02 | C13: MAY011 | D13: CORE DG | E13: n/a | F13: n/a | H13: CIP | I13: Reenpro | J13: n/a | L13: Emerging Market | M13: n/a | O13: Check Availability in New Ark | P13: Shingle | Q13: GF0700000023 | R13: 554542 | S13: TCL-MR515DT182-64NS | T13: 515 | U13: 792 | V13: 0.40788 | W13: 22 | X13: 1 | Y13: COMPLETED | AA13: White glazing | AB13: ±1400mm | AC13: 45822 | AD13: 24 | AE13: POPV260104067 | AF13: 371008611 | AG13: SHANGHAI | AH13: KLAIPEDA | AI13: 45828 | AJ13: 45828 | AK13: 45828 | AL13: 45883 | AM13: 45879 | AN13: 45883 | AO13: CIP | AP13: TIHAMA 525W | AR13: 46010657 | AS13: 254738544 | AT13: 254738544 | AU13: 56 | AV13: Y | AW13: 5 | AX13: 61 | AY13: 45828 | AZ13: 45883 | BA13: #N/A | BC13: 45897 | BD13: 2025 | BE13: 8 | BF13: 35 | BG13: 36 | BH13: 792
A14: MAY014.01 | B14: Yixing | C14: MAY014 | D14: CORE DG | E14: n/a | F14: n/a | H14: DAP | I14: SPIT/ TEST SRL | J14: n/a | K14: 19143069 | L14: Italy & Adriatics Region | M14: n/a | O14: Check Availability in New Ark | P14: Half Cut | Q14: GF0101010094 | R14: 554244 | S14: HSM-ND66-GR615 | T14: 615 | U14: 720 | V14: 0.4428 | W14: 20 | X14: 1 | Y14: COMPLETED | AA14: White glazing | AB14: ±1200mm | AC14: 45817 | AD14: 24 | AE14: POPV251231064 | AF14: 371008567 | AG14: SHANGHAI | AH14: GENOA | AI14: 45821 | AJ14: 45821 | AK14: 45821 | AL14: 45877 | AM14: 45872 | AN14: 45877 | AO14: DAP | AP14: EVER GENTLE/0704-025W | AR14: TPVB20250529006 | AS14: COSU6420591050 | AT14: COSU6420591050 | AU14: 57 | AV14: SWB | AW14: 3 | AX14: 60 | AY14: 45821 | AZ14: 45877 | BA14: #N/A | BC14: 45891 | BD14: 2025 | BE14: 8 | BF14: 34 | BG14: 36 | BH14: 720
A15: MAY014.02 | B15: Yixing | C15: MAY014 | D15: CORE DG | E15: n/a | F15: n/a | H15: CIF | I15: LM Eight | J15: n/a | L15: Iberia Region | M15: n/a | O15: Not Available | P15: Half Cut | Q15: GF0101010094 | R15: 554244 | S15: HSM-ND66-GR615 | T15: 615 | U15: 2880 | V15: 1.7712 | W15: 80 | X15: 4 | Y15: COMPLETED | AA15: White glazing | AB15: ±1200mm | AC15: 45820 | AD15: 24 | AE15: n/a - 2025 legacy | AF15: TPVO2025053014 | AG15: SHANGHAI | AH15: VALENCIA | AI15: 45825 | AJ15: 45825 | AK15: 45825 | AL15: 45869 | AM15: 45869 | AN15: 45869 | AO15: CIF | AP15: COSCO SHIPPING HIMALAYAS/044W | AR15: TPVB20250605003 | AS15: COSU6420290820 | AT15: COSU6420290820 | AU15: 45 | AV15: Y | AW15: 3 | AX15: 49 | AY15: 45825 | AZ15: 45869 | BA15: #N/A | BC15: 45883 | BD15: 2025 | BE15: 8 | BF15: 33 | BG15: 36 | BH15: 720
A16: MAY015.01 | C16: MAY015 | D16: CORE DG | E16: n/a | F16: n/a | H16: DAP | I16: Local WH - SPIT W82 | J16: n/a | L16: Italy & Adriatics Region | M16: n/a | O16: Check Availability in New Ark | P16: Half Cut | Q16: GF0101010095 | R16: 554245 | S16: HSM-ND66-GR620 | T16: 620 | U16: 3600 | V16: 2.232 | W16: 100 | X16: 5 | Y16: COMPLETED | AA16: White glazing | AB16: ±1200mm | AC16: 45823 | AD16: 24 | AE16: POPV251231073 | AF16: 371008568 | AG16: SHANGHAI | AH16: NAPLES | AI16: 45831 | AJ16: 45831 | AK16: 45831 | AL16: 45878 | AM16: 45878 | AN16: 45878 | AO16: DAP | AP16: COSCO SHIPPING SOLAR/033W | AR16: TPVB20250605002 | AS16: COSU6420264270 | AT16: COSU6420264270 | AU16: 48 | AV16: SWB | AW16: 8 | AX16: 55 | AY16: 45831 | AZ16: 45878 | BA16: #N/A | BC16: 45892 | BD16: 2025 | BE16: 8 | BF16: 34 | BG16: 36 | BH16: 720
A17: MAY015.02 | C17: MAY015 | D17: CORE DG | E17: n/a | F17: n/a | H17: CIF | I17: LM Eight | J17: n/a | L17: Iberia Region | M17: n/a | O17: Not Available | P17: Half Cut | Q17: GF0101010095 | R17: 554245 | S17: HSM-ND66-GR620 | T17: 620 | U17: 2880 | V17: 1.7856 | W17: 80 | X17: 4 | Y17: COMPLETED | AA17: White glazing | AB17: ±1200mm | AC17: 45820 | AD17: 24 | AE17: n/a - 2025 legacy | AF17: TPVO2025053014 | AG17: SHANGHAI | AH17: VALENCIA | AI17: 45825 | AJ17: 45825 | AK17: 45825 | AL17: 45869 | AM17: 45869 | AN17: 45869 | AO17: CIF | AP17: COSCO SHIPPING HIMALAYAS/044W | AR17: TPVB20250605003 | AS17: COSU6420290820 | AT17: COSU6420290820 | AU17: 45 | AV17: Y | AW17: 8 | AX17: 49 | AY17: 45825 | AZ17: 45869 | BA17: #N/A | BC17: 45883 | BD17: 2025 | BE17: 8 | BF17: 33 | BG17: 36 | BH17: 720
A18: MAY010.02 | B18: Yixing | C18: MAY010 | D18: CORE DG | E18: n/a | F18: n/a | H18: DAP | I18: Eurologic Sp. Z o.o. | J18: n/a | L18: Emerging Market | M18: n/a | O18: Check Availability in New Ark | P18: Shingle | Q18: GF0700000024 | R18: 554433 | S18: TCL-MR510DT182-64NS | T18: 510 | U18: 2124 | V18: 1.08324 | W18: 59 | X18: 2.6818182 | Y18: COMPLETED | AA18: White glazing | AB18: ±1400mm | AC18: 45830 | AD18: 25 | AE18: POPV251231087 | AF18: 371008577 | AG18: SHANGHAI | AH18: GDANSK | AI18: 45835 | AJ18: 45835 | AK18: 45835 | AL18: 45883 | AM18: 45881 | AN18: 45883 | AO18: DAP | AP18: MANILA EXPRESS/526W | AR18: 46010671 | AS18: MAEU254941683 | AT18: 254941683 | AU18: 49 | AV18: SWB | AW18: 1 | AX18: 53 | AY18: 45835 | AZ18: 45883 | BA18: #N/A | BC18: 45897 | BD18: 2025 | BE18: 8 | BF18: 35 | BG18: 36 | BH18: 792
A19: MAY006.22 | C19: MAY006 | D19: CORE DG | E19: Internal | F19: Arrival Plan-SPTN | G19: SunPower Energy Solutions France SAS | H19: DAP | I19: Local WH | J19: n/a | L19: All | M19: n/a | O19: Check Availability in New Ark | P19: P7 COM S BF IT | Q19: GF0700000769 | R19: 552045 | S19: PVM, SPR-P7-555-COM-S, I BF-G M4.3D EVO2Z6NL 1.5KV IT | T19: 555 | U19: 660 | V19: 0.3663 | W19: 20 | X19: 1 | Y19: COMPLETED | AA19: White glazing | AB19: ±1400mm | AC19: 45826 | AD19: 25 | AE19: POPV251231082 | AF19: 371008584 | AG19: SHANGHAI | AH19: FOS SUR MER | AI19: 45842 | AJ19: 45842 | AK19: 45842 | AL19: 45896 | AM19: 45895 | AN19: 45896 | AO19: DAP | AP19: OOCL HONG KONG 036W | AR19: TPVB20250612001 | AS19: COSU6421224540 | AT19: COSU6421224540_x000D_ | AU19: 55 | AV19: SWB | AW19: 11 | AX19: 70 | AY19: 45842 | AZ19: 45896 | BA19: #N/A | BC19: 45910 | BD19: 2025 | BE19: 9 | BF19: 37 | BG19: 33 | BH19: 660
A20: MAY006.23 | C20: MAY006 | D20: CORE DG | E20: n/a | F20: n/a | H20: DAP | I20: Local WH - SPIT W81 | J20: n/a | L20: Italy & Adriatics Region | M20: n/a | O20: Check Availability in New Ark | P20: P7 COM S BF IT | Q20: GF0700000769 | R20: 552045 | S20: PVM, SPR-P7-555-COM-S, I BF-G M4.3D EVO2Z6NL 1.5KV IT | T20: 555 | U20: 3300 | V20: 1.8315 | W20: 100 | X20: 5 | Y20: COMPLETED | AA20: White glazing | AB20: ±1400mm | AC20: 45830 | AD20: 25 | AE20: POPV251231007 | AF20: 371008585 | AG20: SHANGHAI | AH20: GENOA | AI20: 45842 | AJ20: 45842 | AK20: 45842 | AL20: 45892 | AM20: 45891 | AN20: 45892 | AO20: DAP | AP20: OOCL HONG KONG 036W | AR20: TPVB20250612002 | AS20: COSU6421224760 | AT20: COSU6421224760 | AU20: 51 | AV20: SWB | AW20: 11 | AX20: 62 | AY20: 45842 | AZ20: 45892 | BA20: #N/A | BC20: 45906 | BD20: 2025 | BE20: 9 | BF20: 36 | BG20: 33 | BH20: 660
A21: MAY006.24 | C21: MAY006 | D21: CORE DG | E21: n/a | F21: n/a | H21: DAP | I21: Local WH - SPIT W82 | J21: n/a | L21: Italy & Adriatics Region | M21: n/a | O21: Check Availability in New Ark | P21: P7 COM S BF IT | Q21: GF0700000769 | R21: 552045 | S21: PVM, SPR-P7-555-COM-S, I BF-G M4.3D EVO2Z6NL 1.5KV IT | T21: 555 | U21: 1320 | V21: 0.7326 | W21: 40 | X21: 2 | Y21: COMPLETED | AA21: White glazing | AB21: ±1400mm | AC21: 45826 | AD21: 25 | AE21: POPV251231077 | AF21: 371008586 | AG21: SHANGHAI | AH21: NAPLES | AI21: 45842 | AJ21: 45842 | AK21: 45842 | AL21: 45892 | AM21: 45893 | AN21: 45892 | AO21: DAP | AP21: OOCL HONG KONG 036W | AR21: TPVB20250612003 | AS21: COSU6421224890 | AT21: COSU6421224890_x000D_ | AU21: 51 | AV21: SWB | AW21: 11 | AX21: 66 | AY21: 45842 | AZ21: 45892 | BA21: #N/A | BC21: 45906 | BD21: 2025 | BE21: 9 | BF21: 36 | BG21: 33 | BH21: 660
A22: MAY006.25 | C22: MAY006 | D22: CORE DG | E22: n/a | F22: n/a | H22: DAP | I22: Local WH | J22: n/a | L22: lberia Region | M22: n/a | O22: Check Availability in New Ark | P22: P7 COM S BF IT | Q22: GF0700000769 | R22: 552045 | S22: PVM, SPR-P7-555-COM-S, I BF-G M4.3D EVO2Z6NL 1.5KV IT | T22: 555 | U22: 660 | V22: 0.3663 | W22: 20 | X22: 1 | Y22: COMPLETED | AA22: White glazing | AB22: ±1400mm | AC22: 45826 | AD22: 25 | AE22: POPV251231006 | AF22: 371008587 | AG22: SHANGHAI | AH22: VALENCIA | AI22: 45835 | AJ22: 45835 | AK22: 45835 | AL22: 45882 | AM22: 45882 | AN22: 45882 | AO22: DAP | AP22: CSCL SATURN/085W | AR22: TPVB20250612004 | AS22: COSU6421712120 | AT22: COSU6421712120 | AU22: 48 | AV22: SWB | AW22: 11 | AX22: 56 | AY22: 45835 | AZ22: 45882 | BA22: #N/A | BC22: 45896 | BD22: 2025 | BE22: 8 | BF22: 35 | BG22: 33 | BH22: 660
A23: MAY005.10 | C23: MAY005 | D23: CORE DG | E23: Internal | F23: Arrival Plan-SPTN | G23: SunPower Energy Solutions France SAS | H23: DAP | I23: Local WH | J23: n/a | L23: All | M23: n/a | O23: Check Availability in New Ark | P23: P7 COM S BF IT | Q23: GF0700000766 | R23: 552026 | S23: PVM, SPR-P7-550-COM-S, I BF-G M4.3D EVO2Z6NL 1.5KV IT | T23: 550 | U23: 2640 | V23: 1.452 | W23: 80 | X23: 4 | Y23: COMPLETED | AA23: White glazing | AB23: ±1500mm | AC23: 45826 | AD23: 25 | AE23: POPV251231094 | AF23: 371008581 | AG23: SHANGHAI | AH23: FOS SUR MER | AI23: 45842 | AJ23: 45842 | AK23: 45842 | AL23: 45896 | AM23: 45895 | AN23: 45896 | AO23: DAP | AP23: OOCL HONG KONG 036W | AR23: TPVB20250612001 | AS23: COSU6421224540 | AT23: COSU6421224540 | AU23: 55 | AV23: SWB | AW23: 3 | AX23: 70 | AY23: 45842 | AZ23: 45896 | BA23: #N/A | BC23: 45910 | BD23: 2025 | BE23: 9 | BF23: 37 | BG23: 33 | BH23: 660
A24: MAY005.11 | C24: MAY005 | D24: CORE DG | E24: n/a | F24: n/a | H24: DAP | I24: Local WH - SPIT W81 | J24: n/a | L24: Italy & Adriatics Region | M24: n/a | O24: Check Availability in New Ark | P24: P7 COM S BF IT | Q24: GF0700000766 | R24: 552026 | S24: PVM, SPR-P7-550-COM-S, I BF-G M4.3D EVO2Z6NL 1.5KV IT | T24: 550 | U24: 1320 | V24: 0.726 | W24: 40 | X24: 2 | Y24: COMPLETED | AA24: White glazing | AB24: ±1500mm | AC24: 45830 | AD24: 25 | AE24: POPV251231092 | AF24: 371008582 | AG24: SHANGHAI | AH24: GENOA | AI24: 45842 | AJ24: 45842 | AK24: 45842 | AL24: 45892 | AM24: 45891 | AN24: 45892 | AO24: DAP | AP24: OOCL HONG KONG 036W | AR24: TPVB20250612002 | AS24: COSU6421224760 | AT24: COSU6421224760 | AU24: 51 | AV24: SWB | AW24: 3 | AX24: 62 | AY24: 45842 | AZ24: 45892 | BA24: #N/A | BC24: 45906 | BD24: 2025 | BE24: 9 | BF24: 36 | BG24: 33 | BH24: 660
A25: MAY005.12 | C25: MAY005 | D25: CORE DG | E25: n/a | F25: n/a | H25: DAP | I25: Local WH - SPIT W82 | J25: n/a | L25: Italy & Adriatics Region | M25: n/a | O25: Check Availability in New Ark | P25: P7 COM S BF IT | Q25: GF0700000766 | R25: 552026 | S25: PVM, SPR-P7-550-COM-S, I BF-G M4.3D EVO2Z6NL 1.5KV IT | T25: 550 | U25: 1320 | V25: 0.726 | W25: 40 | X25: 2 | Y25: COMPLETED | AA25: White glazing | AB25: ±1500mm | AC25: 45826 | AD25: 25 | AE25: POPV251231093 | AF25: 371008583 | AG25: SHANGHAI | AH25: NAPLES | AI25: 45842 | AJ25: 45842 | AK25: 45842 | AL25: 45892 | AM25: 45893 | AN25: 45892 | AO25: DAP | AP25: OOCL HONG KONG 036W | AR25: TPVB20250612003 | AS25: COSU6421224890 | AT25: COSU6421224890 | AU25: 51 | AV25: SWB | AW25: 3 | AX25: 66 | AY25: 45842 | AZ25: 45892 | BA25: #N/A | BC25: 45906 | BD25: 2025 | BE25: 9 | BF25: 36 | BG25: 33 | BH25: 660
A26: MAY005 | C26: Main Line | D26: CORE DG | E26: n/a | F26: n/a | H26: DAP | I26: Local WH - SPIT W81 | J26: n/a | L26: Italy & Adriatics Region | M26: n/a | O26: Check Availability in New Ark | P26: P7 COM S BF IT | Q26: GF0700000766 | R26: 552026 | S26: PVM, SPR-P7-550-COM-S, I BF-G M4.3D EVO2Z6NL 1.5KV IT | T26: 550 | U26: 3300 | V26: 1.815 | W26: 100 | X26: 5 | Y26: COMPLETED | AA26: White glazing | AB26: ±1500mm | AC26: 45836 | AD26: 26 | AE26: POPV251231005 | AF26: 371008616 | AG26: SHANGHAI | AH26: GENOA | AI26: 45847 | AJ26: 45847 | AK26: 45847 | AL26: 45903 | AM26: 45900 | AN26: 45903 | AO26: DAP | AP26: EVER GRADE 0707-025W | AR26: TPVB20250619002 | AS26: COSU6422739630 | AT26: COSU6422739630 | AU26: 57 | AV26: SWB | AW26: 39 | AX26: 67 | AY26: 45847 | AZ26: 45903 | BA26: #N/A | BC26: 45917 | BD26: 2025 | BE26: 9 | BF26: 38 | BG26: 33 | BH26: 660
A27: MAY015.03 | B27: Lianyungang | C27: MAY015 | D27: CORE DG | E27: n/a | F27: n/a | H27: FOB | I27: UAB Elmitra | J27: n/a | L27: Emerging Market | M27: n/a | O27: Check Availability in New Ark | P27: Half Cut | Q27: GF0101010095 | R27: 554245 | S27: HSM-ND66-GR620 | T27: 620 | U27: 720 | V27: 0.4464 | W27: 20 | X27: 1 | Y27: COMPLETED | AA27: White glazing | AB27: ±1200mm | AC27: 45831 | AD27: 26 | AE27: POPV260104111 | AF27: 371008612 | AG27: SHANGHAI | AH27: KLAIPEDA | AI27: 45846 | AJ27: 45846 | AK27: 45846 | AL27: 45900 | AN27: 45900 | AO27: FOB | AP27: MSC ALESSIA QB526W | AR27: 46010646 | AS27: 1067418014 | AT27: 177FVKVKS234167 | AU27: 55 | AV27: Y | AW27: 8 | AX27: 69 | AY27: 45846 | AZ27: 45900 | BA27: #N/A | BC27: 45914 | BD27: 2025 | BE27: 9 | BF27: 37 | BG27: 36 | BH27: 720
A28: MAY015.04 | C28: MAY015 | D28: CORE DG | E28: n/a | F28: n/a | H28: DAP | I28: Italy Distrib. | J28: n/a | L28: Italy & Adriatics Region | M28: n/a | O28: Check Availability in New Ark | P28: Half Cut | Q28: GF0101010095 | R28: 554245 | S28: HSM-ND66-GR620 | T28: 620 | U28: 720 | V28: 0.4464 | W28: 20 | X28: 1 | Y28: COMPLETED | AA28: White glazing | AB28: ±1200mm | AC28: 45835 | AD28: 26 | AE28: POPV251231088 | AF28: 371008619 | AG28: SHANGHAI | AH28: GENOA | AI28: 45847 | AJ28: 45847 | AK28: 45847 | AL28: 45903 | AM28: 45900 | AN28: 45903 | AO28: DAP | AP28: EVER GRADE 0707-025W | AR28: TPVB20250619001 | AS28: COSU6421953700 | AT28: COSU6421953700 | AU28: 57 | AV28: SWB | AW28: 8 | AX28: 68 | AY28: 45847 | AZ28: 45903 | BA28: #N/A | BC28: 45917 | BD28: 2025 | BE28: 9 | BF28: 38 | BG28: 36 | BH28: 720
A29: MAY009.08 | C29: MAY009 | D29: CORE DG | E29: n/a | F29: n/a | H29: DAP | I29: Italy Distrib. | J29: n/a | L29: Italy & Adriatics Region | M29: n/a | O29: Check Availability in New Ark | P29: Shingle | Q29: GF0700000025 | R29: 554541 | S29: TCL-MR460DT182-58NS | T29: 460 | U29: 5184 | V29: 2.38464 | W29: 144 | X29: 6 | Y29: COMPLETED | AA29: White glazing | AB29: ±1200mm | AC29: 45835 | AD29: 26 | AE29: POPV251231090 | AF29: 371008618 | AG29: SHANGHAI | AH29: GENOA | AI29: 45847 | AJ29: 45847 | AK29: 45847 | AL29: 45903 | AM29: 45900 | AN29: 45903 | AO29: DAP | AP29: EVER GRADE 0707-025W | AR29: TPVB20250619001 | AS29: COSU6421953700 | AT29: COSU6421953700 | AU29: 57 | AV29: SWB | AW29: 6 | AX29: 68 | AY29: 45847 | AZ29: 45903 | BA29: #N/A | BC29: 45917 | BD29: 2025 | BE29: 9 | BF29: 38 | BG29: 36 | BH29: 864
A30: MAY006.26 | C30: MAY006 | D30: CORE DG | E30: n/a | F30: n/a | H30: DAP | I30: Local WH | J30: n/a | L30: lberia Region | M30: n/a | O30: Check Availability in New Ark | P30: P7 COM S BF IT | Q30: GF0700000769 | R30: 552045 | S30: PVM, SPR-P7-555-COM-S, I BF-G M4.3D EVO2Z6NL 1.5KV IT | T30: 555 | U30: 1320 | V30: 0.7326 | W30: 40 | X30: 2 | Y30: COMPLETED | AA30: White glazing | AB30: ±1400mm | AC30: 45835 | AD30: 26 | AE30: POPV251231071 | AF30: 371008617 | AG30: SHANGHAI | AH30: VALENCIA | AI30: 45844 | AJ30: 45844 | AK30: 45844 | AL30: 45889 | AM30: 45887 | AN30: 45889 | AO30: DAP | AP30: EVER LIFTING 060W | AR30: TPVB20250619004 | AS30: COSU6422019550 | AT30: COSU6422019550 | AU30: 46 | AV30: SWB | AW30: 11 | AX30: 54 | AY30: 45844 | AZ30: 45889 | BA30: #N/A | BC30: 45903 | BD30: 2025 | BE30: 9 | BF30: 36 | BG30: 33 | BH30: 660
A31: JULY004.01 | C31: JULY004 | D31: CORE DG | E31: n/a | F31: n/a | H31: DAP | I31: Local WH - SPIT W81 | J31: n/a | L31: Italy & Adriatics Region | M31: n/a | O31: Check Availability in New Ark | P31: P7 COM S BF IT | Q31: GF0700000766 | R31: 552026 | S31: PVM, SPR-P7-550-COM-S, I BF-G M4.3D EVO2Z6NL 1.5KV IT | T31: 550 | U31: 3960 | V31: 2.178 | W31: 120 | X31: 6 | Y31: COMPLETED | AA31: White glazing | AB31: ±1500mm | AC31: 45836 | AD31: 26 | AE31: POPV251231081 | AF31: 371008620 | AG31: SHANGHAI | AH31: GENOA | AI31: 45847 | AJ31: 45847 | AK31: 45847 | AL31: 45903 | AM31: 45900 | AN31: 45903 | AO31: DAP | AP31: EVER GRADE 0707-025W | AR31: TPVB20250619002 | AS31: COSU6422739630 | AT31: COSU6422739630 | AU31: 57 | AV31: SWB | AW31: 8 | AX31: 67 | AY31: 45847 | AZ31: 45903 | BA31: #N/A | BC31: 45917 | BD31: 2025 | BE31: 9 | BF31: 38 | BG31: 33 | BH31: 660
A32: JULY004.02 | C32: JULY004 | D32: CORE DG | E32: n/a | F32: n/a | H32: DAP | I32: Local WH - SPIT W82 | J32: n/a | L32: Italy & Adriatics Region | M32: n/a | O32: Check Availability in New Ark | P32: P7 COM S BF IT | Q32: GF0700000766 | R32: 552026 | S32: PVM, SPR-P7-550-COM-S, I BF-G M4.3D EVO2Z6NL 1.5KV IT | T32: 550 | U32: 1320 | V32: 0.726 | W32: 40 | X32: 2 | Y32: COMPLETED | AA32: White glazing | AB32: ±1500mm | AC32: 45835 | AD32: 26 | AE32: POPV251231084 | AF32: 371008621 | AG32: SHANGHAI | AH32: NAPLES | AI32: 45847 | AJ32: 45847 | AK32: 45847 | AL32: 45906 | AM32: 45907 | AN32: 45906 | AO32: DAP | AP32: EVER GRADE 0707-025W | AR32: TPVB20250619003 | AS32: COSU6422019170 | AT32: COSU6422019170 | AU32: 60 | AV32: SWB | AW32: 8 | AX32: 71 | AY32: 45847 | AZ32: 45906 | BA32: #N/A | BC32: 45920 | BD32: 2025 | BE32: 9 | BF32: 38 | BG32: 33 | BH32: 660
A33: JULY004.03 | B33: Yixing | C33: JULY004 | D33: CORE DG | E33: Internal | F33: Arrival Plan-SPTN | G33: SunPower Energy Solutions France SAS | H33: DAP | I33: Local WH | J33: n/a | L33: All | M33: n/a | O33: Check Availability in New Ark | P33: P7 COM S BF IT | Q33: GF0700000766 | R33: 552026 | S33: PVM, SPR-P7-550-COM-S, I BF-G M4.3D EVO2Z6NL 1.5KV IT | T33: 550 | U33: 2640 | V33: 1.452 | W33: 80 | X33: 4 | Y33: COMPLETED | AA33: White glazing | AB33: ±1500mm | AC33: 45843 | AD33: 27 | AE33: POPV251231098 | AF33: 371008645 | AG33: SHANGHAI | AH33: FOS SUR MER | AI33: 45857 | AJ33: 45857 | AK33: 45857 | AL33: 45918 | AM33: 45912 | AN33: 45918 | AO33: DAP | AP33: OOCL INDONESIA/033W | AR33: TPVB20250626002-2 | AS33: COSU6422843430 | AT33: COSU6422843430 | AU33: 62 | AV33: SWB | AW33: 8 | AX33: 75 | AY33: 45857 | AZ33: 45918 | BA33: #N/A | BC33: 45932 | BD33: 2025 | BE33: 10 | BF33: 40 | BG33: 33 | BH33: 660
A34: APR003.01 | B34: Yixing | C34: APR003 | D34: CORE DG | E34: Internal | F34: Arrival Plan-SPTN | G34: SunPower Energy Solutions France SAS | H34: DAP | I34: Local WH | J34: n/a | L34: All | M34: n/a | O34: Check Availability in New Ark | P34: P7 COM S CFP | Q34: GF0700000001 | R34: 553098 | S34: PVM, SPR-P7-550-COM-S, I BF-G M4.3D EVO2Z6NL 1.5KV IT P36 | T34: 550 | U34: 3300 | V34: 1.815 | W34: 100 | X34: 5 | Y34: COMPLETED | AA34: White glazing | AB34: ±1400mm | AC34: 45843 | AD34: 27 | AE34: POPV251231085 | AF34: 371008640 | AG34: SHANGHAI | AH34: FOS SUR MER | AI34: 45857 | AJ34: 45857 | AK34: 45857 | AL34: 45918 | AM34: 45912 | AN34: 45918 | AO34: DAP | AP34: OOCL INDONESIA/033W | AR34: TPVB20250626002-2 | AS34: COSU6422843430 | AT34: COSU6422843430 | AU34: 62 | AV34: SWB | AW34: 6 | AX34: 75 | AY34: 45857 | AZ34: 45918 | BA34: #N/A | BC34: 45932 | BD34: 2025 | BE34: 10 | BF34: 40 | BG34: 33 | BH34: 660
A35: MAY006.27 | B35: Yixing | C35: MAY006 | D35: CORE DG | E35: Internal | F35: Arrival Plan-SPTN | G35: SunPower Energy Solutions France SAS | H35: DAP | I35: Local WH | J35: n/a | L35: All | M35: n/a | O35: Check Availability in New Ark | P35: P7 COM S BF IT | Q35: GF0700000769 | R35: 552045 | S35: PVM, SPR-P7-555-COM-S, I BF-G M4.3D EVO2Z6NL 1.5KV IT | T35: 555 | U35: 660 | V35: 0.3663 | W35: 20 | X35: 1 | Y35: COMPLETED | AA35: White glazing | AB35: ±1400mm | AC35: 45843 | AD35: 27 | AE35: POPV251231091 | AF35: 371008642 | AG35: SHANGHAI | AH35: FOS SUR MER | AI35: 45857 | AJ35: 45857 | AK35: 45857 | AL35: 45918 | AM35: 45912 | AN35: 45918 | AO35: DAP | AP35: OOCL INDONESIA/033W | AR35: TPVB20250626002-2 | AS35: COSU6422843430 | AT35: COSU6422843430 | AU35: 62 | AV35: SWB | AW35: 11 | AX35: 75 | AY35: 45857 | AZ35: 45918 | BA35: #N/A | BC35: 45932 | BD35: 2025 | BE35: 10 | BF35: 40 | BG35: 33 | BH35: 660
A36: APR004.01 | B36: Yixing | C36: APR004 | D36: CORE DG | E36: Internal | F36: Arrival Plan-SPTN | G36: SunPower Energy Solutions France SAS | H36: DAP | I36: Local WH | J36: n/a | L36: All | M36: n/a | O36: Check Availability in New Ark | P36: P7 COM S CFP | Q36: GF0700000002 | R36: 553097 | S36: PVM, SPR-P7-555-COM-S, I BF-G M4.3D EVO2Z6NL 1.5KV IT P36 | T36: 555 | U36: 1320 | V36: 0.7326 | W36: 40 | X36: 2 | Y36: COMPLETED | AA36: White glazing | AB36: ±1400mm | AC36: 45842 | AD36: 27 | AE36: POPV251231089 | AF36: 371008641 | AG36: SHANGHAI | AH36: FOS SUR MER | AI36: 45852 | AJ36: 45852 | AK36: 45852 | AL36: 45902 | AM36: 45899 | AN36: 45902 | AO36: DAP | AP36: CMA CGM CEDRUS 0MELBW1MA | AR36: TPVB20250626002-1 | AS36: COSU6422843290 | AT36: COSU6422843290 | AU36: 51 | AV36: SWB | AW36: 4 | AX36: 60 | AY36: 45852 | AZ36: 45902 | BA36: #N/A | BC36: 45916 | BD36: 2025 | BE36: 9 | BF36: 38 | BG36: 33 | BH36: 660
A37: JULY004.04 | B37: Yixing | C37: JULY004 | D37: CORE DG | E37: n/a | F37: n/a | H37: DAP | I37: Local WH - SPIT W81 | J37: n/a | L37: Italy & Adriatics Region | M37: n/a | O37: Check Availability in New Ark | P37: P7 COM S BF IT | Q37: GF0700000766 | R37: 552026 | S37: PVM, SPR-P7-550-COM-S, I BF-G M4.3D EVO2Z6NL 1.5KV IT | T37: 550 | U37: 1980 | V37: 1.089 | W37: 60 | X37: 3 | Y37: COMPLETED | AA37: White glazing | AB37: ±1500mm | AC37: 45844 | AD37: 27 | AE37: POPV251231101 | AF37: 371008646 | AG37: SHANGHAI | AH37: GENOA | AI37: 45857 | AJ37: 45857 | AK37: 45857 | AL37: 45910 | AM37: 45905 | AN37: 45910 | AO37: DAP | AP37: OOCL INDONESIA/033W | AR37: TPVB20250626003 | AS37: COSU6422843570 | AT37: COSU6422843570 | AU37: 54 | AV37: SWB | AW37: 8 | AX37: 66 | AY37: 45857 | AZ37: 45910 | BA37: #N/A | BC37: 45924 | BD37: 2025 | BE37: 9 | BF37: 39 | BG37: 33 | BH37: 660
A38: JULY004.05 | B38: Yixing | C38: JULY004 | D38: CORE DG | E38: n/a | F38: n/a | H38: DAP | I38: Local WH - SPIT W82 | J38: n/a | L38: Italy & Adriatics Region | M38: n/a | O38: Check Availability in New Ark | P38: P7 COM S BF IT | Q38: GF0700000766 | R38: 552026 | S38: PVM, SPR-P7-550-COM-S, I BF-G M4.3D EVO2Z6NL 1.5KV IT | T38: 550 | U38: 3300 | V38: 1.815 | W38: 100 | X38: 5 | Y38: COMPLETED | AA38: White glazing | AB38: ±1500mm | AC38: 45844 | AD38: 27 | AE38: POPV251231097 | AF38: 371008647 | AG38: SHANGHAI | AH38: NAPLES | AI38: 45857 | AJ38: 45857 | AK38: 45857 | AL38: 45912 | AM38: 45907 | AN38: 45912 | AO38: DAP | AP38: OOCL INDONESIA/033W | AR38: TPVB20250626004 | AS38: COSU6422843610 | AT38: COSU6422843610 | AU38: 56 | AV38: SWB | AW38: 8 | AX38: 68 | AY38: 45857 | AZ38: 45912 | BA38: #N/A | BC38: 45926 | BD38: 2025 | BE38: 9 | BF38: 39 | BG38: 33 | BH38: 660
A39: JULY001.01 | B39: Yixing | C39: JULY001 | D39: CORE DG | E39: Internal | F39: Arrival Plan-SPNL | G39: SunPower Energy Solutions France SAS | H39: DAP | I39: Local WH | J39: n/a | L39: All | M39: n/a | O39: Check Availability in New Ark | P39: P7 RES BLK 2.0 | Q39: GF0700000799 | R39: 553146 | S39: PVM, SPR-P7-450-BLK-1500, I BF-G AR-SA M4.4F EVO2Z1NL IT P39 | T39: 450 | U39: 1728 | V39: 0.7776 | W39: 48 | X39: 2 | Y39: COMPLETED | AA39: Black glazing | AB39: ±1200mm | AC39: 45839 | AD39: 27 | AE39: POPV251231096 | AF39: 371008643 | AG39: SHANGHAI | AH39: ROTTERDAM | AI39: 45848 | AJ39: 45848 | AK39: 45848 | AL39: 45882 | AM39: 45881 | AN39: 45882 | AO39: DAP | AP39: COSCO SHIPPING STAR/025W | AR39: TPVB20250626001 | AS39: COSU6422868460 | AT39: COSU6422868460 | AU39: 35 | AV39: SWB | AW39: 2 | AX39: 43 | AY39: 45848 | AZ39: 45882 | BA39: #N/A | BC39: 45896 | BD39: 2025 | BE39: 8 | BF39: 35 | BG39: 36 | BH39: 864
A40: JULY001.02 | B40: Yixing | C40: JULY001 | D40: CORE DG | E40: Internal | F40: Arrival Plan-SPTN | G40: SunPower Energy Solutions France SAS | H40: DAP | I40: Local WH | J40: n/a | L40: All | M40: n/a | O40: Check Availability in New Ark | P40: P7 RES BLK 2.0 | Q40: GF0700000799 | R40: 553146 | S40: PVM, SPR-P7-450-BLK-1500, I BF-G AR-SA M4.4F EVO2Z1NL IT P39 | T40: 450 | U40: 1728 | V40: 0.7776 | W40: 48 | X40: 2 | Y40: COMPLETED | AA40: Black glazing | AB40: ±1200mm | AC40: 45842 | AD40: 27 | AE40: POPV251231008 | AF40: 371008644 | AG40: SHANGHAI | AH40: FOS SUR MER | AI40: 45852 | AJ40: 45852 | AK40: 45852 | AL40: 45902 | AM40: 45899 | AN40: 45902 | AO40: DAP | AP40: CMA CGM CEDRUS 0MELBW1MA | AR40: TPVB20250626002-1 | AS40: COSU6422843290 | AT40: COSU6422843290 | AU40: 51 | AV40: SWB | AW40: 2 | AX40: 60 | AY40: 45852 | AZ40: 45902 | BA40: #N/A | BC40: 45916 | BD40: 2025 | BE40: 9 | BF40: 38 | BG40: 36 | BH40: 864
A41: APR004.02 | B41: Yixing | C41: APR004 | D41: CORE DG | E41: Internal | F41: Arrival Plan-SPTN | G41: SunPower Energy Solutions France SAS | H41: DAP | I41: Local WH | J41: n/a | L41: All | M41: n/a | O41: Check Availability in New Ark | P41: P7 COM S CFP | Q41: GF0700000002 | R41: 553097 | S41: PVM, SPR-P7-555-COM-S, I BF-G M4.3D EVO2Z6NL 1.5KV IT P36 | T41: 555 | U41: 5940 | V41: 3.2967 | W41: 180 | X41: 9 | Y41: COMPLETED | AA41: White glazing | AB41: ±1400mm | AC41: 45851 | AD41: 28 | AE41: POPV251231155 | AF41: 371008672 | AG41: SHANGHAI | AH41: FOS SUR MER | AI41: 45871 | AJ41: 45871 | AK41: 45871 | AL41: 45925 | AM41: 45922 | AN41: 45925 | AO41: DAP | AP41: EVER GIVEN/0709-025W | AR41: TPVB20250703003 | AS41: COSU6424115110 | AT41: COSU6424115110 | AU41: 55 | AV41: SWB | AW41: 4 | AX41: 74 | AY41: 45871 | AZ41: 45925 | BA41: #N/A | BC41: 45939 | BD41: 2025 | BE41: 10 | BF41: 41 | BG41: 33 | BH41: 660
A42: APR003.02 | B42: Yixing | C42: APR003 | D42: CORE DG | E42: Internal | F42: Arrival Plan-SPTN | G42: SunPower Energy Solutions France SAS | H42: DAP | I42: Local WH | J42: n/a | L42: All | M42: n/a | O42: Check Availability in New Ark | P42: P7 COM S CFP | Q42: GF0700000001 | R42: 553098 | S42: PVM, SPR-P7-550-COM-S, I BF-G M4.3D EVO2Z6NL 1.5KV IT P36 | T42: 550 | U42: 1320 | V42: 0.726 | W42: 40 | X42: 2 | Y42: COMPLETED | AA42: White glazing | AB42: ±1400mm | AC42: 45851 | AD42: 28 | AE42: POPV251231152 | AF42: 371008671 | AG42: SHANGHAI | AH42: FOS SUR MER | AI42: 45871 | AJ42: 45871 | AK42: 45871 | AL42: 45925 | AM42: 45922 | AN42: 45925 | AO42: DAP | AP42: EVER GIVEN/0709-025W | AR42: TPVB20250703003 | AS42: COSU6424115110 | AT42: COSU6424115110 | AU42: 55 | AV42: SWB | AW42: 6 | AX42: 74 | AY42: 45871 | AZ42: 45925 | BA42: #N/A | BC42: 45939 | BD42: 2025 | BE42: 10 | BF42: 41 | BG42: 33 | BH42: 660
A43: MAY009.03 | C43: MAY009 | D43: CORE DG | E43: n/a | F43: n/a | H43: DAP | I43: Italy Distrib. | J43: n/a | L43: Italy & Adriatics Region | M43: n/a | O43: Check Availability in New Ark | P43: Shingle | Q43: GF0700000025 | R43: 554541 | S43: TCL-MR460DT182-58NS | T43: 460 | U43: 3456 | V43: 1.58976 | W43: 96 | X43: 4 | Y43: COMPLETED | AA43: White glazing | AB43: ±1200mm | AC43: 45845 | AD43: 28 | AE43: POPV251231066 | AF43: 371008569 | AG43: SHANGHAI | AH43: GENOA | AI43: 45821 | AJ43: 45821 | AK43: 45821 | AL43: 45877 | AM43: 45872 | AN43: 45877 | AO43: DAP | AP43: EVER GENTLE/0704-025W | AR43: TPVB20250529004 | AS43: COSU6419462160 | AT43: COSU6419462160 | AU43: 57 | AV43: SWB | AW43: 6 | AX43: 32 | AY43: 45821 | AZ43: 45877 | BA43: #N/A | BC43: 45891 | BD43: 2025 | BE43: 8 | BF43: 34 | BG43: 36 | BH43: 864
A44: MAY009.04 | C44: MAY009 | D44: CORE DG | E44: n/a | F44: n/a | H44: DAP | I44: Italy Distrib. | J44: n/a | L44: Italy & Adriatics Region | M44: n/a | O44: Check Availability in New Ark | P44: Shingle | Q44: GF0700000025 | R44: 554541 | S44: TCL-MR460DT182-58NS | T44: 460 | U44: 1728 | V44: 0.79488 | W44: 48 | X44: 2 | Y44: COMPLETED | AA44: White glazing | AB44: ±1200mm | AC44: 45845 | AD44: 28 | AE44: POPV251231083 | AF44: 371008570 | AG44: SHANGHAI | AH44: GENOA | AI44: 45821 | AJ44: 45821 | AK44: 45821 | AL44: 45877 | AM44: 45872 | AN44: 45877 | AO44: DAP | AP44: EVER GENTLE/0704-025W | AR44: TPVB20250529005 | AS44: COSU6420615230 | AT44: COSU6420615230 | AU44: 57 | AV44: SWB | AW44: 6 | AX44: 32 | AY44: 45821 | AZ44: 45877 | BA44: #N/A | BC44: 45891 | BD44: 2025 | BE44: 8 | BF44: 34 | BG44: 36 | BH44: 864
A45: MAY016.01 | B45: Tianjin | C45: MAY016 | D45: CORE DG | E45: n/a | F45: n/a | H45: DAP | I45: VP SOLAR | J45: n/a | K45: 19142983 | L45: Italy & Adriatics Region | M45: n/a | O45: Check Availability in New Ark | P45: Half Cut | Q45: GF0700000017 | R45: 554470 | S45: HSM-ND48-DR445 | T45: 445 | U45: 7488 | V45: 3.33216 | W45: 208 | X45: 8 | Y45: COMPLETED | AA45: TRANSPARENT | AB45: ±1200mm | AC45: 45846 | AD45: 28 | AE45: POPV251231166 | AF45: 371008673 | AG45: TIANJIN | AH45: GENOA | AI45: 45852 | AJ45: 45852 | AK45: 45852 | AL45: 45913 | AM45: 45910 | AN45: 45913 | AO45: DAP | AP45: COSCO SHIPPING ARIES 034W | AR45: TPVB20250703005 | AS45: COSU6423839390 | AT45: COSU6423839390 | AU45: 62 | AV45: SWB | AW45: 5 | AX45: 67 | AY45: 45852 | AZ45: 45913 | BA45: #N/A | BC45: 45927 | BD45: 2025 | BE45: 9 | BF45: 39 | BG45: 36 | BH45: 936
A46: MAY019.01 | B46: Lianyungang | C46: MAY019 | D46: CORE DG | E46: n/a | F46: n/a | H46: CIP | I46: Voltaneo | J46: n/a | K46: 46010692 | L46: France and Switzerland Region | M46: n/a | O46: Check Availability in New Ark | P46: Half Cut | Q46: GF0700000071 | R46: 554475 | S46: HSM-ND54-DR500 | T46: 500 | U46: 864 | V46: 0.432 | W46: 24 | X46: 1 | Y46: COMPLETED | AA46: TRANSPARENT | AB46: ±1200mm | AC46: 45848 | AD46: 28 | AE46: POPV251231175 | AF46: 371008674 | AG46: SHANGHAI | AH46: FOS SUR MER | AI46: 45855 | AJ46: 45855 | AK46: 45855 | AL46: 45912 | AM46: 45902 | AN46: 45912 | AO46: CIP | AP46: CMA CGM JULES VERNE 0MELDW1MA | AR46: 46010692 | AS46: COSU6423991700 | AT46: COSU6423991700 | AU46: 58 | AV46: Y | AW46: 12 | AX46: 64 | AY46: 45855 | AZ46: 45912 | BA46: #N/A | BC46: 45926 | BD46: 2025 | BE46: 9 | BF46: 39 | BG46: 36 | BH46: 864
A47: MAY019.02 | B47: Lianyungang | C47: MAY019 | D47: CORE DG | E47: n/a | F47: n/a | H47: CIP | I47: APPROSUD ENVIRONNEMENT | J47: n/a | K47: 46010684 | L47: France and Switzerland Region | M47: n/a | O47: Check Availability in New Ark | P47: Half Cut | Q47: GF0700000071 | R47: 554475 | S47: HSM-ND54-DR500 | T47: 500 | U47: 1728 | V47: 0.864 | W47: 48 | X47: 2 | Y47: COMPLETED | AA47: TRANSPARENT | AB47: ±1200mm | AC47: 45848 | AD47: 28 | AE47: POPV260104107 & POPV260104078 | AF47: 371008675 &371008676 | AG47: SHANGHAI | AH47: FOS SUR MER | AI47: 45855 | AJ47: 45855 | AK47: 45855 | AL47: 45912 | AM47: 45902 | AN47: 45912 | AO47: CIP | AP47: CMA CGM JULES VERNE 0MELDW1MA | AR47: 46010684&46010693 | AS47: COSU6423992580 | AT47: COSU6423992580 | AU47: 58 | AV47: SWB | AW47: 12 | AX47: 64 | AY47: 45855 | AZ47: 45912 | BA47: #N/A | BC47: 45926 | BD47: 2025 | BE47: 9 | BF47: 39 | BG47: 36 | BH47: 864
A48: May020.01 | B48: Lianyungang | C48: May020 | D48: CORE DG | E48: n/a | F48: n/a | H48: DAP | I48: VP SOLAR | J48: n/a | K48: 19142984 | L48: Italy & Adriatics Region | M48: n/a | O48: Check Availability in New Ark | P48: Half Cut | Q48: GF0700000842 | R48: 554476 | S48: HSM-ND54-DR505 | T48: 505 | U48: 864 | V48: 0.43632 | W48: 24 | X48: 1 | Y48: COMPLETED | AA48: TRANSPARENT | AB48: ±1400mm | AC48: 45850 | AD48: 28 | AE48: POPV251231165 | AF48: 371008678 | AG48: SHANGHAI | AH48: GENOA | AI48: 45863 | AJ48: 45863 | AK48: 45863 | AL48: 45913 | AM48: 45910 | AN48: 45913 | AO48: DAP | AP48: EVER GIVEN/0709-025W | AR48: TPVB20250703004 | AS48: COSU6423899400 | AT48: COSU6423899400 | AU48: 51 | AV48: SWB | AW48: 8 | AX48: 63 | AY48: 45863 | AZ48: 45913 | BA48: #N/A | BC48: 45927 | BD48: 2025 | BE48: 9 | BF48: 39 | BG48: 36 | BH48: 864
A49: MAY019.03 | B49: Lianyungang | C49: MAY019 | D49: CORE DG | E49: n/a | F49: n/a | H49: DAP | I49: VP SOLAR | J49: n/a | K49: 19142984 | L49: Italy & Adriatics Region | M49: n/a | O49: Check Availability in New Ark | P49: Half Cut | Q49: GF0700000071 | R49: 554475 | S49: HSM-ND54-DR500 | T49: 500 | U49: 6048 | V49: 3.024 | W49: 168 | X49: 7 | Y49: COMPLETED | AA49: TRANSPARENT | AB49: ±1200mm | AC49: 45850 | AD49: 28 | AE49: POPV251231164 | AF49: 371008677 | AG49: SHANGHAI | AH49: GENOA | AI49: 45863 | AJ49: 45863 | AK49: 45863 | AL49: 45913 | AM49: 45910 | AN49: 45913 | AO49: DAP | AP49: EVER GIVEN/0709-025W | AR49: TPVB20250703004 | AS49: COSU6423899400 | AT49: COSU6423899400 | AU49: 51 | AV49: SWB | AW49: 12 | AX49: 63 | AY49: 45863 | AZ49: 45913 | BA49: #N/A | BC49: 45927 | BD49: 2025 | BE49: 9 | BF49: 39 | BG49: 36 | BH49: 864
A50: APR004.03 | B50: Yixing | C50: APR004 | D50: CORE DG | E50: Internal | F50: Arrival Plan-SPTN | G50: SunPower Energy Solutions France SAS | H50: DAP | I50: Local WH | J50: n/a | L50: All | M50: n/a | O50: Check Availability in New Ark | P50: P7 COM S CFP | Q50: GF0700000002 | R50: 553097 | S50: PVM, SPR-P7-555-COM-S, I BF-G M4.3D EVO2Z6NL 1.5KV IT P36 | T50: 555 | U50: 2640 | V50: 1.4652 | W50: 80 | X50: 4 | Y50: COMPLETED | AA50: White glazing | AB50: ±1400mm | AC50: 45855 | AD50: 29 | AE50: POPV251231161 | AF50: 371008683 | AG50: SHANGHAI | AH50: FOS SUR MER | AI50: 45863 | AJ50: 45863 | AK50: 45863 | AL50: 45912 | AM50: 45908 | AN50: 45912 | AO50: DAP | AP50: CMA CGM UNITY 0MELFW1MA | AR50: TPVB20250710001 | AS50: COSU6424205840 | AT50: COSU6424205840 | AU50: 50 | AV50: SWB | AW50: 4 | AX50: 57 | AY50: 45863 | AZ50: 45912 | BA50: #N/A | BC50: 45926 | BD50: 2025 | BE50: 9 | BF50: 39 | BG50: 33 | BH50: 660
A51: JULY004.07 | B51: Yixing | C51: JULY004 | D51: CORE DG | E51: n/a | F51: n/a | H51: DAP | I51: Local WH - SPIT W82 | J51: n/a | L51: Italy & Adriatics Region | M51: n/a | O51: Check Availability in New Ark | P51: P7 COM S BF IT | Q51: GF0700000766 | R51: 552026 | S51: PVM, SPR-P7-550-COM-S, I BF-G M4.3D EVO2Z6NL 1.5KV IT | T51: 550 | U51: 1320 | V51: 0.726 | W51: 40 | X51: 2 | Y51: COMPLETED | AA51: White glazing | AB51: ±1500mm | AC51: 45855 | AD51: 29 | AE51: POPV251231174 | AF51: 371008687 | AG51: SHANGHAI | AH51: NAPLES | AI51: 45871 | AJ51: 45871 | AK51: 45871 | AL51: 45919 | AM51: 45914 | AN51: 45919 | AO51: DAP | AP51: EVER GIVEN/0709-025W | AR51: TPVB20250710004 | AS51: COSU6424515730 | AT51: COSU6424515730 | AU51: 49 | AV51: SWB | AW51: 8 | AX51: 64 | AY51: 45871 | AZ51: 45919 | BA51: #N/A | BC51: 45933 | BD51: 2025 | BE51: 10 | BF51: 40 | BG51: 33 | BH51: 660
A52: APR004.04 | B52: Yixing | C52: APR004 | D52: CORE DG | E52: Internal | F52: Arrival Plan-SPTN | G52: SunPower Energy Solutions France SAS | H52: DAP | I52: Local WH | J52: n/a | L52: All | M52: n/a | O52: Check Availability in New Ark | P52: P7 COM S CFP | Q52: GF0700000002 | R52: 553097 | S52: PVM, SPR-P7-555-COM-S, I BF-G M4.3D EVO2Z6NL 1.5KV IT P36 | T52: 555 | U52: 2640 | V52: 1.4652 | W52: 80 | X52: 4 | Y52: COMPLETED | AA52: White glazing | AB52: ±1400mm | AC52: 45856 | AD52: 29 | AE52: POPV251231177 | AF52: 371008684 | AG52: SHANGHAI | AH52: FOS SUR MER | AI52: 45863 | AJ52: 45863 | AK52: 45863 | AL52: 45923 | AM52: 45915 | AN52: 45923 | AO52: DAP | AP52: EVER GIVEN/0709-025W | AR52: TPVB20250710002 | AS52: COSU6424515230 | AT52: COSU6424515230 | AU52: 61 | AV52: SWB | AW52: 4 | AX52: 67 | AY52: 45863 | AZ52: 45923 | BA52: #N/A | BC52: 45937 | BD52: 2025 | BE52: 10 | BF52: 41 | BG52: 33 | BH52: 660
A53: JULY003.02 | B53: Yixing | C53: JULY003 | D53: CORE DG | E53: Internal | F53: Arrival Plan-SPTN | G53: SunPower Energy Solutions France SAS | H53: DAP | I53: Local WH - Maisolia | J53: n/a | K53: 46010175 | L53: France and Switzerland Region | M53: n/a | O53: Check Availability in New Ark | P53: P7 RES BLK P | Q53: GF0700000796 | R53: 553120 | S53: PVM, SPR-P7-500-BLK-P, I BF-G AR-SA M4.4F EVO2Z7NL | T53: 500 | U53: 792 | V53: 0.396 | W53: 22 | X53: 1 | Y53: COMPLETED | AA53: Black glazing | AB53: ±1350mm | AC53: 45856 | AD53: 29 | AE53: POPV251231160 | AF53: 371008682 | AG53: SHANGHAI | AH53: FOS SUR MER | AI53: 45863 | AJ53: 45863 | AK53: 45863 | AL53: 45923 | AM53: 45915 | AN53: 45923 | AO53: DAP | AP53: EVER GIVEN/0709-025W | AR53: TPVB20250710002 | AS53: COSU6424515230 | AT53: COSU6424515230 | AU53: 61 | AV53: SWB | AW53: 5 | AX53: 67 | AY53: 45863 | AZ53: 45923 | BA53: #N/A | BC53: 45937 | BD53: 2025 | BE53: 10 | BF53: 41 | BG53: 36 | BH53: 792
A54: MAY016.02 | B54: Tianjin | C54: MAY016 | D54: CORE DG | E54: n/a | F54: n/a | H54: DAP | I54: VP SOLAR | J54: n/a | L54: Italy & Adriatics Region | M54: n/a | O54: Check Availability in New Ark | P54: Half Cut | Q54: GF0700000017 | R54: 554470 | S54: HSM-ND48-DR445 | T54: 445 | U54: 1872 | V54: 0.83304 | W54: 52 | X54: 2 | Y54: COMPLETED | AA54: TRANSPARENT | AB54: ±1200mm | AC54: 45856 | AD54: 29 | AE54: POPV251231154 | AF54: 371008699 | AG54: TIANJIN | AH54: GENOA | AI54: 45864 | AJ54: 45864 | AK54: 45864 | AL54: 45930 | AM54: 45924 | AN54: 45930 | AO54: DAP | AP54: COSCO SHIPPING LEO 033W | AR54: TPVB20250717003 | AS54: COSU6424836960 | AT54: COSU6424836960 | AU54: 67 | AV54: SWB | AW54: 5 | AX54: 74 | AY54: 45864 | AZ54: 45930 | BA54: #N/A | BC54: 45944 | BD54: 2025 | BE54: 10 | BF54: 42 | BG54: 36 | BH54: 936
A55: MAY016.03 | B55: Tianjin | C55: MAY016 | D55: CORE DG | E55: n/a | F55: n/a | H55: DAP | I55: VP Solar | J55: n/a | K55: former VP Solar order | L55: Italy & Adriatics Region | M55: n/a | O55: Check Availability in New Ark | P55: Half Cut | Q55: GF0700000017 | R55: 554470 | S55: HSM-ND48-DR445 | T55: 445 | U55: 4680 | V55: 2.0826 | W55: 130 | X55: 5 | Y55: COMPLETED | AA55: TRANSPARENT | AB55: ±1200mm | AC55: 45857 | AD55: 29 | AE55: POPV251231153 | AF55: 371008700 | AG55: TIANJIN | AH55: GENOA | AI55: 45864 | AJ55: 45864 | AK55: 45864 | AL55: 45930 | AM55: 45924 | AN55: 45930 | AO55: DAP | AP55: COSCO SHIPPING LEO 033W | AR55: TPVB20250717004 | AS55: COSU6424835050 | AT55: COSU6424835050 | AU55: 67 | AV55: SWB | AW55: 5 | AX55: 73 | AY55: 45864 | AZ55: 45930 | BA55: #N/A | BC55: 45944 | BD55: 2025 | BE55: 10 | BF55: 42 | BG55: 36 | BH55: 936
A56: MAY017.01 | B56: Tianjin | C56: MAY017 | D56: CORE DG | E56: n/a | F56: n/a | H56: DAP | I56: VP SOLAR | J56: n/a | K56: 19143010 | L56: Italy & Adriatics Region | M56: n/a | O56: Check Availability in New Ark | P56: Half Cut | Q56: GF0700000078 | R56: 554473 | S56: HSM-ND48-DR450 | T56: 450 | U56: 1872 | V56: 0.8424 | W56: 52 | X56: 2 | Y56: COMPLETED | AA56: TRANSPARENT | AB56: ±1200mm | AC56: 45856 | AD56: 29 | AE56: POPV251231172 | AF56: 371008703 | AG56: TIANJIN | AH56: GENOA | AI56: 45864 | AJ56: 45864 | AK56: 45864 | AL56: 45930 | AM56: 45924 | AN56: 45930 | AO56: DAP | AP56: COSCO SHIPPING LEO 033W | AR56: TPVB20250717003 | AS56: COSU6424836960 | AT56: COSU6424836960_x000D_ | AU56: 67 | AV56: SWB | AW56: 8 | AX56: 74 | AY56: 45864 | AZ56: 45930 | BA56: #N/A | BC56: 45944 | BD56: 2025 | BE56: 10 | BF56: 42 | BG56: 36 | BH56: 936
A57: MAY025.02 | B57: Tianjin | C57: MAY025 | D57: CORE DG | E57: n/a | F57: n/a | H57: CIP | I57: Ecostal Belgium | J57: n/a | K57: 46010730 | L57: Benelux Region | M57: n/a | O57: Check Availability in New Ark | P57: Half Cut | Q57: GF0101010101 | R57: 554236 | S57: HSM-ND48-GR450 | T57: 450 | U57: 1872 | V57: 0.8424 | W57: 52 | X57: 2 | Y57: COMPLETED | AA57: TRANSPARENT | AB57: ±1400mm | AC57: 45857 | AD57: 29 | AE57: POPV260104115 | AF57: 371008710 | AG57: TIANJIN | AH57: ROTTERDAM | AI57: 45864 | AJ57: 45864 | AK57: 45864 | AL57: 45925 | AM57: 45920 | AN57: 45925 | AO57: CIP | AP57: COSCO SHIPPING LEO 033W | AR57: 46010730 | AS57: COSU6424885190 | AT57: COSU6424885190 | AU57: 62 | AV57: Y | AW57: 2 | AX57: 68 | AY57: 45864 | AZ57: 45925 | BA57: #N/A | BC57: 45939 | BD57: 2025 | BE57: 10 | BF57: 41 | BG57: 36 | BH57: 936
A58: MAY017.02 | B58: Tianjin | C58: MAY017 | D58: CORE DG | E58: n/a | F58: n/a | H58: CIP | I58: Forte Solar doo | J58: n/a | K58: 46010725 | L58: Emerging Market | M58: n/a | O58: Check Availability in New Ark | P58: Half Cut | Q58: GF0700000078 | R58: 554473 | S58: HSM-ND48-DR450 | T58: 450 | U58: 936 | V58: 0.4212 | W58: 26 | X58: 1 | Y58: COMPLETED | AA58: TRANSPARENT | AB58: ±1200mm | AC58: 45858 | AD58: 29 | AE58: POPV251231176 | AF58: 371008702 | AG58: TIANJIN | AH58: RIJEKA | AI58: 45864 | AJ58: 45864 | AK58: 45864 | AL58: 45932 | AM58: 45928 | AN58: 45932 | AO58: CIP | AP58: COSCO SHIPPING LEO 033W/CMA CGM OSIRIS 015W | AR58: 46010725 | AS58: COSU6424908540 | AT58: COSU6424908540 | AU58: 69 | AV58: Y | AW58: 8 | AX58: 74 | AY58: 45864 | AZ58: 45932 | BA58: #N/A | BC58: 45946 | BD58: 2025 | BE58: 10 | BF58: 42 | BG58: 36 | BH58: 936
A59: MAY017.03 | B59: Tianjin | C59: MAY017 | D59: CORE DG | E59: Internal | F59: Arrival Plan-SPNL | G59: SunPower Energy Solutions France SAS | H59: DAP | I59: SPTN / SEN Solare Energiesysteme GmbH | J59: n/a | K59: 14130647 | L59: Germany & Austria Region | M59: n/a | O59: Check Availability in New Ark | P59: Half Cut | Q59: GF0700000078 | R59: 554473 | S59: HSM-ND48-DR450 | T59: 450 | U59: 936 | V59: 0.4212 | W59: 26 | X59: 1 | Y59: COMPLETED | AA59: TRANSPARENT | AB59: ±1200mm | AC59: 45857 | AD59: 29 | AE59: POPV251231171 | AF59: 371008701 | AG59: TIANJIN | AH59: ROTTERDAM | AI59: 45864 | AJ59: 45864 | AK59: 45864 | AL59: 45925 | AM59: 45920 | AN59: 45925 | AO59: DAP | AP59: COSCO SHIPPING LEO 033W | AR59: TPVB20250717001 | AS59: COSU6424819590 | AT59: COSU6424819590 | AU59: 62 | AV59: SWB | AW59: 8 | AX59: 68 | AY59: 45864 | AZ59: 45925 | BA59: #N/A | BC59: 45939 | BD59: 2025 | BE59: 10 | BF59: 41 | BG59: 36 | BH59: 936
A60: MAY019.04 | B60: Lianyungang | C60: MAY019 | D60: CORE DG | E60: n/a | F60: n/a | H60: DAP | I60: VP SOLAR | J60: n/a | K60: 19142984 | L60: Italy & Adriatics Region | M60: n/a | O60: Check Availability in New Ark | P60: Half Cut | Q60: GF0700000071 | R60: 554475 | S60: HSM-ND54-DR500 | T60: 500 | U60: 6912 | V60: 3.456 | W60: 192 | X60: 8 | Y60: COMPLETED | AA60: TRANSPARENT | AB60: ±1200mm | AC60: 45855 | AD60: 29 | AE60: POPV251231163 | AF60: 371008685 | AG60: SHANGHAI | AH60: GENOA | AI60: 45871 | AJ60: 45871 | AK60: 45871 | AL60: 45917 | AM60: 45917 | AN60: 45917 | AO60: DAP | AP60: CSCL PACIFIC OCEAN 063W | AR60: TPVB20250710003 | AS60: COSU6424518830 | AT60: COSU6424518830 | AU60: 47 | AV60: SWB | AW60: 12 | AX60: 62 | AY60: 45871 | AZ60: 45917 | BA60: #N/A | BC60: 45931 | BD60: 2025 | BE60: 10 | BF60: 40 | BG60: 36 | BH60: 864
A61: JULY004.06 | B61: Yixing | C61: JULY004 | D61: CORE DG | E61: Internal | F61: Arrival Plan-SPTN | G61: SunPower Energy Solutions France SAS | H61: DAP | I61: Local WH | J61: n/a | L61: All | M61: n/a | O61: Check Availability in New Ark | P61: P7 COM S BF IT | Q61: GF0700000766 | R61: 552026 | S61: PVM, SPR-P7-550-COM-S, I BF-G M4.3D EVO2Z6NL 1.5KV IT | T61: 550 | U61: 660 | V61: 0.363 | W61: 20 | X61: 1 | Y61: COMPLETED | AA61: White glazing | AB61: ±1500mm | AC61: 45863 | AD61: 30 | AE61: POPV251231170 | AF61: 371008686 | AG61: SHANGHAI | AH61: FOS SUR MER | AI61: 45863 | AJ61: 45863 | AK61: 45863 | AL61: 45923 | AM61: 45915 | AN61: 45923 | AO61: DAP | AP61: EVER GIVEN/0709-025W | AR61: TPVB20250710002 | AS61: COSU6424515230 | AT61: COSU6424515230 | AU61: 61 | AV61: SWB | AW61: 8 | AX61: 60 | AY61: 45863 | AZ61: 45923 | BA61: #N/A | BC61: 45937 | BD61: 2025 | BE61: 10 | BF61: 41 | BG61: 33 | BH61: 660
A62: JULY002.03 | B62: Yixing | C62: JULY002 | D62: CORE DG | E62: n/a | F62: n/a | H62: DAP | I62: Local WH | J62: n/a | L62: lberia Region | M62: n/a | O62: Check Availability in New Ark | P62: P7 RES BLK 2.0 | Q62: GF0700000798 | R62: 553145 | S62: PVM, SPR-P7-455-BLK-1500, I BF-G AR-SA M4.4F EVO2Z1NL IT P39 | T62: 455 | U62: 1728 | V62: 0.78624 | W62: 48 | X62: 2 | Y62: COMPLETED | AA62: Black glazing | AB62: ±1200mm | AC62: 45861 | AD62: 30 | AE62: POPV251231179 | AF62: 371008707 | AG62: SHANGHAI | AH62: VALENCIA | AI62: 45870 | AJ62: 45870 | AK62: 45870 | AL62: 45912 | AM62: 45907 | AN62: 45912 | AO62: DAP | AP62: CMA CGM GRACE BAY 0MELHW1MA | AR62: TPVB20250717006 | AS62: COSU6424625040 | AT62: COSU6424625040 | AU62: 43 | AV62: SWB | AW62: 2 | AX62: 51 | AY62: 45870 | AZ62: 45912 | BA62: #N/A | BC62: 45926 | BD62: 2025 | BE62: 9 | BF62: 39 | BG62: 36 | BH62: 864
A63: JULY005.03 | B63: Yixing | C63: JULY005 | D63: CORE DG | E63: n/a | F63: n/a | H63: DAP | I63: Local WH - SPIT W82 | J63: n/a | L63: Italy & Adriatics Region | M63: n/a | O63: Check Availability in New Ark | P63: P7 COM S BF IT | Q63: GF0700000769 | R63: 552045 | S63: PVM, SPR-P7-555-COM-S, I BF-G M4.3D EVO2Z6NL 1.5KV IT | T63: 555 | U63: 1980 | V63: 1.0989 | W63: 60 | X63: 3 | Y63: COMPLETED | AA63: White glazing | AB63: ±1400mm | AC63: 45861 | AD63: 30 | AE63: POPV251231182 | AF63: 371008708 | AG63: SHANGHAI | AH63: NAPLES | AI63: 45871 | AJ63: 45871 | AK63: 45871 | AL63: 45919 | AM63: 45911 | AN63: 45919 | AO63: DAP | AP63: CSCL PACIFIC OCEAN 063W | AR63: TPVB20250717005 | AS63: COSU6424848790 | AT63: COSU6424848790 | AU63: 49 | AV63: SWB | AW63: 11 | AX63: 58 | AY63: 45871 | AZ63: 45919 | BA63: #N/A | BC63: 45933 | BD63: 2025 | BE63: 10 | BF63: 40 | BG63: 33 | BH63: 660
A64: MAY021.01 | B64: Yixing | C64: MAY021 | D64: CORE DG | E64: n/a | F64: n/a | H64: DAP | I64: VP SOLAR | J64: n/a | L64: Italy & Adriatics Region | M64: n/a | O64: Check Availability in New Ark | P64: Half Cut | Q64: GF0700000014 | R64: 554471 | S64: HSM-ND66-GK710 | T64: 710 | U64: 1188 | V64: 0.84348 | W64: 36 | X64: 2 | Y64: COMPLETED | AA64: Redirection Film | AB64: ±1400mm | AC64: 45862 | AD64: 30 | AE64: POPV251231159 | AF64: 371008705 | AG64: SHANGHAI | AH64: GENOA | AI64: 45871 | AJ64: 45871 | AK64: 45871 | AL64: 45917 | AM64: 45917 | AN64: 45917 | AO64: DAP | AP64: CSCL PACIFIC OCEAN 063W | AR64: TPVB20250717002 | AS64: COSU6424848650 | AT64: COSU6424848650 | AU64: 47 | AV64: SWB | AW64: 3 | AX64: 55 | AY64: 45871 | AZ64: 45917 | BA64: #N/A | BC64: 45931 | BD64: 2025 | BE64: 10 | BF64: 40 | BG64: 33 | BH64: 594
A65: MAY021.02 | B65: Yixing | C65: MAY021 | D65: CORE DG | E65: n/a | F65: n/a | H65: DAP | I65: VP SOLAR | J65: n/a | L65: Italy & Adriatics Region | M65: n/a | O65: Check Availability in New Ark | P65: Half Cut | Q65: GF0700000014 | R65: 554471 | S65: HSM-ND66-GK710 | T65: 710 | U65: 2970 | V65: 2.1087 | W65: 90 | X65: 5 | Y65: COMPLETED | AA65: Redirection Film | AB65: ±1400mm | AC65: 45862 | AD65: 30 | AE65: POPV251231169 | AF65: 371008706 | AG65: SHANGHAI | AH65: GENOA | AI65: 45871 | AJ65: 45871 | AK65: 45871 | AL65: 45917 | AM65: 45917 | AN65: 45917 | AO65: DAP | AP65: CSCL PACIFIC OCEAN 063W | AR65: TPVB20250717002 | AS65: COSU6424848650 | AT65: COSU6424848650_x000D_ | AU65: 47 | AV65: SWB | AW65: 3 | AX65: 55 | AY65: 45871 | AZ65: 45917 | BA65: #N/A | BC65: 45931 | BD65: 2025 | BE65: 10 | BF65: 40 | BG65: 33 | BH65: 594
A66: MAY019.08 | B66: Lianyungang | C66: MAY019 | D66: CORE DG | E66: n/a | F66: n/a | H66: DAP | I66: SPIT / ENERGIA ITALIA | J66: n/a | L66: Italy & Adriatics Region | M66: n/a | O66: Check Availability in New Ark | P66: Half Cut | Q66: GF0700000071 | R66: 554475 | S66: HSM-ND54-DR500 | T66: 500 | U66: 4320 | V66: 2.16 | W66: 120 | X66: 5 | Y66: COMPLETED | AA66: TRANSPARENT | AB66: ±1200mm | AC66: 45867 | AD66: 31 | AE66: POPV251231188 | AF66: 371008720 | AG66: SHANGHAI | AH66: NAPLES | AI66: 45877 | AJ66: 45877 | AK66: 45877 | AL66: 45930 | AM66: 45918 | AN66: 45930 | AO66: DAP | AP66: EVER GOODS 0712-032W | AR66: TPVB20250724007 | AS66: COSU6425756250 | AT66: COSU6425756250 | AU66: 54 | AV66: SWB | AW66: 12 | AX66: 63 | AY66: 45877 | AZ66: 45930 | BA66: #N/A | BC66: 45944 | BD66: 2025 | BE66: 10 | BF66: 42 | BG66: 36 | BH66: 864
A67: JULY002.02 | B67: Yixing | C67: JULY002 | D67: CORE DG | E67: n/a | F67: n/a | H67: CIF | I67: NordicSun | J67: n/a | K67: 46010809 | L67: Nordics Region | M67: n/a | O67: Check Availability in New Ark | P67: P7 RES BLK 2.0 | Q67: GF0700000798 | R67: 553145 | S67: PVM, SPR-P7-455-BLK-1500, I BF-G AR-SA M4.4F EVO2Z1NL IT P39 | T67: 455 | U67: 864 | V67: 0.39312 | W67: 24 | X67: 1 | Y67: COMPLETED | AA67: Black glazing | AB67: ±1200mm | AC67: 45866 | AD67: 31 | AE67: POPV251231193 | AF67: 371008727 | AG67: SHANGHAI | AH67: AARHUS | AI67: 45873 | AJ67: 45873 | AK67: 45873 | AL67: 45922 | AM67: 45917 | AN67: 45922 | AO67: CIF | AP67: COSCO SHIPPING LEO 033W | AR67: TPVB20250724008-1 | AS67: COSU6425517330 | AT67: COSU6425517330 | AU67: 50 | AV67: Y | AW67: 2 | AX67: 56 | AY67: 45873 | AZ67: 45922 | BA67: #N/A | BC67: 45936 | BD67: 2025 | BE67: 10 | BF67: 41 | BG67: 36 | BH67: 864
A68: JUNE002.02 | B68: zhuhai | C68: JUNE002 | D68: CORE DG | E68: Internal | F68: Arrival Plan-SPNL | G68: SunPower Energy Solutions France SAS | H68: DAP | I68: SPTN / NATEC Consignment | J68: n/a | L68: Benelux Region | M68: n/a | O68: Check Availability in New Ark | P68: BC | Q68: GF0700000101 | R68: 554320 | S68: HSM-BD54-DA465 | T68: 465 | U68: 962 | V68: 0.44733 | W68: 26 | X68: 1 | Y68: COMPLETED | AA68: Black glazing | AB68: ±1200mm | AC68: 45868 | AD68: 31 | AE68: POPV251231203 | AF68: 371008753 | AG68: ZHUHAI | AH68: ROTTERDAM | AI68: 45871 | AJ68: 45871 | AK68: 45871 | AL68: 45916 | AM68: 45912 | AN68: 45916 | AO68: DAP | AP68: COSCO FORTUNE 080W | AR68: TPVB20250801002 | AS68: COSU6425576700 | AT68: COSU6425576700 | AU68: 46 | AV68: SWB | AW68: 8 | AX68: 48 | AY68: 45871 | AZ68: 45916 | BA68: #N/A | BC68: 45930 | BD68: 2025 | BE68: 9 | BF68: 40 | BG68: 37 | BH68: 962
A69: MAY019.11 | B69: Lianyungang | C69: MAY019 | D69: CORE DG | E69: n/a | F69: n/a | H69: DAP | I69: SPIT / TEST SRL | J69: n/a | L69: Italy & Adriatics Region | M69: n/a | O69: Check Availability in New Ark | P69: Half Cut | Q69: GF0700000071 | R69: 554475 | S69: HSM-ND54-DR500 | T69: 500 | U69: 2592 | V69: 1.296 | W69: 72 | X69: 3 | Y69: COMPLETED | AA69: TRANSPARENT | AB69: ±1200mm | AC69: 45867 | AD69: 31 | AE69: POPV251231187 | AF69: 371008719 | AG69: SHANGHAI | AH69: GENOA | AI69: 45885 | AJ69: 45885 | AK69: 45885 | AL69: 45937 | AM69: 45931 | AN69: 45937 | AO69: DAP | AP69: EVER GOODS 0712-032W | AR69: TPVB20250724006 | AS69: COSU6425754360 | AT69: COSU6425754360 | AU69: 53 | AV69: SWB | AW69: 12 | AX69: 70 | AY69: 45885 | AZ69: 45937 | BA69: #N/A | BC69: 45951 | BD69: 2025 | BE69: 10 | BF69: 43 | BG69: 36 | BH69: 864
A70: JUNE002.04 | B70: zhuhai | C70: JUNE002 | D70: CORE DG | E70: Internal | F70: Arrival Plan-SPNL | G70: SunPower Energy Solutions France SAS | H70: DAP | I70: SPTN / VDH Consignment | J70: n/a | L70: Benelux Region | M70: n/a | O70: Check Availability in New Ark | P70: BC | Q70: GF0700000101 | R70: 554320 | S70: HSM-BD54-DA465 | T70: 465 | U70: 1924 | V70: 0.89466 | W70: 52 | X70: 2 | Y70: COMPLETED | AA70: Black glazing | AB70: ±1200mm | AC70: 45868 | AD70: 31 | AE70: POPV251231202 | AF70: 371008752 | AG70: ZHUHAI | AH70: ROTTERDAM | AI70: 45871 | AJ70: 45871 | AK70: 45871 | AL70: 45916 | AM70: 45912 | AN70: 45916 | AO70: DAP | AP70: COSCO FORTUNE 080W | AR70: TPVB20250801002 | AS70: COSU6425576700 | AT70: COSU6425576700 | AU70: 46 | AV70: SWB | AW70: 8 | AX70: 48 | AY70: 45871 | AZ70: 45916 | BA70: #N/A | BC70: 45930 | BD70: 2025 | BE70: 9 | BF70: 40 | BG70: 37 | BH70: 962
A71: JULY005.04 | B71: Yixing | C71: JULY005 | D71: CORE DG | E71: Internal | F71: Arrival Plan-SPNL | G71: SunPower Energy Solutions France SAS | H71: DAP | I71: Local WH | J71: n/a | L71: All | M71: n/a | O71: Check Availability in New Ark | P71: P7 COM S BF IT | Q71: GF0700000769 | R71: 552045 | S71: PVM, SPR-P7-555-COM-S, I BF-G M4.3D EVO2Z6NL 1.5KV IT | T71: 555 | U71: 1980 | V71: 1.0989 | W71: 60 | X71: 3 | Y71: COMPLETED | AA71: White glazing | AB71: ±1400mm | AC71: 45870 | AD71: 31 | AE71: POPV251231196 | AF71: 371008737 | AG71: SHANGHAI | AH71: ROTTERDAM | AI71: 45875 | AJ71: 45875 | AK71: 45875 | AL71: 45919 | AM71: 45914 | AN71: 45919 | AO71: DAP | AP71: COSCO FORTUNE 080W | AR71: TPVB20250724001-2 | AS71: COSU6426275420 | AT71: COSU6426275420 | AU71: 45 | AV71: SWB | AW71: 11 | AX71: 49 | AY71: 45875 | AZ71: 45919 | BA71: #N/A | BC71: 45933 | BD71: 2025 | BE71: 10 | BF71: 40 | BG71: 33 | BH71: 660
A72: JULY005.05 | B72: Yixing | C72: JULY005 | D72: CORE DG | E72: Internal | F72: Arrival Plan-SPTN | G72: SunPower Energy Solutions France SAS | H72: DAP | I72: Local WH | J72: n/a | L72: All | M72: n/a | O72: Check Availability in New Ark | P72: P7 COM S BF IT | Q72: GF0700000769 | R72: 552045 | S72: PVM, SPR-P7-555-COM-S, I BF-G M4.3D EVO2Z6NL 1.5KV IT | T72: 555 | U72: 1980 | V72: 1.0989 | W72: 60 | X72: 3 | Y72: COMPLETED | AA72: White glazing | AB72: ±1400mm | AC72: 45867 | AD72: 31 | AE72: POPV251231191 | AF72: 371008723 | AG72: SHANGHAI | AH72: FOS SUR MER | AI72: 45878 | AJ72: 45878 | AK72: 45878 | AL72: 45926 | AM72: 45919 | AN72: 45926 | AO72: DAP | AP72: CMA CGM IGUACU 0MELJW1MA | AR72: TPVB20250724002 | AS72: COSU6425546030 | AT72: COSU6425546030 | AU72: 49 | AV72: SWB | AW72: 11 | AX72: 59 | AY72: 45878 | AZ72: 45926 | BA72: #N/A | BC72: 45940 | BD72: 2025 | BE72: 10 | BF72: 41 | BG72: 33 | BH72: 660
A73: JULY005.06 | B73: Yixing | C73: JULY005 | D73: CORE DG | E73: Internal | F73: Arrival Plan-SPNL | G73: SunPower Energy Solutions France SAS | H73: DAP | I73: Local WH | J73: n/a | L73: All | M73: n/a | O73: Check Availability in New Ark | P73: P7 COM S BF IT | Q73: GF0700000769 | R73: 552045 | S73: PVM, SPR-P7-555-COM-S, I BF-G M4.3D EVO2Z6NL 1.5KV IT | T73: 555 | U73: 660 | V73: 0.3663 | W73: 20 | X73: 1 | Y73: COMPLETED | AA73: White glazing | AB73: ±1400mm | AC73: 45870 | AD73: 31 | AE73: POPV251231195 | AF73: 371008736 | AG73: SHANGHAI | AH73: ROTTERDAM | AI73: 45875 | AJ73: 45875 | AK73: 45875 | AL73: 45916 | AM73: 45912 | AN73: 45916 | AO73: DAP | AP73: EVER ARIA1360-012W | AR73: TPVB20250724001-1 | AS73: COSU6426300390 | AT73: COSU6426300390 | AU73: 42 | AV73: SWB | AW73: 11 | AX73: 46 | AY73: 45875 | AZ73: 45916 | BA73: #N/A | BC73: 45930 | BD73: 2025 | BE73: 9 | BF73: 40 | BG73: 33 | BH73: 660
A74: APR003 | B74: Yixing | C74: Main Line | D74: CORE DG | E74: Internal | F74: Arrival Plan-SPTN | G74: SunPower Energy Solutions France SAS | H74: DAP | I74: Local WH | J74: n/a | L74: All | M74: n/a | O74: Check Availability in New Ark | P74: P7 COM S CFP | Q74: GF0700000001 | R74: 553098 | S74: PVM, SPR-P7-550-COM-S, I BF-G M4.3D EVO2Z6NL 1.5KV IT P36 | T74: 550 | U74: 660 | V74: 0.363 | W74: 20 | X74: 1 | Y74: COMPLETED | AA74: White glazing | AB74: ±1400mm | AC74: 45866 | AD74: 31 | AE74: POPV251231180 | AF74: 371008714 | AG74: SHANGHAI | AH74: FOS SUR MER | AI74: 45885 | AJ74: 45885 | AK74: 45885 | AL74: 45942 | AM74: 45936 | AN74: 45942 | AO74: DAP | AP74: EVER GOODS 0712-032W | AR74: TPVB20250724003 | AS74: COSU6425762990 | AT74: COSU6425762990 | AU74: 58 | AV74: SWB | AW74: 39 | AX74: 76 | AY74: 45885 | AZ74: 45942 | BA74: #N/A | BC74: 45956 | BD74: 2025 | BE74: 10 | BF74: 43 | BG74: 33 | BH74: 660
A75: APR004 | B75: Yixing | C75: Main Line | D75: CORE DG | E75: Internal | F75: Arrival Plan-SPTN | G75: SunPower Energy Solutions France SAS | H75: DAP | I75: Local WH | J75: n/a | L75: All | M75: n/a | O75: Check Availability in New Ark | P75: P7 COM S CFP | Q75: GF0700000002 | R75: 553097 | S75: PVM, SPR-P7-555-COM-S, I BF-G M4.3D EVO2Z6NL 1.5KV IT P36 | T75: 555 | U75: 4448 | V75: 2.46864 | W75: 134.78788 | X75: 6.7393939 | Y75: COMPLETED | AA75: White glazing | AB75: ±1400mm | AC75: 45866 | AD75: 31 | AE75: POPV251231183 | AF75: 371008715 | AG75: SHANGHAI | AH75: FOS SUR MER | AI75: 45885 | AJ75: 45885 | AK75: 45885 | AL75: 45942 | AM75: 45936 | AN75: 45942 | AO75: DAP | AP75: EVER GOODS 0712-032W | AR75: TPVB20250724003 | AS75: COSU6425762990 | AT75: COSU6425762990 | AU75: 58 | AV75: SWB | AW75: 39 | AX75: 76 | AY75: 45885 | AZ75: 45942 | BA75: #N/A | BC75: 45956 | BD75: 2025 | BE75: 10 | BF75: 43 | BG75: 33 | BH75: 660
A76: MAY020.02 | B76: Lianyungang | C76: MAY020 | D76: CORE DG | E76: n/a | F76: n/a | H76: DAP | I76: VP SOLAR | J76: n/a | K76: 19143011 | L76: Italy & Adriatics Region | M76: n/a | O76: Check Availability in New Ark | P76: Half Cut | Q76: GF0700000842 | R76: 554476 | S76: HSM-ND54-DR505 | T76: 505 | U76: 864 | V76: 0.43632 | W76: 24 | X76: 1 | Y76: COMPLETED | AA76: TRANSPARENT | AB76: ±1400mm | AC76: 45866 | AD76: 31 | AE76: POPV251231189 | AF76: 371008721 | AG76: SHANGHAI | AH76: GENOA | AI76: 45885 | AJ76: 45885 | AK76: 45885 | AL76: 45937 | AM76: 45931 | AN76: 45937 | AO76: DAP | AP76: EVER GOODS 0712-032W | AR76: TPVB20250724005 | AS76: COSU6425553050 | AT76: COSU6425553050 | AU76: 53 | AV76: SWB | AW76: 8 | AX76: 71 | AY76: 45885 | AZ76: 45937 | BA76: #N/A | BC76: 45951 | BD76: 2025 | BE76: 10 | BF76: 43 | BG76: 36 | BH76: 864
A77: MAY025.01 | B77: Tianjin | C77: MAY025 | D77: CORE DG | E77: n/a | F77: n/a | H77: CIF | I77: NordicSun | J77: n/a | K77: 46010809 | L77: Nordics Region | M77: n/a | O77: Check Availability in New Ark | P77: Half Cut | Q77: GF0101010101 | R77: 554236 | S77: HSM-ND48-GR450 | T77: 450 | U77: 9360 | V77: 4.212 | W77: 260 | X77: 10 | Y77: COMPLETED | AA77: TRANSPARENT | AB77: ±1400mm | AC77: 45868 | AD77: 31 | AE77: POPV251231186 | AF77: 371008718 | AG77: TIANJIN | AH77: AARHUS | AI77: 45877 | AJ77: 45877 | AK77: 45877 | AL77: 45947 | AM77: 45929 | AN77: 45947 | AO77: CIF | AP77: EVER MEGA/0773-006W | AR77: TPVB20250724008-2 | AS77: COSU6425781620 | AT77: COSU6425781620 | AU77: 71 | AV77: Y | AW77: 2 | AX77: 79 | AY77: 45877 | AZ77: 45947 | BA77: #N/A | BC77: 45961 | BD77: 2025 | BE77: 10 | BF77: 44 | BG77: 36 | BH77: 936
A78: MAY020.03 | B78: Lianyungang | C78: MAY020 | D78: CORE DG | E78: n/a | F78: n/a | H78: DAP | I78: SPIT / ENERGIA ITALIA | J78: n/a | L78: Italy & Adriatics Region | M78: n/a | O78: Check Availability in New Ark | P78: Half Cut | Q78: GF0700000842 | R78: 554476 | S78: HSM-ND54-DR505 | T78: 505 | U78: 1728 | V78: 0.87264 | W78: 48 | X78: 2 | Y78: COMPLETED | AA78: TRANSPARENT | AB78: ±1400mm | AC78: 45867 | AD78: 31 | AE78: POPV251231190 | AF78: 371008722 | AG78: SHANGHAI | AH78: NAPLES | AI78: 45877 | AJ78: 45877 | AK78: 45877 | AL78: 45930 | AM78: 45918 | AN78: 45930 | AO78: DAP | AP78: EVER GOODS 0712-032W | AR78: TPVB20250724007 | AS78: COSU6425756250 | AT78: COSU6425756250_x000D_ | AU78: 54 | AV78: SWB | AW78: 8 | AX78: 63 | AY78: 45877 | AZ78: 45930 | BA78: #N/A | BC78: 45944 | BD78: 2025 | BE78: 10 | BF78: 42 | BG78: 36 | BH78: 864
A79: MAY008.02 | B79: Yixing | C79: MAY008 | D79: CORE DG | E79: n/a | F79: n/a | H79: DAP | I79: SPIT / MARINI-PANDOLFI | J79: n/a | K79: 19142931 | L79: Italy & Adriatics Region | M79: n/a | O79: Check Availability in New Ark | P79: Shingle | Q79: GF0700001780 | R79: 554431 | S79: TCL-MR455DT182-58NS | T79: 455 | U79: 864 | V79: 0.39312 | W79: 24 | X79: 1 | Y79: COMPLETED | AA79: White glazing | AB79: ±1400mm | AC79: 45867 | AD79: 31 | AE79: POPV251231184 | AF79: 371008716 | AG79: SHANGHAI | AH79: GENOA | AI79: 45885 | AJ79: 45885 | AK79: 45885 | AL79: 45937 | AM79: 45931 | AN79: 45937 | AO79: DAP | AP79: EVER GOODS 0712-032W | AR79: TPVB20250724004 | AS79: COSU6425637820 | AT79: COSU6425637820_x000D_ | AU79: 53 | AV79: SWB | AW79: 4 | AX79: 70 | AY79: 45885 | AZ79: 45937 | BA79: #N/A | BC79: 45951 | BD79: 2025 | BE79: 10 | BF79: 43 | BG79: 36 | BH79: 864
A80: MAY009 | B80: Yixing | C80: Main Line | D80: CORE DG | E80: n/a | F80: n/a | H80: DAP | I80: SPIT / ALEMPOWER SRL | J80: n/a | K80: 19143026 | L80: Italy & Adriatics Region | M80: n/a | O80: Check Availability in New Ark | P80: Shingle | Q80: GF0700000025 | R80: 554541 | S80: TCL-MR460DT182-58NS | T80: 460 | U80: 864 | V80: 0.39744 | W80: 24 | X80: 1 | Y80: COMPLETED | AA80: White glazing | AB80: ±1200mm | AC80: 45867 | AD80: 31 | AE80: POPV251231185 | AF80: 371008717 | AG80: SHANGHAI | AH80: GENOA | AI80: 45885 | AJ80: 45885 | AK80: 45885 | AL80: 45937 | AM80: 45931 | AN80: 45937 | AO80: DAP | AP80: EVER GOODS 0712-032W | AR80: TPVB20250724004 | AS80: COSU6425637820 | AT80: COSU6425637820 | AU80: 53 | AV80: SWB | AW80: 39 | AX80: 70 | AY80: 45885 | AZ80: 45937 | BA80: #N/A | BC80: 45951 | BD80: 2025 | BE80: 10 | BF80: 43 | BG80: 36 | BH80: 864
A81: JUNE001.01 | B81: zhuhai | C81: JUNE001 | D81: CORE DG | E81: n/a | F81: n/a | H81: DAP | I81: SPGB / Bimble Solar | J81: n/a | K81: 20519113 | L81: UK Region | M81: n/a | O81: Check Availability in New Ark | P81: BC | Q81: GF0700000075 | R81: 554319 | S81: HSM-BD54-DA460 | T81: 460 | U81: 962 | V81: 0.44252 | W81: 26 | X81: 1 | Y81: COMPLETED | AA81: Black glazing | AB81: ±1400mm | AC81: 45868 | AD81: 31 | AE81: POPV251231201 | AF81: 371008751 | AG81: ZHUHAI | AH81: FELIXSTOWE | AI81: 45875 | AJ81: 45875 | AK81: 45875 | AL81: 45923 | AM81: 45917 | AN81: 45923 | AO81: DAP | AP81: EVER ARIA 1360-012W | AR81: TPVB20250801001 | AS81: COSU6425832690 | AT81: COSU6425832690 | AU81: 49 | AV81: Y | AW81: 9 | AX81: 55 | AY81: 45875 | AZ81: 45923 | BA81: #N/A | BC81: 45937 | BD81: 2025 | BE81: 10 | BF81: 41 | BG81: 37 | BH81: 962
A82: AUG002.01 | B82: Yixing | C82: AUG002 | D82: CORE DG | E82: n/a | F82: n/a | H82: DAP | I82: Local WH - SPIT W82 | J82: n/a | L82: Italy & Adriatics Region | M82: n/a | O82: Check Availability in New Ark | P82: P7 RES BLK 2.0 | Q82: GF0700000798 | R82: 553145 | S82: PVM, SPR-P7-455-BLK-1500, I BF-G AR-SA M4.4F EVO2Z1NL IT P39 | T82: 455 | U82: 1728 | V82: 0.78624 | W82: 48 | X82: 2 | Y82: COMPLETED | AA82: Black glazing | AB82: ±1200mm | AC82: 45877 | AD82: 32 | AE82: POPV251231210 | AF82: 371008760 | AG82: SHANGHAI | AH82: NAPLES | AI82: 45885 | AJ82: 45885 | AK82: 45885 | AL82: 45938 | AM82: 45925 | AN82: 45938 | AO82: DAP | AP82: OOCL SCANDINAVIA 034W | AR82: TPVB20250801009 | AS82: COSU6426810780 | AT82: COSU6426810780 | AU82: 54 | AV82: SWB | AW82: 6 | AX82: 61 | AY82: 45885 | AZ82: 45938 | BA82: #N/A | BC82: 45952 | BD82: 2025 | BE82: 10 | BF82: 43 | BG82: 36 | BH82: 864
A83: AUG002.02 | B83: Yixing | C83: AUG002 | D83: CORE DG | E83: Internal | F83: Arrival Plan-SPNL | G83: SunPower Energy Solutions France SAS | H83: DAP | I83: Local WH | J83: n/a | L83: All | M83: n/a | O83: Check Availability in New Ark | P83: P7 RES BLK 2.0 | Q83: GF0700000798 | R83: 553145 | S83: PVM, SPR-P7-455-BLK-1500, I BF-G AR-SA M4.4F EVO2Z1NL IT P39 | T83: 455 | U83: 2592 | V83: 1.17936 | W83: 72 | X83: 3 | Y83: COMPLETED | AA83: Black glazing | AB83: ±1200mm | AC83: 45875 | AD83: 32 | AE83: POPV251231207 | AF83: 371008757 | AG83: SHANGHAI | AH83: ROTTERDAM | AI83: 45879 | AJ83: 45879 | AK83: 45879 | AL83: 45931 | AM83: 45919 | AN83: 45931 | AO83: DAP | AP83: CSCL STAR 088W | AR83: TPVB20250801003 | AS83: COSU6426686290 | AT83: COSU6426686290 | AU83: 53 | AV83: SWB | AW83: 6 | AX83: 56 | AY83: 45879 | AZ83: 45931 | BA83: #N/A | BC83: 45945 | BD83: 2025 | BE83: 10 | BF83: 42 | BG83: 36 | BH83: 864
A84: AUG002.03 | B84: Yixing | C84: AUG002 | D84: CORE DG | E84: Internal | F84: Arrival Plan-SPTN | G84: SunPower Energy Solutions France SAS | H84: DAP | I84: Local WH | J84: n/a | L84: All | M84: n/a | O84: Check Availability in New Ark | P84: P7 RES BLK 2.0 | Q84: GF0700000798 | R84: 553145 | S84: PVM, SPR-P7-455-BLK-1500, I BF-G AR-SA M4.4F EVO2Z1NL IT P39 | T84: 455 | U84: 2592 | V84: 1.17936 | W84: 72 | X84: 3 | Y84: COMPLETED | AA84: Black glazing | AB84: ±1200mm | AC84: 45879 | AD84: 32 | AE84: POPV251231208 | AF84: 371008758 | AG84: SHANGHAI | AH84: FOS SUR MER | AI84: 45884 | AJ84: 45884 | AK84: 45884 | AL84: 45942 | AN84: 45942 | AO84: DAP | AP84: OOCL SCANDINAVIA / 02MLFW1MA | AR84: TPVB20250801004 | AS84: CMDUCHN2603544 | AT84: CHN2603544 | AU84: 59 | AV84: SWB | AW84: 6 | AX84: 63 | AY84: 45884 | AZ84: 45942 | BA84: #N/A | BC84: 45956 | BD84: 2025 | BE84: 10 | BF84: 43 | BG84: 36 | BH84: 864
A85: AUG002.06 | B85: Yixing | C85: AUG002 | D85: CORE DG | E85: Internal | F85: Arrival Plan-SPTN | G85: SunPower Energy Solutions France SAS | H85: DAP | I85: Local WH | J85: n/a | L85: All | M85: n/a | O85: Check Availability in New Ark | P85: P7 RES BLK 2.0 | Q85: GF0700000798 | R85: 553145 | S85: PVM, SPR-P7-455-BLK-1500, I BF-G AR-SA M4.4F EVO2Z1NL IT P39 | T85: 455 | U85: 864 | V85: 0.39312 | W85: 24 | X85: 1 | Y85: COMPLETED | AA85: Black glazing | AB85: ±1200mm | AC85: 45876 | AD85: 32 | AE85: POPV251231209 | AF85: 371008759 | AG85: TIANJIN | AH85: FOS SUR MER | AI85: 45880 | AJ85: 45880 | AK85: 45880 | AL85: 45957 | AM85: 45950 | AN85: 45957 | AO85: DAP | AP85: COSCO SHIPPING SAGITTARIUS /031W | AR85: TPVB20250801012-2 | AS85: COSU6426075020 | AT85: COSU6426075020 | AU85: 78 | AV85: SWB | AW85: 6 | AX85: 81 | AY85: 45880 | AZ85: 45957 | BA85: #N/A | BC85: 45971 | BD85: 2025 | BE85: 11 | BF85: 46 | BG85: 36 | BH85: 864
A86: AUG006.01 | B86: Yixing | C86: AUG006 | D86: CORE DG | E86: Internal | F86: Arrival Plan-SPTN | G86: SunPower Energy Solutions France SAS | H86: DAP | I86: Local WH | J86: n/a | L86: All | M86: n/a | O86: Check Availability in New Ark | P86: P7 COM S CFP | Q86: GF0700000001 | R86: 553098 | S86: PVM, SPR-P7-550-COM-S, I BF-G M4.3D EVO2Z6NL 1.5KV IT P36 | T86: 550 | U86: 1320 | V86: 0.726 | W86: 40 | X86: 2 | Y86: COMPLETED | AA86: White glazing | AB86: ±1400mm | AC86: 45879 | AD86: 32 | AE86: POPV251231229 | AF86: 371008786 | AG86: SHANGHAI | AH86: FOS SUR MER | AI86: 45884 | AJ86: 45884 | AK86: 45884 | AL86: 45942 | AN86: 45942 | AO86: DAP | AP86: OOCL SCANDINAVIA / 02MLFW1MA | AR86: TPVB20250801004 | AS86: CMDUCHN2603544 | AT86: CHN2603544 | AU86: 59 | AV86: SWB | AW86: 1 | AX86: 63 | AY86: 45884 | AZ86: 45942 | BA86: #N/A | BC86: 45956 | BD86: 2025 | BE86: 10 | BF86: 43 | BG86: 33 | BH86: 660
A87: AUG007.01 | B87: Yixing | C87: AUG007 | D87: CORE DG | E87: Internal | F87: Arrival Plan-SPTN | G87: SunPower Energy Solutions France SAS | H87: DAP | I87: Local WH | J87: n/a | L87: All | M87: n/a | O87: Check Availability in New Ark | P87: P7 COM S CFP | Q87: GF0700000002 | R87: 553097 | S87: PVM, SPR-P7-555-COM-S, I BF-G M4.3D EVO2Z6NL 1.5KV IT P36 | T87: 555 | U87: 3300 | V87: 1.8315 | W87: 100 | X87: 5 | Y87: COMPLETED | AA87: White glazing | AB87: ±1400mm | AC87: 45876 | AD87: 32 | AE87: POPV251231231 | AF87: 371008788 | AG87: TIANJIN | AH87: FOS SUR MER | AI87: 45880 | AJ87: 45880 | AK87: 45880 | AL87: 45957 | AM87: 45950 | AN87: 45957 | AO87: DAP | AP87: COSCO SHIPPING SAGITTARIUS /031W | AR87: TPVB20250801012-1 | AS87: COSU6426074980 | AT87: COSU6426074980 | AU87: 78 | AV87: SWB | AW87: 2 | AX87: 81 | AY87: 45880 | AZ87: 45957 | BA87: #N/A | BC87: 45971 | BD87: 2025 | BE87: 11 | BF87: 46 | BG87: 33 | BH87: 660
A88: MAY008.03 | B88: Yixing | C88: MAY008 | D88: CORE DG | E88: n/a | F88: n/a | H88: DAP | I88: SPIT / TEST SRL | J88: n/a | K88: 19143015 | L88: Italy & Adriatics Region | M88: n/a | O88: Check Availability in New Ark | P88: Shingle | Q88: GF0700001780 | R88: 554431 | S88: TCL-MR455DT182-58NS | T88: 455 | U88: 864 | V88: 0.39312 | W88: 24 | X88: 1 | Y88: COMPLETED | AA88: White glazing | AB88: ±1400mm | AC88: 45877 | AD88: 32 | AE88: POPV251231197 | AF88: 371008746 | AG88: SHANGHAI | AH88: GENOA | AI88: 45885 | AJ88: 45885 | AK88: 45885 | AL88: 45937 | AM88: 45931 | AN88: 45937 | AO88: DAP | AP88: OOCL SCANDINAVIA 034W | AR88: TPVB20250801008 | AS88: COSU6426810560 | AT88: COSU6426810560_x000D_ | AU88: 53 | AV88: SWB | AW88: 4 | AX88: 60 | AY88: 45885 | AZ88: 45937 | BA88: #N/A | BC88: 45951 | BD88: 2025 | BE88: 10 | BF88: 43 | BG88: 36 | BH88: 864
A89: JULY005.09 | B89: Yixing | C89: JULY005 | D89: CORE DG | E89: Internal | F89: Arrival Plan-SPTN | G89: SunPower Energy Solutions France SAS | H89: DAP | I89: Local WH | J89: n/a | L89: All | M89: n/a | O89: Check Availability in New Ark | P89: P7 COM S BF IT | Q89: GF0700000769 | R89: 552045 | S89: PVM, SPR-P7-555-COM-S, I BF-G M4.3D EVO2Z6NL 1.5KV IT | T89: 555 | U89: 1980 | V89: 1.0989 | W89: 60 | X89: 3 | Y89: COMPLETED | AA89: White glazing | AB89: ±1400mm | AC89: 45876 | AD89: 32 | AE89: POPV251231218 | AF89: 371008775 | AG89: SHANGHAI | AH89: FOS SUR MER | AI89: 45892 | AJ89: 45892 | AK89: 45892 | AL89: 45949 | AM89: 45943 | AN89: 45949 | AO89: DAP | AP89: COSCO SHIPPING TAURUS 034W | AR89: TPVB20250801013 | AS89: COSU6426635150 | AT89: COSU6426635150 | AU89: 58 | AV89: SWB | AW89: 11 | AX89: 73 | AY89: 45892 | AZ89: 45949 | BA89: #N/A | BC89: 45963 | BD89: 2025 | BE89: 11 | BF89: 44 | BG89: 33 | BH89: 660
A90: MAY019.05 | B90: Lianyungang | C90: MAY019 | D90: CORE DG | E90: n/a | F90: n/a | H90: FOB | I90: UAB Elmitra | J90: n/a | K90: 46010775 | L90: Emerging Market | M90: n/a | O90: Check Availability in New Ark | P90: Half Cut | Q90: GF0700000071 | R90: 554475 | S90: HSM-ND54-DR500 | T90: 500 | U90: 2592 | V90: 1.296 | W90: 72 | X90: 3 | Y90: COMPLETED | AA90: TRANSPARENT | AB90: ±1200mm | AC90: 45877 | AD90: 32 | AE90: POPV251231200 | AF90: 371008750 | AG90: SHANGHAI | AH90: KLAIPEDA | AI90: 45885 | AJ90: 45885 | AK90: 45885 | AL90: 45943 | AN90: 45943 | AO90: FOB | AP90: MARCHEN MAERSK 533W | AR90: 46010775 | AS90: 1068398706 | AT90: HLCUSHA2507HAMP9 | AU90: 59 | AV90: Y | AW90: 12 | AX90: 66 | AY90: 45885 | AZ90: 45943 | BA90: #N/A | BC90: 45957 | BD90: 2025 | BE90: 10 | BF90: 44 | BG90: 36 | BH90: 864
A91: MAY007.01 | B91: Yixing | C91: MAY007 | D91: CORE DG | E91: n/a | F91: n/a | H91: CIP | I91: LM Eight | J91: n/a | L91: Iberia Region | M91: n/a | O91: Not Available | P91: Shingle | Q91: GF0700000877 | R91: 555076 | S91: HSM-GKA-NM720 | T91: 720 | U91: 1188 | V91: 0.85536 | W91: 36 | X91: 2 | Y91: COMPLETED | AA91: White glazing | AB91: ±1400mm | AC91: 45877 | AD91: 32 | AE91: n/a - 2025 legacy | AF91: TPVO2025072719 | AG91: SHANGHAI | AH91: VALENCIA | AI91: 45885 | AJ91: 45885 | AK91: 45885 | AL91: 45939 | AM91: 45925 | AN91: 45939 | AO91: CIF | AP91: EVER LENIENT 063W | AR91: TPVB20250801010-3 | AS91: COSU6426639770 | AT91: COSU6426639770 | AU91: 55 | AV91: Y | AW91: 9 | AX91: 62 | AY91: 45885 | AZ91: 45939 | BA91: #N/A | BC91: 45953 | BD91: 2025 | BE91: 10 | BF91: 43 | BG91: 33 | BH91: 594
A92: MAY015.06 | B92: Yixing | C92: MAY015 | D92: CORE DG | E92: n/a | F92: n/a | H92: CIP | I92: LM Eight | J92: n/a | L92: Iberia Region | M92: n/a | O92: Not Available | P92: Half Cut | Q92: GF0101010095 | R92: 554245 | S92: HSM-ND66-GR620 | T92: 620 | U92: 2880 | V92: 1.7856 | W92: 80 | X92: 4 | Y92: COMPLETED | AA92: White glazing | AB92: ±1200mm | AC92: 45879 | AD92: 32 | AE92: n/a - 2025 legacy | AF92: TPVO2025072719 | AG92: SHANGHAI | AH92: VALENCIA | AI92: 45885 | AJ92: 45885 | AK92: 45885 | AL92: 45953 | AN92: 45953 | AO92: CIF | AP92: OOCL SCANDINAVIA / 02MLFW1MA | AR92: TPVB20250801010-2 | AS92: CHN2603645 | AT92: CHN2603645 | AU92: 69 | AV92: Y | AW92: 8 | AX92: 74 | AY92: 45885 | AZ92: 45953 | BA92: #N/A | BC92: 45967 | BD92: 2025 | BE92: 11 | BF92: 45 | BG92: 36 | BH92: 720
A93: MAY014.03 | B93: Yixing | C93: MAY014 | D93: CORE DG | E93: n/a | F93: n/a | H93: DAP | I93: SPIT / TEST SRL | J93: n/a | K93: 19143078 | L93: Italy & Adriatics Region | M93: n/a | O93: Check Availability in New Ark | P93: Half Cut | Q93: GF0101010094 | R93: 554244 | S93: HSM-ND66-GR615 | T93: 615 | U93: 720 | V93: 0.4428 | W93: 20 | X93: 1 | Y93: COMPLETED | AA93: White glazing | AB93: ±1200mm | AC93: 45877 | AD93: 32 | AE93: POPV251231198 | AF93: 371008747 | AG93: SHANGHAI | AH93: GENOA | AI93: 45885 | AJ93: 45885 | AK93: 45885 | AL93: 45937 | AM93: 45931 | AN93: 45937 | AO93: DAP | AP93: OOCL SCANDINAVIA 034W | AR93: TPVB20250801008 | AS93: COSU6426810560 | AT93: COSU6426810560 | AU93: 53 | AV93: SWB | AW93: 3 | AX93: 60 | AY93: 45885 | AZ93: 45937 | BA93: #N/A | BC93: 45951 | BD93: 2025 | BE93: 10 | BF93: 43 | BG93: 36 | BH93: 720
A94: MAY017.04 | B94: Tianjin | C94: MAY017 | D94: CORE DG | E94: n/a | F94: n/a | H94: DAP | I94: Local WH - SPIT W81 | J94: n/a | K94: wrong product | L94: Italy & Adriatics Region | M94: n/a | O94: Check Availability in New Ark | P94: Half Cut | Q94: GF0700000078 | R94: 554473 | S94: HSM-ND48-DR450 | T94: 450 | U94: 1872 | V94: 0.8424 | W94: 52 | X94: 2 | Y94: COMPLETED | AA94: TRANSPARENT | AB94: ±1200mm | AC94: 45876 | AD94: 32 | AE94: POPV260104108 | AF94: empty | AG94: TIANJIN | AH94: GENOA | AI94: 45880 | AJ94: 45880 | AK94: 45880 | AL94: 45953 | AM94: 45945 | AN94: 45953 | AO94: DAP | AP94: COSCO SHIPPING SAGITTARIUS /031W | AR94: TPVB20250801007 | AS94: COSU6426075230 | AT94: COSU6426075230 | AU94: 74 | AV94: SWB | AW94: 8 | AX94: 77 | AY94: 45880 | AZ94: 45953 | BA94: #N/A | BC94: 45967 | BD94: 2025 | BE94: 11 | BF94: 45 | BG94: 36 | BH94: 936
A95: JULY003.03 | B95: Yixing | C95: JULY003 | D95: CORE DG | E95: n/a | F95: n/a | H95: CIP | I95: Voltaneo | J95: n/a | K95: 46010679 | L95: France and Switzerland Region | M95: n/a | O95: Check Availability in New Ark | P95: P7 RES BLK P | Q95: GF0700000796 | R95: 553120 | S95: PVM, SPR-P7-500-BLK-P, I BF-G AR-SA M4.4F EVO2Z7NL | T95: 500 | U95: 792 | V95: 0.396 | W95: 22 | X95: 1 | Y95: COMPLETED | AA95: Black glazing | AB95: ±1350mm | AC95: 45879 | AD95: 32 | AE95: POPV251231217 | AF95: 371008774 | AG95: SHANGHAI | AH95: FOS SUR MER | AI95: 45885 | AJ95: 45885 | AK95: 45885 | AL95: 45942 | AN95: 45942 | AO95: CIP | AP95: OOCL SCANDINAVIA / 02MLFW1MA | AR95: 46010679 | AS95: CHN2603566 | AT95: CHN2603566 | AU95: 58 | AV95: Y | AW95: 5 | AX95: 63 | AY95: 45885 | AZ95: 45942 | BA95: #N/A | BC95: 45956 | BD95: 2025 | BE95: 10 | BF95: 43 | BG95: 36 | BH95: 792
A96: JULY011.01 | B96: Yixing | C96: JULY011 | D96: CORE DG | E96: Internal | F96: Arrival Plan-SPNL | G96: SunPower Energy Solutions France SAS | H96: CIF | I96: Solar Fabrik | J96: n/a | K96: 14130691 | L96: Germany & Austria Region | M96: n/a | O96: Check Availability in New Ark | P96: Half Cut | Q96: GF0101010095 | R96: 554245 | S96: HSM-ND66-GR620 | T96: 620 | U96: 7920 | V96: 4.9104 | W96: 220 | X96: 11 | Y96: COMPLETED | AA96: White glazing | AB96: ±300mm | AC96: 45875 | AD96: 32 | AE96: POPV251231205 | AF96: 371008755 | AG96: SHANGHAI | AH96: ROTTERDAM | AI96: 45879 | AJ96: 45879 | AK96: 45879 | AL96: 45931 | AM96: 45919 | AN96: 45931 | AO96: CIF | AP96: CSCL STAR 088W | AR96: TPVB20250801011 | AS96: COSU6426576030 | AT96: COSU6426576030 | AU96: 53 | AV96: Y | AW96: 6 | AX96: 56 | AY96: 45879 | AZ96: 45931 | BA96: #N/A | BC96: 45945 | BD96: 2025 | BE96: 10 | BF96: 42 | BG96: 36 | BH96: 720
A97: JULY012.01 | B97: Yixing | C97: JULY012 | D97: CORE DG | E97: Internal | F97: Arrival Plan-SPNL | G97: SunPower Energy Solutions France SAS | H97: CIF | I97: Solar Fabrik | J97: n/a | K97: 14130691 | L97: Germany & Austria Region | M97: n/a | O97: Check Availability in New Ark | P97: Half Cut | Q97: GF0101010096 | R97: 554246 | S97: HSM-ND66-GR625 | T97: 625 | U97: 2880 | V97: 1.8 | W97: 80 | X97: 4 | Y97: COMPLETED | AA97: White glazing | AB97: ±300mm | AC97: 45875 | AD97: 32 | AE97: POPV251231206 | AF97: 371008756 | AG97: SHANGHAI | AH97: ROTTERDAM | AI97: 45879 | AJ97: 45879 | AK97: 45879 | AL97: 45931 | AM97: 45919 | AN97: 45931 | AO97: CIF | AP97: CSCL STAR 088W | AR97: TPVB20250801011 | AS97: COSU6426576030 | AT97: COSU6426576030 | AU97: 53 | AV97: Y | AW97: 5 | AX97: 56 | AY97: 45879 | AZ97: 45931 | BA97: #N/A | BC97: 45945 | BD97: 2025 | BE97: 10 | BF97: 42 | BG97: 36 | BH97: 720
A98: JULY005.01 | B98: Yixing | C98: JULY005 | D98: CORE DG | E98: Internal | F98: Arrival Plan-SPNL | G98: SunPower Energy Solutions France SAS | H98: DAP | I98: Local WH | J98: n/a | L98: All | M98: n/a | O98: Check Availability in New Ark | P98: P7 COM S BF IT | Q98: GF0700000769 | R98: 552045 | S98: PVM, SPR-P7-555-COM-S, I BF-G M4.3D EVO2Z6NL 1.5KV IT | T98: 555 | U98: 1320 | V98: 0.7326 | W98: 40 | X98: 2 | Y98: COMPLETED | AA98: White glazing | AB98: ±1400mm | AC98: 45875 | AD98: 32 | AE98: POPV251231204 | AF98: 371008754 | AG98: SHANGHAI | AH98: ROTTERDAM | AI98: 45879 | AJ98: 45879 | AK98: 45879 | AL98: 45931 | AM98: 45919 | AN98: 45931 | AO98: DAP | AP98: CSCL STAR 088W | AR98: TPVB20250801003 | AS98: COSU6426686290 | AT98: COSU6426686290 | AU98: 53 | AV98: SWB | AW98: 11 | AX98: 56 | AY98: 45879 | AZ98: 45931 | BA98: #N/A | BC98: 45945 | BD98: 2025 | BE98: 10 | BF98: 42 | BG98: 33 | BH98: 660
A99: MAY023.02 | B99: Tianjin | C99: MAY023 | D99: CORE DG | E99: n/a | F99: n/a | H99: CIP | I99: APPROSUD ENVIRONNEMENT | J99: n/a | K99: 46010796 -> 46010785 | L99: France and Switzerland Region | M99: n/a | O99: Check Availability in New Ark | P99: Half Cut | Q99: GF0700000080 | R99: 554480 | S99: HSM-ND48-DR450_CFP | T99: 450 | U99: 936 | V99: 0.4212 | W99: 26 | X99: 1 | Y99: COMPLETED | AA99: Transparent | AB99: ±1200mm | AC99: 45876 | AD99: 32 | AE99: POPV251231199 | AF99: 371008749 | AG99: TIANJIN | AH99: FOS SUR MER | AI99: 45880 | AJ99: 45880 | AK99: 45880 | AL99: 45957 | AM99: 45950 | AN99: 45957 | AO99: DAP | AP99: COSCO SHIPPING SAGITTARIUS /031W | AR99: TPVB20250801006 | AS99: COSU6426075090 | AT99: COSU6426075090 | AU99: 78 | AV99: SWB | AW99: 5 | AX99: 81 | AY99: 45880 | AZ99: 45957 | BA99: #N/A | BC99: 45971 | BD99: 2025 | BE99: 11 | BF99: 46 | BG99: 36 | BH99: 936
A100: MAY023.04 | B100: Tianjin | C100: MAY023 | D100: CORE DG | E100: n/a | F100: n/a | H100: CIP | I100: Ecostal France | J100: n/a | K100: 46010731 | L100: France and Switzerland Region | M100: n/a | O100: Check Availability in New Ark | P100: Half Cut | Q100: GF0700000080 | R100: 554480 | S100: HSM-ND48-DR450_CFP | T100: 450 | U100: 936 | V100: 0.4212 | W100: 26 | X100: 1 | Y100: COMPLETED | AA100: Transparent | AB100: ±1200mm | AC100: 45876 | AD100: 32 | AE100: POPV260104084 | AF100: 371008748 | AG100: TIANJIN | AH100: FOS SUR MER | AI100: 45880 | AJ100: 45880 | AK100: 45880 | AL100: 45957 | AM100: 45950 | AN100: 45957 | AO100: CIP | AP100: COSCO SHIPPING SAGITTARIUS /031W | AR100: 46010731-1 | AS100: COSU9503359210 | AT100: COSU9503359210 | AU100: 78 | AV100: Y | AW100: 5 | AX100: 81 | AY100: 45880 | AZ100: 45957 | BA100: #N/A | BC100: 45971 | BD100: 2025 | BE100: 11 | BF100: 46 | BG100: 36 | BH100: 936
...

Sheet CT capacity tracker
A1: Shanghai | D1: IN-TRANSIT | E1: w21 PICK-UP | F1: w22 PICK-UP | G1: w23 PICK-UP | H1: w24 PICK-UP | I1: w25 PICK-UP | J1: w26 PICK-UP | K1: w27 PICK-UP | L1: w28 PICK-UP | M1: w29 PICK-UP | N1: w30 PICK-UP | O1: w31 PICK-UP | P1: w32 PICK-UP | Q1: w33 PICK-UP | R1: w34 PICK-UP | S1: w35 PICK-UP | T1: w36 PICK-UP | U1: w37 PICK-UP | V1: w38 PICK-UP | W1: w39 PICK-UP | X1: w40 PICK-UP | Y1: w41 PICK-UP | Z1: w42 PICK-UP | AA1: w43 PICK-UP | AB1: w44 PICK-UP | AC1: w45 PICK-UP | AD1: w46 PICK-UP | AE1: w47 PICK-UP | AF1: w48 PICK-UP | AG1: w49 PICK-UP | AH1: w50 PICK-UP | AI1: w51 PICK-UP | AJ1: w52 PICK-UP | AK1: 缺货（no cargo） | AL1: 缺柜(no CTs) | AM1: PLAN SUM VS ACTUAL SUM | AN1: NOTE | AP1: end wk 26
A2: AEU | B2: FELIXSTOWE | C2: plans in ODP | D2: =SUMIFS('PV SUPPLY DATA'!$X:$X,'PV SUPPLY DATA'!$AH:$AH,'CT capacity tracker'!$B2,'PV SUPPLY DATA'!$AG:$AG,'CT capacity tracker'!$A$1,'PV SUPPLY DATA'!$Z:$Z,'CT capacity tracker'!D$1)+SUMIFS('ESS SUPPLY DATA'!$U:$U,'ESS SUPPLY DATA'!$AF:$AF,'CT capacity tracker'!$B2,'ESS SUPPLY DATA'!$AE:$AE,'CT capacity tracker'!$A$1,'ESS SUPPLY DATA'!$X:$X,'CT capacity tracker'!D$1) -> 11 | E2: =SUMIFS('PV SUPPLY DATA'!$X:$X,'PV SUPPLY DATA'!$AH:$AH,'CT capacity tracker'!$B2,'PV SUPPLY DATA'!$AG:$AG,'CT capacity tracker'!$A$1,'PV SUPPLY DATA'!$Y:$Y,'CT capacity tracker'!E$1)+SUMIFS('ESS SUPPLY DATA'!$U:$U,'ESS SUPPLY DATA'!$AF:$AF,'CT capacity tracker'!$B2,'ESS SUPPLY DATA'!$AE:$AE,'CT capacity tracker'!$A$1,'ESS SUPPLY DATA'!$W:$W,'CT capacity tracker'!E$1) -> 0 | F2: =SUMIFS('PV SUPPLY DATA'!$X:$X,'PV SUPPLY DATA'!$AH:$AH,'CT capacity tracker'!$B2,'PV SUPPLY DATA'!$AG:$AG,'CT capacity tracker'!$A$1,'PV SUPPLY DATA'!$Y:$Y,'CT capacity tracker'!F$1)+SUMIFS('ESS SUPPLY DATA'!$U:$U,'ESS SUPPLY DATA'!$AF:$AF,'CT capacity tracker'!$B2,'ESS SUPPLY DATA'!$AE:$AE,'CT capacity tracker'!$A$1,'ESS SUPPLY DATA'!$W:$W,'CT capacity tracker'!F$1) -> 0 | G2: =SUMIFS('PV SUPPLY DATA'!$X:$X,'PV SUPPLY DATA'!$AH:$AH,'CT capacity tracker'!$B2,'PV SUPPLY DATA'!$AG:$AG,'CT capacity tracker'!$A$1,'PV SUPPLY DATA'!$Y:$Y,'CT capacity tracker'!G$1)+SUMIFS('ESS SUPPLY DATA'!$U:$U,'ESS SUPPLY DATA'!$AF:$AF,'CT capacity tracker'!$B2,'ESS SUPPLY DATA'!$AE:$AE,'CT capacity tracker'!$A$1,'ESS SUPPLY DATA'!$W:$W,'CT capacity tracker'!G$1) -> 0 | H2: =SUMIFS('PV SUPPLY DATA'!$X:$X,'PV SUPPLY DATA'!$AH:$AH,'CT capacity tracker'!$B2,'PV SUPPLY DATA'!$AG:$AG,'CT capacity tracker'!$A$1,'PV SUPPLY DATA'!$Y:$Y,'CT capacity tracker'!H$1)+SUMIFS('ESS SUPPLY DATA'!$U:$U,'ESS SUPPLY DATA'!$AF:$AF,'CT capacity tracker'!$B2,'ESS SUPPLY DATA'!$AE:$AE,'CT capacity tracker'!$A$1,'ESS SUPPLY DATA'!$W:$W,'CT capacity tracker'!H$1) -> 3 | I2: =SUMIFS('PV SUPPLY DATA'!$X:$X,'PV SUPPLY DATA'!$AH:$AH,'CT capacity tracker'!$B2,'PV SUPPLY DATA'!$AG:$AG,'CT capacity tracker'!$A$1,'PV SUPPLY DATA'!$Y:$Y,'CT capacity tracker'!I$1)+SUMIFS('ESS SUPPLY DATA'!$U:$U,'ESS SUPPLY DATA'!$AF:$AF,'CT capacity tracker'!$B2,'ESS SUPPLY DATA'!$AE:$AE,'CT capacity tracker'!$A$1,'ESS SUPPLY DATA'!$W:$W,'CT capacity tracker'!I$1) -> 0 | J2: =SUMIFS('PV SUPPLY DATA'!$X:$X,'PV SUPPLY DATA'!$AH:$AH,'CT capacity tracker'!$B2,'PV SUPPLY DATA'!$AG:$AG,'CT capacity tracker'!$A$1,'PV SUPPLY DATA'!$Y:$Y,'CT capacity tracker'!J$1)+SUMIFS('ESS SUPPLY DATA'!$U:$U,'ESS SUPPLY DATA'!$AF:$AF,'CT capacity tracker'!$B2,'ESS SUPPLY DATA'!$AE:$AE,'CT capacity tracker'!$A$1,'ESS SUPPLY DATA'!$W:$W,'CT capacity tracker'!J$1) -> 3 | K2: =SUMIFS('PV SUPPLY DATA'!$X:$X,'PV SUPPLY DATA'!$AH:$AH,'CT capacity tracker'!$B2,'PV SUPPLY DATA'!$AG:$AG,'CT capacity tracker'!$A$1,'PV SUPPLY DATA'!$Y:$Y,'CT capacity tracker'!K$1)+SUMIFS('ESS SUPPLY DATA'!$U:$U,'ESS SUPPLY DATA'!$AF:$AF,'CT capacity tracker'!$B2,'ESS SUPPLY DATA'!$AE:$AE,'CT capacity tracker'!$A$1,'ESS SUPPLY DATA'!$W:$W,'CT capacity tracker'!K$1) -> 0 | L2: =SUMIFS('PV SUPPLY DATA'!$X:$X,'PV SUPPLY DATA'!$AH:$AH,'CT capacity tracker'!$B2,'PV SUPPLY DATA'!$AG:$AG,'CT capacity tracker'!$A$1,'PV SUPPLY DATA'!$Y:$Y,'CT capacity tracker'!L$1)+SUMIFS('ESS SUPPLY DATA'!$U:$U,'ESS SUPPLY DATA'!$AF:$AF,'CT capacity tracker'!$B2,'ESS SUPPLY DATA'!$AE:$AE,'CT capacity tracker'!$A$1,'ESS SUPPLY DATA'!$W:$W,'CT capacity tracker'!L$1) -> 1 | ... AJ2: =SUMIFS('PV SUPPLY DATA'!$X:$X,'PV SUPPLY DATA'!$AH:$AH,'CT capacity tracker'!$B2,'PV SUPPLY DATA'!$AG:$AG,'CT capacity tracker'!$A$1,'PV SUPPLY DATA'!$Y:$Y,'CT capacity tracker'!AJ$1)+SUMIFS('ESS SUPPLY DATA'!$U:$U,'ESS SUPPLY DATA'!$AF:$AF,'CT capacity tracker'!$B2,'ESS SUPPLY DATA'!$AE:$AE,'CT capacity tracker'!$A$1,'ESS SUPPLY DATA'!$W:$W,'CT capacity tracker'!AJ$1) -> 0 | AM2: =SUM(E2:X2) -> 34
C3: available slots | E3: 3 | F3: 3 | G3: 3 | H3: 3 | I3: 0 | J3: 3 | K3: 0 | L3: 1 | M3: 5 | N3: 0 | O3: 5 | P3: =5-1 -> 4 | Q3: 0 | R3: 5 | S3: 3 | T3: 5 | U3: 0 | X3: 0 | Y3: 5 | Z3: 5 | AA3: 5 | AB3: 0 | AC3: 5 | AD3: 5 | AE3: 5 | AF3: 0
C4: GAP | E4: =E3-E2 -> 3 | F4: =F3-F2 -> 3 | G4: =G3-G2 -> 3 | H4: =H3-H2 -> 0 | I4: =I3-I2 -> 0 | J4: =J3-J2 -> 0 | K4: =K3-K2 -> 0 | L4: =L3-L2 -> 0 | ... AJ4: =AJ3-AJ2 -> 0 | AK4: =SUMIF($E4:$X4,">0") -> 17 | AL4: =SUMIF($E4:$X4,"<0") -> -8 | AP4: =SUM(G4:J4) -> 3
C5: Actual Shipment | E5: =SUMIFS('PV SUPPLY DATA'!$X:$X,'PV SUPPLY DATA'!$AH:$AH,'CT capacity tracker'!$B2,'PV SUPPLY DATA'!$AG:$AG,'CT capacity tracker'!$A$1,'PV SUPPLY DATA'!$Y:$Y,E$1,'PV SUPPLY DATA'!$AQ:$AQ,"cosco")+SUMIFS('PV SUPPLY DATA'!$X:$X,'PV SUPPLY DATA'!$AH:$AH,'CT capacity tracker'!$B2,'PV SUPPLY DATA'!$AG:$AG,'CT capacity tracker'!$A$1,'PV SUPPLY DATA'!$Y:$Y,E$1,'PV SUPPLY DATA'!$AQ:$AQ,"other")+SUMIFS('ESS SUPPLY DATA'!$U:$U,'ESS SUPPLY DATA'!$AF:$AF,'CT capacity tracker'!$B2,'ESS SUPPLY DATA'!$AE:$AE,'CT capacity tracker'!$A$1,'ESS SUPPLY DATA'!$W:$W,'CT capacity tracker'!E$1,'ESS SUPPLY DATA'!$AO:$AO,"cosco")+SUMIFS('ESS SUPPLY DATA'!$U:$U,'ESS SUPPLY DATA'!$AF:$AF,'CT capacity tracker'!$B2,'ESS SUPPLY DATA'!$AE:$AE,'CT capacity tracker'!$A$1,'ESS SUPPLY DATA'!$W:$W,'CT capacity tracker'!E$1,'ESS SUPPLY DATA'!$AO:$AO,"other") -> 0 | F5: =SUMIFS('PV SUPPLY DATA'!$X:$X,'PV SUPPLY DATA'!$AH:$AH,'CT capacity tracker'!$B2,'PV SUPPLY DATA'!$AG:$AG,'CT capacity tracker'!$A$1,'PV SUPPLY DATA'!$Y:$Y,F$1,'PV SUPPLY DATA'!$AQ:$AQ,"cosco")+SUMIFS('PV SUPPLY DATA'!$X:$X,'PV SUPPLY DATA'!$AH:$AH,'CT capacity tracker'!$B2,'PV SUPPLY DATA'!$AG:$AG,'CT capacity tracker'!$A$1,'PV SUPPLY DATA'!$Y:$Y,F$1,'PV SUPPLY DATA'!$AQ:$AQ,"other")+SUMIFS('ESS SUPPLY DATA'!$U:$U,'ESS SUPPLY DATA'!$AF:$AF,'CT capacity tracker'!$B2,'ESS SUPPLY DATA'!$AE:$AE,'CT capacity tracker'!$A$1,'ESS SUPPLY DATA'!$W:$W,'CT capacity tracker'!F$1,'ESS SUPPLY DATA'!$AO:$AO,"cosco")+SUMIFS('ESS SUPPLY DATA'!$U:$U,'ESS SUPPLY DATA'!$AF:$AF,'CT capacity tracker'!$B2,'ESS SUPPLY DATA'!$AE:$AE,'CT capacity tracker'!$A$1,'ESS SUPPLY DATA'!$W:$W,'CT capacity tracker'!F$1,'ESS SUPPLY DATA'!$AO:$AO,"other") -> 0 | G5: =SUMIFS('PV SUPPLY DATA'!$X:$X,'PV SUPPLY DATA'!$AH:$AH,'CT capacity tracker'!$B2,'PV SUPPLY DATA'!$AG:$AG,'CT capacity tracker'!$A$1,'PV SUPPLY DATA'!$Y:$Y,G$1,'PV SUPPLY DATA'!$AQ:$AQ,"cosco")+SUMIFS('PV SUPPLY DATA'!$X:$X,'PV SUPPLY DATA'!$AH:$AH,'CT capacity tracker'!$B2,'PV SUPPLY DATA'!$AG:$AG,'CT capacity tracker'!$A$1,'PV SUPPLY DATA'!$Y:$Y,G$1,'PV SUPPLY DATA'!$AQ:$AQ,"other")+SUMIFS('ESS SUPPLY DATA'!$U:$U,'ESS SUPPLY DATA'!$AF:$AF,'CT capacity tracker'!$B2,'ESS SUPPLY DATA'!$AE:$AE,'CT capacity tracker'!$A$1,'ESS SUPPLY DATA'!$W:$W,'CT capacity tracker'!G$1,'ESS SUPPLY DATA'!$AO:$AO,"cosco")+SUMIFS('ESS SUPPLY DATA'!$U:$U,'ESS SUPPLY DATA'!$AF:$AF,'CT capacity tracker'!$B2,'ESS SUPPLY DATA'!$AE:$AE,'CT capacity tracker'!$A$1,'ESS SUPPLY DATA'!$W:$W,'CT capacity tracker'!G$1,'ESS SUPPLY DATA'!$AO:$AO,"other") -> 0 | H5: =SUMIFS('PV SUPPLY DATA'!$X:$X,'PV SUPPLY DATA'!$AH:$AH,'CT capacity tracker'!$B2,'PV SUPPLY DATA'!$AG:$AG,'CT capacity tracker'!$A$1,'PV SUPPLY DATA'!$Y:$Y,H$1,'PV SUPPLY DATA'!$AQ:$AQ,"cosco")+SUMIFS('PV SUPPLY DATA'!$X:$X,'PV SUPPLY DATA'!$AH:$AH,'CT capacity tracker'!$B2,'PV SUPPLY DATA'!$AG:$AG,'CT capacity tracker'!$A$1,'PV SUPPLY DATA'!$Y:$Y,H$1,'PV SUPPLY DATA'!$AQ:$AQ,"other")+SUMIFS('ESS SUPPLY DATA'!$U:$U,'ESS SUPPLY DATA'!$AF:$AF,'CT capacity tracker'!$B2,'ESS SUPPLY DATA'!$AE:$AE,'CT capacity tracker'!$A$1,'ESS SUPPLY DATA'!$W:$W,'CT capacity tracker'!H$1,'ESS SUPPLY DATA'!$AO:$AO,"cosco")+SUMIFS('ESS SUPPLY DATA'!$U:$U,'ESS SUPPLY DATA'!$AF:$AF,'CT capacity tracker'!$B2,'ESS SUPPLY DATA'!$AE:$AE,'CT capacity tracker'!$A$1,'ESS SUPPLY DATA'!$W:$W,'CT capacity tracker'!H$1,'ESS SUPPLY DATA'!$AO:$AO,"other") -> 3 | I5: =SUMIFS('PV SUPPLY DATA'!$X:$X,'PV SUPPLY DATA'!$AH:$AH,'CT capacity tracker'!$B2,'PV SUPPLY DATA'!$AG:$AG,'CT capacity tracker'!$A$1,'PV SUPPLY DATA'!$Y:$Y,I$1,'PV SUPPLY DATA'!$AQ:$AQ,"cosco")+SUMIFS('PV SUPPLY DATA'!$X:$X,'PV SUPPLY DATA'!$AH:$AH,'CT capacity tracker'!$B2,'PV SUPPLY DATA'!$AG:$AG,'CT capacity tracker'!$A$1,'PV SUPPLY DATA'!$Y:$Y,I$1,'PV SUPPLY DATA'!$AQ:$AQ,"other")+SUMIFS('ESS SUPPLY DATA'!$U:$U,'ESS SUPPLY DATA'!$AF:$AF,'CT capacity tracker'!$B2,'ESS SUPPLY DATA'!$AE:$AE,'CT capacity tracker'!$A$1,'ESS SUPPLY DATA'!$W:$W,'CT capacity tracker'!I$1,'ESS SUPPLY DATA'!$AO:$AO,"cosco")+SUMIFS('ESS SUPPLY DATA'!$U:$U,'ESS SUPPLY DATA'!$AF:$AF,'CT capacity tracker'!$B2,'ESS SUPPLY DATA'!$AE:$AE,'CT capacity tracker'!$A$1,'ESS SUPPLY DATA'!$W:$W,'CT capacity tracker'!I$1,'ESS SUPPLY DATA'!$AO:$AO,"other") -> 0 | J5: =SUMIFS('PV SUPPLY DATA'!$X:$X,'PV SUPPLY DATA'!$AH:$AH,'CT capacity tracker'!$B2,'PV SUPPLY DATA'!$AG:$AG,'CT capacity tracker'!$A$1,'PV SUPPLY DATA'!$Y:$Y,J$1,'PV SUPPLY DATA'!$AQ:$AQ,"cosco")+SUMIFS('PV SUPPLY DATA'!$X:$X,'PV SUPPLY DATA'!$AH:$AH,'CT capacity tracker'!$B2,'PV SUPPLY DATA'!$AG:$AG,'CT capacity tracker'!$A$1,'PV SUPPLY DATA'!$Y:$Y,J$1,'PV SUPPLY DATA'!$AQ:$AQ,"other")+SUMIFS('ESS SUPPLY DATA'!$U:$U,'ESS SUPPLY DATA'!$AF:$AF,'CT capacity tracker'!$B2,'ESS SUPPLY DATA'!$AE:$AE,'CT capacity tracker'!$A$1,'ESS SUPPLY DATA'!$W:$W,'CT capacity tracker'!J$1,'ESS SUPPLY DATA'!$AO:$AO,"cosco")+SUMIFS('ESS SUPPLY DATA'!$U:$U,'ESS SUPPLY DATA'!$AF:$AF,'CT capacity tracker'!$B2,'ESS SUPPLY DATA'!$AE:$AE,'CT capacity tracker'!$A$1,'ESS SUPPLY DATA'!$W:$W,'CT capacity tracker'!J$1,'ESS SUPPLY DATA'!$AO:$AO,"other") -> 3 | K5: =SUMIFS('PV SUPPLY DATA'!$X:$X,'PV SUPPLY DATA'!$AH:$AH,'CT capacity tracker'!$B2,'PV SUPPLY DATA'!$AG:$AG,'CT capacity tracker'!$A$1,'PV SUPPLY DATA'!$Y:$Y,K$1,'PV SUPPLY DATA'!$AQ:$AQ,"cosco")+SUMIFS('PV SUPPLY DATA'!$X:$X,'PV SUPPLY DATA'!$AH:$AH,'CT capacity tracker'!$B2,'PV SUPPLY DATA'!$AG:$AG,'CT capacity tracker'!$A$1,'PV SUPPLY DATA'!$Y:$Y,K$1,'PV SUPPLY DATA'!$AQ:$AQ,"other")+SUMIFS('ESS SUPPLY DATA'!$U:$U,'ESS SUPPLY DATA'!$AF:$AF,'CT capacity tracker'!$B2,'ESS SUPPLY DATA'!$AE:$AE,'CT capacity tracker'!$A$1,'ESS SUPPLY DATA'!$W:$W,'CT capacity tracker'!K$1,'ESS SUPPLY DATA'!$AO:$AO,"cosco")+SUMIFS('ESS SUPPLY DATA'!$U:$U,'ESS SUPPLY DATA'!$AF:$AF,'CT capacity tracker'!$B2,'ESS SUPPLY DATA'!$AE:$AE,'CT capacity tracker'!$A$1,'ESS SUPPLY DATA'!$W:$W,'CT capacity tracker'!K$1,'ESS SUPPLY DATA'!$AO:$AO,"other") -> 0 | L5: =SUMIFS('PV SUPPLY DATA'!$X:$X,'PV SUPPLY DATA'!$AH:$AH,'CT capacity tracker'!$B2,'PV SUPPLY DATA'!$AG:$AG,'CT capacity tracker'!$A$1,'PV SUPPLY DATA'!$Y:$Y,L$1,'PV SUPPLY DATA'!$AQ:$AQ,"cosco")+SUMIFS('PV SUPPLY DATA'!$X:$X,'PV SUPPLY DATA'!$AH:$AH,'CT capacity tracker'!$B2,'PV SUPPLY DATA'!$AG:$AG,'CT capacity tracker'!$A$1,'PV SUPPLY DATA'!$Y:$Y,L$1,'PV SUPPLY DATA'!$AQ:$AQ,"other")+SUMIFS('ESS SUPPLY DATA'!$U:$U,'ESS SUPPLY DATA'!$AF:$AF,'CT capacity tracker'!$B2,'ESS SUPPLY DATA'!$AE:$AE,'CT capacity tracker'!$A$1,'ESS SUPPLY DATA'!$W:$W,'CT capacity tracker'!L$1,'ESS SUPPLY DATA'!$AO:$AO,"cosco")+SUMIFS('ESS SUPPLY DATA'!$U:$U,'ESS SUPPLY DATA'!$AF:$AF,'CT capacity tracker'!$B2,'ESS SUPPLY DATA'!$AE:$AE,'CT capacity tracker'!$A$1,'ESS SUPPLY DATA'!$W:$W,'CT capacity tracker'!L$1,'ESS SUPPLY DATA'!$AO:$AO,"other") -> 1 | ... AJ5: =SUMIFS('PV SUPPLY DATA'!$X:$X,'PV SUPPLY DATA'!$AH:$AH,'CT capacity tracker'!$B2,'PV SUPPLY DATA'!$AG:$AG,'CT capacity tracker'!$A$1,'PV SUPPLY DATA'!$Y:$Y,AJ$1,'PV SUPPLY DATA'!$AQ:$AQ,"cosco")+SUMIFS('PV SUPPLY DATA'!$X:$X,'PV SUPPLY DATA'!$AH:$AH,'CT capacity tracker'!$B2,'PV SUPPLY DATA'!$AG:$AG,'CT capacity tracker'!$A$1,'PV SUPPLY DATA'!$Y:$Y,AJ$1,'PV SUPPLY DATA'!$AQ:$AQ,"other")+SUMIFS('ESS SUPPLY DATA'!$U:$U,'ESS SUPPLY DATA'!$AF:$AF,'CT capacity tracker'!$B2,'ESS SUPPLY DATA'!$AE:$AE,'CT capacity tracker'!$A$1,'ESS SUPPLY DATA'!$W:$W,'CT capacity tracker'!AJ$1,'ESS SUPPLY DATA'!$AO:$AO,"cosco")+SUMIFS('ESS SUPPLY DATA'!$U:$U,'ESS SUPPLY DATA'!$AF:$AF,'CT capacity tracker'!$B2,'ESS SUPPLY DATA'!$AE:$AE,'CT capacity tracker'!$A$1,'ESS SUPPLY DATA'!$W:$W,'CT capacity tracker'!AJ$1,'ESS SUPPLY DATA'!$AO:$AO,"other") -> 0 | AM5: =SUM(E5:X5) -> 34
B6: ROTTERDAM | C6: plans in ODP | D6: =SUMIFS('PV SUPPLY DATA'!$X:$X,'PV SUPPLY DATA'!$AH:$AH,'CT capacity tracker'!$B6,'PV SUPPLY DATA'!$AG:$AG,'CT capacity tracker'!$A$1,'PV SUPPLY DATA'!$Z:$Z,'CT capacity tracker'!D$1)+SUMIFS('ESS SUPPLY DATA'!$U:$U,'ESS SUPPLY DATA'!$AF:$AF,'CT capacity tracker'!$B6,'ESS SUPPLY DATA'!$AE:$AE,'CT capacity tracker'!$A$1,'ESS SUPPLY DATA'!$X:$X,'CT capacity tracker'!D$1) -> 209 | E6: =SUMIFS('PV SUPPLY DATA'!$X:$X,'PV SUPPLY DATA'!$AH:$AH,'CT capacity tracker'!$B6,'PV SUPPLY DATA'!$AG:$AG,'CT capacity tracker'!$A$1,'PV SUPPLY DATA'!$Y:$Y,'CT capacity tracker'!E$1)+SUMIFS('ESS SUPPLY DATA'!$U:$U,'ESS SUPPLY DATA'!$AF:$AF,'CT capacity tracker'!$B6,'ESS SUPPLY DATA'!$AE:$AE,'CT capacity tracker'!$A$1,'ESS SUPPLY DATA'!$W:$W,'CT capacity tracker'!E$1) -> 38 | F6: =SUMIFS('PV SUPPLY DATA'!$X:$X,'PV SUPPLY DATA'!$AH:$AH,'CT capacity tracker'!$B6,'PV SUPPLY DATA'!$AG:$AG,'CT capacity tracker'!$A$1,'PV SUPPLY DATA'!$Y:$Y,'CT capacity tracker'!F$1)+SUMIFS('ESS SUPPLY DATA'!$U:$U,'ESS SUPPLY DATA'!$AF:$AF,'CT capacity tracker'!$B6,'ESS SUPPLY DATA'!$AE:$AE,'CT capacity tracker'!$A$1,'ESS SUPPLY DATA'!$W:$W,'CT capacity tracker'!F$1) -> 0 | G6: =SUMIFS('PV SUPPLY DATA'!$X:$X,'PV SUPPLY DATA'!$AH:$AH,'CT capacity tracker'!$B6,'PV SUPPLY DATA'!$AG:$AG,'CT capacity tracker'!$A$1,'PV SUPPLY DATA'!$Y:$Y,'CT capacity tracker'!G$1)+SUMIFS('ESS SUPPLY DATA'!$U:$U,'ESS SUPPLY DATA'!$AF:$AF,'CT capacity tracker'!$B6,'ESS SUPPLY DATA'!$AE:$AE,'CT capacity tracker'!$A$1,'ESS SUPPLY DATA'!$W:$W,'CT capacity tracker'!G$1) -> 37 | H6: =SUMIFS('PV SUPPLY DATA'!$X:$X,'PV SUPPLY DATA'!$AH:$AH,'CT capacity tracker'!$B6,'PV SUPPLY DATA'!$AG:$AG,'CT capacity tracker'!$A$1,'PV SUPPLY DATA'!$Y:$Y,'CT capacity tracker'!H$1)+SUMIFS('ESS SUPPLY DATA'!$U:$U,'ESS SUPPLY DATA'!$AF:$AF,'CT capacity tracker'!$B6,'ESS SUPPLY DATA'!$AE:$AE,'CT capacity tracker'!$A$1,'ESS SUPPLY DATA'!$W:$W,'CT capacity tracker'!H$1) -> 29 | I6: =SUMIFS('PV SUPPLY DATA'!$X:$X,'PV SUPPLY DATA'!$AH:$AH,'CT capacity tracker'!$B6,'PV SUPPLY DATA'!$AG:$AG,'CT capacity tracker'!$A$1,'PV SUPPLY DATA'!$Y:$Y,'CT capacity tracker'!I$1)+SUMIFS('ESS SUPPLY DATA'!$U:$U,'ESS SUPPLY DATA'!$AF:$AF,'CT capacity tracker'!$B6,'ESS SUPPLY DATA'!$AE:$AE,'CT capacity tracker'!$A$1,'ESS SUPPLY DATA'!$W:$W,'CT capacity tracker'!I$1) -> 32.912556 | J6: =SUMIFS('PV SUPPLY DATA'!$X:$X,'PV SUPPLY DATA'!$AH:$AH,'CT capacity tracker'!$B6,'PV SUPPLY DATA'!$AG:$AG,'CT capacity tracker'!$A$1,'PV SUPPLY DATA'!$Y:$Y,'CT capacity tracker'!J$1)+SUMIFS('ESS SUPPLY DATA'!$U:$U,'ESS SUPPLY DATA'!$AF:$AF,'CT capacity tracker'!$B6,'ESS SUPPLY DATA'!$AE:$AE,'CT capacity tracker'!$A$1,'ESS SUPPLY DATA'!$W:$W,'CT capacity tracker'!J$1) -> 28.87709 | K6: =SUMIFS('PV SUPPLY DATA'!$X:$X,'PV SUPPLY DATA'!$AH:$AH,'CT capacity tracker'!$B6,'PV SUPPLY DATA'!$AG:$AG,'CT capacity tracker'!$A$1,'PV SUPPLY DATA'!$Y:$Y,'CT capacity tracker'!K$1)+SUMIFS('ESS SUPPLY DATA'!$U:$U,'ESS SUPPLY DATA'!$AF:$AF,'CT capacity tracker'!$B6,'ESS SUPPLY DATA'!$AE:$AE,'CT capacity tracker'!$A$1,'ESS SUPPLY DATA'!$W:$W,'CT capacity tracker'!K$1) -> 71 | L6: =SUMIFS('PV SUPPLY DATA'!$X:$X,'PV SUPPLY DATA'!$AH:$AH,'CT capacity tracker'!$B6,'PV SUPPLY DATA'!$AG:$AG,'CT capacity tracker'!$A$1,'PV SUPPLY DATA'!$Y:$Y,'CT capacity tracker'!L$1)+SUMIFS('ESS SUPPLY DATA'!$U:$U,'ESS SUPPLY DATA'!$AF:$AF,'CT capacity tracker'!$B6,'ESS SUPPLY DATA'!$AE:$AE,'CT capacity tracker'!$A$1,'ESS SUPPLY DATA'!$W:$W,'CT capacity tracker'!L$1) -> 39 | ... AJ6: =SUMIFS('PV SUPPLY DATA'!$X:$X,'PV SUPPLY DATA'!$AH:$AH,'CT capacity tracker'!$B6,'PV SUPPLY DATA'!$AG:$AG,'CT capacity tracker'!$A$1,'PV SUPPLY DATA'!$Y:$Y,'CT capacity tracker'!AJ$1)+SUMIFS('ESS SUPPLY DATA'!$U:$U,'ESS SUPPLY DATA'!$AF:$AF,'CT capacity tracker'!$B6,'ESS SUPPLY DATA'!$AE:$AE,'CT capacity tracker'!$A$1,'ESS SUPPLY DATA'!$W:$W,'CT capacity tracker'!AJ$1) -> 0 | AM6: =SUM(E6:X6) -> 693.78965 | AP6: =SUM(G6:J6) -> 127.78965
C7: available slots | E7: 54 | F7: 24 | G7: =16+1 -> 17 | H7: 29 | I7: =29+3 -> 32 | J7: =22+1 -> 23 | K7: =11+8+5 -> 24 | L7: =11+5+8+5+9+9 -> 47 | M7: =5 -> 5 | N7: =8+7+5+38 -> 58 | O7: =11+5 -> 16 | P7: =11+5+8+21+15 -> 60 | Q7: =5+8+11+7+19 -> 50 | R7: =8+11+2+8+20 -> 49 | S7: =11+8+20 -> 39 | T7: =5+8+11+5+7 -> 36 | U7: =11+5+8+20 -> 44 | V7: =11+8+5+2+10 -> 36 | W7: =11+8+5+12+20 -> 56 | X7: =11+8+5 -> 24 | Y7: 11 | Z7: =11+5+8 -> 24 | AA7: =11+5+8 -> 24 | AB7: =4+5+8 -> 17 | AC7: =5+8 -> 13 | AD7: =5+11 -> 16 | AE7: =5+8+11 -> 24 | AF7: =11+8 -> 19 | AP7: =SUM(G7:J7) -> 101
C8: GAP | E8: =E7-E6 -> 16 | F8: =F7-F6 -> 24 | G8: =G7-G6 -> -20 | H8: =H7-H6 -> 0 | I8: =I7-I6 -> -0.91255614 | J8: =J7-J6 -> -5.8770903 | K8: =K7-K6 -> -47 | L8: =L7-L6 -> 8 | ... AJ8: =AJ7-AJ6 -> 0 | AK8: =SUMIF($E8:$X8,">0") -> 171 | AL8: =SUMIF($E8:$X8,"<0") -> -141.78965 | AP8: =SUM(G8:J8) -> -26.789646
